Workbook

Sheet DASHBOARD2
A2: DATAPHONE | COBROS | H2: FUNNEL DE COBROS
H3: Status | I3: Cant
H4: Asignadas | I4: =datos!B33 -> 1073
H5: Gestionadas | I5: =datos!B34 -> 989
H6: Contactadas | I6: =datos!B35 -> 630
H7: Promesas | I7: =datos!B36 -> 85
H8: Pagos | I8: =datos!B37 -> 46
A12: RESUMEN | MES EN TRANSITO (MAYO) | C12: Resultados Financieros | F12: % PROMESA
A13: HC | B13: 1 | C13: Segmento | D13: Promesa de Pago | E13: Monto Recuperado | F13: =B20/B14 -> 0.079217148
A14: Cuentas asignadas | B14: =datos!B4 -> 1073 | C14: Call Center Outbound | D14: =+IFERROR(_xlfn.XLOOKUP(C14,datos!A16:A23,datos!B16:B23,,0),0) -> 234.44 | E14: =+IFERROR(_xlfn.XLOOKUP(C14,datos!A16:A23,datos!C16:C23,,0),0) -> 0
A15: Cartera ($) | B15: =datos!B5 -> 3570.68 | C15: Digital | D15: =+IFERROR(_xlfn.XLOOKUP(C15,datos!A17:A24,datos!B17:B24,,0),0) -> 160.35 | E15: =+IFERROR(_xlfn.XLOOKUP(C15,datos!A17:A24,datos!C17:C24,,0),0) -> 0
A16: Recuperación ($) | B16: =datos!B6 -> 1145.24 | C16: La doña | D16: =+IFERROR(_xlfn.XLOOKUP(C16,datos!A18:A25,datos!B18:B25,,0),0) -> 0 | E16: =+IFERROR(_xlfn.XLOOKUP(C16,datos!A18:A25,datos!C18:C25,,0),0) -> 0
A17: % Recuperación | B17: =datos!B7 -> 0.32073443 | C17: Masivo (D2D) | D17: =+IFERROR(_xlfn.XLOOKUP(C17,datos!A19:A26,datos!B19:B26,,0),0) -> 2542.91 | E17: =+IFERROR(_xlfn.XLOOKUP(C17,datos!A19:A26,datos!C19:C26,,0),0) -> 882.48
A18: Contactabilidad | B18: =datos!B8 -> 0.12745296 | C18: Movil | D18: =+IFERROR(_xlfn.XLOOKUP(C18,datos!A20:A27,datos!B20:B27,,0),0) -> 0 | E18: =+IFERROR(_xlfn.XLOOKUP(C18,datos!A20:A27,datos!C20:C27,,0),0) -> 0
A19: RPC | B19: =datos!B9 -> 0.79206349 | C19: Oeste | D19: =+IFERROR(_xlfn.XLOOKUP(C19,datos!A21:A28,datos!B21:B28,,0),0) -> 0 | E19: =+IFERROR(_xlfn.XLOOKUP(C19,datos!A21:A28,datos!C21:C28,,0),0) -> 0 | F19: % RECUPERACION
A20: Promesas | B20: =datos!B10 -> 85 | C20: Punto de ventas | D20: =+IFERROR(_xlfn.XLOOKUP(C20,datos!A22:A29,datos!B22:B29,,0),0) -> 0 | E20: =+IFERROR(_xlfn.XLOOKUP(C20,datos!A22:A29,datos!C22:C29,,0),0) -> 0 | F20: =B21/B14 -> 0.042870457
A21: Promesas cumplidas | B21: =datos!B11 -> 46 | C21: Soho | D21: =GETPIVOTDATA(" Promesa de Pago",datos!$A$16,"Canal","Soho") -> 600.74 | E21: =GETPIVOTDATA(" Monto Recuperado",datos!$A$16,"Canal","Soho") -> 262.76
A22: % Cumplimiento | B22: =datos!B12 -> 0.54117647 | C22: Soho -Callcenter | D22: =GETPIVOTDATA(" Promesa de Pago",datos!$A$16,"Canal","Soho -Callcenter") -> 32.24 | E22: =+IFERROR(_xlfn.XLOOKUP(C22,datos!A24:A31,datos!C24:C31,,0),0) -> 0
C23: Total general | D23: =SUM(D14:D22) -> 3570.68 | E23: =SUM(E14:E22) -> 1145.24
A25: PERFORMANCE POR AGENTE
A26: AGENTE | B26: Cartera | C26: Recuperado | D26: % Recuperación | E26: Promesas | F26: Cumplidas | G26: % Efectividad
A27: Lili Velez | B27: =datos!B27 -> 1073 | C27: =datos!C27 -> 46 | D27: =datos!D27 -> 0.042870457 | E27: =datos!E27 -> 3570.68 | F27: =datos!F27 -> 1145.24 | G27: =datos!G27 -> 0.32073443
A28: Total | B28: =+SUM(B27:B27) -> 1073 | C28: =+SUM(C27:C27) -> 46 | D28: =+SUM(D27:D27) -> 0.042870457 | E28: =+SUM(E27:E27) -> 3570.68 | F28: =+SUM(F27:F27) -> 1145.24 | G28: =AVERAGE(G27:G27) -> 0.32073443
A29: PRODUCTIVIDAD OPERATIVA | H29: PROMESA VS PAGOS
A30: AGENTE | B30: Llamadas | C30: Contactos | D30: RPC | E30: Cant Promesas de pago | F30: % RPC | G30: % Contactos
A31: Lili Velez | B31: =GETPIVOTDATA("Intentos",analisis!$A$11,"full_name","Lili Velez") -> 1157 | C31: =GETPIVOTDATA(" Connect",analisis!$A$21,"full_name","Lili Velez") -> 630 | D31: =GETPIVOTDATA(" RPC",analisis!$A$21,"full_name","Lili Velez") -> 499 | E31: =GETPIVOTDATA("Suma de Intentos de Promesas",analisis!$G$34,"Agente ","Lili Velez") -> 85 | F31: =D31/C31 -> 0.79206349 | G31: =C31/B31 -> 0.54451167
A32: Total | B32: =+SUM(B31:B31) -> 1157 | C32: =+SUM(C31:C31) -> 630 | D32: =+SUM(D31:D31) -> 499 | E32: =+SUM(E31:E31) -> 85 | F32: =D32/C32 -> 0.79206349 | G32: =C32/B32 -> 0.54451167
A33: DIVISION POR MES PENDIENTE | E33: Cuentas Cesadas / Al Dia
A34: PENDIENTES POR MES | B34: REGISTROS CARGADOS | C34: RECUPERADO | E34: Cliente al dia | F34: Cuenta cesada
A35: 1 MES PENDIENTE | B35: =datos!B57 -> 43 | C35: =datos!C57 -> 3 | E35: =GETPIVOTDATA("Contacto1",analisis!$Z$21,"_Producto_Linea","Cliente al dia") -> 8 | F35: =GETPIVOTDATA("Contacto1",analisis!$Z$21,"_Producto_Linea","Cuenta cesada") -> 82
A36: 2 MESES PENDIENTES | B36: =datos!B58 -> 159 | C36: =datos!C58 -> 10
A37: 3 MESES PENDIENTES | B37: =datos!B59 -> 178 | C37: =datos!C59 -> 3
A38: 4 MESES PENDIENTES | B38: =datos!B60 -> 25 | C38: =datos!C60 -> 0
A39: NPN | B39: =datos!B61 -> 359 | C39: =datos!C61 -> 30
A41: LLAMADAS DIARIAS

Sheet dashboard

Sheet analisis
B1: =GETPIVOTDATA("Intentos",$A$2) -> 4943 | S1: =GETPIVOTDATA("Intentos",$A$2,"full_name","Lili Velez") -> 1157 | AH1: Fecha | AI1: (Todas)
A2: Llamadas diarias | B2: Dia | AH2: Escenario | AI2: (Todas)
A3: Agentes | B3: 02/may | C3: 04/may | D3: 05/may | E3: 06/may | F3: 07/may | G3: 08/may | H3: 09/may | I3: 11/may | J3: 12/may | K3: 13/may | L3: 14/may | M3: 15/may | N3: 16/may | O3: 18/may | P3: 19/may | Q3: 20/may | R3: 21/may | S3: 22/may | T3: Total general | AI3: =GETPIVOTDATA(" Monto de Promesa de Pago",$G$34) -> 3570.68 | AJ3: =GETPIVOTDATA("Suma de Monto pagado",$G$34) -> 1145.24 | AK3: =GETPIVOTDATA("Suma de Intentos de Promesas",$G$34,"Agente ","Lili Velez") -> 85 | AL3: =GETPIVOTDATA("Suma de Intentos de pago",$G$34,"Agente ","Lili Velez") -> 46
A4: Lili Velez | B4: 17 | C4: 42 | D4: 27 | E4: 55 | F4: 38 | G4: 60 | H4: 48 | I4: 102 | J4: 110 | K4: 101 | L4: 99 | M4: 35 | N4: 21 | O4: 91 | P4: 83 | Q4: 95 | R4: 102 | S4: 31 | T4: 1157 | AH4: Agentes | AI4: Promesa de Pago | AJ4: Cant Promesa
A5: Outbound Auto Dial | B5: 51 | C5: 108 | D5: 44 | E5: 119 | F5: 75 | G5: 122 | H5: 150 | I5: 350 | J5: 354 | K5: 363 | L5: 355 | M5: 147 | N5: 70 | O5: 311 | P5: 298 | Q5: 309 | R5: 412 | S5: 148 | T5: 3786 | AH5: Lili Velez | AI5: 3570.68 | AJ5: 85
A6: Total general | B6: 68 | C6: 150 | D6: 71 | E6: 174 | F6: 113 | G6: 182 | H6: 198 | I6: 452 | J6: 464 | K6: 464 | L6: 454 | M6: 182 | N6: 91 | O6: 402 | P6: 381 | Q6: 404 | R6: 514 | S6: 179 | T6: 4943 | AH6: may | AI6: 3545 | AJ6: 84
Y8: PENDIENTES POR MES | Z8: REGISTROS CARGADOS | AA8: RECUPERADO | AH8: jun | AI8: 25.68 | AJ8: 1
A9: Contar | B9: (Todas) | Y9: 1 MES PENDIENTE | AH9: Total general | AI9: 3570.68 | AJ9: 85
D10: Contar | E10: 1 | H10: _Producto_Linea | I10: (Varios elementos) | K10: _Producto_Linea | L10: (Todas) | T10: Fecha | U10: (Todas) | Y10: 2 MESES PENDIENTES
A11: Agentes | B11: Llamadas | D11: unicos | H11: utiliuzada | K11: Base | T11: Escenario | U11: (Varios elementos) | Y11: 3 MESES PENDIENTES
A12: Lili Velez | B12: 1157 | D12: Agentes | E12: Llamadas | H12: Etiquetas de fila | I12: Cuenta de Contacto1 | K12: Etiquetas de fila | L12: Cuenta de Contacto1 | Y12: 4 MESES PENDIENTES
A13: Outbound Auto Dial | B13: 3786 | D13: Lili Velez | E13: 942 | H13: Cobros Mayo | I13: 989 | K13: Cobros Mayo | L13: 1073 | T13: Etiquetas de fila | U13: Cuenta de Tiempo de mora (días) | Y13: NPN
A14: Total general | B14: 4943 | D14: Outbound Auto Dial | E14: 322 | H14: Total general | I14: 989 | K14: Total general | L14: 1073 | T14: 1 MES PENDIENTE | U14: 43
D15: Total general | E15: 1264 | T15: 2 MESES PENDIENTES | U15: 159
T16: 3 MESES PENDIENTES | U16: 178
I17: =GETPIVOTDATA("Contacto1",$H$12,"Source.Name","Cobros Mayo") -> 989 | L17: =GETPIVOTDATA("Contacto1",$K$12) -> 1073 | T17: 4 MESES PENDIENTES | U17: 25
T18: NPN | U18: 359 | AH18: Fecha | AI18: (Todas)
A19: Contar | B19: 1 | T19: Total general | U19: 764 | Z19: Source.Name | AA19: Cobros Mayo | AH19: Escenario | AI19: (Todas)
H20: _Producto_Linea | I20: (Todas) | Z20: utiliuzada | AI20: =GETPIVOTDATA(" Monto de Promesa de Pago",$G$34) -> 3570.68 | AJ20: =GETPIVOTDATA("Suma de Monto pagado",$G$34) -> 1145.24
A21: Agentes | B21: Connect | C21: RPC | H21: Base | T21: Fecha | U21: (Todas) | Z21: Etiquetas de fila | AA21: Cuenta de Contacto1 | AH21: Meses | AI21: Monto pagado | AJ21: Intentos de pago
A22: Lili Velez | B22: 630 | C22: 499 | H22: Etiquetas de fila | I22: Cuenta de Contacto1 | T22: Mes Pago | U22: (Varios elementos) | Z22: Cliente al dia | AA22: 8 | AH22: abr | AI22: 197.5 | AJ22: 5
A23: Outbound Auto Dial | B23: 0 | C23: 0 | H23: Cobros Mayo | I23: 1073 | T23: Escenario | U23: (Todas) | Z23: Cuenta cesada | AA23: 82 | AH23: may | AI23: 947.74 | AJ23: 41
A24: Total general | B24: 630 | C24: 499 | H24: Total general | I24: 1073 | Z24: #N/D | AA24: 2 | AH24: Total general | AI24: 1145.24 | AJ24: 46
T25: Etiquetas de fila | U25: Cuenta de Mes Pago | Z25: Total general | AA25: 92
T26: 1 MES PENDIENTE | U26: 3
T27: 2 MESES PENDIENTES | U27: 10
T28: 3 MESES PENDIENTES | U28: 3
T29: NPN | U29: 30 | AA29: 1347
B30: =GETPIVOTDATA("Monto de Promesa de Pago",$A$34) -> 3570.68 | C30: =GETPIVOTDATA(" Monto Recuperado",$A$34) -> 1145.24 | T30: Total general | U30: 46 | AA30: -361
A31: Mes Pago | B31: (Todas) | G31: Fecha | H31: (Todas)
A32: Mes Promesa | B32: (Todas) | G32: Escenario | H32: (Todas) | Q32: Agentes | R32: Suma de Monto pagado
A33: Resultados Financieros | H33: =GETPIVOTDATA(" Monto de Promesa de Pago",$G$34) -> 3570.68 | I33: =GETPIVOTDATA("Suma de Monto pagado",$G$34) -> 1145.24 | J33: =GETPIVOTDATA("Suma de Intentos de Promesas",$G$34) -> 85 | K33: =GETPIVOTDATA("Cuenta de Intentos de pago",$G$45,"Agente ","Lili Velez") -> 46 | Q33: Lili Velez | R33: 1145.24
A34: Canal | B34: Promesa de Pago | C34: Monto Recuperado | G34: Canal | H34: Monto de Promesa de Pago | I34: Suma de Monto pagado | J34: Suma de Intentos de Promesas | K34: Suma de Intentos de pago | L34: Cartera | Q34: Total general | R34: 1145.24
A35: Call Center Outbound | B35: 234.44 | C35: 0 | G35: Lili Velez | H35: 3570.68 | I35: 1145.24 | J35: 85 | K35: 46 | L35: =C54/C55 -> 1073
A36: Digital | B36: 160.35 | C36: 0 | G36: Total general | H36: 3570.68 | I36: 1145.24 | J36: 85 | K36: 46 | L36: =C54/C55 -> 1073
A37: Masivo (D2D) | B37: 2542.91 | C37: 882.48
A38: Punto de ventas | B38: 0 | C38: 0
A39: Soho | B39: 600.74 | C39: 262.76
A40: Soho -Callcenter | B40: 32.24 | C40: 0
A41: Total general | B41: 3570.68 | C41: 1145.24 | G41: Fecha | H41: (Todas)
G42: Mes Promesa | H42: (Todas)
G43: Mes Pago | H43: (Varios elementos)
H44: =GETPIVOTDATA(" Monto de Promesa de Pago",$G$34) -> 3570.68 | I44: =GETPIVOTDATA("Suma de Monto pagado",$G$34) -> 1145.24 | J44: =J33 -> 85 | K44: =K33 -> 46
G45: Canal | H45: Monto de Promesa de Pago | I45: Suma de Monto pagado | J45: Suma de Pago | K45: Cuenta de Intentos de pago
D46: Valores | G46: Lili Velez | I46: 1145.24 | K46: 46
D47: Cuenta de Promesa de Pago | E47: 85 | G47: Total general | I47: 1145.24 | K47: 46
D48: Cuenta de Monto pagado | E48: 29
A53: Cartera | C53: Total
A54: Etiquetas de fila | B54: Cant | C54: =GETPIVOTDATA("Contacto1",$A$54,"Source.Name","Cobros Mayo") -> 1073 | F54: Llamadas diarias | G54: Dia
A55: Cobros Abril Canal Fijo | B55: 1347 | C55: 1 | F55: Agentes | G55: Lili Velez
A56: Cobros Mayo | B56: 1073 | F56: 02/may | G56: 17
A57: Total general | B57: 2420 | C57: =C54/C55 -> 1073 | F57: 04/may | G57: 42
F58: 05/may | G58: 27
F59: 06/may | G59: 55
A60: Recuperacion diaria | F60: 07/may | G60: 38
A61: Canal | B61: Monto de Promesa de Pago | F61: 08/may | G61: 60
A62: 04/may | B62: 396.71 | F62: 09/may | G62: 48
A63: 05/may | B63: 119.96 | F63: 11/may | G63: 102
A64: 06/may | B64: 241.32 | F64: 12/may | G64: 110
A65: 07/may | B65: 159.4 | F65: 13/may | G65: 101
A66: 08/may | B66: 34.85 | F66: 14/may | G66: 99
A67: 09/may | B67: 32.42 | F67: 15/may | G67: 35
A68: 11/may | B68: 173.68 | F68: 16/may | G68: 21
A69: 12/may | B69: 362.32 | F69: 18/may | G69: 91
A70: 13/may | B70: 200.84 | F70: 19/may | G70: 83
A71: 14/may | B71: 305.58 | F71: 20/may | G71: 95
A72: 15/may | B72: 202.68 | F72: 21/may | G72: 102
A73: 16/may | B73: 168.4 | F73: 22/may | G73: 31
A74: 18/may | B74: 279.8
A75: 19/may | B75: 356.11
A76: 20/may | B76: 202.57
A77: 21/may | B77: 244.04
A78: 22/may | B78: 90
A79: Total general | B79: 3570.68
F88: Mes Promesa | G88: may
F89: Resultados Financieros
F90: Canal | G90: Promesa de Pago
F91: Call Center Outbound | G91: 234.44
F92: Digital | G92: 160.35
F93: Masivo (D2D) | G93: 2517.23
F94: Soho | G94: 600.74
F95: Soho -Callcenter | G95: 32.24
F96: Total general | G96: 3545
F100: Mes Pago | G100: (Varios elementos)
F101: Mes Promesa | G101: (Todas)
F102: Resultados Financieros
F103: Canal | G103: Monto Recuperado
F104: Call Center Outbound | G104: 0
F105: Masivo (D2D) | G105: 882.48
F106: Soho | G106: 262.76
F107: Total general | G107: 1145.24

Sheet datos
A2: Resumen Ejecutivo | E2: Productividad Operativa
A3: HC | B3: 1 | E3: Indicador | F3: Valor
A4: Cuentas asignadas | B4: =analisis!L17 -> 1073 | E4: Llamadas | F4: Contactos | G4: RPC | H4: Cant Promesas de pago | I4: % RPC
A5: Cartera ($) | B5: =GETPIVOTDATA(" Monto de Promesa de Pago",analisis!$G$34) -> 3570.68 | E5: =GETPIVOTDATA("Intentos",analisis!$A$11) -> 4943 | F5: =GETPIVOTDATA(" Connect",analisis!$A$21) -> 630 | G5: =GETPIVOTDATA(" RPC",analisis!$A$21) -> 499 | H5: =analisis!J33 -> 85 | I5: =G5/F5 -> 0.79206349
A6: Recuperación ($) | B6: =GETPIVOTDATA("Suma de Monto pagado",analisis!$G$34) -> 1145.24
A7: % Recuperación | B7: =B6/B5 -> 0.32073443
A8: Contactabilidad | B8: =F5/E5 -> 0.12745296
A9: RPC | B9: =G5/F5 -> 0.79206349
A10: Promesas | B10: =H5 -> 85
A11: Promesas cumplidas | B11: =B37 -> 46
A12: % Cumplimiento | B12: =B11/B10 -> 0.54117647
A15: Resultados Financieros
A16: Canal | B16: Promesa de Pago | C16: Monto Recuperado
A17: Call Center Outbound | B17: 234.44 | C17: 0
A18: Digital | B18: 160.35 | C18: 0
A19: Masivo (D2D) | B19: 2542.91 | C19: 882.48
A20: Punto de ventas | B20: 0 | C20: 0
A21: Soho | B21: 600.74 | C21: 262.76
A22: Soho -Callcenter | B22: 32.24 | C22: 0
A23: Total general | B23: 3570.68 | C23: 1145.24
A25: Performance por Agente
A26: Agente | B26: Cartera | C26: Recuperado | D26: % Recuperación | E26: Promesas | F26: Cumplidas | G26: % Efectividad
A27: Lili Velez | B27: =analisis!C57 -> 1073 | C27: =GETPIVOTDATA("Suma de Intentos de pago",analisis!$G$34,"Agente ","Lili Velez") -> 46 | D27: =C27/B27 -> 0.042870457 | E27: =GETPIVOTDATA(" Monto de Promesa de Pago",analisis!$G$34,"Agente ","Lili Velez") -> 3570.68 | F27: =GETPIVOTDATA("Suma de Monto pagado",analisis!$G$34,"Agente ","Lili Velez") -> 1145.24 | G27: =F27/E27 -> 0.32073443
A31: Funnel de Cobranza
A32: Etapa | B32: Cantidad
A33: Asignadas | B33: =B4 -> 1073
A34: Gestionadas | B34: =analisis!I17 -> 989
A35: Contactadas | B35: =F5 -> 630
A36: Promesas | B36: =analisis!J33 -> 85
A37: Pagos | B37: =analisis!K33 -> 46
A40: Promesas vs Pagos
A41: Indicador | B41: Valor | C41: Porcentaje
A42: Promesas | B42: =H5 -> 85 | C42: =B42/$B$4 -> 0.079217148
A43: Pagos | B43: =B11 -> 46 | C43: =B43/$B$4 -> 0.042870457
A44: % Cumplimiento | B44: =(B43/B42) -> 0.54117647
A47: Efectividad de Cobranza
A48: Indicador | B48: Valor
A49: Gestiones Totales | B49: =analisis!L17 -> 1073
A50: Gestiones Productivas | B50: =analisis!I17 -> 989
A51: % Efectividad | B51: =B50/B49 -> 0.92171482
A56: PENDIENTES POR MES | B56: REGISTROS CARGADOS | C56: RECUPERADO
A57: 1 MES PENDIENTE | B57: =_xlfn.XLOOKUP($A$57,analisis!T14:T18,analisis!U14:U18,,0) -> 43 | C57: =IFERROR(_xlfn.XLOOKUP(A57,analisis!T26:T30,analisis!U26:U30,,0),0) -> 3
A58: 2 MESES PENDIENTES | B58: =_xlfn.XLOOKUP(A58,analisis!T15:T19,analisis!U15:U19,,0) -> 159 | C58: =IFERROR(_xlfn.XLOOKUP(A58,analisis!T27:T31,analisis!U27:U31,,0),0) -> 10
A59: 3 MESES PENDIENTES | B59: =_xlfn.XLOOKUP(A59,analisis!T16:T20,analisis!U16:U20,,0) -> 178 | C59: =IFERROR(_xlfn.XLOOKUP(A59,analisis!T28:T32,analisis!U28:U32,,0),0) -> 3
A60: 4 MESES PENDIENTES | B60: =_xlfn.XLOOKUP(A60,analisis!T17:T21,analisis!U17:U21,,0) -> 25 | C60: =IFERROR(_xlfn.XLOOKUP(A60,analisis!T29:T33,analisis!U29:U33,,0),0) -> 0
A61: NPN | B61: =_xlfn.XLOOKUP(A61,analisis!T18:T22,analisis!U18:U22,,0) -> 359 | C61: =GETPIVOTDATA("Mes Pago",analisis!$T$25,"Tiempo de mora (días)","NPN") -> 30
A62: TOTAL | B62: =SUM(B57:B61) -> 764 | C62: =SUM(C57:C61) -> 46

Sheet Resumen Ejecutivo
A2: Resumen Ejecutivo
A3: HC | B3: 2
A4: Cuentas asignadas | B4: 1000
A5: Cartera ($) | B5: 150000
A6: Recuperación ($) | B6: 45000
A7: % Recuperación | B7: =B6/B5 -> 0.3
A8: RPC | B8: 300
A9: Contactabilidad | B9: 0.65
A10: Promesas | B10: 120
A11: Promesas cumplidas | B11: 90
A12: % Cumplimiento | B12: =B11/B10 -> 0.75

Sheet Productividad
A1: Indicador | B1: Valor
A2: Llamadas | B2: Contactos | C2: RPC | D2: Cant Promesas de pago
A3: 2500 | B3: 1600 | C3: 300 | D3: 120

Sheet Financieros
A1: Segmento | B1: Recuperación ($)
A2: Call Center | B2: 30000
A3: Digital | B3: 15000

Sheet Agentes
A1: Agente | B1: Cartera | C1: Recuperado | D1: % Recuperación | E1: Promesas | F1: Cumplidas | G1: % Efectividad
A2: Agente 1 | B2: 75000 | C2: 25000 | D2: =C2/B2 -> 0.33333333 | E2: 70 | F2: 50 | G2: =F2/E2 -> 0.71428571
A3: Agente 2 | B3: 75000 | C3: 20000 | D3: =C3/B3 -> 0.26666667 | E3: 50 | F3: 40 | G3: =F3/E3 -> 0.8

Sheet Funnel
A1: Etapa | B1: Cantidad
A2: Asignadas | B2: 1000
A3: Gestionadas | B3: 800
A4: Contactadas | B4: 650
A5: Promesas | B5: 120
A6: Pagos | B6: 90

Sheet Promesas vs Pagos
A1: Indicador | B1: Valor
A2: Promesas | B2: 120
A3: Pagos | B3: 90
A4: % Cumplimiento | B4: =B3/B2 -> 0.75

Sheet Efectividad
A1: Indicador | B1: Valor
A2: Gestiones Totales | B2: 2500
A3: Gestiones Productivas | B3: 300
A4: % Efectividad | B4: =B3/B2 -> 0.12

Sheet bases UTILIZADAS
A1: Source.Name | B1: Nombre_Cliente | C1: Numero_Cuenta | D1: Nombre de Lista | E1: Provincia | F1: Dias_morosidad | G1: Fecha_Ult_Pago | H1: Contacto1 | I1: Contacto2 | J1: Contacto3 | K1: email | L1: Monto_Vencido | M1: Monto_Total | N1: Ciclo | O1: Fecha_Promesa_Pago | P1: Numero_de_orden | Q1: Segmentacion_de_cliente | R1: Direccion | S1: Cedula_del_cliente | T1: Canal | U1: Tiempo de mora | V1: _Producto_Linea | W1: _Renta_BB | X1: _Renta_Linea | Y1: _Renta_TV | Z1: Pago_de_entrada
A2: Cobros Abril Canal Fijo | B2: Delfina gonzalez Martinez | C2: 359331050000 | D2: Cobros Abril Canal Fijo 2 meses a NPN | E2: =+_xlfn.XLOOKUP(UTILIZADAS[[#This Row],[Numero_Cuenta]],'[1]cobros_marzo (fijo)'!$B:$B,'[1]cobros_marzo (fijo)'!$D:$D,,0) -> Provincia | G2: 46026 | H2: 67523877 | I2: 67523877 | K2: preciadoiranelda@gmail.com | O2: 46026 | S2: 10-8-653 | T2: MASIVO | U2: NPN | V2: =_xlfn.XLOOKUP(UTILIZADAS[[#This Row],[Contacto1]],Tabla2[phone_number_dialed],Tabla2[status_name],,0) -> #N/A
A3: Cobros Abril Canal Fijo | B3: Juliana concepción | C3: 356789000000 | D3: Cobros Abril Canal Fijo 2 meses a NPN | E3: =+_xlfn.XLOOKUP(UTILIZADAS[[#This Row],[Numero_Cuenta]],'[1]cobros_marzo (fijo)'!$B:$B,'[1]cobros_marzo (fijo)'!$D:$D,,0) -> PANAMA | G3: 46026 | H3: 68905432 | I3: 68905432 | K3: juancarlos@gmail.com | O3: 46026 | S3: 9-748-246 | T3: MASIVO | U3: NPN | V3: =_xlfn.XLOOKUP(UTILIZADAS[[#This Row],[Contacto1]],Tabla2[phone_number_dialed],Tabla2[status_name],,0) -> Agent Not Available
A4: Cobros Abril Canal Fijo | B4: Angeles barahona | C4: 355339190000 | D4: Cobros Abril Canal Fijo 2 meses a NPN | E4: =+_xlfn.XLOOKUP(UTILIZADAS[[#This Row],[Numero_Cuenta]],'[1]cobros_marzo (fijo)'!$B:$B,'[1]cobros_marzo (fijo)'!$D:$D,,0) -> PANAMA | G4: 46026 | H4: 68905432 | I4: 68905432 | K4: danirudas42@gmail.com | O4: 46026 | S4: 7-712-2265 | T4: MASIVO | U4: NPN | V4: =_xlfn.XLOOKUP(UTILIZADAS[[#This Row],[Contacto1]],Tabla2[phone_number_dialed],Tabla2[status_name],,0) -> Agent Not Available
A5: Cobros Abril Canal Fijo | B5: Stacy suseth Murillo de Leon | C5: 357337110000 | D5: Cobros Abril Canal Fijo 2 meses a NPN | E5: =+_xlfn.XLOOKUP(UTILIZADAS[[#This Row],[Numero_Cuenta]],'[1]cobros_marzo (fijo)'!$B:$B,'[1]cobros_marzo (fijo)'!$D:$D,,0) -> PANAMA | G5: 46026 | H5: 63277219 | I5: 63277219 | K5: stacymrillo28@icloud.com | O5: 46026 | S5: 8-994-968 | T5: MASIVO | U5: NPN | V5: =_xlfn.XLOOKUP(UTILIZADAS[[#This Row],[Contacto1]],Tabla2[phone_number_dialed],Tabla2[status_name],,0) -> #N/A
A6: Cobros Abril Canal Fijo | B6: Roberto Linton | C6: 359338710000 | D6: Cobros Abril Canal Fijo 2 meses a NPN | E6: =+_xlfn.XLOOKUP(UTILIZADAS[[#This Row],[Numero_Cuenta]],'[1]cobros_marzo (fijo)'!$B:$B,'[1]cobros_marzo (fijo)'!$D:$D,,0) -> 0 | G6: 46026 | H6: 64628032 | I6: 64628032 | K6: Fabian022431@gmail.com | O6: 46026 | S6: 8-257-865 | T6: MASIVO | U6: NPN | V6: =_xlfn.XLOOKUP(UTILIZADAS[[#This Row],[Contacto1]],Tabla2[phone_number_dialed],Tabla2[status_name],,0) -> #N/A
A7: Cobros Abril Canal Fijo | B7: MARIO AUGUSTO ARJONA ARJONA | C7: 352335700000 | D7: Cobros Abril Canal Fijo 2 meses a NPN | E7: =+_xlfn.XLOOKUP(UTILIZADAS[[#This Row],[Numero_Cuenta]],'[1]cobros_marzo (fijo)'!$B:$B,'[1]cobros_marzo (fijo)'!$D:$D,,0) -> PANAMA | G7: 46026 | H7: 65117775 | I7: 65117775 | K7: marioarjona1956@gmail.com | O7: 46026 | S7: 6-41-2503 | T7: MASIVO | U7: NPN | V7: =_xlfn.XLOOKUP(UTILIZADAS[[#This Row],[Contacto1]],Tabla2[phone_number_dialed],Tabla2[status_name],,0) -> #N/A
A8: Cobros Abril Canal Fijo | B8: Edith Montes | C8: 357338020000 | D8: Cobros Abril Canal Fijo 2 meses a NPN | E8: =+_xlfn.XLOOKUP(UTILIZADAS[[#This Row],[Numero_Cuenta]],'[1]cobros_marzo (fijo)'!$B:$B,'[1]cobros_marzo (fijo)'!$D:$D,,0) -> HERRERA | G8: 46026 | H8: 63822556 | I8: 63822556 | K8: Edithmontes300@gmail.com | O8: 46026 | S8: 9-742-14 | T8: MASIVO | U8: NPN | V8: =_xlfn.XLOOKUP(UTILIZADAS[[#This Row],[Contacto1]],Tabla2[phone_number_dialed],Tabla2[status_name],,0) -> #N/A
A9: Cobros Abril Canal Fijo | B9: CARLOSENRIQUE DOMINGUEZVERGARA | C9: 359339470000 | D9: Cobros Abril Canal Fijo 2 meses a NPN | E9: =+_xlfn.XLOOKUP(UTILIZADAS[[#This Row],[Numero_Cuenta]],'[1]cobros_marzo (fijo)'!$B:$B,'[1]cobros_marzo (fijo)'!$D:$D,,0) -> VERAGUAS | G9: 46026 | H9: 63701410 | I9: 63701410 | K9: Cdominguezvergara939@gmail.com | O9: 46026 | S9: 8-796-2451 | T9: MASIVO | U9: NPN | V9: =_xlfn.XLOOKUP(UTILIZADAS[[#This Row],[Contacto1]],Tabla2[phone_number_dialed],Tabla2[status_name],,0) -> #N/A
A10: Cobros Abril Canal Fijo | B10: Nelis Pérez Jiménez | C10: 356338650000 | D10: Cobros Abril Canal Fijo 2 meses a NPN | E10: =+_xlfn.XLOOKUP(UTILIZADAS[[#This Row],[Numero_Cuenta]],'[1]cobros_marzo (fijo)'!$B:$B,'[1]cobros_marzo (fijo)'!$D:$D,,0) -> PANAMA | G10: 46026 | H10: 64205199 | I10: 64205199 | K10: nelisperez955@gmail.com | O10: 46026 | S10: 8-969-831 | T10: MASIVO | U10: NPN | V10: =_xlfn.XLOOKUP(UTILIZADAS[[#This Row],[Contacto1]],Tabla2[phone_number_dialed],Tabla2[status_name],,0) -> #N/A
A11: Cobros Abril Canal Fijo | B11: Luz Mina solis diaz | C11: 369328670000 | D11: Cobros Abril Canal Fijo 2 meses a NPN | E11: =+_xlfn.XLOOKUP(UTILIZADAS[[#This Row],[Numero_Cuenta]],'[1]cobros_marzo (fijo)'!$B:$B,'[1]cobros_marzo (fijo)'!$D:$D,,0) -> 0 | G11: 46026 | H11: 66330979 | I11: 66330979 | K11: diaslineth73@gmail.com | O11: 46026 | S11: 8-897-1143 | T11: MASIVO | U11: NPN | V11: =_xlfn.XLOOKUP(UTILIZADAS[[#This Row],[Contacto1]],Tabla2[phone_number_dialed],Tabla2[status_name],,0) -> #N/A
A12: Cobros Abril Canal Fijo | B12: Gloria Saday Peralta Espino | C12: 355318600000 | D12: Cobros Abril Canal Fijo 2 meses a NPN | E12: =+_xlfn.XLOOKUP(UTILIZADAS[[#This Row],[Numero_Cuenta]],'[1]cobros_marzo (fijo)'!$B:$B,'[1]cobros_marzo (fijo)'!$D:$D,,0) -> PANAMA | G12: 46026 | H12: 63498225 | I12: 63498225 | K12: 06.alayna@gmail.com | O12: 46026 | S12: 8-1043-2239 | T12: MASIVO | U12: NPN | V12: =_xlfn.XLOOKUP(UTILIZADAS[[#This Row],[Contacto1]],Tabla2[phone_number_dialed],Tabla2[status_name],,0) -> #N/A
A13: Cobros Abril Canal Fijo | B13: Disleydis quintero | C13: 356340020000 | D13: Cobros Abril Canal Fijo 2 meses a NPN | E13: =+_xlfn.XLOOKUP(UTILIZADAS[[#This Row],[Numero_Cuenta]],'[1]cobros_marzo (fijo)'!$B:$B,'[1]cobros_marzo (fijo)'!$D:$D,,0) -> PANAMA | G13: 46026 | H13: 67778877 | I13: 67778877 | K13: Disleydiquintero@gmail.com | O13: 46026 | S13: 8-1033-671 | T13: MASIVO | U13: NPN | V13: =_xlfn.XLOOKUP(UTILIZADAS[[#This Row],[Contacto1]],Tabla2[phone_number_dialed],Tabla2[status_name],,0) -> #N/A
... A189: Cobros Abril Canal Fijo | B189: EMIDIO ROBINSON GARCIA | C189: 351354250000 | D189: Cobros Abril Canal Fijo 2 meses a NPN | E189: =+_xlfn.XLOOKUP(UTILIZADAS[[#This Row],[Numero_Cuenta]],'[1]cobros_marzo (fijo)'!$B:$B,'[1]cobros_marzo (fijo)'!$D:$D,,0) -> CHIRIQUI | G189: 46026 | H189: 67369139 | I189: 67369139 | K189: Emidiorobinson@gmail.com | O189: 46026 | S189: 10-708-2196 | T189: MASIVO | U189: NPN | V189: =_xlfn.XLOOKUP(UTILIZADAS[[#This Row],[Contacto1]],Tabla2[phone_number_dialed],Tabla2[status_name],,0) -> #N/A
A190: Cobros Abril Canal Fijo | B190: María Aleida Cooper | C190: 351353940000 | D190: Cobros Abril Canal Fijo 2 meses a NPN | E190: =+_xlfn.XLOOKUP(UTILIZADAS[[#This Row],[Numero_Cuenta]],'[1]cobros_marzo (fijo)'!$B:$B,'[1]cobros_marzo (fijo)'!$D:$D,,0) -> PANAMA | G190: 46026 | H190: 68244153 | I190: 68244153 | K190: patricia5042056601@gmail.com | O190: 46026 | S190: 570783804 | T190: MASIVO | U190: NPN | V190: =_xlfn.XLOOKUP(UTILIZADAS[[#This Row],[Contacto1]],Tabla2[phone_number_dialed],Tabla2[status_name],,0) -> #N/A
A191: Cobros Abril Canal Fijo | B191: Gerson Ney Lasso Balanta | C191: 354352440000 | D191: Cobros Abril Canal Fijo 2 meses a NPN | E191: =+_xlfn.XLOOKUP(UTILIZADAS[[#This Row],[Numero_Cuenta]],'[1]cobros_marzo (fijo)'!$B:$B,'[1]cobros_marzo (fijo)'!$D:$D,,0) -> PANAMA | G191: 46026 | H191: 69054703 | I191: 69054703 | K191: Lassogerson35@gmail.com | O191: 46026 | S191: FB662738 | T191: MASIVO | U191: NPN | V191: =_xlfn.XLOOKUP(UTILIZADAS[[#This Row],[Contacto1]],Tabla2[phone_number_dialed],Tabla2[status_name],,0) -> #N/A
A192: Cobros Abril Canal Fijo | B192: KAREN CAMACHO | C192: 358348350000 | D192: Cobros Abril Canal Fijo 2 meses a NPN | E192: =+_xlfn.XLOOKUP(UTILIZADAS[[#This Row],[Numero_Cuenta]],'[1]cobros_marzo (fijo)'!$B:$B,'[1]cobros_marzo (fijo)'!$D:$D,,0) -> COLON | G192: 46026 | H192: 67787532 | I192: 67787532 | K192: Barcenaseder58@gmail.com | O192: 46026 | S192: 3-743-363 | T192: MASIVO | U192: NPN | V192: =_xlfn.XLOOKUP(UTILIZADAS[[#This Row],[Contacto1]],Tabla2[phone_number_dialed],Tabla2[status_name],,0) -> #N/A
A193: Cobros Abril Canal Fijo | B193: Rony garcia | C193: 359354680000 | D193: Cobros Abril Canal Fijo 2 meses a NPN | E193: =+_xlfn.XLOOKUP(UTILIZADAS[[#This Row],[Numero_Cuenta]],'[1]cobros_marzo (fijo)'!$B:$B,'[1]cobros_marzo (fijo)'!$D:$D,,0) -> COLON | G193: 46026 | H193: 61669203 | I193: 61669203 | K193: ronygarcia24@gmail.com | O193: 46026 | S193: 8-1047-2365 | T193: MASIVO | U193: NPN | V193: =_xlfn.XLOOKUP(UTILIZADAS[[#This Row],[Contacto1]],Tabla2[phone_number_dialed],Tabla2[status_name],,0) -> #N/A
A194: Cobros Abril Canal Fijo | B194: Sofía Navarro | C194: 357335980000 | D194: Cobros Abril Canal Fijo 2 meses a NPN | E194: =+_xlfn.XLOOKUP(UTILIZADAS[[#This Row],[Numero_Cuenta]],'[1]cobros_marzo (fijo)'!$B:$B,'[1]cobros_marzo (fijo)'!$D:$D,,0) -> PANAMA | G194: 46026 | H194: 62665510 | I194: 62665510 | K194: sofiadenavarro@gmail.com | O194: 46026 | S194: AX939366 | T194: SOHO | U194: NPN | V194: =_xlfn.XLOOKUP(UTILIZADAS[[#This Row],[Contacto1]],Tabla2[phone_number_dialed],Tabla2[status_name],,0) -> #N/A
A195: Cobros Abril Canal Fijo | B195: Karen Vergara | C195: 354352630000 | D195: Cobros Abril Canal Fijo 2 meses a NPN | E195: =+_xlfn.XLOOKUP(UTILIZADAS[[#This Row],[Numero_Cuenta]],'[1]cobros_marzo (fijo)'!$B:$B,'[1]cobros_marzo (fijo)'!$D:$D,,0) -> PANAMA | G195: 46026 | H195: 68162584 | I195: 68162584 | K195: kvergara0328@gmail.com | O195: 46026 | S195: 8-998-2253 | T195: MASIVO | U195: NPN | V195: =_xlfn.XLOOKUP(UTILIZADAS[[#This Row],[Contacto1]],Tabla2[phone_number_dialed],Tabla2[status_name],,0) -> #N/A
A196: Cobros Abril Canal Fijo | B196: CESAR GONZALEZ | C196: 356353170000 | D196: Cobros Abril Canal Fijo 2 meses a NPN | E196: =+_xlfn.XLOOKUP(UTILIZADAS[[#This Row],[Numero_Cuenta]],'[1]cobros_marzo (fijo)'!$B:$B,'[1]cobros_marzo (fijo)'!$D:$D,,0) -> HERRERA | G196: 46026 | H196: 68462020 | I196: 68462020 | K196: Eutimiaguerra213@gmail.com | O196: 46026 | S196: 9-61-437 | T196: MASIVO | U196: NPN | V196: =_xlfn.XLOOKUP(UTILIZADAS[[#This Row],[Contacto1]],Tabla2[phone_number_dialed],Tabla2[status_name],,0) -> #N/A
A197: Cobros Abril Canal Fijo | B197: Cecibel rios | C197: 357353980000 | D197: Cobros Abril Canal Fijo 2 meses a NPN | E197: =+_xlfn.XLOOKUP(UTILIZADAS[[#This Row],[Numero_Cuenta]],'[1]cobros_marzo (fijo)'!$B:$B,'[1]cobros_marzo (fijo)'!$D:$D,,0) -> VERAGUAS | G197: 46026 | H197: 65279813 | I197: 65279813 | K197: crios3131@hotmail.com | O197: 46026 | S197: 8-303-7 | T197: MASIVO | U197: NPN | V197: =_xlfn.XLOOKUP(UTILIZADAS[[#This Row],[Contacto1]],Tabla2[phone_number_dialed],Tabla2[status_name],,0) -> #N/A
A198: Cobros Abril Canal Fijo | B198: Alexandra Raquel Mora Quijano | C198: 357353490000 | D198: Cobros Abril Canal Fijo 2 meses a NPN | E198: =+_xlfn.XLOOKUP(UTILIZADAS[[#This Row],[Numero_Cuenta]],'[1]cobros_marzo (fijo)'!$B:$B,'[1]cobros_marzo (fijo)'!$D:$D,,0) -> PANAMA | G198: 46026 | H198: 67011734 | I198: 67011734 | K198: lilymoraquijano1705@gmail.com | O198: 46026 | S198: 4-763-1902 | T198: MASIVO | U198: NPN | V198: =_xlfn.XLOOKUP(UTILIZADAS[[#This Row],[Contacto1]],Tabla2[phone_number_dialed],Tabla2[status_name],,0) -> #N/A
A199: Cobros Abril Canal Fijo | B199: YENITZEL ARGELYS AGUILAR SANTOS | C199: 351355390000 | D199: Cobros Abril Canal Fijo 2 meses a NPN | E199: =+_xlfn.XLOOKUP(UTILIZADAS[[#This Row],[Numero_Cuenta]],'[1]cobros_marzo (fijo)'!$B:$B,'[1]cobros_marzo (fijo)'!$D:$D,,0) -> CHIRIQUI | G199: 46026 | H199: 61948388 | I199: 61948388 | K199: msantoscontrera@gmail.com | O199: 46026 | S199: 4-827-1762 | T199: MASIVO | U199: NPN | V199: =_xlfn.XLOOKUP(UTILIZADAS[[#This Row],[Contacto1]],Tabla2[phone_number_dialed],Tabla2[status_name],,0) -> #N/A
A200: Cobros Abril Canal Fijo | B200: ESTEBAN GARY ROJAS | C200: 357355760000 | D200: Cobros Abril Canal Fijo 2 meses a NPN | E200: =+_xlfn.XLOOKUP(UTILIZADAS[[#This Row],[Numero_Cuenta]],'[1]cobros_marzo (fijo)'!$B:$B,'[1]cobros_marzo (fijo)'!$D:$D,,0) -> CHIRIQUI | G200: 46026 | H200: 68930634 | I200: 68930634 | K200: mariadegary1959@gmail.com | O200: 46026 | S200: 3-42-581 | T200: MASIVO | U200: NPN | V200: =_xlfn.XLOOKUP(UTILIZADAS[[#This Row],[Contacto1]],Tabla2[phone_number_dialed],Tabla2[status_name],,0) -> #N/A
A201: Cobros Abril Canal Fijo | B201: Enilda Yuribel Perrz Ruiz | C201: 354354860000 | D201: Cobros Abril Canal Fijo 2 meses a NPN | E201: =+_xlfn.XLOOKUP(UTILIZADAS[[#This Row],[Numero_Cuenta]],'[1]cobros_marzo (fijo)'!$B:$B,'[1]cobros_marzo (fijo)'!$D:$D,,0) -> CHIRIQUI | G201: 46026 | H201: 68366223 | I201: 68366223 | K201: eperez@corromaduro.com | O201: 46026 | S201: 9-734-1467 | T201: MASIVO | U201: NPN | V201: =_xlfn.XLOOKUP(UTILIZADAS[[#This Row],[Contacto1]],Tabla2[phone_number_dialed],Tabla2[status_name],,0) -> #N/A
A202: Cobros Abril Canal Fijo | B202: Horacia solis | C202: 356789050000 | D202: Cobros Abril Canal Fijo 2 meses a NPN | E202: =+_xlfn.XLOOKUP(UTILIZADAS[[#This Row],[Numero_Cuenta]],'[1]cobros_marzo (fijo)'!$B:$B,'[1]cobros_marzo (fijo)'!$D:$D,,0) -> PANAMA | G202: 46026 | H202: 67890453 | I202: 67890453 | K202: juancarlos@gmail.com | O202: 46026 | S202: 9-139-25 | T202: MASIVO | U202: NPN | V202: =_xlfn.XLOOKUP(UTILIZADAS[[#This Row],[Contacto1]],Tabla2[phone_number_dialed],Tabla2[status_name],,0) -> Buzon de voz
... A243: Cobros Abril Canal Fijo | B243: Alan Yeison Castillo Ruiz | C243: 358358400000 | D243: Cobros Abril Canal Fijo 2 meses a NPN | E243: =+_xlfn.XLOOKUP(UTILIZADAS[[#This Row],[Numero_Cuenta]],'[1]cobros_marzo (fijo)'!$B:$B,'[1]cobros_marzo (fijo)'!$D:$D,,0) -> 0 | G243: 46026 | H243: 69799498 | I243: 69799498 | K243: josekeran@gmail.com | O243: 46026 | S243: 8-912-1027 | T243: MASIVO | U243: NPN | V243: =_xlfn.XLOOKUP(UTILIZADAS[[#This Row],[Contacto1]],Tabla2[phone_number_dialed],Tabla2[status_name],,0) -> #N/A
A244: Cobros Abril Canal Fijo | B244: Yenifer Michelle ruiz Duarte | C244: 352358100000 | D244: Cobros Abril Canal Fijo 2 meses a NPN | E244: =+_xlfn.XLOOKUP(UTILIZADAS[[#This Row],[Numero_Cuenta]],'[1]cobros_marzo (fijo)'!$B:$B,'[1]cobros_marzo (fijo)'!$D:$D,,0) -> 0 | G244: 46026 | H244: 64178091 | I244: 64178091 | K244: ruizyenifer905@gmail.com | O244: 46026 | S244: 9762438 | T244: MASIVO | U244: NPN | V244: =_xlfn.XLOOKUP(UTILIZADAS[[#This Row],[Contacto1]],Tabla2[phone_number_dialed],Tabla2[status_name],,0) -> #N/A
A245: Cobros Abril Canal Fijo | B245: Isidra Méndez barsallo | C245: 354359510000 | D245: Cobros Abril Canal Fijo 2 meses a NPN | E245: =+_xlfn.XLOOKUP(UTILIZADAS[[#This Row],[Numero_Cuenta]],'[1]cobros_marzo (fijo)'!$B:$B,'[1]cobros_marzo (fijo)'!$D:$D,,0) -> 0 | G245: 46026 | H245: 66641321 | I245: 66641321 | K245: mendeznba13@gmail.com | O245: 46026 | S245: 9-66-513 | T245: MASIVO | U245: NPN | V245: =_xlfn.XLOOKUP(UTILIZADAS[[#This Row],[Contacto1]],Tabla2[phone_number_dialed],Tabla2[status_name],,0) -> #N/A
A246: Cobros Abril Canal Fijo | B246: Irving Virgilio Perez Madrid | C246: 352343340000 | D246: Cobros Abril Canal Fijo 2 meses a NPN | E246: =+_xlfn.XLOOKUP(UTILIZADAS[[#This Row],[Numero_Cuenta]],'[1]cobros_marzo (fijo)'!$B:$B,'[1]cobros_marzo (fijo)'!$D:$D,,0) -> 0 | G246: 46026 | H246: 68010681 | I246: 68010681 | K246: Vergararosaalicia@gmail.com | O246: 46026 | S246: 8-870-2359 | T246: MASIVO | U246: NPN | V246: =_xlfn.XLOOKUP(UTILIZADAS[[#This Row],[Contacto1]],Tabla2[phone_number_dialed],Tabla2[status_name],,0) -> #N/A
A247: Cobros Abril Canal Fijo | B247: William Solis Clement | C247: 354360650000 | D247: Cobros Abril Canal Fijo 2 meses a NPN | E247: =+_xlfn.XLOOKUP(UTILIZADAS[[#This Row],[Numero_Cuenta]],'[1]cobros_marzo (fijo)'!$B:$B,'[1]cobros_marzo (fijo)'!$D:$D,,0) -> 0 | G247: 46026 | H247: 61016174 | I247: 61016174 | K247: idilciaortega049@gmail.com | O247: 46026 | S247: 10-32-500 | T247: MASIVO | U247: NPN | V247: =_xlfn.XLOOKUP(UTILIZADAS[[#This Row],[Contacto1]],Tabla2[phone_number_dialed],Tabla2[status_name],,0) -> #N/A
A248: Cobros Abril Canal Fijo | B248: Mavelyn palacio | C248: 357334100000 | D248: Cobros Abril Canal Fijo 2 meses a NPN | E248: =+_xlfn.XLOOKUP(UTILIZADAS[[#This Row],[Numero_Cuenta]],'[1]cobros_marzo (fijo)'!$B:$B,'[1]cobros_marzo (fijo)'!$D:$D,,0) -> 0 | G248: 46026 | H248: 66839768 | I248: 66839768 | K248: Palaciomabelin346@gmail.com | O248: 46026 | S248: 5-716-2130 | T248: MASIVO | U248: NPN | V248: =_xlfn.XLOOKUP(UTILIZADAS[[#This Row],[Contacto1]],Tabla2[phone_number_dialed],Tabla2[status_name],,0) -> #N/A
A249: Cobros Abril Canal Fijo | B249: Nasaret masckill Tenorio | C249: 358355590000 | D249: Cobros Abril Canal Fijo 2 meses a NPN | E249: =+_xlfn.XLOOKUP(UTILIZADAS[[#This Row],[Numero_Cuenta]],'[1]cobros_marzo (fijo)'!$B:$B,'[1]cobros_marzo (fijo)'!$D:$D,,0) -> 0 | G249: 46026 | H249: 63321872 | I249: 63321872 | K249: tenorio.06@outlook.com | O249: 46026 | S249: 9-749-486 | T249: MASIVO | U249: NPN | V249: =_xlfn.XLOOKUP(UTILIZADAS[[#This Row],[Contacto1]],Tabla2[phone_number_dialed],Tabla2[status_name],,0) -> No Answer AutoDial
A250: Cobros Abril Canal Fijo | B250: Julieth Ortega | C250: 357082970000 | D250: Cobros Abril Canal Fijo 2 meses a NPN | E250: =+_xlfn.XLOOKUP(UTILIZADAS[[#This Row],[Numero_Cuenta]],'[1]cobros_marzo (fijo)'!$B:$B,'[1]cobros_marzo (fijo)'!$D:$D,,0) -> 0 | G250: 46026 | H250: 67030325 | I250: 67030325 | K250: juliethdelrosario@gmail.com | O250: 46026 | S250: 8-927-546 | T250: MASIVO | U250: NPN | V250: =_xlfn.XLOOKUP(UTILIZADAS[[#This Row],[Contacto1]],Tabla2[phone_number_dialed],Tabla2[status_name],,0) -> #N/A
A251: Cobros Abril Canal Fijo | B251: Angel lorenzo | C251: 354358380000 | D251: Cobros Abril Canal Fijo 2 meses a NPN | E251: =+_xlfn.XLOOKUP(UTILIZADAS[[#This Row],[Numero_Cuenta]],'[1]cobros_marzo (fijo)'!$B:$B,'[1]cobros_marzo (fijo)'!$D:$D,,0) -> 0 | G251: 46026 | H251: 68906543 | I251: 68906543 | K251: tribaldoszadkiel88@gmail.com | O251: 46026 | S251: 2-162-764 | T251: MASIVO | U251: NPN | V251: =_xlfn.XLOOKUP(UTILIZADAS[[#This Row],[Contacto1]],Tabla2[phone_number_dialed],Tabla2[status_name],,0) -> Agent Not Available
A252: Cobros Abril Canal Fijo | B252: Eduardo Abel Iturralde Duarte | C252: 353360370000 | D252: Cobros Abril Canal Fijo 2 meses a NPN | E252: =+_xlfn.XLOOKUP(UTILIZADAS[[#This Row],[Numero_Cuenta]],'[1]cobros_marzo (fijo)'!$B:$B,'[1]cobros_marzo (fijo)'!$D:$D,,0) -> 0 | G252: 46026 | H252: 65880586 | I252: 65880586 | K252: iturraldee053@gmail.com | O252: 46026 | S252: 8-444-381 | T252: SOHO | U252: NPN | V252: =_xlfn.XLOOKUP(UTILIZADAS[[#This Row],[Contacto1]],Tabla2[phone_number_dialed],Tabla2[status_name],,0) -> Agent Not Available
A253: Cobros Abril Canal Fijo | B253: Maryerlin Ballesteros | C253: 352351310000 | D253: Cobros Abril Canal Fijo 2 meses a NPN | E253: =+_xlfn.XLOOKUP(UTILIZADAS[[#This Row],[Numero_Cuenta]],'[1]cobros_marzo (fijo)'!$B:$B,'[1]cobros_marzo (fijo)'!$D:$D,,0) -> 0 | G253: 46026 | H253: 68981704 | I253: 68981704 | K253: maryerlingb@gmail.com | O253: 46026 | S253: 2-731-577 | T253: MASIVO | U253: NPN | V253: =_xlfn.XLOOKUP(UTILIZADAS[[#This Row],[Contacto1]],Tabla2[phone_number_dialed],Tabla2[status_name],,0) -> #N/A
A254: Cobros Abril Canal Fijo | B254: Mariela Atencio barria de Aparicio | C254: 354278250000 | D254: Cobros Abril Canal Fijo 2 meses a NPN | E254: =+_xlfn.XLOOKUP(UTILIZADAS[[#This Row],[Numero_Cuenta]],'[1]cobros_marzo (fijo)'!$B:$B,'[1]cobros_marzo (fijo)'!$D:$D,,0) -> 0 | G254: 46026 | H254: 61598243 | I254: 61598243 | K254: Lupiita33343@gmail.com | O254: 46026 | S254: 6-701-40 | T254: MASIVO | U254: NPN | V254: =_xlfn.XLOOKUP(UTILIZADAS[[#This Row],[Contacto1]],Tabla2[phone_number_dialed],Tabla2[status_name],,0) -> Auto busy
A255: Cobros Abril Canal Fijo | B255: Mariela Atencio barria de Aparicio | C255: 354278250000 | D255: Cobros Abril Canal Fijo 2 meses a NPN | E255: =+_xlfn.XLOOKUP(UTILIZADAS[[#This Row],[Numero_Cuenta]],'[1]cobros_marzo (fijo)'!$B:$B,'[1]cobros_marzo (fijo)'!$D:$D,,0) -> 0 | G255: 46026 | H255: 61598243 | I255: 61598243 | K255: Lupiita33344@gmail.com | O255: 46026 | S255: 6-701-40 | T255: MASIVO | U255: NPN | V255: =_xlfn.XLOOKUP(UTILIZADAS[[#This Row],[Contacto1]],Tabla2[phone_number_dialed],Tabla2[status_name],,0) -> Auto busy
A256: Cobros Abril Canal Fijo | B256: Juan navas | C256: 352359920000 | D256: Cobros Abril Canal Fijo 2 meses a NPN | E256: =+_xlfn.XLOOKUP(UTILIZADAS[[#This Row],[Numero_Cuenta]],'[1]cobros_marzo (fijo)'!$B:$B,'[1]cobros_marzo (fijo)'!$D:$D,,0) -> 0 | G256: 46026 | H256: 67890543 | I256: 67890543 | K256: Juannavas@gmail.com | O256: 46026 | S256: 2-163-1211 | T256: MASIVO | U256: NPN | V256: =_xlfn.XLOOKUP(UTILIZADAS[[#This Row],[Contacto1]],Tabla2[phone_number_dialed],Tabla2[status_name],,0) -> Buzon de voz
... A315: Cobros Abril Canal Fijo | B315: Lurelys yanisel Sánchez Alee | C315: 357357890000 | D315: Cobros Abril Canal Fijo 2 meses a NPN | E315: =+_xlfn.XLOOKUP(UTILIZADAS[[#This Row],[Numero_Cuenta]],'[1]cobros_marzo (fijo)'!$B:$B,'[1]cobros_marzo (fijo)'!$D:$D,,0) -> 0 | G315: 46026 | H315: 63030594 | I315: 63030594 | K315: Franklin.abraham.43@gmail.com | O315: 46026 | S315: 8-894-2244 | T315: MASIVO | U315: NPN | V315: =_xlfn.XLOOKUP(UTILIZADAS[[#This Row],[Contacto1]],Tabla2[phone_number_dialed],Tabla2[status_name],,0) -> Agent Not Available
A316: Cobros Abril Canal Fijo | B316: Juan Montes | C316: 357369770000 | D316: Cobros Abril Canal Fijo 2 meses a NPN | E316: =+_xlfn.XLOOKUP(UTILIZADAS[[#This Row],[Numero_Cuenta]],'[1]cobros_marzo (fijo)'!$B:$B,'[1]cobros_marzo (fijo)'!$D:$D,,0) -> 0 | G316: 46026 | H316: 67248799 | I316: 67248799 | K316: juanmontesgallardo007@gmail.com | O316: 46026 | S316: 72172508 | T316: MASIVO | U316: NPN | V316: =_xlfn.XLOOKUP(UTILIZADAS[[#This Row],[Contacto1]],Tabla2[phone_number_dialed],Tabla2[status_name],,0) -> Auto busy
A317: Cobros Abril Canal Fijo | B317: Victor manuel lopez Velasquez | C317: 351363700000 | D317: Cobros Abril Canal Fijo 2 meses a NPN | E317: =+_xlfn.XLOOKUP(UTILIZADAS[[#This Row],[Numero_Cuenta]],'[1]cobros_marzo (fijo)'!$B:$B,'[1]cobros_marzo (fijo)'!$D:$D,,0) -> 0 | G317: 46026 | H317: 67895566 | I317: 67895566 | K317: Vmanuellopez608@gmai.com | O317: 46026 | S317: C03481288 | T317: MASIVO | U317: NPN | V317: =_xlfn.XLOOKUP(UTILIZADAS[[#This Row],[Contacto1]],Tabla2[phone_number_dialed],Tabla2[status_name],,0) -> Agent Not Available
A318: Cobros Abril Canal Fijo | B318: Ruth soto | C318: 352369680000 | D318: Cobros Abril Canal Fijo 2 meses a NPN | E318: =+_xlfn.XLOOKUP(UTILIZADAS[[#This Row],[Numero_Cuenta]],'[1]cobros_marzo (fijo)'!$B:$B,'[1]cobros_marzo (fijo)'!$D:$D,,0) -> 0 | G318: 46026 | H318: 67890543 | I318: 67890543 | K318: juancarlos@gmail.com | O318: 46026 | S318: 8-795-1362 | T318: MASIVO | U318: NPN | V318: =_xlfn.XLOOKUP(UTILIZADAS[[#This Row],[Contacto1]],Tabla2[phone_number_dialed],Tabla2[status_name],,0) -> Buzon de voz
A319: Cobros Abril Canal Fijo | B319: Sugey Gomez | C319: 278068620000 | D319: Cobros Abril Canal Fijo 2 meses a NPN | E319: =+_xlfn.XLOOKUP(UTILIZADAS[[#This Row],[Numero_Cuenta]],'[1]cobros_marzo (fijo)'!$B:$B,'[1]cobros_marzo (fijo)'!$D:$D,,0) -> 0 | G319: 46026 | H319: 62663429 | I319: 62663429 | K319: sugeygomez87@gmail.com | O319: 46026 | S319: 8-806-530 | T319: DIGITAL | U319: NPN | V319: =_xlfn.XLOOKUP(UTILIZADAS[[#This Row],[Contacto1]],Tabla2[phone_number_dialed],Tabla2[status_name],,0) -> Agent Not Available
A320: Cobros Abril Canal Fijo | B320: CLARK STEVE MEDINA GRANADOS | C320: 354361130000 | D320: Cobros Abril Canal Fijo 2 meses a NPN | E320: =+_xlfn.XLOOKUP(UTILIZADAS[[#This Row],[Numero_Cuenta]],'[1]cobros_marzo (fijo)'!$B:$B,'[1]cobros_marzo (fijo)'!$D:$D,,0) -> 0 | G320: 46026 | H320: 63580364 | I320: 63580364 | K320: Clarkstivenmedina@gmail.com | O320: 46026 | S320: PE-12-562 | T320: MASIVO | U320: NPN | V320: =_xlfn.XLOOKUP(UTILIZADAS[[#This Row],[Contacto1]],Tabla2[phone_number_dialed],Tabla2[status_name],,0) -> #N/A
A321: Cobros Abril Canal Fijo | B321: Pablo Torres osorio | C321: 353363240000 | D321: Cobros Abril Canal Fijo 2 meses a NPN | E321: =+_xlfn.XLOOKUP(UTILIZADAS[[#This Row],[Numero_Cuenta]],'[1]cobros_marzo (fijo)'!$B:$B,'[1]cobros_marzo (fijo)'!$D:$D,,0) -> 0 | G321: 46026 | H321: 68451482 | I321: 68451482 | K321: Piinedaezequiel23@gmail.com | O321: 46026 | S321: 8-294-118 | T321: MASIVO | U321: NPN | V321: =_xlfn.XLOOKUP(UTILIZADAS[[#This Row],[Contacto1]],Tabla2[phone_number_dialed],Tabla2[status_name],,0) -> Cuenta cesada
A322: Cobros Abril Canal Fijo | B322: Raúl Antonio West Linares | C322: 353369960000 | D322: Cobros Abril Canal Fijo 2 meses a NPN | E322: =+_xlfn.XLOOKUP(UTILIZADAS[[#This Row],[Numero_Cuenta]],'[1]cobros_marzo (fijo)'!$B:$B,'[1]cobros_marzo (fijo)'!$D:$D,,0) -> 0 | G322: 46026 | H322: 68061435 | I322: 68061435 | K322: wyirely@gmail.com | O322: 46026 | S322: 8-1062-670 | T322: MASIVO | U322: NPN | V322: =_xlfn.XLOOKUP(UTILIZADAS[[#This Row],[Contacto1]],Tabla2[phone_number_dialed],Tabla2[status_name],,0) -> Agent Not Available
A323: Cobros Abril Canal Fijo | B323: MARTINA GONZALEZ ARROCHA | C323: 354371690000 | D323: Cobros Abril Canal Fijo 2 meses a NPN | E323: =+_xlfn.XLOOKUP(UTILIZADAS[[#This Row],[Numero_Cuenta]],'[1]cobros_marzo (fijo)'!$B:$B,'[1]cobros_marzo (fijo)'!$D:$D,,0) -> 0 | G323: 46026 | H323: 65294266 | I323: 65294266 | K323: Martina02@gmail.com | O323: 46026 | S323: 2-722-1424 | T323: MASIVO | U323: NPN | V323: =_xlfn.XLOOKUP(UTILIZADAS[[#This Row],[Contacto1]],Tabla2[phone_number_dialed],Tabla2[status_name],,0) -> Buzon de voz
A324: Cobros Abril Canal Fijo | B324: ROBINSON RIBET RODRIGUEZ DIAZ | C324: 359371560000 | D324: Cobros Abril Canal Fijo 2 meses a NPN | E324: =+_xlfn.XLOOKUP(UTILIZADAS[[#This Row],[Numero_Cuenta]],'[1]cobros_marzo (fijo)'!$B:$B,'[1]cobros_marzo (fijo)'!$D:$D,,0) -> 0 | G324: 46026 | H324: 64283894 | I324: 64283894 | K324: robinrodri73@gmail.com | O324: 46026 | S324: 6-81-609 | T324: MASIVO | U324: NPN | V324: =_xlfn.XLOOKUP(UTILIZADAS[[#This Row],[Contacto1]],Tabla2[phone_number_dialed],Tabla2[status_name],,0) -> Agent Not Available
A325: Cobros Abril Canal Fijo | B325: ERICK BRUCE | C325: 214048580000 | D325: Cobros Abril Canal Fijo 2 meses a NPN | E325: =+_xlfn.XLOOKUP(UTILIZADAS[[#This Row],[Numero_Cuenta]],'[1]cobros_marzo (fijo)'!$B:$B,'[1]cobros_marzo (fijo)'!$D:$D,,0) -> 0 | G325: 46026 | H325: 62254511 | I325: 62254511 | K325: ebruce807@gmail.com | O325: 46026 | S325: 8-814-663 | T325: DIGITAL | U325: NPN | V325: =_xlfn.XLOOKUP(UTILIZADAS[[#This Row],[Contacto1]],Tabla2[phone_number_dialed],Tabla2[status_name],,0) -> Auto busy
A326: Cobros Abril Canal Fijo | B326: MARTINA GONZALEZ ARROCHA | C326: 354371690000 | D326: Cobros Abril Canal Fijo 2 meses a NPN | E326: =+_xlfn.XLOOKUP(UTILIZADAS[[#This Row],[Numero_Cuenta]],'[1]cobros_marzo (fijo)'!$B:$B,'[1]cobros_marzo (fijo)'!$D:$D,,0) -> 0 | G326: 46026 | H326: 65294266 | I326: 65294266 | K326: marrocha@gmail.com | O326: 46026 | S326: 2-722-1424 | T326: MASIVO | U326: NPN | V326: =_xlfn.XLOOKUP(UTILIZADAS[[#This Row],[Contacto1]],Tabla2[phone_number_dialed],Tabla2[status_name],,0) -> Buzon de voz
A327: Cobros Abril Canal Fijo | B327: Cristina Shannin Mendez Mancilla | C327: 355369030000 | D327: Cobros Abril Canal Fijo 2 meses a NPN | E327: =+_xlfn.XLOOKUP(UTILIZADAS[[#This Row],[Numero_Cuenta]],'[1]cobros_marzo (fijo)'!$B:$B,'[1]cobros_marzo (fijo)'!$D:$D,,0) -> 0 | G327: 46026 | H327: 60450970 | I327: 60450970 | K327: kellijannell1118@hotmail.com | O327: 46026 | S327: 8-1051-1434 | T327: MASIVO | U327: NPN | V327: =_xlfn.XLOOKUP(UTILIZADAS[[#This Row],[Contacto1]],Tabla2[phone_number_dialed],Tabla2[status_name],,0) -> #N/A
A328: Cobros Abril Canal Fijo | B328: Fermin Eduardo Chong | C328: 352369050000 | D328: Cobros Abril Canal Fijo 2 meses a NPN | E328: =+_xlfn.XLOOKUP(UTILIZADAS[[#This Row],[Numero_Cuenta]],'[1]cobros_marzo (fijo)'!$B:$B,'[1]cobros_marzo (fijo)'!$D:$D,,0) -> 0 | G328: 46026 | H328: 66507107 | I328: 66507107 | K328: eduarchong@gmail.com | O328: 46026 | S328: 8-748-558 | T328: MASIVO | U328: NPN | V328: =_xlfn.XLOOKUP(UTILIZADAS[[#This Row],[Contacto1]],Tabla2[phone_number_dialed],Tabla2[status_name],,0) -> Cuenta cesada
... A458: Cobros Abril Canal Fijo | B458: Addys ramof | C458: 352385470000 | D458: Cobros Abril Canal Fijo 2 meses a NPN | E458: =+_xlfn.XLOOKUP(UTILIZADAS[[#This Row],[Numero_Cuenta]],'[1]cobros_marzo (fijo)'!$B:$B,'[1]cobros_marzo (fijo)'!$D:$D,,0) -> 0 | G458: 46026 | H458: 68905432 | I458: 68905432 | K458: juancarlos@gmail.com | O458: 46026 | S458: 8-916-491 | T458: MASIVO | U458: NPN | V458: =_xlfn.XLOOKUP(UTILIZADAS[[#This Row],[Contacto1]],Tabla2[phone_number_dialed],Tabla2[status_name],,0) -> Agent Not Available
A459: Cobros Abril Canal Fijo | B459: Alex Jonel Bracho Manzanero | C459: 354386270000 | D459: Cobros Abril Canal Fijo 2 meses a NPN | E459: =+_xlfn.XLOOKUP(UTILIZADAS[[#This Row],[Numero_Cuenta]],'[1]cobros_marzo (fijo)'!$B:$B,'[1]cobros_marzo (fijo)'!$D:$D,,0) -> 0 | G459: 46026 | H459: 68745282 | I459: 68745282 | K459: 000fdiaz@gmail.com | O459: 46026 | S459: 118866555 | T459: MASIVO | U459: NPN | V459: =_xlfn.XLOOKUP(UTILIZADAS[[#This Row],[Contacto1]],Tabla2[phone_number_dialed],Tabla2[status_name],,0) -> Buzon de voz
A460: Cobros Abril Canal Fijo | B460: Kibler herrera | C460: 359385400000 | D460: Cobros Abril Canal Fijo 2 meses a NPN | E460: =+_xlfn.XLOOKUP(UTILIZADAS[[#This Row],[Numero_Cuenta]],'[1]cobros_marzo (fijo)'!$B:$B,'[1]cobros_marzo (fijo)'!$D:$D,,0) -> 0 | G460: 46026 | H460: 64098122 | I460: 64098122 | K460: Benitezandrelina72@gmail.com | O460: 46026 | S460: 10-720-238 | T460: MASIVO | U460: NPN | V460: =_xlfn.XLOOKUP(UTILIZADAS[[#This Row],[Contacto1]],Tabla2[phone_number_dialed],Tabla2[status_name],,0) -> Agent Not Available
A461: Cobros Abril Canal Fijo | B461: JESUS MARIO RESTREPO CHAVARRIAGA | C461: 353383450000 | D461: Cobros Abril Canal Fijo 2 meses a NPN | E461: =+_xlfn.XLOOKUP(UTILIZADAS[[#This Row],[Numero_Cuenta]],'[1]cobros_marzo (fijo)'!$B:$B,'[1]cobros_marzo (fijo)'!$D:$D,,0) -> 0 | G461: 46026 | H461: 65311544 | I461: 65311544 | K461: Bcj7822panama@gmail.com | O461: 46026 | S461: E-8-225177 | T461: DIGITAL | U461: NPN | V461: =_xlfn.XLOOKUP(UTILIZADAS[[#This Row],[Contacto1]],Tabla2[phone_number_dialed],Tabla2[status_name],,0) -> #N/A
A462: Cobros Abril Canal Fijo | B462: JOE DANIELS SMITH ATENCIO | C462: 353385560000 | D462: Cobros Abril Canal Fijo 2 meses a NPN | E462: =+_xlfn.XLOOKUP(UTILIZADAS[[#This Row],[Numero_Cuenta]],'[1]cobros_marzo (fijo)'!$B:$B,'[1]cobros_marzo (fijo)'!$D:$D,,0) -> 0 | G462: 46026 | H462: 63407637 | I462: 63407637 | K462: joe0197smith@gmail.com | O462: 46026 | S462: 4-790-639 | T462: MASIVO | U462: NPN | V462: =_xlfn.XLOOKUP(UTILIZADAS[[#This Row],[Contacto1]],Tabla2[phone_number_dialed],Tabla2[status_name],,0) -> #N/A
A463: Cobros Abril Canal Fijo | B463: YIVIANA YIVELIS ESQUINA PEREZ | C463: 352385790000 | D463: Cobros Abril Canal Fijo 2 meses a NPN | E463: =+_xlfn.XLOOKUP(UTILIZADAS[[#This Row],[Numero_Cuenta]],'[1]cobros_marzo (fijo)'!$B:$B,'[1]cobros_marzo (fijo)'!$D:$D,,0) -> 0 | G463: 46026 | H463: 65599146 | I463: 65599146 | K463: Esquinayiviani@gmail.com | O463: 46026 | S463: 3-737-1542 | T463: MASIVO | U463: NPN | V463: =_xlfn.XLOOKUP(UTILIZADAS[[#This Row],[Contacto1]],Tabla2[phone_number_dialed],Tabla2[status_name],,0) -> #N/A
A464: Cobros Abril Canal Fijo | B464: Javier González Brown | C464: 219058320000 | D464: Cobros Abril Canal Fijo 2 meses a NPN | E464: =+_xlfn.XLOOKUP(UTILIZADAS[[#This Row],[Numero_Cuenta]],'[1]cobros_marzo (fijo)'!$B:$B,'[1]cobros_marzo (fijo)'!$D:$D,,0) -> 0 | G464: 46026 | H464: 65695107 | I464: 65695107 | K464: Javier009@gmail.com | O464: 46026 | S464: 3-710-1453 | T464: MASIVO | U464: NPN | V464: =_xlfn.XLOOKUP(UTILIZADAS[[#This Row],[Contacto1]],Tabla2[phone_number_dialed],Tabla2[status_name],,0) -> Agent Not Available
A465: Cobros Abril Canal Fijo | B465: LUIS ALFREDO GALLARDO REID | C465: 352384910000 | D465: Cobros Abril Canal Fijo 2 meses a NPN | E465: =+_xlfn.XLOOKUP(UTILIZADAS[[#This Row],[Numero_Cuenta]],'[1]cobros_marzo (fijo)'!$B:$B,'[1]cobros_marzo (fijo)'!$D:$D,,0) -> 0 | G465: 46026 | H465: 62929057 | I465: 62929057 | K465: christopher27marceline@gmail.com | O465: 46026 | S465: 8-960-2125 | T465: MASIVO | U465: NPN | V465: =_xlfn.XLOOKUP(UTILIZADAS[[#This Row],[Contacto1]],Tabla2[phone_number_dialed],Tabla2[status_name],,0) -> Auto busy
A466: Cobros Abril Canal Fijo | B466: ROSIBEL OSIRIS ALFREDO MOLINO | C466: 355385090000 | D466: Cobros Abril Canal Fijo 2 meses a NPN | E466: =+_xlfn.XLOOKUP(UTILIZADAS[[#This Row],[Numero_Cuenta]],'[1]cobros_marzo (fijo)'!$B:$B,'[1]cobros_marzo (fijo)'!$D:$D,,0) -> 0 | G466: 46026 | H466: 66838567 | I466: 66838567 | K466: rosibelosiris1993@gmail.com | O466: 46026 | S466: 1-732-2281 | T466: MASIVO | U466: NPN | V466: =_xlfn.XLOOKUP(UTILIZADAS[[#This Row],[Contacto1]],Tabla2[phone_number_dialed],Tabla2[status_name],,0) -> Agent Not Available
A467: Cobros Abril Canal Fijo | B467: Ixia ixania Samudio Perez | C467: 297038390000 | D467: Cobros Abril Canal Fijo 2 meses a NPN | E467: =+_xlfn.XLOOKUP(UTILIZADAS[[#This Row],[Numero_Cuenta]],'[1]cobros_marzo (fijo)'!$B:$B,'[1]cobros_marzo (fijo)'!$D:$D,,0) -> 0 | G467: 46026 | H467: 66030778 | I467: 66030778 | K467: Samudioixa@gmail.com | O467: 46026 | S467: 4-768-2366 | T467: MASIVO | U467: NPN | V467: =_xlfn.XLOOKUP(UTILIZADAS[[#This Row],[Contacto1]],Tabla2[phone_number_dialed],Tabla2[status_name],,0) -> Call Back
A468: Cobros Abril Canal Fijo | B468: Javier Rodolfo Carpintero Quintero | C468: 355386550000 | D468: Cobros Abril Canal Fijo 2 meses a NPN | E468: =+_xlfn.XLOOKUP(UTILIZADAS[[#This Row],[Numero_Cuenta]],'[1]cobros_marzo (fijo)'!$B:$B,'[1]cobros_marzo (fijo)'!$D:$D,,0) -> 0 | G468: 46026 | H468: 66680977 | I468: 66680977 | K468: carpinterojavier92@gmail.com | O468: 46026 | S468: 6-728-2234 | T468: MASIVO | U468: NPN | V468: =_xlfn.XLOOKUP(UTILIZADAS[[#This Row],[Contacto1]],Tabla2[phone_number_dialed],Tabla2[status_name],,0) -> Cuenta cesada
A469: Cobros Abril Canal Fijo | B469: DANIEL ALEXIS BATISTA DELGADO | C469: 359384340000 | D469: Cobros Abril Canal Fijo 2 meses a NPN | E469: =+_xlfn.XLOOKUP(UTILIZADAS[[#This Row],[Numero_Cuenta]],'[1]cobros_marzo (fijo)'!$B:$B,'[1]cobros_marzo (fijo)'!$D:$D,,0) -> 0 | G469: 46026 | H469: 67990181 | I469: 67990181 | K469: gabrielareyes04@gmail.com | O469: 46026 | S469: 8-809-1503 | T469: MASIVO | U469: NPN | V469: =_xlfn.XLOOKUP(UTILIZADAS[[#This Row],[Contacto1]],Tabla2[phone_number_dialed],Tabla2[status_name],,0) -> Agent Not Available
A470: Cobros Abril Canal Fijo | B470: Daniel Yoel Mosquera | C470: 352381260000 | D470: Cobros Abril Canal Fijo 2 meses a NPN | E470: =+_xlfn.XLOOKUP(UTILIZADAS[[#This Row],[Numero_Cuenta]],'[1]cobros_marzo (fijo)'!$B:$B,'[1]cobros_marzo (fijo)'!$D:$D,,0) -> 0 | G470: 46026 | H470: 62876593 | I470: 62876593 | K470: danielmosquera@gmail.com | O470: 46026 | S470: 8-511-2 DV 10 | T470: SOHO | U470: NPN | V470: =_xlfn.XLOOKUP(UTILIZADAS[[#This Row],[Contacto1]],Tabla2[phone_number_dialed],Tabla2[status_name],,0) -> #N/A
A471: Cobros Abril Canal Fijo | B471: Ladilla paredes barsallo | C471: 354384850000 | D471: Cobros Abril Canal Fijo 2 meses a NPN | E471: =+_xlfn.XLOOKUP(UTILIZADAS[[#This Row],[Numero_Cuenta]],'[1]cobros_marzo (fijo)'!$B:$B,'[1]cobros_marzo (fijo)'!$D:$D,,0) -> 0 | G471: 46026 | H471: 64624750 | I471: 64624750 | K471: Cleinparedes@gmail.com | O471: 46026 | S471: 10-709-1872 | T471: MASIVO | U471: NPN | V471: =_xlfn.XLOOKUP(UTILIZADAS[[#This Row],[Contacto1]],Tabla2[phone_number_dialed],Tabla2[status_name],,0) -> Agent Not Available
... A518: Cobros Abril Canal Fijo | B518: Pedro Chanel Guerrero Ortega | C518: 372005030000 | D518: Cobros Abril Canal Fijo 2 meses a NPN | E518: =+_xlfn.XLOOKUP(UTILIZADAS[[#This Row],[Numero_Cuenta]],'[1]cobros_marzo (fijo)'!$B:$B,'[1]cobros_marzo (fijo)'!$D:$D,,0) -> 0 | G518: 46026 | H518: 65510120 | I518: 65510120 | K518: pitergm31@gmail.com | O518: 46026 | S518: CÃ©dula | T518: SOHO | U518: NPN | V518: =_xlfn.XLOOKUP(UTILIZADAS[[#This Row],[Contacto1]],Tabla2[phone_number_dialed],Tabla2[status_name],,0) -> Agent Not Available
A519: Cobros Abril Canal Fijo | B519: JOSE JESUS BORREGALES ABREU | C519: 363005990000 | D519: Cobros Abril Canal Fijo 2 meses a NPN | E519: =+_xlfn.XLOOKUP(UTILIZADAS[[#This Row],[Numero_Cuenta]],'[1]cobros_marzo (fijo)'!$B:$B,'[1]cobros_marzo (fijo)'!$D:$D,,0) -> 0 | G519: 46026 | H519: 69082411 | I519: 69082411 | K519: jesusabreu0235@gmail.com | O519: 46026 | S519: 104726581 | T519: DIGITAL | U519: NPN | V519: =_xlfn.XLOOKUP(UTILIZADAS[[#This Row],[Contacto1]],Tabla2[phone_number_dialed],Tabla2[status_name],,0) -> Agent Not Available
A520: Cobros Abril Canal Fijo | B520: Genessis Mayelis Saldaña Pineda | C520: 285057050000 | D520: Cobros Abril Canal Fijo 2 meses a NPN | E520: =+_xlfn.XLOOKUP(UTILIZADAS[[#This Row],[Numero_Cuenta]],'[1]cobros_marzo (fijo)'!$B:$B,'[1]cobros_marzo (fijo)'!$D:$D,,0) -> 0 | G520: 46026 | H520: 65149033 | I520: 65149033 | K520: genessissaldana@gmail.com | O520: 46026 | S520: 4-769-2248 | T520: MASIVO | U520: NPN | V520: =_xlfn.XLOOKUP(UTILIZADAS[[#This Row],[Contacto1]],Tabla2[phone_number_dialed],Tabla2[status_name],,0) -> Agent Not Available
A521: Cobros Abril Canal Fijo | B521: MARIA CATALINA HERNANDEZ PINO | C521: 365006510000 | D521: Cobros Abril Canal Fijo 2 meses a NPN | E521: =+_xlfn.XLOOKUP(UTILIZADAS[[#This Row],[Numero_Cuenta]],'[1]cobros_marzo (fijo)'!$B:$B,'[1]cobros_marzo (fijo)'!$D:$D,,0) -> 0 | G521: 46026 | H521: 66831414 | I521: 66831414 | K521: friopino@gmail.com | O521: 46026 | S521: 9-82-1944 | T521: MASIVO | U521: NPN | V521: =_xlfn.XLOOKUP(UTILIZADAS[[#This Row],[Contacto1]],Tabla2[phone_number_dialed],Tabla2[status_name],,0) -> Agent Not Available
A522: Cobros Abril Canal Fijo | B522: Argelis Vanegas | C522: 355001270000 | D522: Cobros Abril Canal Fijo 2 meses a NPN | E522: =+_xlfn.XLOOKUP(UTILIZADAS[[#This Row],[Numero_Cuenta]],'[1]cobros_marzo (fijo)'!$B:$B,'[1]cobros_marzo (fijo)'!$D:$D,,0) -> 0 | G522: 46026 | H522: 69907641 | I522: 69907641 | K522: Tobiicastle@gmail.com | O522: 46026 | S522: 8-994-1586 | T522: MASIVO | U522: NPN | V522: =_xlfn.XLOOKUP(UTILIZADAS[[#This Row],[Contacto1]],Tabla2[phone_number_dialed],Tabla2[status_name],,0) -> No Answer AutoDial
A523: Cobros Abril Canal Fijo | B523: María Marilin Gómez | C523: 364006990000 | D523: Cobros Abril Canal Fijo 2 meses a NPN | E523: =+_xlfn.XLOOKUP(UTILIZADAS[[#This Row],[Numero_Cuenta]],'[1]cobros_marzo (fijo)'!$B:$B,'[1]cobros_marzo (fijo)'!$D:$D,,0) -> 0 | G523: 46026 | H523: 64193122 | I523: 64193122 | K523: mariamarylingomez@gmail.com | O523: 46026 | S523: 8-1056-1162 | T523: MASIVO | U523: NPN | V523: =_xlfn.XLOOKUP(UTILIZADAS[[#This Row],[Contacto1]],Tabla2[phone_number_dialed],Tabla2[status_name],,0) -> #N/A
A524: Cobros Abril Canal Fijo | B524: Sabino González | C524: 361006340000 | D524: Cobros Abril Canal Fijo 2 meses a NPN | E524: =+_xlfn.XLOOKUP(UTILIZADAS[[#This Row],[Numero_Cuenta]],'[1]cobros_marzo (fijo)'!$B:$B,'[1]cobros_marzo (fijo)'!$D:$D,,0) -> 0 | G524: 46026 | H524: 67898031 | I524: 67898031 | K524: SabinoGonzales55@gmail.com | O524: 46026 | S524: 3-79-2494 | T524: MASIVO | U524: NPN | V524: =_xlfn.XLOOKUP(UTILIZADAS[[#This Row],[Contacto1]],Tabla2[phone_number_dialed],Tabla2[status_name],,0) -> Agent Not Available
A525: Cobros Abril Canal Fijo | B525: EZEQUIEL QUINTERO POLONIA | C525: 369008540000 | D525: Cobros Abril Canal Fijo 2 meses a NPN | E525: =+_xlfn.XLOOKUP(UTILIZADAS[[#This Row],[Numero_Cuenta]],'[1]cobros_marzo (fijo)'!$B:$B,'[1]cobros_marzo (fijo)'!$D:$D,,0) -> 0 | G525: 46026 | H525: 65362954 | I525: 65362954 | K525: equinterop38@gmail.com | O525: 46026 | S525: 8-247-924 | T525: MASIVO | U525: NPN | V525: =_xlfn.XLOOKUP(UTILIZADAS[[#This Row],[Contacto1]],Tabla2[phone_number_dialed],Tabla2[status_name],,0) -> Auto busy
A526: Cobros Abril Canal Fijo | B526: Yessica Andrea Panuela Arroyave | C526: 369007690000 | D526: Cobros Abril Canal Fijo 2 meses a NPN | E526: =+_xlfn.XLOOKUP(UTILIZADAS[[#This Row],[Numero_Cuenta]],'[1]cobros_marzo (fijo)'!$B:$B,'[1]cobros_marzo (fijo)'!$D:$D,,0) -> 0 | G526: 46026 | H526: 63573718 | I526: 63573718 | K526: andrearroyave.1989@gmail.com | O526: 46026 | S526: BF006377 | T526: MASIVO | U526: NPN | V526: =_xlfn.XLOOKUP(UTILIZADAS[[#This Row],[Contacto1]],Tabla2[phone_number_dialed],Tabla2[status_name],,0) -> Agent Not Available
A527: Cobros Abril Canal Fijo | B527: FRANCISCA GOMEZ | C527: 366007100000 | D527: Cobros Abril Canal Fijo 2 meses a NPN | E527: =+_xlfn.XLOOKUP(UTILIZADAS[[#This Row],[Numero_Cuenta]],'[1]cobros_marzo (fijo)'!$B:$B,'[1]cobros_marzo (fijo)'!$D:$D,,0) -> 0 | G527: 46026 | H527: 66566488 | I527: 66566488 | K527: Kaisuzeth@gmail.com | O527: 46026 | S527: 4-81-158 | T527: MASIVO | U527: NPN | V527: =_xlfn.XLOOKUP(UTILIZADAS[[#This Row],[Contacto1]],Tabla2[phone_number_dialed],Tabla2[status_name],,0) -> Cuenta cesada
A528: Cobros Abril Canal Fijo | B528: VICTOR DANIEL GARCIAN DE GRACIA | C528: 366007030000 | D528: Cobros Abril Canal Fijo 2 meses a NPN | E528: =+_xlfn.XLOOKUP(UTILIZADAS[[#This Row],[Numero_Cuenta]],'[1]cobros_marzo (fijo)'!$B:$B,'[1]cobros_marzo (fijo)'!$D:$D,,0) -> 0 | G528: 46026 | H528: 69365329 | I528: 69365329 | K528: danygracias0805@gmail.com | O528: 46026 | S528: 8-1003-615 | T528: MASIVO | U528: NPN | V528: =_xlfn.XLOOKUP(UTILIZADAS[[#This Row],[Contacto1]],Tabla2[phone_number_dialed],Tabla2[status_name],,0) -> Agent Not Available
A529: Cobros Abril Canal Fijo | B529: Marta Alicia Beltrán García de Sealy | C529: 364008580000 | D529: Cobros Abril Canal Fijo 2 meses a NPN | E529: =+_xlfn.XLOOKUP(UTILIZADAS[[#This Row],[Numero_Cuenta]],'[1]cobros_marzo (fijo)'!$B:$B,'[1]cobros_marzo (fijo)'!$D:$D,,0) -> 0 | G529: 46026 | H529: 69489822 | I529: 69489822 | K529: alfreditos.507@gmail.com | O529: 46026 | S529: E-8-44624 | T529: MASIVO | U529: NPN | V529: =_xlfn.XLOOKUP(UTILIZADAS[[#This Row],[Contacto1]],Tabla2[phone_number_dialed],Tabla2[status_name],,0) -> Auto busy
A530: Cobros Abril Canal Fijo | B530: Ernesto Lam Velasquez | C530: 346382020000 | D530: Cobros Abril Canal Fijo 2 meses a NPN | E530: =+_xlfn.XLOOKUP(UTILIZADAS[[#This Row],[Numero_Cuenta]],'[1]cobros_marzo (fijo)'!$B:$B,'[1]cobros_marzo (fijo)'!$D:$D,,0) -> 0 | G530: 46026 | H530: 68184307 | I530: 68184307 | K530: Lamernesto120@gmail.com | O530: 46026 | S530: 3-753-110 | T530: MASIVO | U530: NPN | V530: =_xlfn.XLOOKUP(UTILIZADAS[[#This Row],[Contacto1]],Tabla2[phone_number_dialed],Tabla2[status_name],,0) -> Cuenta cesada
A531: Cobros Abril Canal Fijo | B531: Miguel Puello | C531: 363010370000 | D531: Cobros Abril Canal Fijo 2 meses a NPN | E531: =+_xlfn.XLOOKUP(UTILIZADAS[[#This Row],[Numero_Cuenta]],'[1]cobros_marzo (fijo)'!$B:$B,'[1]cobros_marzo (fijo)'!$D:$D,,0) -> 0 | G531: 46026 | H531: 68838441 | I531: 68838441 | K531: mibett0227@gmaim.com | O531: 46026 | S531: BH138232 | T531: MASIVO | U531: NPN | V531: =_xlfn.XLOOKUP(UTILIZADAS[[#This Row],[Contacto1]],Tabla2[phone_number_dialed],Tabla2[status_name],,0) -> Auto busy
... A555: Cobros Abril Canal Fijo | B555: Luis Carlos Quintero Almanza | C555: 303032830000 | D555: Cobros Abril Canal Fijo 2 meses a NPN | E555: =+_xlfn.XLOOKUP(UTILIZADAS[[#This Row],[Numero_Cuenta]],'[1]cobros_marzo (fijo)'!$B:$B,'[1]cobros_marzo (fijo)'!$D:$D,,0) -> 0 | G555: 46026 | H555: 64701986 | I555: 64701986 | K555: carlosquinteroluis17@gmail.com | O555: 46026 | S555: 3-738-1347 | T555: CALL CENTER | U555: NPN | V555: =_xlfn.XLOOKUP(UTILIZADAS[[#This Row],[Contacto1]],Tabla2[phone_number_dialed],Tabla2[status_name],,0) -> Agent Not Available
A556: Cobros Abril Canal Fijo | B556: CESAR ANDRES SUAREZ RODRIGUEZ | C556: 368014210000 | D556: Cobros Abril Canal Fijo 2 meses a NPN | E556: =+_xlfn.XLOOKUP(UTILIZADAS[[#This Row],[Numero_Cuenta]],'[1]cobros_marzo (fijo)'!$B:$B,'[1]cobros_marzo (fijo)'!$D:$D,,0) -> 0 | G556: 46026 | H556: 64883347 | I556: 64883347 | K556: Rachel.carrillo291719@gmail.com | O556: 46026 | S556: 187320623 | T556: MASIVO | U556: NPN | V556: =_xlfn.XLOOKUP(UTILIZADAS[[#This Row],[Contacto1]],Tabla2[phone_number_dialed],Tabla2[status_name],,0) -> Auto busy
A557: Cobros Abril Canal Fijo | B557: Etilcia ernela acostá Martínez | C557: 367012450000 | D557: Cobros Abril Canal Fijo 2 meses a NPN | E557: =+_xlfn.XLOOKUP(UTILIZADAS[[#This Row],[Numero_Cuenta]],'[1]cobros_marzo (fijo)'!$B:$B,'[1]cobros_marzo (fijo)'!$D:$D,,0) -> 0 | G557: 46026 | H557: 64024594 | I557: 64024594 | K557: ranjeliagonzalez2@Gmail.com | O557: 46026 | S557: 10-706-1839 | T557: MASIVO | U557: NPN | V557: =_xlfn.XLOOKUP(UTILIZADAS[[#This Row],[Contacto1]],Tabla2[phone_number_dialed],Tabla2[status_name],,0) -> Cuenta cesada
A558: Cobros Abril Canal Fijo | B558: ALEIDA LINETH RODRIGUEZ DUART | C558: 368011420000 | D558: Cobros Abril Canal Fijo 2 meses a NPN | E558: =+_xlfn.XLOOKUP(UTILIZADAS[[#This Row],[Numero_Cuenta]],'[1]cobros_marzo (fijo)'!$B:$B,'[1]cobros_marzo (fijo)'!$D:$D,,0) -> 0 | G558: 46026 | H558: 68211838 | I558: 68211838 | K558: aleidalineth95@hotmail.com | O558: 46026 | S558: 9-746-1198 | T558: MASIVO | U558: NPN | V558: =_xlfn.XLOOKUP(UTILIZADAS[[#This Row],[Contacto1]],Tabla2[phone_number_dialed],Tabla2[status_name],,0) -> #N/A
A559: Cobros Abril Canal Fijo | B559: Oscar Alexi Antencio arauz | C559: 361008990000 | D559: Cobros Abril Canal Fijo 2 meses a NPN | E559: =+_xlfn.XLOOKUP(UTILIZADAS[[#This Row],[Numero_Cuenta]],'[1]cobros_marzo (fijo)'!$B:$B,'[1]cobros_marzo (fijo)'!$D:$D,,0) -> 0 | G559: 46026 | H559: 69662263 | I559: 69662263 | K559: oatencii@gmail.com | O559: 46026 | S559: 1-51-133 | T559: MASIVO | U559: NPN | V559: =_xlfn.XLOOKUP(UTILIZADAS[[#This Row],[Contacto1]],Tabla2[phone_number_dialed],Tabla2[status_name],,0) -> No Answer AutoDial
A560: Cobros Abril Canal Fijo | B560: Marcos Antonio Howard catuy | C560: 359242000000 | D560: Cobros Abril Canal Fijo 2 meses a NPN | E560: =+_xlfn.XLOOKUP(UTILIZADAS[[#This Row],[Numero_Cuenta]],'[1]cobros_marzo (fijo)'!$B:$B,'[1]cobros_marzo (fijo)'!$D:$D,,0) -> 0 | G560: 46026 | H560: 64079225 | I560: 64079225 | K560: kimberlydelaespada0@gmail.com | O560: 46026 | S560: 3-761-2136 | T560: MASIVO | U560: NPN | V560: =_xlfn.XLOOKUP(UTILIZADAS[[#This Row],[Contacto1]],Tabla2[phone_number_dialed],Tabla2[status_name],,0) -> Cuenta cesada
A561: Cobros Abril Canal Fijo | B561: Algis Humberto cedeño Sánchez | C561: 354055900000 | D561: Cobros Abril Canal Fijo 2 meses a NPN | E561: =+_xlfn.XLOOKUP(UTILIZADAS[[#This Row],[Numero_Cuenta]],'[1]cobros_marzo (fijo)'!$B:$B,'[1]cobros_marzo (fijo)'!$D:$D,,0) -> 0 | G561: 46026 | H561: 69227968 | I561: 69227968 | K561: 19sanchez.mariela28@gmail.com | O561: 46026 | S561: 8-756-1517 | T561: MASIVO | U561: NPN | V561: =_xlfn.XLOOKUP(UTILIZADAS[[#This Row],[Contacto1]],Tabla2[phone_number_dialed],Tabla2[status_name],,0) -> Agent Not Available
A562: Cobros Abril Canal Fijo | B562: Luis Alberto Lañas Guerrero | C562: 362011030000 | D562: Cobros Abril Canal Fijo 2 meses a NPN | E562: =+_xlfn.XLOOKUP(UTILIZADAS[[#This Row],[Numero_Cuenta]],'[1]cobros_marzo (fijo)'!$B:$B,'[1]cobros_marzo (fijo)'!$D:$D,,0) -> 0 | G562: 46026 | H562: 67082818 | I562: 67082818 | K562: luislana982@gmail.com | O562: 46026 | S562: 8-441-11 | T562: MASIVO | U562: NPN | V562: =_xlfn.XLOOKUP(UTILIZADAS[[#This Row],[Contacto1]],Tabla2[phone_number_dialed],Tabla2[status_name],,0) -> #N/A
A563: Cobros Abril Canal Fijo | B563: Juan Carlos Zamora Rodriguez | C563: 205010200000 | D563: Cobros Abril Canal Fijo 2 meses a NPN | E563: =+_xlfn.XLOOKUP(UTILIZADAS[[#This Row],[Numero_Cuenta]],'[1]cobros_marzo (fijo)'!$B:$B,'[1]cobros_marzo (fijo)'!$D:$D,,0) -> 0 | G563: 46026 | H563: 67920874 | I563: 67920874 | K563: juanzamora2913@gmail.com | O563: 46026 | S563: 8-783-775 | T563: MASIVO | U563: NPN | V563: =_xlfn.XLOOKUP(UTILIZADAS[[#This Row],[Contacto1]],Tabla2[phone_number_dialed],Tabla2[status_name],,0) -> Auto busy
A564: Cobros Abril Canal Fijo | B564: Yaneli lisbeth navalo Martinez | C564: 351247450000 | D564: Cobros Abril Canal Fijo 2 meses a NPN | E564: =+_xlfn.XLOOKUP(UTILIZADAS[[#This Row],[Numero_Cuenta]],'[1]cobros_marzo (fijo)'!$B:$B,'[1]cobros_marzo (fijo)'!$D:$D,,0) -> 0 | G564: 46026 | H564: 64296356 | I564: 64296356 | K564: Marysincontreras@gmail.com | O564: 46026 | S564: 3-730-2220 | T564: MASIVO | U564: NPN | V564: =_xlfn.XLOOKUP(UTILIZADAS[[#This Row],[Contacto1]],Tabla2[phone_number_dialed],Tabla2[status_name],,0) -> Cuenta cesada
A565: Cobros Abril Canal Fijo | B565: Freddy balza | C565: 368014280000 | D565: Cobros Abril Canal Fijo 2 meses a NPN | E565: =+_xlfn.XLOOKUP(UTILIZADAS[[#This Row],[Numero_Cuenta]],'[1]cobros_marzo (fijo)'!$B:$B,'[1]cobros_marzo (fijo)'!$D:$D,,0) -> 0 | G565: 46026 | H565: 68211872 | I565: 68211872 | K565: Freddybalza@gmail.com | O565: 46026 | S565: Bf558050 | T565: SOHO | U565: NPN | V565: =_xlfn.XLOOKUP(UTILIZADAS[[#This Row],[Contacto1]],Tabla2[phone_number_dialed],Tabla2[status_name],,0) -> Buzon de voz
A566: Cobros Abril Canal Fijo | B566: Erick Alberto Gómez Ávila | C566: 362012510000 | D566: Cobros Abril Canal Fijo 2 meses a NPN | E566: =+_xlfn.XLOOKUP(UTILIZADAS[[#This Row],[Numero_Cuenta]],'[1]cobros_marzo (fijo)'!$B:$B,'[1]cobros_marzo (fijo)'!$D:$D,,0) -> 0 | G566: 46026 | H566: 63835021 | I566: 63835021 | K566: tg9442944@gmail.com | O566: 46026 | S566: 5-712-2177 | T566: MASIVO | U566: NPN | V566: =_xlfn.XLOOKUP(UTILIZADAS[[#This Row],[Contacto1]],Tabla2[phone_number_dialed],Tabla2[status_name],,0) -> Agent Not Available
A567: Cobros Abril Canal Fijo | B567: TONY MC KALOMAN | C567: 362016470000 | D567: Cobros Abril Canal Fijo 2 meses a NPN | E567: =+_xlfn.XLOOKUP(UTILIZADAS[[#This Row],[Numero_Cuenta]],'[1]cobros_marzo (fijo)'!$B:$B,'[1]cobros_marzo (fijo)'!$D:$D,,0) -> 0 | G567: 46026 | H567: 69868393 | I567: 69868393 | K567: juliapalacios.0621@gmail.com | O567: 46026 | S567: 8-784-361 | T567: CALL CENTER | U567: NPN | V567: =_xlfn.XLOOKUP(UTILIZADAS[[#This Row],[Contacto1]],Tabla2[phone_number_dialed],Tabla2[status_name],,0) -> Agent Not Available
A568: Cobros Abril Canal Fijo | B568: Estephany Lineth Jiménez Pitti | C568: 363014040000 | D568: Cobros Abril Canal Fijo 2 meses a NPN | E568: =+_xlfn.XLOOKUP(UTILIZADAS[[#This Row],[Numero_Cuenta]],'[1]cobros_marzo (fijo)'!$B:$B,'[1]cobros_marzo (fijo)'!$D:$D,,0) -> 0 | G568: 46026 | H568: 63485982 | I568: 63485982 | K568: estephanylineth24@gmail.com | O568: 46026 | S568: 4-808-197 | T568: MASIVO | U568: NPN | V568: =_xlfn.XLOOKUP(UTILIZADAS[[#This Row],[Contacto1]],Tabla2[phone_number_dialed],Tabla2[status_name],,0) -> #N/A
... A570: Cobros Abril Canal Fijo | B570: Víctor Manuel Guzmán Guerrel | C570: 362014660000 | D570: Cobros Abril Canal Fijo 2 meses a NPN | E570: =+_xlfn.XLOOKUP(UTILIZADAS[[#This Row],[Numero_Cuenta]],'[1]cobros_marzo (fijo)'!$B:$B,'[1]cobros_marzo (fijo)'!$D:$D,,0) -> 0 | G570: 46026 | H570: 65579008 | I570: 65579008 | K570: Vg7479242@gmail.com | O570: 46026 | S570: 8-318-539 | T570: MASIVO | U570: NPN | V570: =_xlfn.XLOOKUP(UTILIZADAS[[#This Row],[Contacto1]],Tabla2[phone_number_dialed],Tabla2[status_name],,0) -> Buzon de voz
A571: Cobros Abril Canal Fijo | B571: Alexia Ramos | C571: 362013760000 | D571: Cobros Abril Canal Fijo 2 meses a NPN | E571: =+_xlfn.XLOOKUP(UTILIZADAS[[#This Row],[Numero_Cuenta]],'[1]cobros_marzo (fijo)'!$B:$B,'[1]cobros_marzo (fijo)'!$D:$D,,0) -> 0 | G571: 46026 | H571: 67542007 | I571: 67542007 | K571: franklinb10709294@gmail.com | O571: 46026 | S571: 312109 | T571: MASIVO | U571: NPN | V571: =_xlfn.XLOOKUP(UTILIZADAS[[#This Row],[Contacto1]],Tabla2[phone_number_dialed],Tabla2[status_name],,0) -> Agent Not Available
A572: Cobros Abril Canal Fijo | B572: MARCO TULIO ALBEAR SIVALA | C572: 357386290000 | D572: Cobros Abril Canal Fijo 2 meses a NPN | E572: =+_xlfn.XLOOKUP(UTILIZADAS[[#This Row],[Numero_Cuenta]],'[1]cobros_marzo (fijo)'!$B:$B,'[1]cobros_marzo (fijo)'!$D:$D,,0) -> 0 | G572: 46026 | H572: 65190440 | I572: 65190440 | K572: fg461953@gmail.com | O572: 46026 | S572: 8-909-2163 | T572: MASIVO | U572: NPN | V572: =_xlfn.XLOOKUP(UTILIZADAS[[#This Row],[Contacto1]],Tabla2[phone_number_dialed],Tabla2[status_name],,0) -> Auto busy
...

Sheet Promesas se pago dinero
A1: Fecha | B1: Marca temporal | C1: Agente | D1: Numero celular | E1: Cuenta | F1: Identificación (cedula) | G1: Campaña | H1: Canal | I1: Escenario | J1: Motivo | K1: Fecha promesa de pago | L1: Monto de promesa de pago | M1: Realiza el pago | N1: Fecha de Pago | O1: Monto pagado | P1: Tiempo de mora (días) | Q1: Campaña | R1: Mes Pago | S1: Mes Promesa | T1: Dia Pago | U1: Dia Promesa | V1: Intentos de Promesas | W1: Intentos de pago
A2: =TEXT(promesas[[#This Row],[Marca temporal]],"dd/mmm") -> 04/may | B2: 46146.426 | C2: Lili Velez | D2: 68503631 | E2: 366022500000 | F2: 10-717-221 | G2: Fijo | H2: Masivo (D2D) | I2: Correo de voz | M2: no | P2: 3 MESES PENDIENTES | R2: =IF(promesas[[#This Row],[Fecha de Pago]]="", "", TEXT(promesas[[#This Row],[Fecha de Pago]], "mmm")) | S2: =IF(promesas[[#This Row],[Fecha promesa de pago]]="", "", TEXT(promesas[[#This Row],[Fecha promesa de pago]], "mmm")) | T2: =IF(promesas[[#This Row],[Fecha de Pago]]="", "", TEXT(promesas[[#This Row],[Fecha de Pago]], "dd/mmm")) | U2: =IF(promesas[[#This Row],[Fecha promesa de pago]]="", "", TEXT(promesas[[#This Row],[Fecha promesa de pago]], "dd/mmm")) | V2: =IF(LEN(TRIM(promesas[[#This Row],[Fecha promesa de pago]]))>0,1,"") | W2: =IF(LEN(TRIM(promesas[[#This Row],[Fecha de Pago]]))>0,1,"")
A3: =TEXT(promesas[[#This Row],[Marca temporal]],"dd/mmm") -> 04/may | B3: 46146.434 | C3: Lili Velez | D3: 66293335 | E3: 363026120000 | F3: 9-755-801 | G3: Fijo | H3: Masivo (D2D) | I3: Correo de voz | M3: no | P3: 3 MESES PENDIENTES | R3: =IF(promesas[[#This Row],[Fecha de Pago]]="", "", TEXT(promesas[[#This Row],[Fecha de Pago]], "mmm")) | S3: =IF(promesas[[#This Row],[Fecha promesa de pago]]="", "", TEXT(promesas[[#This Row],[Fecha promesa de pago]], "mmm")) | T3: =IF(promesas[[#This Row],[Fecha de Pago]]="", "", TEXT(promesas[[#This Row],[Fecha de Pago]], "dd/mmm")) | U3: =IF(promesas[[#This Row],[Fecha promesa de pago]]="", "", TEXT(promesas[[#This Row],[Fecha promesa de pago]], "dd/mmm")) | V3: =IF(LEN(TRIM(promesas[[#This Row],[Fecha promesa de pago]]))>0,1,"") | W3: =IF(LEN(TRIM(promesas[[#This Row],[Fecha de Pago]]))>0,1,"")
A4: =TEXT(promesas[[#This Row],[Marca temporal]],"dd/mmm") -> 04/may | B4: 46146.441 | C4: Lili Velez | D4: 67450828 | E4: 357317130000 | F4: 10-716-744 | G4: Fijo | H4: Masivo (D2D) | I4: Correo de voz | M4: no | P4: 2 MESES PENDIENTES | R4: =IF(promesas[[#This Row],[Fecha de Pago]]="", "", TEXT(promesas[[#This Row],[Fecha de Pago]], "mmm")) | S4: =IF(promesas[[#This Row],[Fecha promesa de pago]]="", "", TEXT(promesas[[#This Row],[Fecha promesa de pago]], "mmm")) | T4: =IF(promesas[[#This Row],[Fecha de Pago]]="", "", TEXT(promesas[[#This Row],[Fecha de Pago]], "dd/mmm")) | U4: =IF(promesas[[#This Row],[Fecha promesa de pago]]="", "", TEXT(promesas[[#This Row],[Fecha promesa de pago]], "dd/mmm")) | V4: =IF(LEN(TRIM(promesas[[#This Row],[Fecha promesa de pago]]))>0,1,"") | W4: =IF(LEN(TRIM(promesas[[#This Row],[Fecha de Pago]]))>0,1,"")
A5: =TEXT(promesas[[#This Row],[Marca temporal]],"dd/mmm") -> 04/may | B5: 46146.446 | C5: Lili Velez | D5: 68612220 | E5: 352368230000 | F5: 8-992-495 | G5: Fijo | H5: Masivo (D2D) | I5: Mensaje a tercero | M5: no | P5: 2 MESES PENDIENTES | R5: =IF(promesas[[#This Row],[Fecha de Pago]]="", "", TEXT(promesas[[#This Row],[Fecha de Pago]], "mmm")) | S5: =IF(promesas[[#This Row],[Fecha promesa de pago]]="", "", TEXT(promesas[[#This Row],[Fecha promesa de pago]], "mmm")) | T5: =IF(promesas[[#This Row],[Fecha de Pago]]="", "", TEXT(promesas[[#This Row],[Fecha de Pago]], "dd/mmm")) | U5: =IF(promesas[[#This Row],[Fecha promesa de pago]]="", "", TEXT(promesas[[#This Row],[Fecha promesa de pago]], "dd/mmm")) | V5: =IF(LEN(TRIM(promesas[[#This Row],[Fecha promesa de pago]]))>0,1,"") | W5: =IF(LEN(TRIM(promesas[[#This Row],[Fecha de Pago]]))>0,1,"")
A6: =TEXT(promesas[[#This Row],[Marca temporal]],"dd/mmm") -> 04/may | B6: 46146.461 | C6: Lili Velez | D6: 62389137 | E6: 362010140000 | F6: 8-825-575 | G6: Fijo | H6: Masivo (D2D) | I6: Correo de voz | M6: no | P6: 1 MES PENDIENTE | R6: =IF(promesas[[#This Row],[Fecha de Pago]]="", "", TEXT(promesas[[#This Row],[Fecha de Pago]], "mmm")) | S6: =IF(promesas[[#This Row],[Fecha promesa de pago]]="", "", TEXT(promesas[[#This Row],[Fecha promesa de pago]], "mmm")) | T6: =IF(promesas[[#This Row],[Fecha de Pago]]="", "", TEXT(promesas[[#This Row],[Fecha de Pago]], "dd/mmm")) | U6: =IF(promesas[[#This Row],[Fecha promesa de pago]]="", "", TEXT(promesas[[#This Row],[Fecha promesa de pago]], "dd/mmm")) | V6: =IF(LEN(TRIM(promesas[[#This Row],[Fecha promesa de pago]]))>0,1,"") | W6: =IF(LEN(TRIM(promesas[[#This Row],[Fecha de Pago]]))>0,1,"")
A7: =TEXT(promesas[[#This Row],[Marca temporal]],"dd/mmm") -> 04/may | B7: 46146.466 | C7: Lili Velez | D7: 63645460 | E7: 359347200000 | F7: 8-876-1341 | G7: Fijo | H7: Masivo (D2D) | I7: Correo de voz | M7: no | P7: 2 MESES PENDIENTES | R7: =IF(promesas[[#This Row],[Fecha de Pago]]="", "", TEXT(promesas[[#This Row],[Fecha de Pago]], "mmm")) | S7: =IF(promesas[[#This Row],[Fecha promesa de pago]]="", "", TEXT(promesas[[#This Row],[Fecha promesa de pago]], "mmm")) | T7: =IF(promesas[[#This Row],[Fecha de Pago]]="", "", TEXT(promesas[[#This Row],[Fecha de Pago]], "dd/mmm")) | U7: =IF(promesas[[#This Row],[Fecha promesa de pago]]="", "", TEXT(promesas[[#This Row],[Fecha promesa de pago]], "dd/mmm")) | V7: =IF(LEN(TRIM(promesas[[#This Row],[Fecha promesa de pago]]))>0,1,"") | W7: =IF(LEN(TRIM(promesas[[#This Row],[Fecha de Pago]]))>0,1,"")
A8: =TEXT(promesas[[#This Row],[Marca temporal]],"dd/mmm") -> 04/may | B8: 46146.472 | C8: Lili Velez | D8: 66634767 | E8: 152071270000 | F8: 8-357-660 | G8: Fijo | H8: Masivo (D2D) | I8: Cliente al dia | M8: si | N8: 46142 | O8: 40.82 | P8: 2 MESES PENDIENTES | R8: =IF(promesas[[#This Row],[Fecha de Pago]]="", "", TEXT(promesas[[#This Row],[Fecha de Pago]], "mmm")) -> abr | S8: =IF(promesas[[#This Row],[Fecha promesa de pago]]="", "", TEXT(promesas[[#This Row],[Fecha promesa de pago]], "mmm")) | T8: =IF(promesas[[#This Row],[Fecha de Pago]]="", "", TEXT(promesas[[#This Row],[Fecha de Pago]], "dd/mmm")) -> 30/abr | U8: =IF(promesas[[#This Row],[Fecha promesa de pago]]="", "", TEXT(promesas[[#This Row],[Fecha promesa de pago]], "dd/mmm")) | V8: =IF(LEN(TRIM(promesas[[#This Row],[Fecha promesa de pago]]))>0,1,"") | W8: =IF(LEN(TRIM(promesas[[#This Row],[Fecha de Pago]]))>0,1,"") -> 1
A9: =TEXT(promesas[[#This Row],[Marca temporal]],"dd/mmm") -> 04/may | B9: 46146.487 | C9: Lili Velez | D9: 66047682 | E9: 361074360000 | F9: 8-956-716 | G9: Fijo | H9: Masivo (D2D) | I9: Contactado | K9: 46146 | L9: 37.52 | M9: no | P9: 1 MES PENDIENTE | R9: =IF(promesas[[#This Row],[Fecha de Pago]]="", "", TEXT(promesas[[#This Row],[Fecha de Pago]], "mmm")) | S9: =IF(promesas[[#This Row],[Fecha promesa de pago]]="", "", TEXT(promesas[[#This Row],[Fecha promesa de pago]], "mmm")) -> may | T9: =IF(promesas[[#This Row],[Fecha de Pago]]="", "", TEXT(promesas[[#This Row],[Fecha de Pago]], "dd/mmm")) | U9: =IF(promesas[[#This Row],[Fecha promesa de pago]]="", "", TEXT(promesas[[#This Row],[Fecha promesa de pago]], "dd/mmm")) -> 04/may | V9: =IF(LEN(TRIM(promesas[[#This Row],[Fecha promesa de pago]]))>0,1,"") -> 1 | W9: =IF(LEN(TRIM(promesas[[#This Row],[Fecha de Pago]]))>0,1,"")
A10: =TEXT(promesas[[#This Row],[Marca temporal]],"dd/mmm") -> 04/may | B10: 46146.492 | C10: Lili Velez | D10: 64320903 | E10: 352366440000 | F10: 4-277-831 | G10: Fijo | H10: Masivo (D2D) | I10: Contactado | M10: no | P10: 2 MESES PENDIENTES | R10: =IF(promesas[[#This Row],[Fecha de Pago]]="", "", TEXT(promesas[[#This Row],[Fecha de Pago]], "mmm")) | S10: =IF(promesas[[#This Row],[Fecha promesa de pago]]="", "", TEXT(promesas[[#This Row],[Fecha promesa de pago]], "mmm")) | T10: =IF(promesas[[#This Row],[Fecha de Pago]]="", "", TEXT(promesas[[#This Row],[Fecha de Pago]], "dd/mmm")) | U10: =IF(promesas[[#This Row],[Fecha promesa de pago]]="", "", TEXT(promesas[[#This Row],[Fecha promesa de pago]], "dd/mmm")) | V10: =IF(LEN(TRIM(promesas[[#This Row],[Fecha promesa de pago]]))>0,1,"") | W10: =IF(LEN(TRIM(promesas[[#This Row],[Fecha de Pago]]))>0,1,"")
A11: =TEXT(promesas[[#This Row],[Marca temporal]],"dd/mmm") -> 04/may | B11: 46146.497 | C11: Lili Velez | D11: 65441317 | E11: 358381400000 | F11: 8-989-2135 | G11: Fijo | H11: Soho | I11: Correo de voz | M11: no | P11: 2 MESES PENDIENTES | R11: =IF(promesas[[#This Row],[Fecha de Pago]]="", "", TEXT(promesas[[#This Row],[Fecha de Pago]], "mmm")) | S11: =IF(promesas[[#This Row],[Fecha promesa de pago]]="", "", TEXT(promesas[[#This Row],[Fecha promesa de pago]], "mmm")) | T11: =IF(promesas[[#This Row],[Fecha de Pago]]="", "", TEXT(promesas[[#This Row],[Fecha de Pago]], "dd/mmm")) | U11: =IF(promesas[[#This Row],[Fecha promesa de pago]]="", "", TEXT(promesas[[#This Row],[Fecha promesa de pago]], "dd/mmm")) | V11: =IF(LEN(TRIM(promesas[[#This Row],[Fecha promesa de pago]]))>0,1,"") | W11: =IF(LEN(TRIM(promesas[[#This Row],[Fecha de Pago]]))>0,1,"")
A12: =TEXT(promesas[[#This Row],[Marca temporal]],"dd/mmm") -> 04/may | B12: 46146.503 | C12: Lili Velez | D12: 66103004 | E12: 353339160000 | F12: 8-794-5030 | G12: Fijo | H12: Digital | I12: Contactado | K12: 46148 | L12: 79.65 | M12: no | P12: 4 MESES PENDIENTES | R12: =IF(promesas[[#This Row],[Fecha de Pago]]="", "", TEXT(promesas[[#This Row],[Fecha de Pago]], "mmm")) | S12: =IF(promesas[[#This Row],[Fecha promesa de pago]]="", "", TEXT(promesas[[#This Row],[Fecha promesa de pago]], "mmm")) -> may | T12: =IF(promesas[[#This Row],[Fecha de Pago]]="", "", TEXT(promesas[[#This Row],[Fecha de Pago]], "dd/mmm")) | U12: =IF(promesas[[#This Row],[Fecha promesa de pago]]="", "", TEXT(promesas[[#This Row],[Fecha promesa de pago]], "dd/mmm")) -> 06/may | V12: =IF(LEN(TRIM(promesas[[#This Row],[Fecha promesa de pago]]))>0,1,"") -> 1 | W12: =IF(LEN(TRIM(promesas[[#This Row],[Fecha de Pago]]))>0,1,"")
A13: =TEXT(promesas[[#This Row],[Marca temporal]],"dd/mmm") -> 04/may | B13: 46146.514 | C13: Lili Velez | D13: 67611194 | E13: 155078170000 | F13: 2-46-534 | G13: Fijo | H13: Masivo (D2D) | I13: Contactado | K13: 46146 | L13: 34.92 | M13: no | P13: 2 MESES PENDIENTES | R13: =IF(promesas[[#This Row],[Fecha de Pago]]="", "", TEXT(promesas[[#This Row],[Fecha de Pago]], "mmm")) | S13: =IF(promesas[[#This Row],[Fecha promesa de pago]]="", "", TEXT(promesas[[#This Row],[Fecha promesa de pago]], "mmm")) -> may | T13: =IF(promesas[[#This Row],[Fecha de Pago]]="", "", TEXT(promesas[[#This Row],[Fecha de Pago]], "dd/mmm")) | U13: =IF(promesas[[#This Row],[Fecha promesa de pago]]="", "", TEXT(promesas[[#This Row],[Fecha promesa de pago]], "dd/mmm")) -> 04/may | V13: =IF(LEN(TRIM(promesas[[#This Row],[Fecha promesa de pago]]))>0,1,"") -> 1 | W13: =IF(LEN(TRIM(promesas[[#This Row],[Fecha de Pago]]))>0,1,"")
A14: =TEXT(promesas[[#This Row],[Marca temporal]],"dd/mmm") -> 04/may | B14: 46146.522 | C14: Lili Velez | D14: 66386838 | E14: 364028530000 | F14: 167126182 | G14: Fijo | H14: Masivo (D2D) | I14: Correo de voz | M14: no | P14: 3 MESES PENDIENTES | R14: =IF(promesas[[#This Row],[Fecha de Pago]]="", "", TEXT(promesas[[#This Row],[Fecha de Pago]], "mmm")) | S14: =IF(promesas[[#This Row],[Fecha promesa de pago]]="", "", TEXT(promesas[[#This Row],[Fecha promesa de pago]], "mmm")) | T14: =IF(promesas[[#This Row],[Fecha de Pago]]="", "", TEXT(promesas[[#This Row],[Fecha de Pago]], "dd/mmm")) | U14: =IF(promesas[[#This Row],[Fecha promesa de pago]]="", "", TEXT(promesas[[#This Row],[Fecha promesa de pago]], "dd/mmm")) | V14: =IF(LEN(TRIM(promesas[[#This Row],[Fecha promesa de pago]]))>0,1,"") | W14: =IF(LEN(TRIM(promesas[[#This Row],[Fecha de Pago]]))>0,1,"")
A15: =TEXT(promesas[[#This Row],[Marca temporal]],"dd/mmm") -> 04/may | B15: 46146.528 | C15: Lili Velez | D15: 63026745 | E15: 366022910000 | F15: 8-1056-88 | G15: Fijo | H15: Masivo (D2D) | I15: No contactado | M15: no | P15: 3 MESES PENDIENTES | R15: =IF(promesas[[#This Row],[Fecha de Pago]]="", "", TEXT(promesas[[#This Row],[Fecha de Pago]], "mmm")) | S15: =IF(promesas[[#This Row],[Fecha promesa de pago]]="", "", TEXT(promesas[[#This Row],[Fecha promesa de pago]], "mmm")) | T15: =IF(promesas[[#This Row],[Fecha de Pago]]="", "", TEXT(promesas[[#This Row],[Fecha de Pago]], "dd/mmm")) | U15: =IF(promesas[[#This Row],[Fecha promesa de pago]]="", "", TEXT(promesas[[#This Row],[Fecha promesa de pago]], "dd/mmm")) | V15: =IF(LEN(TRIM(promesas[[#This Row],[Fecha promesa de pago]]))>0,1,"") | W15: =IF(LEN(TRIM(promesas[[#This Row],[Fecha de Pago]]))>0,1,"")
A16: =TEXT(promesas[[#This Row],[Marca temporal]],"dd/mmm") -> 04/may | B16: 46146.534 | C16: Lili Velez | D16: 63836298 | E16: 365022950000 | F16: 4-113-733 | G16: Fijo | H16: Masivo (D2D) | I16: Correo de voz | M16: no | P16: 2 MESES PENDIENTES | R16: =IF(promesas[[#This Row],[Fecha de Pago]]="", "", TEXT(promesas[[#This Row],[Fecha de Pago]], "mmm")) | S16: =IF(promesas[[#This Row],[Fecha promesa de pago]]="", "", TEXT(promesas[[#This Row],[Fecha promesa de pago]], "mmm")) | T16: =IF(promesas[[#This Row],[Fecha de Pago]]="", "", TEXT(promesas[[#This Row],[Fecha de Pago]], "dd/mmm")) | U16: =IF(promesas[[#This Row],[Fecha promesa de pago]]="", "", TEXT(promesas[[#This Row],[Fecha promesa de pago]], "dd/mmm")) | V16: =IF(LEN(TRIM(promesas[[#This Row],[Fecha promesa de pago]]))>0,1,"") | W16: =IF(LEN(TRIM(promesas[[#This Row],[Fecha de Pago]]))>0,1,"")
A17: =TEXT(promesas[[#This Row],[Marca temporal]],"dd/mmm") -> 04/may | B17: 46146.541 | C17: Lili Velez | D17: 63165778 | E17: 366023610000 | F17: 8-761-80 | G17: Fijo | H17: Masivo (D2D) | I17: Correo de voz | M17: no | P17: 3 MESES PENDIENTES | R17: =IF(promesas[[#This Row],[Fecha de Pago]]="", "", TEXT(promesas[[#This Row],[Fecha de Pago]], "mmm")) | S17: =IF(promesas[[#This Row],[Fecha promesa de pago]]="", "", TEXT(promesas[[#This Row],[Fecha promesa de pago]], "mmm")) | T17: =IF(promesas[[#This Row],[Fecha de Pago]]="", "", TEXT(promesas[[#This Row],[Fecha de Pago]], "dd/mmm")) | U17: =IF(promesas[[#This Row],[Fecha promesa de pago]]="", "", TEXT(promesas[[#This Row],[Fecha promesa de pago]], "dd/mmm")) | V17: =IF(LEN(TRIM(promesas[[#This Row],[Fecha promesa de pago]]))>0,1,"") | W17: =IF(LEN(TRIM(promesas[[#This Row],[Fecha de Pago]]))>0,1,"")
A18: =TEXT(promesas[[#This Row],[Marca temporal]],"dd/mmm") -> 04/may | B18: 46146.596 | C18: Lili Velez | D18: 62294843 | E18: 272063460000 | F18: 8-898-2194 | G18: Fijo | H18: Masivo (D2D) | I18: Correo de voz | M18: no | P18: 3 MESES PENDIENTES | R18: =IF(promesas[[#This Row],[Fecha de Pago]]="", "", TEXT(promesas[[#This Row],[Fecha de Pago]], "mmm")) | S18: =IF(promesas[[#This Row],[Fecha promesa de pago]]="", "", TEXT(promesas[[#This Row],[Fecha promesa de pago]], "mmm")) | T18: =IF(promesas[[#This Row],[Fecha de Pago]]="", "", TEXT(promesas[[#This Row],[Fecha de Pago]], "dd/mmm")) | U18: =IF(promesas[[#This Row],[Fecha promesa de pago]]="", "", TEXT(promesas[[#This Row],[Fecha promesa de pago]], "dd/mmm")) | V18: =IF(LEN(TRIM(promesas[[#This Row],[Fecha promesa de pago]]))>0,1,"") | W18: =IF(LEN(TRIM(promesas[[#This Row],[Fecha de Pago]]))>0,1,"")
A19: =TEXT(promesas[[#This Row],[Marca temporal]],"dd/mmm") -> 04/may | B19: 46146.61 | C19: Lili Velez | D19: 66189666 | E19: 138017580000 | F19: 3-711-225 | G19: Fijo | H19: Digital | I19: Correo de voz | M19: no | P19: 2 MESES PENDIENTES | R19: =IF(promesas[[#This Row],[Fecha de Pago]]="", "", TEXT(promesas[[#This Row],[Fecha de Pago]], "mmm")) | S19: =IF(promesas[[#This Row],[Fecha promesa de pago]]="", "", TEXT(promesas[[#This Row],[Fecha promesa de pago]], "mmm")) | T19: =IF(promesas[[#This Row],[Fecha de Pago]]="", "", TEXT(promesas[[#This Row],[Fecha de Pago]], "dd/mmm")) | U19: =IF(promesas[[#This Row],[Fecha promesa de pago]]="", "", TEXT(promesas[[#This Row],[Fecha promesa de pago]], "dd/mmm")) | V19: =IF(LEN(TRIM(promesas[[#This Row],[Fecha promesa de pago]]))>0,1,"") | W19: =IF(LEN(TRIM(promesas[[#This Row],[Fecha de Pago]]))>0,1,"")
A20: =TEXT(promesas[[#This Row],[Marca temporal]],"dd/mmm") -> 04/may | B20: 46146.621 | C20: Lili Velez | D20: 64381146 | E20: 361023080000 | F20: 9-754-2237 | G20: Fijo | H20: Masivo (D2D) | I20: Contactado | K20: 46147 | L20: 76.18 | M20: no | P20: 3 MESES PENDIENTES | R20: =IF(promesas[[#This Row],[Fecha de Pago]]="", "", TEXT(promesas[[#This Row],[Fecha de Pago]], "mmm")) | S20: =IF(promesas[[#This Row],[Fecha promesa de pago]]="", "", TEXT(promesas[[#This Row],[Fecha promesa de pago]], "mmm")) -> may | T20: =IF(promesas[[#This Row],[Fecha de Pago]]="", "", TEXT(promesas[[#This Row],[Fecha de Pago]], "dd/mmm")) | U20: =IF(promesas[[#This Row],[Fecha promesa de pago]]="", "", TEXT(promesas[[#This Row],[Fecha promesa de pago]], "dd/mmm")) -> 05/may | V20: =IF(LEN(TRIM(promesas[[#This Row],[Fecha promesa de pago]]))>0,1,"") -> 1 | W20: =IF(LEN(TRIM(promesas[[#This Row],[Fecha de Pago]]))>0,1,"")
A21: =TEXT(promesas[[#This Row],[Marca temporal]],"dd/mmm") -> 04/may | B21: 46146.626 | C21: Lili Velez | D21: 64590545 | E21: 313014210000 | F21: 8-210-104 | G21: Fijo | H21: Call Center Outbound | I21: Correo de voz | M21: no | P21: 2 MESES PENDIENTES | R21: =IF(promesas[[#This Row],[Fecha de Pago]]="", "", TEXT(promesas[[#This Row],[Fecha de Pago]], "mmm")) | S21: =IF(promesas[[#This Row],[Fecha promesa de pago]]="", "", TEXT(promesas[[#This Row],[Fecha promesa de pago]], "mmm")) | T21: =IF(promesas[[#This Row],[Fecha de Pago]]="", "", TEXT(promesas[[#This Row],[Fecha de Pago]], "dd/mmm")) | U21: =IF(promesas[[#This Row],[Fecha promesa de pago]]="", "", TEXT(promesas[[#This Row],[Fecha promesa de pago]], "dd/mmm")) | V21: =IF(LEN(TRIM(promesas[[#This Row],[Fecha promesa de pago]]))>0,1,"") | W21: =IF(LEN(TRIM(promesas[[#This Row],[Fecha de Pago]]))>0,1,"")
A22: =TEXT(promesas[[#This Row],[Marca temporal]],"dd/mmm") -> 04/may | B22: 46146.637 | C22: Lili Velez | D22: 65245107 | E22: 367021660000 | F22: 9-208-975 | G22: Fijo | H22: Masivo (D2D) | I22: Correo de voz | M22: no | P22: 1 MES PENDIENTE | R22: =IF(promesas[[#This Row],[Fecha de Pago]]="", "", TEXT(promesas[[#This Row],[Fecha de Pago]], "mmm")) | S22: =IF(promesas[[#This Row],[Fecha promesa de pago]]="", "", TEXT(promesas[[#This Row],[Fecha promesa de pago]], "mmm")) | T22: =IF(promesas[[#This Row],[Fecha de Pago]]="", "", TEXT(promesas[[#This Row],[Fecha de Pago]], "dd/mmm")) | U22: =IF(promesas[[#This Row],[Fecha promesa de pago]]="", "", TEXT(promesas[[#This Row],[Fecha promesa de pago]], "dd/mmm")) | V22: =IF(LEN(TRIM(promesas[[#This Row],[Fecha promesa de pago]]))>0,1,"") | W22: =IF(LEN(TRIM(promesas[[#This Row],[Fecha de Pago]]))>0,1,"")
A23: =TEXT(promesas[[#This Row],[Marca temporal]],"dd/mmm") -> 04/may | B23: 46146.646 | C23: Lili Velez | D23: 66469658 | E23: 369019030000 | F23: 7-119-519 | G23: Fijo | H23: Masivo (D2D) | I23: Correo de voz | M23: no | P23: 3 MESES PENDIENTES | R23: =IF(promesas[[#This Row],[Fecha de Pago]]="", "", TEXT(promesas[[#This Row],[Fecha de Pago]], "mmm")) | S23: =IF(promesas[[#This Row],[Fecha promesa de pago]]="", "", TEXT(promesas[[#This Row],[Fecha promesa de pago]], "mmm")) | T23: =IF(promesas[[#This Row],[Fecha de Pago]]="", "", TEXT(promesas[[#This Row],[Fecha de Pago]], "dd/mmm")) | U23: =IF(promesas[[#This Row],[Fecha promesa de pago]]="", "", TEXT(promesas[[#This Row],[Fecha promesa de pago]], "dd/mmm")) | V23: =IF(LEN(TRIM(promesas[[#This Row],[Fecha promesa de pago]]))>0,1,"") | W23: =IF(LEN(TRIM(promesas[[#This Row],[Fecha de Pago]]))>0,1,"")
A24: =TEXT(promesas[[#This Row],[Marca temporal]],"dd/mmm") -> 04/may | B24: 46146.652 | C24: Lili Velez | D24: 67283336 | E24: 362024880000 | F24: 8-513-298 | G24: Fijo | H24: Masivo (D2D) | I24: No contactado | M24: no | P24: 1 MES PENDIENTE | R24: =IF(promesas[[#This Row],[Fecha de Pago]]="", "", TEXT(promesas[[#This Row],[Fecha de Pago]], "mmm")) | S24: =IF(promesas[[#This Row],[Fecha promesa de pago]]="", "", TEXT(promesas[[#This Row],[Fecha promesa de pago]], "mmm")) | T24: =IF(promesas[[#This Row],[Fecha de Pago]]="", "", TEXT(promesas[[#This Row],[Fecha de Pago]], "dd/mmm")) | U24: =IF(promesas[[#This Row],[Fecha promesa de pago]]="", "", TEXT(promesas[[#This Row],[Fecha promesa de pago]], "dd/mmm")) | V24: =IF(LEN(TRIM(promesas[[#This Row],[Fecha promesa de pago]]))>0,1,"") | W24: =IF(LEN(TRIM(promesas[[#This Row],[Fecha de Pago]]))>0,1,"")
A25: =TEXT(promesas[[#This Row],[Marca temporal]],"dd/mmm") -> 04/may | B25: 46146.657 | C25: Lili Velez | D25: 69023547 | E25: 361023680000 | F25: 3-70-145 | G25: Fijo | H25: Masivo (D2D) | I25: Numero equivocado | M25: no | P25: 3 MESES PENDIENTES | R25: =IF(promesas[[#This Row],[Fecha de Pago]]="", "", TEXT(promesas[[#This Row],[Fecha de Pago]], "mmm")) | S25: =IF(promesas[[#This Row],[Fecha promesa de pago]]="", "", TEXT(promesas[[#This Row],[Fecha promesa de pago]], "mmm")) | T25: =IF(promesas[[#This Row],[Fecha de Pago]]="", "", TEXT(promesas[[#This Row],[Fecha de Pago]], "dd/mmm")) | U25: =IF(promesas[[#This Row],[Fecha promesa de pago]]="", "", TEXT(promesas[[#This Row],[Fecha promesa de pago]], "dd/mmm")) | V25: =IF(LEN(TRIM(promesas[[#This Row],[Fecha promesa de pago]]))>0,1,"") | W25: =IF(LEN(TRIM(promesas[[#This Row],[Fecha de Pago]]))>0,1,"")
A26: =TEXT(promesas[[#This Row],[Marca temporal]],"dd/mmm") -> 04/may | B26: 46146.66 | C26: Lili Velez | D26: 65097861 | E26: 364023810000 | F26: 2-725-700 | G26: Fijo | H26: Masivo (D2D) | I26: No contactado | M26: no | P26: NPN | R26: =IF(promesas[[#This Row],[Fecha de Pago]]="", "", TEXT(promesas[[#This Row],[Fecha de Pago]], "mmm")) | S26: =IF(promesas[[#This Row],[Fecha promesa de pago]]="", "", TEXT(promesas[[#This Row],[Fecha promesa de pago]], "mmm")) | T26: =IF(promesas[[#This Row],[Fecha de Pago]]="", "", TEXT(promesas[[#This Row],[Fecha de Pago]], "dd/mmm")) | U26: =IF(promesas[[#This Row],[Fecha promesa de pago]]="", "", TEXT(promesas[[#This Row],[Fecha promesa de pago]], "dd/mmm")) | V26: =IF(LEN(TRIM(promesas[[#This Row],[Fecha promesa de pago]]))>0,1,"") | W26: =IF(LEN(TRIM(promesas[[#This Row],[Fecha de Pago]]))>0,1,"")
A27: =TEXT(promesas[[#This Row],[Marca temporal]],"dd/mmm") -> 04/may | B27: 46146.673 | C27: Lili Velez | D27: 69601798 | E27: 361023570000 | F27: 8-716-184 | G27: Fijo | H27: Masivo (D2D) | I27: Contactado | K27: 46150 | L27: 67.56 | M27: no | P27: 3 MESES PENDIENTES | R27: =IF(promesas[[#This Row],[Fecha de Pago]]="", "", TEXT(promesas[[#This Row],[Fecha de Pago]], "mmm")) | S27: =IF(promesas[[#This Row],[Fecha promesa de pago]]="", "", TEXT(promesas[[#This Row],[Fecha promesa de pago]], "mmm")) -> may | T27: =IF(promesas[[#This Row],[Fecha de Pago]]="", "", TEXT(promesas[[#This Row],[Fecha de Pago]], "dd/mmm")) | U27: =IF(promesas[[#This Row],[Fecha promesa de pago]]="", "", TEXT(promesas[[#This Row],[Fecha promesa de pago]], "dd/mmm")) -> 08/may | V27: =IF(LEN(TRIM(promesas[[#This Row],[Fecha promesa de pago]]))>0,1,"") -> 1 | W27: =IF(LEN(TRIM(promesas[[#This Row],[Fecha de Pago]]))>0,1,"")
A28: =TEXT(promesas[[#This Row],[Marca temporal]],"dd/mmm") -> 04/may | B28: 46146.681 | C28: Lili Velez | D28: 67467158 | E28: 361011900000 | F28: 8-1001-1937 | G28: Fijo | H28: Masivo (D2D) | I28: Correo de voz | M28: no | P28: 2 MESES PENDIENTES | R28: =IF(promesas[[#This Row],[Fecha de Pago]]="", "", TEXT(promesas[[#This Row],[Fecha de Pago]], "mmm")) | S28: =IF(promesas[[#This Row],[Fecha promesa de pago]]="", "", TEXT(promesas[[#This Row],[Fecha promesa de pago]], "mmm")) | T28: =IF(promesas[[#This Row],[Fecha de Pago]]="", "", TEXT(promesas[[#This Row],[Fecha de Pago]], "dd/mmm")) | U28: =IF(promesas[[#This Row],[Fecha promesa de pago]]="", "", TEXT(promesas[[#This Row],[Fecha promesa de pago]], "dd/mmm")) | V28: =IF(LEN(TRIM(promesas[[#This Row],[Fecha promesa de pago]]))>0,1,"") | W28: =IF(LEN(TRIM(promesas[[#This Row],[Fecha de Pago]]))>0,1,"")
A29: =TEXT(promesas[[#This Row],[Marca temporal]],"dd/mmm") -> 04/may | B29: 46146.69 | C29: Lili Velez | D29: 65556178 | E29: 365023490000 | F29: PE-9-1322 | G29: Fijo | H29: Masivo (D2D) | I29: Contactado | K29: 46172 | L29: 60.88 | M29: no | P29: 3 MESES PENDIENTES | R29: =IF(promesas[[#This Row],[Fecha de Pago]]="", "", TEXT(promesas[[#This Row],[Fecha de Pago]], "mmm")) | S29: =IF(promesas[[#This Row],[Fecha promesa de pago]]="", "", TEXT(promesas[[#This Row],[Fecha promesa de pago]], "mmm")) -> may | T29: =IF(promesas[[#This Row],[Fecha de Pago]]="", "", TEXT(promesas[[#This Row],[Fecha de Pago]], "dd/mmm")) | U29: =IF(promesas[[#This Row],[Fecha promesa de pago]]="", "", TEXT(promesas[[#This Row],[Fecha promesa de pago]], "dd/mmm")) -> 30/may | V29: =IF(LEN(TRIM(promesas[[#This Row],[Fecha promesa de pago]]))>0,1,"") -> 1 | W29: =IF(LEN(TRIM(promesas[[#This Row],[Fecha de Pago]]))>0,1,"")
A30: =TEXT(promesas[[#This Row],[Marca temporal]],"dd/mmm") -> 04/may | B30: 46146.698 | C30: Lili Velez | D30: 68195123 | E30: 362022960000 | F30: C03759902 | G30: Fijo | H30: Masivo (D2D) | I30: Correo de voz | M30: no | P30: 1 MES PENDIENTE | R30: =IF(promesas[[#This Row],[Fecha de Pago]]="", "", TEXT(promesas[[#This Row],[Fecha de Pago]], "mmm")) | S30: =IF(promesas[[#This Row],[Fecha promesa de pago]]="", "", TEXT(promesas[[#This Row],[Fecha promesa de pago]], "mmm")) | T30: =IF(promesas[[#This Row],[Fecha de Pago]]="", "", TEXT(promesas[[#This Row],[Fecha de Pago]], "dd/mmm")) | U30: =IF(promesas[[#This Row],[Fecha promesa de pago]]="", "", TEXT(promesas[[#This Row],[Fecha promesa de pago]], "dd/mmm")) | V30: =IF(LEN(TRIM(promesas[[#This Row],[Fecha promesa de pago]]))>0,1,"") | W30: =IF(LEN(TRIM(promesas[[#This Row],[Fecha de Pago]]))>0,1,"")
A31: =TEXT(promesas[[#This Row],[Marca temporal]],"dd/mmm") -> 04/may | B31: 46146.706 | C31: Lili Velez | D31: 63415263 | E31: 369023860000 | F31: 1-759-2223 | G31: Fijo | H31: Masivo (D2D) | I31: No contactado | M31: no | P31: 1 MES PENDIENTE | R31: =IF(promesas[[#This Row],[Fecha de Pago]]="", "", TEXT(promesas[[#This Row],[Fecha de Pago]], "mmm")) | S31: =IF(promesas[[#This Row],[Fecha promesa de pago]]="", "", TEXT(promesas[[#This Row],[Fecha promesa de pago]], "mmm")) | T31: =IF(promesas[[#This Row],[Fecha de Pago]]="", "", TEXT(promesas[[#This Row],[Fecha de Pago]], "dd/mmm")) | U31: =IF(promesas[[#This Row],[Fecha promesa de pago]]="", "", TEXT(promesas[[#This Row],[Fecha promesa de pago]], "dd/mmm")) | V31: =IF(LEN(TRIM(promesas[[#This Row],[Fecha promesa de pago]]))>0,1,"") | W31: =IF(LEN(TRIM(promesas[[#This Row],[Fecha de Pago]]))>0,1,"")
A32: =TEXT(promesas[[#This Row],[Marca temporal]],"dd/mmm") -> 04/may | B32: 46146.712 | C32: Lili Velez | D32: 60345653 | E32: 361020710000 | F32: 8-273-58 | G32: Fijo | H32: Masivo (D2D) | I32: No contactado | M32: no | P32: 3 MESES PENDIENTES | R32: =IF(promesas[[#This Row],[Fecha de Pago]]="", "", TEXT(promesas[[#This Row],[Fecha de Pago]], "mmm")) | S32: =IF(promesas[[#This Row],[Fecha promesa de pago]]="", "", TEXT(promesas[[#This Row],[Fecha promesa de pago]], "mmm")) | T32: =IF(promesas[[#This Row],[Fecha de Pago]]="", "", TEXT(promesas[[#This Row],[Fecha de Pago]], "dd/mmm")) | U32: =IF(promesas[[#This Row],[Fecha promesa de pago]]="", "", TEXT(promesas[[#This Row],[Fecha promesa de pago]], "dd/mmm")) | V32: =IF(LEN(TRIM(promesas[[#This Row],[Fecha promesa de pago]]))>0,1,"") | W32: =IF(LEN(TRIM(promesas[[#This Row],[Fecha de Pago]]))>0,1,"")
A33: =TEXT(promesas[[#This Row],[Marca temporal]],"dd/mmm") -> 04/may | B33: 46146.72 | C33: Lili Velez | D33: 68824497 | E33: 364023730000 | F33: 7-92-1201 | G33: Fijo | H33: Masivo (D2D) | I33: Contactado | K33: 46157 | L33: 40 | M33: no | P33: 3 MESES PENDIENTES | R33: =IF(promesas[[#This Row],[Fecha de Pago]]="", "", TEXT(promesas[[#This Row],[Fecha de Pago]], "mmm")) | S33: =IF(promesas[[#This Row],[Fecha promesa de pago]]="", "", TEXT(promesas[[#This Row],[Fecha promesa de pago]], "mmm")) -> may | T33: =IF(promesas[[#This Row],[Fecha de Pago]]="", "", TEXT(promesas[[#This Row],[Fecha de Pago]], "dd/mmm")) | U33: =IF(promesas[[#This Row],[Fecha promesa de pago]]="", "", TEXT(promesas[[#This Row],[Fecha promesa de pago]], "dd/mmm")) -> 15/may | V33: =IF(LEN(TRIM(promesas[[#This Row],[Fecha promesa de pago]]))>0,1,"") -> 1 | W33: =IF(LEN(TRIM(promesas[[#This Row],[Fecha de Pago]]))>0,1,"")
A34: =TEXT(promesas[[#This Row],[Marca temporal]],"dd/mmm") -> 04/may | B34: 46146.725 | C34: Lili Velez | D34: 61000685 | E34: 368023430000 | F34: 7-44-788 | G34: Fijo | H34: Masivo (D2D) | I34: No contactado | M34: no | P34: 3 MESES PENDIENTES | R34: =IF(promesas[[#This Row],[Fecha de Pago]]="", "", TEXT(promesas[[#This Row],[Fecha de Pago]], "mmm")) | S34: =IF(promesas[[#This Row],[Fecha promesa de pago]]="", "", TEXT(promesas[[#This Row],[Fecha promesa de pago]], "mmm")) | T34: =IF(promesas[[#This Row],[Fecha de Pago]]="", "", TEXT(promesas[[#This Row],[Fecha de Pago]], "dd/mmm")) | U34: =IF(promesas[[#This Row],[Fecha promesa de pago]]="", "", TEXT(promesas[[#This Row],[Fecha promesa de pago]], "dd/mmm")) | V34: =IF(LEN(TRIM(promesas[[#This Row],[Fecha promesa de pago]]))>0,1,"") | W34: =IF(LEN(TRIM(promesas[[#This Row],[Fecha de Pago]]))>0,1,"")
A35: =TEXT(promesas[[#This Row],[Marca temporal]],"dd/mmm") -> 04/may | B35: 46146.735 | C35: Lili Velez | D35: 69113842 | E35: 363022490000 | F35: E-8-57306 | G35: Fijo | H35: Masivo (D2D) | I35: Correo de voz | M35: no | P35: 1 MES PENDIENTE | R35: =IF(promesas[[#This Row],[Fecha de Pago]]="", "", TEXT(promesas[[#This Row],[Fecha de Pago]], "mmm")) | S35: =IF(promesas[[#This Row],[Fecha promesa de pago]]="", "", TEXT(promesas[[#This Row],[Fecha promesa de pago]], "mmm")) | T35: =IF(promesas[[#This Row],[Fecha de Pago]]="", "", TEXT(promesas[[#This Row],[Fecha de Pago]], "dd/mmm")) | U35: =IF(promesas[[#This Row],[Fecha promesa de pago]]="", "", TEXT(promesas[[#This Row],[Fecha promesa de pago]], "dd/mmm")) | V35: =IF(LEN(TRIM(promesas[[#This Row],[Fecha promesa de pago]]))>0,1,"") | W35: =IF(LEN(TRIM(promesas[[#This Row],[Fecha de Pago]]))>0,1,"")
A36: =TEXT(promesas[[#This Row],[Marca temporal]],"dd/mmm") -> 04/may | B36: 46146.741 | C36: Lili Velez | D36: 67432803 | E36: 361021220000 | F36: 6-720-1210 | G36: Fijo | H36: Masivo (D2D) | I36: Mensaje a tercero | M36: no | P36: 2 MESES PENDIENTES | R36: =IF(promesas[[#This Row],[Fecha de Pago]]="", "", TEXT(promesas[[#This Row],[Fecha de Pago]], "mmm")) | S36: =IF(promesas[[#This Row],[Fecha promesa de pago]]="", "", TEXT(promesas[[#This Row],[Fecha promesa de pago]], "mmm")) | T36: =IF(promesas[[#This Row],[Fecha de Pago]]="", "", TEXT(promesas[[#This Row],[Fecha de Pago]], "dd/mmm")) | U36: =IF(promesas[[#This Row],[Fecha promesa de pago]]="", "", TEXT(promesas[[#This Row],[Fecha promesa de pago]], "dd/mmm")) | V36: =IF(LEN(TRIM(promesas[[#This Row],[Fecha promesa de pago]]))>0,1,"") | W36: =IF(LEN(TRIM(promesas[[#This Row],[Fecha de Pago]]))>0,1,"")
A37: =TEXT(promesas[[#This Row],[Marca temporal]],"dd/mmm") -> 04/may | B37: 46146.75 | C37: Lili Velez | D37: 67748938 | E37: 368018700000 | F37: 4-792-837 | G37: Fijo | H37: Soho | I37: Correo de voz | M37: no | P37: 3 MESES PENDIENTES | R37: =IF(promesas[[#This Row],[Fecha de Pago]]="", "", TEXT(promesas[[#This Row],[Fecha de Pago]], "mmm")) | S37: =IF(promesas[[#This Row],[Fecha promesa de pago]]="", "", TEXT(promesas[[#This Row],[Fecha promesa de pago]], "mmm")) | T37: =IF(promesas[[#This Row],[Fecha de Pago]]="", "", TEXT(promesas[[#This Row],[Fecha de Pago]], "dd/mmm")) | U37: =IF(promesas[[#This Row],[Fecha promesa de pago]]="", "", TEXT(promesas[[#This Row],[Fecha promesa de pago]], "dd/mmm")) | V37: =IF(LEN(TRIM(promesas[[#This Row],[Fecha promesa de pago]]))>0,1,"") | W37: =IF(LEN(TRIM(promesas[[#This Row],[Fecha de Pago]]))>0,1,"")
A38: =TEXT(promesas[[#This Row],[Marca temporal]],"dd/mmm") -> 05/may | B38: 46147.397 | C38: Lili Velez | D38: 67748938 | E38: 368018700000 | F38: 4-792-837 | G38: Fijo | H38: Soho | I38: Correo de voz | M38: no | P38: 3 MESES PENDIENTES | R38: =IF(promesas[[#This Row],[Fecha de Pago]]="", "", TEXT(promesas[[#This Row],[Fecha de Pago]], "mmm")) | S38: =IF(promesas[[#This Row],[Fecha promesa de pago]]="", "", TEXT(promesas[[#This Row],[Fecha promesa de pago]], "mmm")) | T38: =IF(promesas[[#This Row],[Fecha de Pago]]="", "", TEXT(promesas[[#This Row],[Fecha de Pago]], "dd/mmm")) | U38: =IF(promesas[[#This Row],[Fecha promesa de pago]]="", "", TEXT(promesas[[#This Row],[Fecha promesa de pago]], "dd/mmm")) | V38: =IF(LEN(TRIM(promesas[[#This Row],[Fecha promesa de pago]]))>0,1,"") | W38: =IF(LEN(TRIM(promesas[[#This Row],[Fecha de Pago]]))>0,1,"")
A39: =TEXT(promesas[[#This Row],[Marca temporal]],"dd/mmm") -> 05/may | B39: 46147.409 | C39: Lili Velez | D39: 65084271 | E39: 363022960000 | F39: 8-832-1132 | G39: Fijo | H39: Masivo (D2D) | I39: Mensaje a tercero | M39: no | P39: 3 MESES PENDIENTES | R39: =IF(promesas[[#This Row],[Fecha de Pago]]="", "", TEXT(promesas[[#This Row],[Fecha de Pago]], "mmm")) | S39: =IF(promesas[[#This Row],[Fecha promesa de pago]]="", "", TEXT(promesas[[#This Row],[Fecha promesa de pago]], "mmm")) | T39: =IF(promesas[[#This Row],[Fecha de Pago]]="", "", TEXT(promesas[[#This Row],[Fecha de Pago]], "dd/mmm")) | U39: =IF(promesas[[#This Row],[Fecha promesa de pago]]="", "", TEXT(promesas[[#This Row],[Fecha promesa de pago]], "dd/mmm")) | V39: =IF(LEN(TRIM(promesas[[#This Row],[Fecha promesa de pago]]))>0,1,"") | W39: =IF(LEN(TRIM(promesas[[#This Row],[Fecha de Pago]]))>0,1,"")
A40: =TEXT(promesas[[#This Row],[Marca temporal]],"dd/mmm") -> 05/may | B40: 46147.415 | C40: Lili Velez | D40: 63593036 | E40: 369021040000 | F40: 8-890-1841 | G40: Fijo | H40: Masivo (D2D) | I40: Correo de voz | M40: no | P40: 3 MESES PENDIENTES | R40: =IF(promesas[[#This Row],[Fecha de Pago]]="", "", TEXT(promesas[[#This Row],[Fecha de Pago]], "mmm")) | S40: =IF(promesas[[#This Row],[Fecha promesa de pago]]="", "", TEXT(promesas[[#This Row],[Fecha promesa de pago]], "mmm")) | T40: =IF(promesas[[#This Row],[Fecha de Pago]]="", "", TEXT(promesas[[#This Row],[Fecha de Pago]], "dd/mmm")) | U40: =IF(promesas[[#This Row],[Fecha promesa de pago]]="", "", TEXT(promesas[[#This Row],[Fecha promesa de pago]], "dd/mmm")) | V40: =IF(LEN(TRIM(promesas[[#This Row],[Fecha promesa de pago]]))>0,1,"") | W40: =IF(LEN(TRIM(promesas[[#This Row],[Fecha de Pago]]))>0,1,"")
A41: =TEXT(promesas[[#This Row],[Marca temporal]],"dd/mmm") -> 05/may | B41: 46147.419 | C41: Lili Velez | D41: 64742350 | E41: 368012480000 | F41: 2-756-2423 | G41: Fijo | H41: Masivo (D2D) | I41: Correo de voz | M41: no | P41: 3 MESES PENDIENTES | R41: =IF(promesas[[#This Row],[Fecha de Pago]]="", "", TEXT(promesas[[#This Row],[Fecha de Pago]], "mmm")) | S41: =IF(promesas[[#This Row],[Fecha promesa de pago]]="", "", TEXT(promesas[[#This Row],[Fecha promesa de pago]], "mmm")) | T41: =IF(promesas[[#This Row],[Fecha de Pago]]="", "", TEXT(promesas[[#This Row],[Fecha de Pago]], "dd/mmm")) | U41: =IF(promesas[[#This Row],[Fecha promesa de pago]]="", "", TEXT(promesas[[#This Row],[Fecha promesa de pago]], "dd/mmm")) | V41: =IF(LEN(TRIM(promesas[[#This Row],[Fecha promesa de pago]]))>0,1,"") | W41: =IF(LEN(TRIM(promesas[[#This Row],[Fecha de Pago]]))>0,1,"")
A42: =TEXT(promesas[[#This Row],[Marca temporal]],"dd/mmm") -> 05/may | B42: 46147.427 | C42: Lili Velez | D42: 64116796 | E42: 363009000000 | F42: AU915051 | G42: Fijo | H42: Masivo (D2D) | I42: Mensaje a tercero | M42: no | P42: 3 MESES PENDIENTES | R42: =IF(promesas[[#This Row],[Fecha de Pago]]="", "", TEXT(promesas[[#This Row],[Fecha de Pago]], "mmm")) | S42: =IF(promesas[[#This Row],[Fecha promesa de pago]]="", "", TEXT(promesas[[#This Row],[Fecha promesa de pago]], "mmm")) | T42: =IF(promesas[[#This Row],[Fecha de Pago]]="", "", TEXT(promesas[[#This Row],[Fecha de Pago]], "dd/mmm")) | U42: =IF(promesas[[#This Row],[Fecha promesa de pago]]="", "", TEXT(promesas[[#This Row],[Fecha promesa de pago]], "dd/mmm")) | V42: =IF(LEN(TRIM(promesas[[#This Row],[Fecha promesa de pago]]))>0,1,"") | W42: =IF(LEN(TRIM(promesas[[#This Row],[Fecha de Pago]]))>0,1,"")
A43: =TEXT(promesas[[#This Row],[Marca temporal]],"dd/mmm") -> 05/may | B43: 46147.439 | C43: Lili Velez | D43: 61772742 | E43: 366021580000 | F43: 3-739-2335 | G43: Fijo | H43: Masivo (D2D) | I43: Mensaje a tercero | M43: no | P43: 3 MESES PENDIENTES | R43: =IF(promesas[[#This Row],[Fecha de Pago]]="", "", TEXT(promesas[[#This Row],[Fecha de Pago]], "mmm")) | S43: =IF(promesas[[#This Row],[Fecha promesa de pago]]="", "", TEXT(promesas[[#This Row],[Fecha promesa de pago]], "mmm")) | T43: =IF(promesas[[#This Row],[Fecha de Pago]]="", "", TEXT(promesas[[#This Row],[Fecha de Pago]], "dd/mmm")) | U43: =IF(promesas[[#This Row],[Fecha promesa de pago]]="", "", TEXT(promesas[[#This Row],[Fecha promesa de pago]], "dd/mmm")) | V43: =IF(LEN(TRIM(promesas[[#This Row],[Fecha promesa de pago]]))>0,1,"") | W43: =IF(LEN(TRIM(promesas[[#This Row],[Fecha de Pago]]))>0,1,"")
A44: =TEXT(promesas[[#This Row],[Marca temporal]],"dd/mmm") -> 05/may | B44: 46147.468 | C44: Lili Velez | D44: 66819667 | E44: 366021350000 | F44: 4-763-1330 | G44: Fijo | H44: Digital | I44: Contactado | K44: 46156 | L44: 15.64 | M44: no | P44: 1 MES PENDIENTE | R44: =IF(promesas[[#This Row],[Fecha de Pago]]="", "", TEXT(promesas[[#This Row],[Fecha de Pago]], "mmm")) | S44: =IF(promesas[[#This Row],[Fecha promesa de pago]]="", "", TEXT(promesas[[#This Row],[Fecha promesa de pago]], "mmm")) -> may | T44: =IF(promesas[[#This Row],[Fecha de Pago]]="", "", TEXT(promesas[[#This Row],[Fecha de Pago]], "dd/mmm")) | U44: =IF(promesas[[#This Row],[Fecha promesa de pago]]="", "", TEXT(promesas[[#This Row],[Fecha promesa de pago]], "dd/mmm")) -> 14/may | V44: =IF(LEN(TRIM(promesas[[#This Row],[Fecha promesa de pago]]))>0,1,"") -> 1 | W44: =IF(LEN(TRIM(promesas[[#This Row],[Fecha de Pago]]))>0,1,"")
A45: =TEXT(promesas[[#This Row],[Marca temporal]],"dd/mmm") -> 05/may | B45: 46147.623 | C45: Lili Velez | D45: 63992816 | E45: 369018720000 | F45: 9-756-2437 | G45: Fijo | H45: Masivo (D2D) | I45: Correo de voz | M45: no | P45: 3 MESES PENDIENTES | R45: =IF(promesas[[#This Row],[Fecha de Pago]]="", "", TEXT(promesas[[#This Row],[Fecha de Pago]], "mmm")) | S45: =IF(promesas[[#This Row],[Fecha promesa de pago]]="", "", TEXT(promesas[[#This Row],[Fecha promesa de pago]], "mmm")) | T45: =IF(promesas[[#This Row],[Fecha de Pago]]="", "", TEXT(promesas[[#This Row],[Fecha de Pago]], "dd/mmm")) | U45: =IF(promesas[[#This Row],[Fecha promesa de pago]]="", "", TEXT(promesas[[#This Row],[Fecha promesa de pago]], "dd/mmm")) | V45: =IF(LEN(TRIM(promesas[[#This Row],[Fecha promesa de pago]]))>0,1,"") | W45: =IF(LEN(TRIM(promesas[[#This Row],[Fecha de Pago]]))>0,1,"")
A46: =TEXT(promesas[[#This Row],[Marca temporal]],"dd/mmm") -> 05/may | B46: 46147.63 | C46: Lili Velez | D46: 65132135 | E46: 361016470000 | F46: 8-1045-1303 | G46: Fijo | H46: Masivo (D2D) | I46: Contactado | K46: 46148 | L46: 69.7 | M46: no | P46: 3 MESES PENDIENTES | R46: =IF(promesas[[#This Row],[Fecha de Pago]]="", "", TEXT(promesas[[#This Row],[Fecha de Pago]], "mmm")) | S46: =IF(promesas[[#This Row],[Fecha promesa de pago]]="", "", TEXT(promesas[[#This Row],[Fecha promesa de pago]], "mmm")) -> may | T46: =IF(promesas[[#This Row],[Fecha de Pago]]="", "", TEXT(promesas[[#This Row],[Fecha de Pago]], "dd/mmm")) | U46: =IF(promesas[[#This Row],[Fecha promesa de pago]]="", "", TEXT(promesas[[#This Row],[Fecha promesa de pago]], "dd/mmm")) -> 06/may | V46: =IF(LEN(TRIM(promesas[[#This Row],[Fecha promesa de pago]]))>0,1,"") -> 1 | W46: =IF(LEN(TRIM(promesas[[#This Row],[Fecha de Pago]]))>0,1,"")
A47: =TEXT(promesas[[#This Row],[Marca temporal]],"dd/mmm") -> 05/may | B47: 46147.635 | C47: Lili Velez | D47: 69332905 | E47: 366017230000 | F47: 10-707-1251 | G47: Fijo | H47: Masivo (D2D) | I47: Correo de voz | M47: no | P47: 3 MESES PENDIENTES | R47: =IF(promesas[[#This Row],[Fecha de Pago]]="", "", TEXT(promesas[[#This Row],[Fecha de Pago]], "mmm")) | S47: =IF(promesas[[#This Row],[Fecha promesa de pago]]="", "", TEXT(promesas[[#This Row],[Fecha promesa de pago]], "mmm")) | T47: =IF(promesas[[#This Row],[Fecha de Pago]]="", "", TEXT(promesas[[#This Row],[Fecha de Pago]], "dd/mmm")) | U47: =IF(promesas[[#This Row],[Fecha promesa de pago]]="", "", TEXT(promesas[[#This Row],[Fecha promesa de pago]], "dd/mmm")) | V47: =IF(LEN(TRIM(promesas[[#This Row],[Fecha promesa de pago]]))>0,1,"") | W47: =IF(LEN(TRIM(promesas[[#This Row],[Fecha de Pago]]))>0,1,"")
A48: =TEXT(promesas[[#This Row],[Marca temporal]],"dd/mmm") -> 05/may | B48: 46147.641 | C48: Lili Velez | D48: 66148382 | E48: 362021500000 | F48: 3-107-311 | G48: Fijo | H48: Soho | I48: Correo de voz | M48: no | P48: 1 MES PENDIENTE | R48: =IF(promesas[[#This Row],[Fecha de Pago]]="", "", TEXT(promesas[[#This Row],[Fecha de Pago]], "mmm")) | S48: =IF(promesas[[#This Row],[Fecha promesa de pago]]="", "", TEXT(promesas[[#This Row],[Fecha promesa de pago]], "mmm")) | T48: =IF(promesas[[#This Row],[Fecha de Pago]]="", "", TEXT(promesas[[#This Row],[Fecha de Pago]], "dd/mmm")) | U48: =IF(promesas[[#This Row],[Fecha promesa de pago]]="", "", TEXT(promesas[[#This Row],[Fecha promesa de pago]], "dd/mmm")) | V48: =IF(LEN(TRIM(promesas[[#This Row],[Fecha promesa de pago]]))>0,1,"") | W48: =IF(LEN(TRIM(promesas[[#This Row],[Fecha de Pago]]))>0,1,"")
A49: =TEXT(promesas[[#This Row],[Marca temporal]],"dd/mmm") -> 05/may | B49: 46147.648 | C49: Lili Velez | D49: 65476390 | E49: 365021010000 | F49: 8-1045-1324 | G49: Fijo | H49: Masivo (D2D) | I49: Correo de voz | M49: no | P49: 3 MESES PENDIENTES | R49: =IF(promesas[[#This Row],[Fecha de Pago]]="", "", TEXT(promesas[[#This Row],[Fecha de Pago]], "mmm")) | S49: =IF(promesas[[#This Row],[Fecha promesa de pago]]="", "", TEXT(promesas[[#This Row],[Fecha promesa de pago]], "mmm")) | T49: =IF(promesas[[#This Row],[Fecha de Pago]]="", "", TEXT(promesas[[#This Row],[Fecha de Pago]], "dd/mmm")) | U49: =IF(promesas[[#This Row],[Fecha promesa de pago]]="", "", TEXT(promesas[[#This Row],[Fecha promesa de pago]], "dd/mmm")) | V49: =IF(LEN(TRIM(promesas[[#This Row],[Fecha promesa de pago]]))>0,1,"") | W49: =IF(LEN(TRIM(promesas[[#This Row],[Fecha de Pago]]))>0,1,"")
A50: =TEXT(promesas[[#This Row],[Marca temporal]],"dd/mmm") -> 05/may | B50: 46147.657 | C50: Lili Velez | D50: 65577131 | E50: JUAN CARLOS CORONADO SAMANIEGO | F50: 4-172-402 | G50: Fijo | H50: Masivo (D2D) | I50: Contactado | M50: no | P50: 3 MESES PENDIENTES | R50: =IF(promesas[[#This Row],[Fecha de Pago]]="", "", TEXT(promesas[[#This Row],[Fecha de Pago]], "mmm")) | S50: =IF(promesas[[#This Row],[Fecha promesa de pago]]="", "", TEXT(promesas[[#This Row],[Fecha promesa de pago]], "mmm")) | T50: =IF(promesas[[#This Row],[Fecha de Pago]]="", "", TEXT(promesas[[#This Row],[Fecha de Pago]], "dd/mmm")) | U50: =IF(promesas[[#This Row],[Fecha promesa de pago]]="", "", TEXT(promesas[[#This Row],[Fecha promesa de pago]], "dd/mmm")) | V50: =IF(LEN(TRIM(promesas[[#This Row],[Fecha promesa de pago]]))>0,1,"") | W50: =IF(LEN(TRIM(promesas[[#This Row],[Fecha de Pago]]))>0,1,"")
A51: =TEXT(promesas[[#This Row],[Marca temporal]],"dd/mmm") -> 05/may | B51: 46147.664 | C51: Lili Velez | D51: 69212257 | E51: 361019140000 | F51: 8-718-979 | G51: Fijo | H51: Masivo (D2D) | I51: Correo de voz | M51: no | P51: 3 MESES PENDIENTES | R51: =IF(promesas[[#This Row],[Fecha de Pago]]="", "", TEXT(promesas[[#This Row],[Fecha de Pago]], "mmm")) | S51: =IF(promesas[[#This Row],[Fecha promesa de pago]]="", "", TEXT(promesas[[#This Row],[Fecha promesa de pago]], "mmm")) | T51: =IF(promesas[[#This Row],[Fecha de Pago]]="", "", TEXT(promesas[[#This Row],[Fecha de Pago]], "dd/mmm")) | U51: =IF(promesas[[#This Row],[Fecha promesa de pago]]="", "", TEXT(promesas[[#This Row],[Fecha promesa de pago]], "dd/mmm")) | V51: =IF(LEN(TRIM(promesas[[#This Row],[Fecha promesa de pago]]))>0,1,"") | W51: =IF(LEN(TRIM(promesas[[#This Row],[Fecha de Pago]]))>0,1,"")
A52: =TEXT(promesas[[#This Row],[Marca temporal]],"dd/mmm") -> 05/may | B52: 46147.669 | C52: Lili Velez | D52: 66292976 | E52: 362013050000 | F52: 6-50-347 | G52: Fijo | H52: Masivo (D2D) | I52: Mensaje a tercero | M52: no | P52: 3 MESES PENDIENTES | R52: =IF(promesas[[#This Row],[Fecha de Pago]]="", "", TEXT(promesas[[#This Row],[Fecha de Pago]], "mmm")) | S52: =IF(promesas[[#This Row],[Fecha promesa de pago]]="", "", TEXT(promesas[[#This Row],[Fecha promesa de pago]], "mmm")) | T52: =IF(promesas[[#This Row],[Fecha de Pago]]="", "", TEXT(promesas[[#This Row],[Fecha de Pago]], "dd/mmm")) | U52: =IF(promesas[[#This Row],[Fecha promesa de pago]]="", "", TEXT(promesas[[#This Row],[Fecha promesa de pago]], "dd/mmm")) | V52: =IF(LEN(TRIM(promesas[[#This Row],[Fecha promesa de pago]]))>0,1,"") | W52: =IF(LEN(TRIM(promesas[[#This Row],[Fecha de Pago]]))>0,1,"")
A53: =TEXT(promesas[[#This Row],[Marca temporal]],"dd/mmm") -> 05/may | B53: 46147.678 | C53: Lili Velez | D53: 66558136 | E53: 365021050000 | F53: 9-161-670 | G53: Fijo | H53: Masivo (D2D) | I53: No contactado | M53: no | P53: 2 MESES PENDIENTES | R53: =IF(promesas[[#This Row],[Fecha de Pago]]="", "", TEXT(promesas[[#This Row],[Fecha de Pago]], "mmm")) | S53: =IF(promesas[[#This Row],[Fecha promesa de pago]]="", "", TEXT(promesas[[#This Row],[Fecha promesa de pago]], "mmm")) | T53: =IF(promesas[[#This Row],[Fecha de Pago]]="", "", TEXT(promesas[[#This Row],[Fecha de Pago]], "dd/mmm")) | U53: =IF(promesas[[#This Row],[Fecha promesa de pago]]="", "", TEXT(promesas[[#This Row],[Fecha promesa de pago]], "dd/mmm")) | V53: =IF(LEN(TRIM(promesas[[#This Row],[Fecha promesa de pago]]))>0,1,"") | W53: =IF(LEN(TRIM(promesas[[#This Row],[Fecha de Pago]]))>0,1,"")
A54: =TEXT(promesas[[#This Row],[Marca temporal]],"dd/mmm") -> 05/may | B54: 46147.683 | C54: Lili Velez | D54: 63468147 | E54: 366011850000 | F54: 12-723-1932 | G54: Fijo | H54: Masivo (D2D) | I54: No contactado | M54: no | P54: 3 MESES PENDIENTES | R54: =IF(promesas[[#This Row],[Fecha de Pago]]="", "", TEXT(promesas[[#This Row],[Fecha de Pago]], "mmm")) | S54: =IF(promesas[[#This Row],[Fecha promesa de pago]]="", "", TEXT(promesas[[#This Row],[Fecha promesa de pago]], "mmm")) | T54: =IF(promesas[[#This Row],[Fecha de Pago]]="", "", TEXT(promesas[[#This Row],[Fecha de Pago]], "dd/mmm")) | U54: =IF(promesas[[#This Row],[Fecha promesa de pago]]="", "", TEXT(promesas[[#This Row],[Fecha promesa de pago]], "dd/mmm")) | V54: =IF(LEN(TRIM(promesas[[#This Row],[Fecha promesa de pago]]))>0,1,"") | W54: =IF(LEN(TRIM(promesas[[#This Row],[Fecha de Pago]]))>0,1,"")
A55: =TEXT(promesas[[#This Row],[Marca temporal]],"dd/mmm") -> 05/may | B55: 46147.688 | C55: Lili Velez | D55: 61750050 | E55: 366011850000 | F55: 12-709-2024 | G55: Fijo | H55: Masivo (D2D) | I55: Correo de voz | M55: no | P55: 3 MESES PENDIENTES | R55: =IF(promesas[[#This Row],[Fecha de Pago]]="", "", TEXT(promesas[[#This Row],[Fecha de Pago]], "mmm")) | S55: =IF(promesas[[#This Row],[Fecha promesa de pago]]="", "", TEXT(promesas[[#This Row],[Fecha promesa de pago]], "mmm")) | T55: =IF(promesas[[#This Row],[Fecha de Pago]]="", "", TEXT(promesas[[#This Row],[Fecha de Pago]], "dd/mmm")) | U55: =IF(promesas[[#This Row],[Fecha promesa de pago]]="", "", TEXT(promesas[[#This Row],[Fecha promesa de pago]], "dd/mmm")) | V55: =IF(LEN(TRIM(promesas[[#This Row],[Fecha promesa de pago]]))>0,1,"") | W55: =IF(LEN(TRIM(promesas[[#This Row],[Fecha de Pago]]))>0,1,"")
A56: =TEXT(promesas[[#This Row],[Marca temporal]],"dd/mmm") -> 05/may | B56: 46147.694 | C56: Lili Velez | D56: 66875447 | E56: 357365610000 | F56: 3-757-1943 | G56: Fijo | H56: Masivo (D2D) | I56: Numero equivocado | M56: no | P56: 4 MESES PENDIENTES | R56: =IF(promesas[[#This Row],[Fecha de Pago]]="", "", TEXT(promesas[[#This Row],[Fecha de Pago]], "mmm")) | S56: =IF(promesas[[#This Row],[Fecha promesa de pago]]="", "", TEXT(promesas[[#This Row],[Fecha promesa de pago]], "mmm")) | T56: =IF(promesas[[#This Row],[Fecha de Pago]]="", "", TEXT(promesas[[#This Row],[Fecha de Pago]], "dd/mmm")) | U56: =IF(promesas[[#This Row],[Fecha promesa de pago]]="", "", TEXT(promesas[[#This Row],[Fecha promesa de pago]], "dd/mmm")) | V56: =IF(LEN(TRIM(promesas[[#This Row],[Fecha promesa de pago]]))>0,1,"") | W56: =IF(LEN(TRIM(promesas[[#This Row],[Fecha de Pago]]))>0,1,"")
A57: =TEXT(promesas[[#This Row],[Marca temporal]],"dd/mmm") -> 05/may | B57: 46147.698 | C57: Lili Velez | D57: 66875447 | E57: 367019580000 | F57: 3-757-1943 | G57: Fijo | H57: Masivo (D2D) | I57: Numero equivocado | M57: no | P57: 3 MESES PENDIENTES | R57: =IF(promesas[[#This Row],[Fecha de Pago]]="", "", TEXT(promesas[[#This Row],[Fecha de Pago]], "mmm")) | S57: =IF(promesas[[#This Row],[Fecha promesa de pago]]="", "", TEXT(promesas[[#This Row],[Fecha promesa de pago]], "mmm")) | T57: =IF(promesas[[#This Row],[Fecha de Pago]]="", "", TEXT(promesas[[#This Row],[Fecha de Pago]], "dd/mmm")) | U57: =IF(promesas[[#This Row],[Fecha promesa de pago]]="", "", TEXT(promesas[[#This Row],[Fecha promesa de pago]], "dd/mmm")) | V57: =IF(LEN(TRIM(promesas[[#This Row],[Fecha promesa de pago]]))>0,1,"") | W57: =IF(LEN(TRIM(promesas[[#This Row],[Fecha de Pago]]))>0,1,"")
A58: =TEXT(promesas[[#This Row],[Marca temporal]],"dd/mmm") -> 05/may | B58: 46147.703 | C58: Lili Velez | D58: 64553233 | E58: 361020260000 | F58: 5-708-2167 | G58: Fijo | H58: Digital | I58: Contactado | K58: 46149 | L58: 34.62 | M58: no | P58: 1 MES PENDIENTE | R58: =IF(promesas[[#This Row],[Fecha de Pago]]="", "", TEXT(promesas[[#This Row],[Fecha de Pago]], "mmm")) | S58: =IF(promesas[[#This Row],[Fecha promesa de pago]]="", "", TEXT(promesas[[#This Row],[Fecha promesa de pago]], "mmm")) -> may | T58: =IF(promesas[[#This Row],[Fecha de Pago]]="", "", TEXT(promesas[[#This Row],[Fecha de Pago]], "dd/mmm")) | U58: =IF(promesas[[#This Row],[Fecha promesa de pago]]="", "", TEXT(promesas[[#This Row],[Fecha promesa de pago]], "dd/mmm")) -> 07/may | V58: =IF(LEN(TRIM(promesas[[#This Row],[Fecha promesa de pago]]))>0,1,"") -> 1 | W58: =IF(LEN(TRIM(promesas[[#This Row],[Fecha de Pago]]))>0,1,"")
A59: =TEXT(promesas[[#This Row],[Marca temporal]],"dd/mmm") -> 05/may | B59: 46147.707 | C59: Lili Velez | D59: 65569320 | E59: 364020320000 | F59: 5-21-481 | G59: Fijo | H59: Masivo (D2D) | I59: No contactado | M59: no | P59: NPN | R59: =IF(promesas[[#This Row],[Fecha de Pago]]="", "", TEXT(promesas[[#This Row],[Fecha de Pago]], "mmm")) | S59: =IF(promesas[[#This Row],[Fecha promesa de pago]]="", "", TEXT(promesas[[#This Row],[Fecha promesa de pago]], "mmm")) | T59: =IF(promesas[[#This Row],[Fecha de Pago]]="", "", TEXT(promesas[[#This Row],[Fecha de Pago]], "dd/mmm")) | U59: =IF(promesas[[#This Row],[Fecha promesa de pago]]="", "", TEXT(promesas[[#This Row],[Fecha promesa de pago]], "dd/mmm")) | V59: =IF(LEN(TRIM(promesas[[#This Row],[Fecha promesa de pago]]))>0,1,"") | W59: =IF(LEN(TRIM(promesas[[#This Row],[Fecha de Pago]]))>0,1,"")
A60: =TEXT(promesas[[#This Row],[Marca temporal]],"dd/mmm") -> 05/may | B60: 46147.737 | C60: Lili Velez | D60: 67701108 | E60: 369020630000 | F60: 8-1028-1678 | G60: Fijo | H60: Masivo (D2D) | I60: Correo de voz | M60: no | P60: 3 MESES PENDIENTES | R60: =IF(promesas[[#This Row],[Fecha de Pago]]="", "", TEXT(promesas[[#This Row],[Fecha de Pago]], "mmm")) | S60: =IF(promesas[[#This Row],[Fecha promesa de pago]]="", "", TEXT(promesas[[#This Row],[Fecha promesa de pago]], "mmm")) | T60: =IF(promesas[[#This Row],[Fecha de Pago]]="", "", TEXT(promesas[[#This Row],[Fecha de Pago]], "dd/mmm")) | U60: =IF(promesas[[#This Row],[Fecha promesa de pago]]="", "", TEXT(promesas[[#This Row],[Fecha promesa de pago]], "dd/mmm")) | V60: =IF(LEN(TRIM(promesas[[#This Row],[Fecha promesa de pago]]))>0,1,"") | W60: =IF(LEN(TRIM(promesas[[#This Row],[Fecha de Pago]]))>0,1,"")
A61: =TEXT(promesas[[#This Row],[Marca temporal]],"dd/mmm") -> 05/may | B61: 46147.74 | C61: Lili Velez | D61: 62472323 | E61: 361019250000 | F61: 4-832-2012 | G61: Fijo | H61: Soho | I61: No contactado | M61: no | P61: 1 MES PENDIENTE | R61: =IF(promesas[[#This Row],[Fecha de Pago]]="", "", TEXT(promesas[[#This Row],[Fecha de Pago]], "mmm")) | S61: =IF(promesas[[#This Row],[Fecha promesa de pago]]="", "", TEXT(promesas[[#This Row],[Fecha promesa de pago]], "mmm")) | T61: =IF(promesas[[#This Row],[Fecha de Pago]]="", "", TEXT(promesas[[#This Row],[Fecha de Pago]], "dd/mmm")) | U61: =IF(promesas[[#This Row],[Fecha promesa de pago]]="", "", TEXT(promesas[[#This Row],[Fecha promesa de pago]], "dd/mmm")) | V61: =IF(LEN(TRIM(promesas[[#This Row],[Fecha promesa de pago]]))>0,1,"") | W61: =IF(LEN(TRIM(promesas[[#This Row],[Fecha de Pago]]))>0,1,"")
A62: =TEXT(promesas[[#This Row],[Marca temporal]],"dd/mmm") -> 05/may | B62: 46147.743 | C62: Lili Velez | D62: 68006980 | E62: 369019460000 | F62: 3-701-694 | G62: Fijo | H62: Masivo (D2D) | I62: No contactado | M62: no | P62: 1 MES PENDIENTE | R62: =IF(promesas[[#This Row],[Fecha de Pago]]="", "", TEXT(promesas[[#This Row],[Fecha de Pago]], "mmm")) | S62: =IF(promesas[[#This Row],[Fecha promesa de pago]]="", "", TEXT(promesas[[#This Row],[Fecha promesa de pago]], "mmm")) | T62: =IF(promesas[[#This Row],[Fecha de Pago]]="", "", TEXT(promesas[[#This Row],[Fecha de Pago]], "dd/mmm")) | U62: =IF(promesas[[#This Row],[Fecha promesa de pago]]="", "", TEXT(promesas[[#This Row],[Fecha promesa de pago]], "dd/mmm")) | V62: =IF(LEN(TRIM(promesas[[#This Row],[Fecha promesa de pago]]))>0,1,"") | W62: =IF(LEN(TRIM(promesas[[#This Row],[Fecha de Pago]]))>0,1,"")
A63: =TEXT(promesas[[#This Row],[Marca temporal]],"dd/mmm") -> 05/may | B63: 46147.746 | C63: Lili Velez | D63: 63246343 | E63: 358371710000 | F63: 9-157-407 | G63: Fijo | H63: Masivo (D2D) | I63: No contactado | M63: no | P63: 3 MESES PENDIENTES | R63: =IF(promesas[[#This Row],[Fecha de Pago]]="", "", TEXT(promesas[[#This Row],[Fecha de Pago]], "mmm")) | S63: =IF(promesas[[#This Row],[Fecha promesa de pago]]="", "", TEXT(promesas[[#This Row],[Fecha promesa de pago]], "mmm")) | T63: =IF(promesas[[#This Row],[Fecha de Pago]]="", "", TEXT(promesas[[#This Row],[Fecha de Pago]], "dd/mmm")) | U63: =IF(promesas[[#This Row],[Fecha promesa de pago]]="", "", TEXT(promesas[[#This Row],[Fecha promesa de pago]], "dd/mmm")) | V63: =IF(LEN(TRIM(promesas[[#This Row],[Fecha promesa de pago]]))>0,1,"") | W63: =IF(LEN(TRIM(promesas[[#This Row],[Fecha de Pago]]))>0,1,"")
A64: =TEXT(promesas[[#This Row],[Marca temporal]],"dd/mmm") -> 05/may | B64: 46147.749 | C64: Lili Velez | D64: 69694351 | E64: 362020360000 | F64: 8-1049-578 | G64: Fijo | H64: Masivo (D2D) | I64: Correo de voz | M64: no | P64: 1 MES PENDIENTE | R64: =IF(promesas[[#This Row],[Fecha de Pago]]="", "", TEXT(promesas[[#This Row],[Fecha de Pago]], "mmm")) | S64: =IF(promesas[[#This Row],[Fecha promesa de pago]]="", "", TEXT(promesas[[#This Row],[Fecha promesa de pago]], "mmm")) | T64: =IF(promesas[[#This Row],[Fecha de Pago]]="", "", TEXT(promesas[[#This Row],[Fecha de Pago]], "dd/mmm")) | U64: =IF(promesas[[#This Row],[Fecha promesa de pago]]="", "", TEXT(promesas[[#This Row],[Fecha promesa de pago]], "dd/mmm")) | V64: =IF(LEN(TRIM(promesas[[#This Row],[Fecha promesa de pago]]))>0,1,"") | W64: =IF(LEN(TRIM(promesas[[#This Row],[Fecha de Pago]]))>0,1,"")
A65: =TEXT(promesas[[#This Row],[Marca temporal]],"dd/mmm") -> 06/may | B65: 46148.395 | C65: Lili Velez | D65: 64449407 | E65: 366018320000 | F65: 8-1041-1168 | G65: Fijo | H65: Masivo (D2D) | I65: Correo de voz | M65: no | P65: 3 MESES PENDIENTES | R65: =IF(promesas[[#This Row],[Fecha de Pago]]="", "", TEXT(promesas[[#This Row],[Fecha de Pago]], "mmm")) | S65: =IF(promesas[[#This Row],[Fecha promesa de pago]]="", "", TEXT(promesas[[#This Row],[Fecha promesa de pago]], "mmm")) | T65: =IF(promesas[[#This Row],[Fecha de Pago]]="", "", TEXT(promesas[[#This Row],[Fecha de Pago]], "dd/mmm")) | U65: =IF(promesas[[#This Row],[Fecha promesa de pago]]="", "", TEXT(promesas[[#This Row],[Fecha promesa de pago]], "dd/mmm")) | V65: =IF(LEN(TRIM(promesas[[#This Row],[Fecha promesa de pago]]))>0,1,"") | W65: =IF(LEN(TRIM(promesas[[#This Row],[Fecha de Pago]]))>0,1,"")
A66: =TEXT(promesas[[#This Row],[Marca temporal]],"dd/mmm") -> 06/may | B66: 46148.404 | C66: Lili Velez | D66: 64449407 | E66: 357186870000 | F66: 8-813-1496 | G66: Fijo | H66: Masivo (D2D) | I66: Correo de voz | M66: no | P66: 3 MESES PENDIENTES | R66: =IF(promesas[[#This Row],[Fecha de Pago]]="", "", TEXT(promesas[[#This Row],[Fecha de Pago]], "mmm")) | S66: =IF(promesas[[#This Row],[Fecha promesa de pago]]="", "", TEXT(promesas[[#This Row],[Fecha promesa de pago]], "mmm")) | T66: =IF(promesas[[#This Row],[Fecha de Pago]]="", "", TEXT(promesas[[#This Row],[Fecha de Pago]], "dd/mmm")) | U66: =IF(promesas[[#This Row],[Fecha promesa de pago]]="", "", TEXT(promesas[[#This Row],[Fecha promesa de pago]], "dd/mmm")) | V66: =IF(LEN(TRIM(promesas[[#This Row],[Fecha promesa de pago]]))>0,1,"") | W66: =IF(LEN(TRIM(promesas[[#This Row],[Fecha de Pago]]))>0,1,"")
A67: =TEXT(promesas[[#This Row],[Marca temporal]],"dd/mmm") -> 06/may | B67: 46148.407 | C67: Lili Velez | D67: 68962490 | E67: 281011940000 | F67: 8-866-1822 | G67: Fijo | H67: Masivo (D2D) | I67: Contactado | K67: 46148 | L67: 30.44 | M67: no | P67: 2 MESES PENDIENTES | R67: =IF(promesas[[#This Row],[Fecha de Pago]]="", "", TEXT(promesas[[#This Row],[Fecha de Pago]], "mmm")) | S67: =IF(promesas[[#This Row],[Fecha promesa de pago]]="", "", TEXT(promesas[[#This Row],[Fecha promesa de pago]], "mmm")) -> may | T67: =IF(promesas[[#This Row],[Fecha de Pago]]="", "", TEXT(promesas[[#This Row],[Fecha de Pago]], "dd/mmm")) | U67: =IF(promesas[[#This Row],[Fecha promesa de pago]]="", "", TEXT(promesas[[#This Row],[Fecha promesa de pago]], "dd/mmm")) -> 06/may | V67: =IF(LEN(TRIM(promesas[[#This Row],[Fecha promesa de pago]]))>0,1,"") -> 1 | W67: =IF(LEN(TRIM(promesas[[#This Row],[Fecha de Pago]]))>0,1,"")
A68: =TEXT(promesas[[#This Row],[Marca temporal]],"dd/mmm") -> 06/may | B68: 46148.412 | C68: Lili Velez | D68: 66047682 | E68: 361074360000 | F68: 8-956-716 | G68: Fijo | H68: Masivo (D2D) | I68: Correo de voz | M68: no | P68: NPN | R68: =IF(promesas[[#This Row],[Fecha de Pago]]="", "", TEXT(promesas[[#This Row],[Fecha de Pago]], "mmm")) | S68: =IF(promesas[[#This Row],[Fecha promesa de pago]]="", "", TEXT(promesas[[#This Row],[Fecha promesa de pago]], "mmm")) | T68: =IF(promesas[[#This Row],[Fecha de Pago]]="", "", TEXT(promesas[[#This Row],[Fecha de Pago]], "dd/mmm")) | U68: =IF(promesas[[#This Row],[Fecha promesa de pago]]="", "", TEXT(promesas[[#This Row],[Fecha promesa de pago]], "dd/mmm")) | V68: =IF(LEN(TRIM(promesas[[#This Row],[Fecha promesa de pago]]))>0,1,"") | W68: =IF(LEN(TRIM(promesas[[#This Row],[Fecha de Pago]]))>0,1,"")
A69: =TEXT(promesas[[#This Row],[Marca temporal]],"dd/mmm") -> 06/may | B69: 46148.426 | C69: Lili Velez | D69: 64449407 | E69: 155078170000 | F69: 2-46-534 | G69: Fijo | H69: Masivo (D2D) | I69: Contactado | K69: 46150 | L69: 34.92 | M69: no | P69: 2 MESES PENDIENTES | R69: =IF(promesas[[#This Row],[Fecha de Pago]]="", "", TEXT(promesas[[#This Row],[Fecha de Pago]], "mmm")) | S69: =IF(promesas[[#This Row],[Fecha promesa de pago]]="", "", TEXT(promesas[[#This Row],[Fecha promesa de pago]], "mmm")) -> may | T69: =IF(promesas[[#This Row],[Fecha de Pago]]="", "", TEXT(promesas[[#This Row],[Fecha de Pago]], "dd/mmm")) | U69: =IF(promesas[[#This Row],[Fecha promesa de pago]]="", "", TEXT(promesas[[#This Row],[Fecha promesa de pago]], "dd/mmm")) -> 08/may | V69: =IF(LEN(TRIM(promesas[[#This Row],[Fecha promesa de pago]]))>0,1,"") -> 1 | W69: =IF(LEN(TRIM(promesas[[#This Row],[Fecha de Pago]]))>0,1,"")
A70: =TEXT(promesas[[#This Row],[Marca temporal]],"dd/mmm") -> 06/may | B70: 46148.431 | C70: Lili Velez | D70: 66662952 | E70: 292092850000 | F70: 8-885-662 | G70: Fijo | H70: Call Center Outbound | I70: No contactado | M70: no | P70: 2 MESES PENDIENTES | R70: =IF(promesas[[#This Row],[Fecha de Pago]]="", "", TEXT(promesas[[#This Row],[Fecha de Pago]], "mmm")) | S70: =IF(promesas[[#This Row],[Fecha promesa de pago]]="", "", TEXT(promesas[[#This Row],[Fecha promesa de pago]], "mmm")) | T70: =IF(promesas[[#This Row],[Fecha de Pago]]="", "", TEXT(promesas[[#This Row],[Fecha de Pago]], "dd/mmm")) | U70: =IF(promesas[[#This Row],[Fecha promesa de pago]]="", "", TEXT(promesas[[#This Row],[Fecha promesa de pago]], "dd/mmm")) | V70: =IF(LEN(TRIM(promesas[[#This Row],[Fecha promesa de pago]]))>0,1,"") | W70: =IF(LEN(TRIM(promesas[[#This Row],[Fecha de Pago]]))>0,1,"")
A71: =TEXT(promesas[[#This Row],[Marca temporal]],"dd/mmm") -> 06/may | B71: 46148.438 | C71: Lili Velez | D71: 64449407 | E71: 361023080000 | F71: 9-754-2237 | G71: Fijo | H71: Masivo (D2D) | I71: Contactado | K71: 46152 | L71: 76.18 | M71: no | P71: 3 MESES PENDIENTES | R71: =IF(promesas[[#This Row],[Fecha de Pago]]="", "", TEXT(promesas[[#This Row],[Fecha de Pago]], "mmm")) | S71: =IF(promesas[[#This Row],[Fecha promesa de pago]]="", "", TEXT(promesas[[#This Row],[Fecha promesa de pago]], "mmm")) -> may | T71: =IF(promesas[[#This Row],[Fecha de Pago]]="", "", TEXT(promesas[[#This Row],[Fecha de Pago]], "dd/mmm")) | U71: =IF(promesas[[#This Row],[Fecha promesa de pago]]="", "", TEXT(promesas[[#This Row],[Fecha promesa de pago]], "dd/mmm")) -> 10/may | V71: =IF(LEN(TRIM(promesas[[#This Row],[Fecha promesa de pago]]))>0,1,"") -> 1 | W71: =IF(LEN(TRIM(promesas[[#This Row],[Fecha de Pago]]))>0,1,"")
A72: =TEXT(promesas[[#This Row],[Marca temporal]],"dd/mmm") -> 06/may | B72: 46148.443 | C72: Lili Velez | D72: 64449407 | E72: 366018320000 | F72: 8-1041-1168 | G72: Fijo | H72: Masivo (D2D) | I72: No contactado | M72: no | P72: 3 MESES PENDIENTES | R72: =IF(promesas[[#This Row],[Fecha de Pago]]="", "", TEXT(promesas[[#This Row],[Fecha de Pago]], "mmm")) | S72: =IF(promesas[[#This Row],[Fecha promesa de pago]]="", "", TEXT(promesas[[#This Row],[Fecha promesa de pago]], "mmm")) | T72: =IF(promesas[[#This Row],[Fecha de Pago]]="", "", TEXT(promesas[[#This Row],[Fecha de Pago]], "dd/mmm")) | U72: =IF(promesas[[#This Row],[Fecha promesa de pago]]="", "", TEXT(promesas[[#This Row],[Fecha promesa de pago]], "dd/mmm")) | V72: =IF(LEN(TRIM(promesas[[#This Row],[Fecha promesa de pago]]))>0,1,"") | W72: =IF(LEN(TRIM(promesas[[#This Row],[Fecha de Pago]]))>0,1,"")
A73: =TEXT(promesas[[#This Row],[Marca temporal]],"dd/mmm") -> 06/may | B73: 46148.449 | C73: Lili Velez | D73: 66256004 | E73: 369016760000 | F73: AV080090 | G73: Fijo | H73: Masivo (D2D) | I73: Correo de voz | M73: no | P73: 3 MESES PENDIENTES | R73: =IF(promesas[[#This Row],[Fecha de Pago]]="", "", TEXT(promesas[[#This Row],[Fecha de Pago]], "mmm")) | S73: =IF(promesas[[#This Row],[Fecha promesa de pago]]="", "", TEXT(promesas[[#This Row],[Fecha promesa de pago]], "mmm")) | T73: =IF(promesas[[#This Row],[Fecha de Pago]]="", "", TEXT(promesas[[#This Row],[Fecha de Pago]], "dd/mmm")) | U73: =IF(promesas[[#This Row],[Fecha promesa de pago]]="", "", TEXT(promesas[[#This Row],[Fecha promesa de pago]], "dd/mmm")) | V73: =IF(LEN(TRIM(promesas[[#This Row],[Fecha promesa de pago]]))>0,1,"") | W73: =IF(LEN(TRIM(promesas[[#This Row],[Fecha de Pago]]))>0,1,"")
A74: =TEXT(promesas[[#This Row],[Marca temporal]],"dd/mmm") -> 06/may | B74: 46148.458 | C74: Lili Velez | D74: 67147458 | E74: 362019070000 | F74: 2-116-496 | G74: Fijo | H74: Masivo (D2D) | I74: No contactado | M74: no | P74: 2 MESES PENDIENTES | R74: =IF(promesas[[#This Row],[Fecha de Pago]]="", "", TEXT(promesas[[#This Row],[Fecha de Pago]], "mmm")) | S74: =IF(promesas[[#This Row],[Fecha promesa de pago]]="", "", TEXT(promesas[[#This Row],[Fecha promesa de pago]], "mmm")) | T74: =IF(promesas[[#This Row],[Fecha de Pago]]="", "", TEXT(promesas[[#This Row],[Fecha de Pago]], "dd/mmm")) | U74: =IF(promesas[[#This Row],[Fecha promesa de pago]]="", "", TEXT(promesas[[#This Row],[Fecha promesa de pago]], "dd/mmm")) | V74: =IF(LEN(TRIM(promesas[[#This Row],[Fecha promesa de pago]]))>0,1,"") | W74: =IF(LEN(TRIM(promesas[[#This Row],[Fecha de Pago]]))>0,1,"")
A75: =TEXT(promesas[[#This Row],[Marca temporal]],"dd/mmm") -> 06/may | B75: 46148.465 | C75: Lili Velez | D75: 64443816 | E75: 368018640000 | F75: 8-954-559 | G75: Fijo | H75: Soho | I75: Correo de voz | M75: no | P75: 1 MES PENDIENTE | R75: =IF(promesas[[#This Row],[Fecha de Pago]]="", "", TEXT(promesas[[#This Row],[Fecha de Pago]], "mmm")) | S75: =IF(promesas[[#This Row],[Fecha promesa de pago]]="", "", TEXT(promesas[[#This Row],[Fecha promesa de pago]], "mmm")) | T75: =IF(promesas[[#This Row],[Fecha de Pago]]="", "", TEXT(promesas[[#This Row],[Fecha de Pago]], "dd/mmm")) | U75: =IF(promesas[[#This Row],[Fecha promesa de pago]]="", "", TEXT(promesas[[#This Row],[Fecha promesa de pago]], "dd/mmm")) | V75: =IF(LEN(TRIM(promesas[[#This Row],[Fecha promesa de pago]]))>0,1,"") | W75: =IF(LEN(TRIM(promesas[[#This Row],[Fecha de Pago]]))>0,1,"")
A76: =TEXT(promesas[[#This Row],[Marca temporal]],"dd/mmm") -> 06/may | B76: 46148.469 | C76: Lili Velez | D76: 65160807 | E76: 366014760000 | F76: CO3818210 | G76: Fijo | H76: Masivo (D2D) | I76: Mensaje a tercero | M76: no | P76: 3 MESES PENDIENTES | R76: =IF(promesas[[#This Row],[Fecha de Pago]]="", "", TEXT(promesas[[#This Row],[Fecha de Pago]], "mmm")) | S76: =IF(promesas[[#This Row],[Fecha promesa de pago]]="", "", TEXT(promesas[[#This Row],[Fecha promesa de pago]], "mmm")) | T76: =IF(promesas[[#This Row],[Fecha de Pago]]="", "", TEXT(promesas[[#This Row],[Fecha de Pago]], "dd/mmm")) | U76: =IF(promesas[[#This Row],[Fecha promesa de pago]]="", "", TEXT(promesas[[#This Row],[Fecha promesa de pago]], "dd/mmm")) | V76: =IF(LEN(TRIM(promesas[[#This Row],[Fecha promesa de pago]]))>0,1,"") | W76: =IF(LEN(TRIM(promesas[[#This Row],[Fecha de Pago]]))>0,1,"")
A77: =TEXT(promesas[[#This Row],[Marca temporal]],"dd/mmm") -> 06/may | B77: 46148.473 | C77: Lili Velez | D77: 61266064 | E77: 365016880000 | F77: 10-710-1003 | G77: Fijo | H77: Masivo (D2D) | I77: No contactado | M77: no | P77: 1 MES PENDIENTE | R77: =IF(promesas[[#This Row],[Fecha de Pago]]="", "", TEXT(promesas[[#This Row],[Fecha de Pago]], "mmm")) | S77: =IF(promesas[[#This Row],[Fecha promesa de pago]]="", "", TEXT(promesas[[#This Row],[Fecha promesa de pago]], "mmm")) | T77: =IF(promesas[[#This Row],[Fecha de Pago]]="", "", TEXT(promesas[[#This Row],[Fecha de Pago]], "dd/mmm")) | U77: =IF(promesas[[#This Row],[Fecha promesa de pago]]="", "", TEXT(promesas[[#This Row],[Fecha promesa de pago]], "dd/mmm")) | V77: =IF(LEN(TRIM(promesas[[#This Row],[Fecha promesa de pago]]))>0,1,"") | W77: =IF(LEN(TRIM(promesas[[#This Row],[Fecha de Pago]]))>0,1,"")
A78: =TEXT(promesas[[#This Row],[Marca temporal]],"dd/mmm") -> 06/may | B78: 46148.478 | C78: Lili Velez | D78: 68342815 | E78: 365012970000 | F78: 8-810-2035 | G78: Fijo | H78: Masivo (D2D) | I78: Mensaje a tercero | M78: no | P78: 3 MESES PENDIENTES | R78: =IF(promesas[[#This Row],[Fecha de Pago]]="", "", TEXT(promesas[[#This Row],[Fecha de Pago]], "mmm")) | S78: =IF(promesas[[#This Row],[Fecha promesa de pago]]="", "", TEXT(promesas[[#This Row],[Fecha promesa de pago]], "mmm")) | T78: =IF(promesas[[#This Row],[Fecha de Pago]]="", "", TEXT(promesas[[#This Row],[Fecha de Pago]], "dd/mmm")) | U78: =IF(promesas[[#This Row],[Fecha promesa de pago]]="", "", TEXT(promesas[[#This Row],[Fecha promesa de pago]], "dd/mmm")) | V78: =IF(LEN(TRIM(promesas[[#This Row],[Fecha promesa de pago]]))>0,1,"") | W78: =IF(LEN(TRIM(promesas[[#This Row],[Fecha de Pago]]))>0,1,"")
A79: =TEXT(promesas[[#This Row],[Marca temporal]],"dd/mmm") -> 06/may | B79: 46148.484 | C79: Lili Velez | D79: 63916067 | E79: 363007240000 | F79: 8-1024-159 | G79: Fijo | H79: Masivo (D2D) | I79: Correo de voz | M79: no | P79: 3 MESES PENDIENTES | R79: =IF(promesas[[#This Row],[Fecha de Pago]]="", "", TEXT(promesas[[#This Row],[Fecha de Pago]], "mmm")) | S79: =IF(promesas[[#This Row],[Fecha promesa de pago]]="", "", TEXT(promesas[[#This Row],[Fecha promesa de pago]], "mmm")) | T79: =IF(promesas[[#This Row],[Fecha de Pago]]="", "", TEXT(promesas[[#This Row],[Fecha de Pago]], "dd/mmm")) | U79: =IF(promesas[[#This Row],[Fecha promesa de pago]]="", "", TEXT(promesas[[#This Row],[Fecha promesa de pago]], "dd/mmm")) | V79: =IF(LEN(TRIM(promesas[[#This Row],[Fecha promesa de pago]]))>0,1,"") | W79: =IF(LEN(TRIM(promesas[[#This Row],[Fecha de Pago]]))>0,1,"")
A80: =TEXT(promesas[[#This Row],[Marca temporal]],"dd/mmm") -> 06/may | B80: 46148.489 | C80: Lili Velez | D80: 68933284 | E80: 368018870000 | F80: 8-996-123 | G80: Fijo | H80: Masivo (D2D) | I80: Mensaje a tercero | M80: no | P80: 3 MESES PENDIENTES | R80: =IF(promesas[[#This Row],[Fecha de Pago]]="", "", TEXT(promesas[[#This Row],[Fecha de Pago]], "mmm")) | S80: =IF(promesas[[#This Row],[Fecha promesa de pago]]="", "", TEXT(promesas[[#This Row],[Fecha promesa de pago]], "mmm")) | T80: =IF(promesas[[#This Row],[Fecha de Pago]]="", "", TEXT(promesas[[#This Row],[Fecha de Pago]], "dd/mmm")) | U80: =IF(promesas[[#This Row],[Fecha promesa de pago]]="", "", TEXT(promesas[[#This Row],[Fecha promesa de pago]], "dd/mmm")) | V80: =IF(LEN(TRIM(promesas[[#This Row],[Fecha promesa de pago]]))>0,1,"") | W80: =IF(LEN(TRIM(promesas[[#This Row],[Fecha de Pago]]))>0,1,"")
A81: =TEXT(promesas[[#This Row],[Marca temporal]],"dd/mmm") -> 06/may | B81: 46148.493 | C81: Lili Velez | D81: 64757907 | E81: 369018260000 | F81: 8-83-248 | G81: Fijo | H81: Masivo (D2D) | I81: Correo de voz | M81: no | P81: 3 MESES PENDIENTES | R81: =IF(promesas[[#This Row],[Fecha de Pago]]="", "", TEXT(promesas[[#This Row],[Fecha de Pago]], "mmm")) | S81: =IF(promesas[[#This Row],[Fecha promesa de pago]]="", "", TEXT(promesas[[#This Row],[Fecha promesa de pago]], "mmm")) | T81: =IF(promesas[[#This Row],[Fecha de Pago]]="", "", TEXT(promesas[[#This Row],[Fecha de Pago]], "dd/mmm")) | U81: =IF(promesas[[#This Row],[Fecha promesa de pago]]="", "", TEXT(promesas[[#This Row],[Fecha promesa de pago]], "dd/mmm")) | V81: =IF(LEN(TRIM(promesas[[#This Row],[Fecha promesa de pago]]))>0,1,"") | W81: =IF(LEN(TRIM(promesas[[#This Row],[Fecha de Pago]]))>0,1,"")
A82: =TEXT(promesas[[#This Row],[Marca temporal]],"dd/mmm") -> 06/may | B82: 46148.5 | C82: Lili Velez | D82: 63968835 | E82: 359264140000 | F82: 8-865-1901 | G82: Fijo | H82: Masivo (D2D) | I82: Contactado | M82: no | P82: 2 MESES PENDIENTES | R82: =IF(promesas[[#This Row],[Fecha de Pago]]="", "", TEXT(promesas[[#This Row],[Fecha de Pago]], "mmm")) | S82: =IF(promesas[[#This Row],[Fecha promesa de pago]]="", "", TEXT(promesas[[#This Row],[Fecha promesa de pago]], "mmm")) | T82: =IF(promesas[[#This Row],[Fecha de Pago]]="", "", TEXT(promesas[[#This Row],[Fecha de Pago]], "dd/mmm")) | U82: =IF(promesas[[#This Row],[Fecha promesa de pago]]="", "", TEXT(promesas[[#This Row],[Fecha promesa de pago]], "dd/mmm")) | V82: =IF(LEN(TRIM(promesas[[#This Row],[Fecha promesa de pago]]))>0,1,"") | W82: =IF(LEN(TRIM(promesas[[#This Row],[Fecha de Pago]]))>0,1,"")
A83: =TEXT(promesas[[#This Row],[Marca temporal]],"dd/mmm") -> 06/may | B83: 46148.507 | C83: Lili Velez | D83: 64847304 | E83: 364016680000 | F83: 167067023 | G83: Fijo | H83: Digital | I83: No contactado | M83: no | P83: 3 MESES PENDIENTES | R83: =IF(promesas[[#This Row],[Fecha de Pago]]="", "", TEXT(promesas[[#This Row],[Fecha de Pago]], "mmm")) | S83: =IF(promesas[[#This Row],[Fecha promesa de pago]]="", "", TEXT(promesas[[#This Row],[Fecha promesa de pago]], "mmm")) | T83: =IF(promesas[[#This Row],[Fecha de Pago]]="", "", TEXT(promesas[[#This Row],[Fecha de Pago]], "dd/mmm")) | U83: =IF(promesas[[#This Row],[Fecha promesa de pago]]="", "", TEXT(promesas[[#This Row],[Fecha promesa de pago]], "dd/mmm")) | V83: =IF(LEN(TRIM(promesas[[#This Row],[Fecha promesa de pago]]))>0,1,"") | W83: =IF(LEN(TRIM(promesas[[#This Row],[Fecha de Pago]]))>0,1,"")
A84: =TEXT(promesas[[#This Row],[Marca temporal]],"dd/mmm") -> 06/may | B84: 46148.512 | C84: Lili Velez | D84: 67729632 | E84: 361007990000 | F84: BG422717 | G84: Fijo | H84: Soho | I84: Contactado | K84: 46157 | L84: 31.34 | M84: no | P84: 1 MES PENDIENTE | R84: =IF(promesas[[#This Row],[Fecha de Pago]]="", "", TEXT(promesas[[#This Row],[Fecha de Pago]], "mmm")) | S84: =IF(promesas[[#This Row],[Fecha promesa de pago]]="", "", TEXT(promesas[[#This Row],[Fecha promesa de pago]], "mmm")) -> may | T84: =IF(promesas[[#This Row],[Fecha de Pago]]="", "", TEXT(promesas[[#This Row],[Fecha de Pago]], "dd/mmm")) | U84: =IF(promesas[[#This Row],[Fecha promesa de pago]]="", "", TEXT(promesas[[#This Row],[Fecha promesa de pago]], "dd/mmm")) -> 15/may | V84: =IF(LEN(TRIM(promesas[[#This Row],[Fecha promesa de pago]]))>0,1,"") -> 1 | W84: =IF(LEN(TRIM(promesas[[#This Row],[Fecha de Pago]]))>0,1,"")
A85: =TEXT(promesas[[#This Row],[Marca temporal]],"dd/mmm") -> 06/may | B85: 46148.519 | C85: Lili Velez | D85: 63916363 | E85: 363016010000 | F85: 8-1038-1551 | G85: Fijo | H85: Masivo (D2D) | I85: Correo de voz | M85: no | P85: 3 MESES PENDIENTES | R85: =IF(promesas[[#This Row],[Fecha de Pago]]="", "", TEXT(promesas[[#This Row],[Fecha de Pago]], "mmm")) | S85: =IF(promesas[[#This Row],[Fecha promesa de pago]]="", "", TEXT(promesas[[#This Row],[Fecha promesa de pago]], "mmm")) | T85: =IF(promesas[[#This Row],[Fecha de Pago]]="", "", TEXT(promesas[[#This Row],[Fecha de Pago]], "dd/mmm")) | U85: =IF(promesas[[#This Row],[Fecha promesa de pago]]="", "", TEXT(promesas[[#This Row],[Fecha promesa de pago]], "dd/mmm")) | V85: =IF(LEN(TRIM(promesas[[#This Row],[Fecha promesa de pago]]))>0,1,"") | W85: =IF(LEN(TRIM(promesas[[#This Row],[Fecha de Pago]]))>0,1,"")
A86: =TEXT(promesas[[#This Row],[Marca temporal]],"dd/mmm") -> 06/may | B86: 46148.523 | C86: Lili Velez | D86: 64935364 | E86: 362013070000 | F86: 5-9-623 | G86: Fijo | H86: Masivo (D2D) | I86: Correo de voz | M86: no | P86: 3 MESES PENDIENTES | R86: =IF(promesas[[#This Row],[Fecha de Pago]]="", "", TEXT(promesas[[#This Row],[Fecha de Pago]], "mmm")) | S86: =IF(promesas[[#This Row],[Fecha promesa de pago]]="", "", TEXT(promesas[[#This Row],[Fecha promesa de pago]], "mmm")) | T86: =IF(promesas[[#This Row],[Fecha de Pago]]="", "", TEXT(promesas[[#This Row],[Fecha de Pago]], "dd/mmm")) | U86: =IF(promesas[[#This Row],[Fecha promesa de pago]]="", "", TEXT(promesas[[#This Row],[Fecha promesa de pago]], "dd/mmm")) | V86: =IF(LEN(TRIM(promesas[[#This Row],[Fecha promesa de pago]]))>0,1,"") | W86: =IF(LEN(TRIM(promesas[[#This Row],[Fecha de Pago]]))>0,1,"")
A87: =TEXT(promesas[[#This Row],[Marca temporal]],"dd/mmm") -> 06/may | B87: 46148.529 | C87: Lili Velez | D87: 64590545 | E87: 313014210000 | F87: 8-210-104 | G87: Fijo | H87: Call Center Outbound | I87: Correo de voz | M87: no | P87: 2 MESES PENDIENTES | R87: =IF(promesas[[#This Row],[Fecha de Pago]]="", "", TEXT(promesas[[#This Row],[Fecha de Pago]], "mmm")) | S87: =IF(promesas[[#This Row],[Fecha promesa de pago]]="", "", TEXT(promesas[[#This Row],[Fecha promesa de pago]], "mmm")) | T87: =IF(promesas[[#This Row],[Fecha de Pago]]="", "", TEXT(promesas[[#This Row],[Fecha de Pago]], "dd/mmm")) | U87: =IF(promesas[[#This Row],[Fecha promesa de pago]]="", "", TEXT(promesas[[#This Row],[Fecha promesa de pago]], "dd/mmm")) | V87: =IF(LEN(TRIM(promesas[[#This Row],[Fecha promesa de pago]]))>0,1,"") | W87: =IF(LEN(TRIM(promesas[[#This Row],[Fecha de Pago]]))>0,1,"")
A88: =TEXT(promesas[[#This Row],[Marca temporal]],"dd/mmm") -> 06/may | B88: 46148.533 | C88: Lili Velez | D88: 69787829 | E88: 258018770000 | F88: 8-899-34 | G88: Fijo | H88: Masivo (D2D) | I88: Correo de voz | M88: no | P88: 2 MESES PENDIENTES | R88: =IF(promesas[[#This Row],[Fecha de Pago]]="", "", TEXT(promesas[[#This Row],[Fecha de Pago]], "mmm")) | S88: =IF(promesas[[#This Row],[Fecha promesa de pago]]="", "", TEXT(promesas[[#This Row],[Fecha promesa de pago]], "mmm")) | T88: =IF(promesas[[#This Row],[Fecha de Pago]]="", "", TEXT(promesas[[#This Row],[Fecha de Pago]], "dd/mmm")) | U88: =IF(promesas[[#This Row],[Fecha promesa de pago]]="", "", TEXT(promesas[[#This Row],[Fecha promesa de pago]], "dd/mmm")) | V88: =IF(LEN(TRIM(promesas[[#This Row],[Fecha promesa de pago]]))>0,1,"") | W88: =IF(LEN(TRIM(promesas[[#This Row],[Fecha de Pago]]))>0,1,"")
A89: =TEXT(promesas[[#This Row],[Marca temporal]],"dd/mmm") -> 06/may | B89: 46148.537 | C89: Lili Velez | D89: 63368388 | E89: 362012640000 | F89: 8-923-1869 | G89: Fijo | H89: Masivo (D2D) | I89: No contactado | M89: no | P89: 3 MESES PENDIENTES | R89: =IF(promesas[[#This Row],[Fecha de Pago]]="", "", TEXT(promesas[[#This Row],[Fecha de Pago]], "mmm")) | S89: =IF(promesas[[#This Row],[Fecha promesa de pago]]="", "", TEXT(promesas[[#This Row],[Fecha promesa de pago]], "mmm")) | T89: =IF(promesas[[#This Row],[Fecha de Pago]]="", "", TEXT(promesas[[#This Row],[Fecha de Pago]], "dd/mmm")) | U89: =IF(promesas[[#This Row],[Fecha promesa de pago]]="", "", TEXT(promesas[[#This Row],[Fecha promesa de pago]], "dd/mmm")) | V89: =IF(LEN(TRIM(promesas[[#This Row],[Fecha promesa de pago]]))>0,1,"") | W89: =IF(LEN(TRIM(promesas[[#This Row],[Fecha de Pago]]))>0,1,"")
A90: =TEXT(promesas[[#This Row],[Marca temporal]],"dd/mmm") -> 06/may | B90: 46148.541 | C90: Lili Velez | D90: 65910205 | E90: 365018580000 | F90: 8-1068-1829 | G90: Fijo | H90: Masivo (D2D) | I90: Correo de voz | M90: no | P90: 3 MESES PENDIENTES | R90: =IF(promesas[[#This Row],[Fecha de Pago]]="", "", TEXT(promesas[[#This Row],[Fecha de Pago]], "mmm")) | S90: =IF(promesas[[#This Row],[Fecha promesa de pago]]="", "", TEXT(promesas[[#This Row],[Fecha promesa de pago]], "mmm")) | T90: =IF(promesas[[#This Row],[Fecha de Pago]]="", "", TEXT(promesas[[#This Row],[Fecha de Pago]], "dd/mmm")) | U90: =IF(promesas[[#This Row],[Fecha promesa de pago]]="", "", TEXT(promesas[[#This Row],[Fecha promesa de pago]], "dd/mmm")) | V90: =IF(LEN(TRIM(promesas[[#This Row],[Fecha promesa de pago]]))>0,1,"") | W90: =IF(LEN(TRIM(promesas[[#This Row],[Fecha de Pago]]))>0,1,"")
A91: =TEXT(promesas[[#This Row],[Marca temporal]],"dd/mmm") -> 06/may | B91: 46148.595 | C91: Lili Velez | D91: 68129364 | E91: 364016430000 | F91: 11-700-412 | G91: Fijo | H91: Masivo (D2D) | I91: Menor de edad | M91: no | P91: 3 MESES PENDIENTES | R91: =IF(promesas[[#This Row],[Fecha de Pago]]="", "", TEXT(promesas[[#This Row],[Fecha de Pago]], "mmm")) | S91: =IF(promesas[[#This Row],[Fecha promesa de pago]]="", "", TEXT(promesas[[#This Row],[Fecha promesa de pago]], "mmm")) | T91: =IF(promesas[[#This Row],[Fecha de Pago]]="", "", TEXT(promesas[[#This Row],[Fecha de Pago]], "dd/mmm")) | U91: =IF(promesas[[#This Row],[Fecha promesa de pago]]="", "", TEXT(promesas[[#This Row],[Fecha promesa de pago]], "dd/mmm")) | V91: =IF(LEN(TRIM(promesas[[#This Row],[Fecha promesa de pago]]))>0,1,"") | W91: =IF(LEN(TRIM(promesas[[#This Row],[Fecha de Pago]]))>0,1,"")
A92: =TEXT(promesas[[#This Row],[Marca temporal]],"dd/mmm") -> 06/may | B92: 46148.603 | C92: Lili Velez | D92: 63189537 | E92: 368014360000 | F92: 3-756-2112 | G92: Fijo | H92: Masivo (D2D) | I92: Correo de voz | M92: no | P92: 3 MESES PENDIENTES | R92: =IF(promesas[[#This Row],[Fecha de Pago]]="", "", TEXT(promesas[[#This Row],[Fecha de Pago]], "mmm")) | S92: =IF(promesas[[#This Row],[Fecha promesa de pago]]="", "", TEXT(promesas[[#This Row],[Fecha promesa de pago]], "mmm")) | T92: =IF(promesas[[#This Row],[Fecha de Pago]]="", "", TEXT(promesas[[#This Row],[Fecha de Pago]], "dd/mmm")) | U92: =IF(promesas[[#This Row],[Fecha promesa de pago]]="", "", TEXT(promesas[[#This Row],[Fecha promesa de pago]], "dd/mmm")) | V92: =IF(LEN(TRIM(promesas[[#This Row],[Fecha promesa de pago]]))>0,1,"") | W92: =IF(LEN(TRIM(promesas[[#This Row],[Fecha de Pago]]))>0,1,"")
A93: =TEXT(promesas[[#This Row],[Marca temporal]],"dd/mmm") -> 06/may | B93: 46148.611 | C93: Lili Velez | D93: 69686466 | E93: 363013770000 | F93: 3-53-106 | G93: Fijo | H93: Masivo (D2D) | I93: Mensaje a tercero | M93: no | P93: 3 MESES PENDIENTES | R93: =IF(promesas[[#This Row],[Fecha de Pago]]="", "", TEXT(promesas[[#This Row],[Fecha de Pago]], "mmm")) | S93: =IF(promesas[[#This Row],[Fecha promesa de pago]]="", "", TEXT(promesas[[#This Row],[Fecha promesa de pago]], "mmm")) | T93: =IF(promesas[[#This Row],[Fecha de Pago]]="", "", TEXT(promesas[[#This Row],[Fecha de Pago]], "dd/mmm")) | U93: =IF(promesas[[#This Row],[Fecha promesa de pago]]="", "", TEXT(promesas[[#This Row],[Fecha promesa de pago]], "dd/mmm")) | V93: =IF(LEN(TRIM(promesas[[#This Row],[Fecha promesa de pago]]))>0,1,"") | W93: =IF(LEN(TRIM(promesas[[#This Row],[Fecha de Pago]]))>0,1,"")
A94: =TEXT(promesas[[#This Row],[Marca temporal]],"dd/mmm") -> 06/may | B94: 46148.615 | C94: Lili Velez | D94: 64975971 | E94: 369016990000 | F94: 3-729-138 | G94: Fijo | H94: Masivo (D2D) | I94: No contactado | M94: no | P94: 3 MESES PENDIENTES | R94: =IF(promesas[[#This Row],[Fecha de Pago]]="", "", TEXT(promesas[[#This Row],[Fecha de Pago]], "mmm")) | S94: =IF(promesas[[#This Row],[Fecha promesa de pago]]="", "", TEXT(promesas[[#This Row],[Fecha promesa de pago]], "mmm")) | T94: =IF(promesas[[#This Row],[Fecha de Pago]]="", "", TEXT(promesas[[#This Row],[Fecha de Pago]], "dd/mmm")) | U94: =IF(promesas[[#This Row],[Fecha promesa de pago]]="", "", TEXT(promesas[[#This Row],[Fecha promesa de pago]], "dd/mmm")) | V94: =IF(LEN(TRIM(promesas[[#This Row],[Fecha promesa de pago]]))>0,1,"") | W94: =IF(LEN(TRIM(promesas[[#This Row],[Fecha de Pago]]))>0,1,"")
A95: =TEXT(promesas[[#This Row],[Marca temporal]],"dd/mmm") -> 06/may | B95: 46148.62 | C95: Lili Velez | D95: 64228138 | E95: 368014920000 | F95: 4-830-1884 | G95: Fijo | H95: Masivo (D2D) | I95: Correo de voz | M95: no | P95: 2 MESES PENDIENTES | R95: =IF(promesas[[#This Row],[Fecha de Pago]]="", "", TEXT(promesas[[#This Row],[Fecha de Pago]], "mmm")) | S95: =IF(promesas[[#This Row],[Fecha promesa de pago]]="", "", TEXT(promesas[[#This Row],[Fecha promesa de pago]], "mmm")) | T95: =IF(promesas[[#This Row],[Fecha de Pago]]="", "", TEXT(promesas[[#This Row],[Fecha de Pago]], "dd/mmm")) | U95: =IF(promesas[[#This Row],[Fecha promesa de pago]]="", "", TEXT(promesas[[#This Row],[Fecha promesa de pago]], "dd/mmm")) | V95: =IF(LEN(TRIM(promesas[[#This Row],[Fecha promesa de pago]]))>0,1,"") | W95: =IF(LEN(TRIM(promesas[[#This Row],[Fecha de Pago]]))>0,1,"")
A96: =TEXT(promesas[[#This Row],[Marca temporal]],"dd/mmm") -> 06/may | B96: 46148.623 | C96: Lili Velez | D96: 69690208 | E96: 361006620000 | F96: 8-905-2074 | G96: Fijo | H96: Soho | I96: No contactado | M96: no | P96: 1 MES PENDIENTE | R96: =IF(promesas[[#This Row],[Fecha de Pago]]="", "", TEXT(promesas[[#This Row],[Fecha de Pago]], "mmm")) | S96: =IF(promesas[[#This Row],[Fecha promesa de pago]]="", "", TEXT(promesas[[#This Row],[Fecha promesa de pago]], "mmm")) | T96: =IF(promesas[[#This Row],[Fecha de Pago]]="", "", TEXT(promesas[[#This Row],[Fecha de Pago]], "dd/mmm")) | U96: =IF(promesas[[#This Row],[Fecha promesa de pago]]="", "", TEXT(promesas[[#This Row],[Fecha promesa de pago]], "dd/mmm")) | V96: =IF(LEN(TRIM(promesas[[#This Row],[Fecha promesa de pago]]))>0,1,"") | W96: =IF(LEN(TRIM(promesas[[#This Row],[Fecha de Pago]]))>0,1,"")
... A111: =TEXT(promesas[[#This Row],[Marca temporal]],"dd/mmm") -> 06/may | B111: 46148.712 | C111: Lili Velez | D111: 66046678 | E111: 364010560000 | F111: 8-1056-1092 | G111: Fijo | H111: Masivo (D2D) | I111: Correo de voz | M111: no | P111: 3 MESES PENDIENTES | R111: =IF(promesas[[#This Row],[Fecha de Pago]]="", "", TEXT(promesas[[#This Row],[Fecha de Pago]], "mmm")) | S111: =IF(promesas[[#This Row],[Fecha promesa de pago]]="", "", TEXT(promesas[[#This Row],[Fecha promesa de pago]], "mmm")) | T111: =IF(promesas[[#This Row],[Fecha de Pago]]="", "", TEXT(promesas[[#This Row],[Fecha de Pago]], "dd/mmm")) | U111: =IF(promesas[[#This Row],[Fecha promesa de pago]]="", "", TEXT(promesas[[#This Row],[Fecha promesa de pago]], "dd/mmm")) | V111: =IF(LEN(TRIM(promesas[[#This Row],[Fecha promesa de pago]]))>0,1,"") | W111: =IF(LEN(TRIM(promesas[[#This Row],[Fecha de Pago]]))>0,1,"")
A112: =TEXT(promesas[[#This Row],[Marca temporal]],"dd/mmm") -> 06/may | B112: 46148.719 | C112: Lili Velez | D112: 62750138 | E112: 325006000000 | F112: 160138889 | G112: Fijo | H112: Masivo (D2D) | I112: Contactado | K112: 46149 | L112: 30.44 | M112: no | P112: 1 MES PENDIENTE | R112: =IF(promesas[[#This Row],[Fecha de Pago]]="", "", TEXT(promesas[[#This Row],[Fecha de Pago]], "mmm")) | S112: =IF(promesas[[#This Row],[Fecha promesa de pago]]="", "", TEXT(promesas[[#This Row],[Fecha promesa de pago]], "mmm")) -> may | T112: =IF(promesas[[#This Row],[Fecha de Pago]]="", "", TEXT(promesas[[#This Row],[Fecha de Pago]], "dd/mmm")) | U112: =IF(promesas[[#This Row],[Fecha promesa de pago]]="", "", TEXT(promesas[[#This Row],[Fecha promesa de pago]], "dd/mmm")) -> 07/may | V112: =IF(LEN(TRIM(promesas[[#This Row],[Fecha promesa de pago]]))>0,1,"") -> 1 | W112: =IF(LEN(TRIM(promesas[[#This Row],[Fecha de Pago]]))>0,1,"")
A113: =TEXT(promesas[[#This Row],[Marca temporal]],"dd/mmm") -> 06/may | B113: 46148.724 | C113: Lili Velez | D113: 65417427 | E113: 351373200000 | F113: 10-5-375 | G113: Fijo | H113: Masivo (D2D) | I113: Correo de voz | M113: no | P113: 3 MESES PENDIENTES | R113: =IF(promesas[[#This Row],[Fecha de Pago]]="", "", TEXT(promesas[[#This Row],[Fecha de Pago]], "mmm")) | S113: =IF(promesas[[#This Row],[Fecha promesa de pago]]="", "", TEXT(promesas[[#This Row],[Fecha promesa de pago]], "mmm")) | T113: =IF(promesas[[#This Row],[Fecha de Pago]]="", "", TEXT(promesas[[#This Row],[Fecha de Pago]], "dd/mmm")) | U113: =IF(promesas[[#This Row],[Fecha promesa de pago]]="", "", TEXT(promesas[[#This Row],[Fecha promesa de pago]], "dd/mmm")) | V113: =IF(LEN(TRIM(promesas[[#This Row],[Fecha promesa de pago]]))>0,1,"") | W113: =IF(LEN(TRIM(promesas[[#This Row],[Fecha de Pago]]))>0,1,"")
A114: =TEXT(promesas[[#This Row],[Marca temporal]],"dd/mmm") -> 06/may | B114: 46148.728 | C114: Lili Velez | D114: 62062713 | E114: 366007280000 | F114: 8-796-2216 | G114: Fijo | H114: Masivo (D2D) | I114: No contactado | M114: no | P114: 1 MES PENDIENTE | R114: =IF(promesas[[#This Row],[Fecha de Pago]]="", "", TEXT(promesas[[#This Row],[Fecha de Pago]], "mmm")) | S114: =IF(promesas[[#This Row],[Fecha promesa de pago]]="", "", TEXT(promesas[[#This Row],[Fecha promesa de pago]], "mmm")) | T114: =IF(promesas[[#This Row],[Fecha de Pago]]="", "", TEXT(promesas[[#This Row],[Fecha de Pago]], "dd/mmm")) | U114: =IF(promesas[[#This Row],[Fecha promesa de pago]]="", "", TEXT(promesas[[#This Row],[Fecha promesa de pago]], "dd/mmm")) | V114: =IF(LEN(TRIM(promesas[[#This Row],[Fecha promesa de pago]]))>0,1,"") | W114: =IF(LEN(TRIM(promesas[[#This Row],[Fecha de Pago]]))>0,1,"")
...

Sheet Vici
A1: Campaña | B1: Connect | C1: RPC | D1: Call Day | E1: Frecuencia | F1: Intentos | G1: Contar | H1: call_date | I1: phone_number_dialed | J1: status | K1: user | L1: full_name | M1: campaign_id | N1: vendor_lead_code | O1: source_id | P1: list_id | Q1: gmt_offset_now | R1: phone_code | S1: phone_number | T1: title | U1: first_name | V1: middle_initial | W1: last_name | X1: address1 | Y1: address2 | Z1: address3 | AA1: city | AB1: state | AC1: province | AD1: postal_code | AE1: country_code | AF1: gender | AG1: date_of_birth | AH1: alt_phone | AI1: email | AJ1: security_phrase | AK1: comments | AL1: length_in_sec | AM1: user_group | AN1: alt_dial | AO1: rank | AP1: owner | AQ1: lead_id | AR1: list_name | AS1: list_description | AT1: status_name
A2: =_xlfn.XLOOKUP(I2,UTILIZADAS[Contacto1],UTILIZADAS[Source.Name],,0) -> Cobros Mayo | B2: =VLOOKUP(J2,Ref!A:C,3,0) -> 0 | C2: =VLOOKUP(J2,Ref!A:D,4,0) -> 0 | D2: =TEXT(H2,"dd/mmm") -> 09/may | E2: =+COUNTIF(I:I,I2) -> 6 | F2: 1 | G2: =IF(I2=I3,0,1) -> 0 | H2: 46151.465 | I2: 2246572 | J2: AB | K2: VDAD | L2: Outbound Auto Dial | M2: COBRO | O2: 369079250000 | P2: 16018 | Q2: -5 | R2: 1 | S2: 2246572 | U2: Kevin Pan | W2: 8-1032-1440 | X2: 369079250000 | Y2: SOHO | Z2: NPN | AG2: 0000-00-00 | AL2: 0 | AN2: NONE | AO2: 0 | AQ2: 2257626 | AR2: Cobros Mayo | AS2: Cobros Mayo NPN | AT2: Auto busy
A3: =_xlfn.XLOOKUP(I3,UTILIZADAS[Contacto1],UTILIZADAS[Source.Name],,0) -> Cobros Mayo | B3: =VLOOKUP(J3,Ref!A:C,3,0) -> 0 | C3: =VLOOKUP(J3,Ref!A:D,4,0) -> 0 | D3: =TEXT(H3,"dd/mmm") -> 13/may | E3: =+COUNTIF(I:I,I3) -> 6 | F3: 1 | G3: =IF(I3=I4,0,1) -> 0 | H3: 46155.602 | I3: 2246572 | J3: AB | K3: VDAD | L3: Outbound Auto Dial | M3: COBRO | O3: 369079250000 | P3: 16018 | Q3: -5 | R3: 1 | S3: 2246572 | U3: Kevin Pan | W3: 8-1032-1440 | X3: 369079250000 | Y3: SOHO | Z3: NPN | AG3: 0000-00-00 | AL3: 0 | AN3: NONE | AO3: 0 | AQ3: 2257626 | AR3: Cobros Mayo | AS3: Cobros Mayo NPN | AT3: Auto busy
A4: =_xlfn.XLOOKUP(I4,UTILIZADAS[Contacto1],UTILIZADAS[Source.Name],,0) -> Cobros Mayo | B4: =VLOOKUP(J4,Ref!A:C,3,0) -> 0 | C4: =VLOOKUP(J4,Ref!A:D,4,0) -> 0 | D4: =TEXT(H4,"dd/mmm") -> 16/may | E4: =+COUNTIF(I:I,I4) -> 6 | F4: 1 | G4: =IF(I4=I5,0,1) -> 0 | H4: 46158.425 | I4: 2246572 | J4: AB | K4: VDAD | L4: Outbound Auto Dial | M4: COBRO | O4: 369079250000 | P4: 16018 | Q4: -5 | R4: 1 | S4: 2246572 | U4: Kevin Pan | W4: 8-1032-1440 | X4: 369079250000 | Y4: SOHO | Z4: NPN | AG4: 0000-00-00 | AL4: 0 | AN4: NONE | AO4: 0 | AQ4: 2257626 | AR4: Cobros Mayo | AS4: Cobros Mayo NPN | AT4: Auto busy
A5: =_xlfn.XLOOKUP(I5,UTILIZADAS[Contacto1],UTILIZADAS[Source.Name],,0) -> Cobros Mayo | B5: =VLOOKUP(J5,Ref!A:C,3,0) -> 0 | C5: =VLOOKUP(J5,Ref!A:D,4,0) -> 0 | D5: =TEXT(H5,"dd/mmm") -> 19/may | E5: =+COUNTIF(I:I,I5) -> 6 | F5: 1 | G5: =IF(I5=I6,0,1) -> 0 | H5: 46161.653 | I5: 2246572 | J5: AB | K5: VDAD | L5: Outbound Auto Dial | M5: COBRO | O5: 369079250000 | P5: 16018 | Q5: -5 | R5: 1 | S5: 2246572 | U5: Kevin Pan | W5: 8-1032-1440 | X5: 369079250000 | Y5: SOHO | Z5: NPN | AG5: 0000-00-00 | AL5: 0 | AN5: NONE | AO5: 0 | AQ5: 2257626 | AR5: Cobros Mayo | AS5: Cobros Mayo NPN | AT5: Auto busy
A6: =_xlfn.XLOOKUP(I6,UTILIZADAS[Contacto1],UTILIZADAS[Source.Name],,0) -> Cobros Mayo | B6: =VLOOKUP(J6,Ref!A:C,3,0) -> 0 | C6: =VLOOKUP(J6,Ref!A:D,4,0) -> 0 | D6: =TEXT(H6,"dd/mmm") -> 21/may | E6: =+COUNTIF(I:I,I6) -> 6 | F6: 1 | G6: =IF(I6=I7,0,1) -> 0 | H6: 46163.44 | I6: 2246572 | J6: AB | K6: VDAD | L6: Outbound Auto Dial | M6: COBRO | O6: 369079250000 | P6: 16018 | Q6: -5 | R6: 1 | S6: 2246572 | U6: Kevin Pan | W6: 8-1032-1440 | X6: 369079250000 | Y6: SOHO | Z6: NPN | AG6: 0000-00-00 | AL6: 0 | AN6: NONE | AO6: 0 | AQ6: 2257626 | AR6: Cobros Mayo | AS6: Cobros Mayo NPN | AT6: Auto busy
A7: =_xlfn.XLOOKUP(I7,UTILIZADAS[Contacto1],UTILIZADAS[Source.Name],,0) -> Cobros Mayo | B7: =VLOOKUP(J7,Ref!A:C,3,0) -> 0 | C7: =VLOOKUP(J7,Ref!A:D,4,0) -> 0 | D7: =TEXT(H7,"dd/mmm") -> 21/may | E7: =+COUNTIF(I:I,I7) -> 6 | F7: 1 | G7: =IF(I7=I8,0,1) -> 1 | H7: 46163.703 | I7: 2246572 | J7: AB | K7: VDAD | L7: Outbound Auto Dial | M7: COBRO | O7: 369079250000 | P7: 16018 | Q7: -5 | R7: 1 | S7: 2246572 | U7: Kevin Pan | W7: 8-1032-1440 | X7: 369079250000 | Y7: SOHO | Z7: NPN | AG7: 0000-00-00 | AL7: 0 | AN7: NONE | AO7: 0 | AQ7: 2257626 | AR7: Cobros Mayo | AS7: Cobros Mayo NPN | AT7: Auto busy
A8: =_xlfn.XLOOKUP(I8,UTILIZADAS[Contacto1],UTILIZADAS[Source.Name],,0) -> Cobros Mayo | B8: =VLOOKUP(J8,Ref!A:C,3,0) -> 0 | C8: =VLOOKUP(J8,Ref!A:D,4,0) -> 0 | D8: =TEXT(H8,"dd/mmm") -> 09/may | E8: =+COUNTIF(I:I,I8) -> 6 | F8: 1 | G8: =IF(I8=I9,0,1) -> 0 | H8: 46151.465 | I8: 2345678 | J8: AB | K8: VDAD | L8: Outbound Auto Dial | M8: COBRO | O8: 367037840000 | P8: 16018 | Q8: -4 | R8: 1 | S8: 2345678 | U8: Maria elena medina | W8: 2-140-174 | X8: 367037840000 | Y8: MASIVO | Z8: NPN | AG8: 0000-00-00 | AL8: 0 | AN8: NONE | AO8: 0 | AQ8: 2257623 | AR8: Cobros Mayo | AS8: Cobros Mayo NPN | AT8: Auto busy
A9: =_xlfn.XLOOKUP(I9,UTILIZADAS[Contacto1],UTILIZADAS[Source.Name],,0) -> Cobros Mayo | B9: =VLOOKUP(J9,Ref!A:C,3,0) -> 0 | C9: =VLOOKUP(J9,Ref!A:D,4,0) -> 0 | D9: =TEXT(H9,"dd/mmm") -> 13/may | E9: =+COUNTIF(I:I,I9) -> 6 | F9: 1 | G9: =IF(I9=I10,0,1) -> 0 | H9: 46155.602 | I9: 2345678 | J9: AB | K9: VDAD | L9: Outbound Auto Dial | M9: COBRO | O9: 367037840000 | P9: 16018 | Q9: -4 | R9: 1 | S9: 2345678 | U9: Maria elena medina | W9: 2-140-174 | X9: 367037840000 | Y9: MASIVO | Z9: NPN | AG9: 0000-00-00 | AL9: 0 | AN9: NONE | AO9: 0 | AQ9: 2257623 | AR9: Cobros Mayo | AS9: Cobros Mayo NPN | AT9: Auto busy
A10: =_xlfn.XLOOKUP(I10,UTILIZADAS[Contacto1],UTILIZADAS[Source.Name],,0) -> Cobros Mayo | B10: =VLOOKUP(J10,Ref!A:C,3,0) -> 0 | C10: =VLOOKUP(J10,Ref!A:D,4,0) -> 0 | D10: =TEXT(H10,"dd/mmm") -> 16/may | E10: =+COUNTIF(I:I,I10) -> 6 | F10: 1 | G10: =IF(I10=I11,0,1) -> 0 | H10: 46158.425 | I10: 2345678 | J10: AB | K10: VDAD | L10: Outbound Auto Dial | M10: COBRO | O10: 367037840000 | P10: 16018 | Q10: -4 | R10: 1 | S10: 2345678 | U10: Maria elena medina | W10: 2-140-174 | X10: 367037840000 | Y10: MASIVO | Z10: NPN | AG10: 0000-00-00 | AL10: 0 | AN10: NONE | AO10: 0 | AQ10: 2257623 | AR10: Cobros Mayo | AS10: Cobros Mayo NPN | AT10: Auto busy
A11: =_xlfn.XLOOKUP(I11,UTILIZADAS[Contacto1],UTILIZADAS[Source.Name],,0) -> Cobros Mayo | B11: =VLOOKUP(J11,Ref!A:C,3,0) -> 0 | C11: =VLOOKUP(J11,Ref!A:D,4,0) -> 0 | D11: =TEXT(H11,"dd/mmm") -> 19/may | E11: =+COUNTIF(I:I,I11) -> 6 | F11: 1 | G11: =IF(I11=I12,0,1) -> 0 | H11: 46161.653 | I11: 2345678 | J11: AB | K11: VDAD | L11: Outbound Auto Dial | M11: COBRO | O11: 367037840000 | P11: 16018 | Q11: -4 | R11: 1 | S11: 2345678 | U11: Maria elena medina | W11: 2-140-174 | X11: 367037840000 | Y11: MASIVO | Z11: NPN | AG11: 0000-00-00 | AL11: 0 | AN11: NONE | AO11: 0 | AQ11: 2257623 | AR11: Cobros Mayo | AS11: Cobros Mayo NPN | AT11: Auto busy
A12: =_xlfn.XLOOKUP(I12,UTILIZADAS[Contacto1],UTILIZADAS[Source.Name],,0) -> Cobros Mayo | B12: =VLOOKUP(J12,Ref!A:C,3,0) -> 0 | C12: =VLOOKUP(J12,Ref!A:D,4,0) -> 0 | D12: =TEXT(H12,"dd/mmm") -> 21/may | E12: =+COUNTIF(I:I,I12) -> 6 | F12: 1 | G12: =IF(I12=I13,0,1) -> 0 | H12: 46163.44 | I12: 2345678 | J12: AB | K12: VDAD | L12: Outbound Auto Dial | M12: COBRO | O12: 367037840000 | P12: 16018 | Q12: -4 | R12: 1 | S12: 2345678 | U12: Maria elena medina | W12: 2-140-174 | X12: 367037840000 | Y12: MASIVO | Z12: NPN | AG12: 0000-00-00 | AL12: 0 | AN12: NONE | AO12: 0 | AQ12: 2257623 | AR12: Cobros Mayo | AS12: Cobros Mayo NPN | AT12: Auto busy
A13: =_xlfn.XLOOKUP(I13,UTILIZADAS[Contacto1],UTILIZADAS[Source.Name],,0) -> Cobros Mayo | B13: =VLOOKUP(J13,Ref!A:C,3,0) -> 0 | C13: =VLOOKUP(J13,Ref!A:D,4,0) -> 0 | D13: =TEXT(H13,"dd/mmm") -> 21/may | E13: =+COUNTIF(I:I,I13) -> 6 | F13: 1 | G13: =IF(I13=I14,0,1) -> 1 | H13: 46163.703 | I13: 2345678 | J13: AB | K13: VDAD | L13: Outbound Auto Dial | M13: COBRO | O13: 367037840000 | P13: 16018 | Q13: -4 | R13: 1 | S13: 2345678 | U13: Maria elena medina | W13: 2-140-174 | X13: 367037840000 | Y13: MASIVO | Z13: NPN | AG13: 0000-00-00 | AL13: 0 | AN13: NONE | AO13: 0 | AQ13: 2257623 | AR13: Cobros Mayo | AS13: Cobros Mayo NPN | AT13: Auto busy
... A31: =_xlfn.XLOOKUP(I31,UTILIZADAS[Contacto1],UTILIZADAS[Source.Name],,0) -> Cobros Mayo | B31: =VLOOKUP(J31,Ref!A:C,3,0) -> 0 | C31: =VLOOKUP(J31,Ref!A:D,4,0) -> 0 | D31: =TEXT(H31,"dd/mmm") -> 21/may | E31: =+COUNTIF(I:I,I31) -> 6 | F31: 1 | G31: =IF(I31=I32,0,1) -> 1 | H31: 46163.703 | I31: 4446270 | J31: AB | K31: VDAD | L31: Outbound Auto Dial | M31: COBRO | O31: 366044350000 | P31: 16018 | Q31: -4 | R31: 1 | S31: 4446270 | U31: Selma Judith MartÃ­nez Ortiz | W31: 8-210-1623 | X31: 366044350000 | Y31: MASIVO | Z31: NPN | AG31: 0000-00-00 | AL31: 0 | AN31: NONE | AO31: 0 | AQ31: 2257625 | AR31: Cobros Mayo | AS31: Cobros Mayo NPN | AT31: Auto busy
A32: =_xlfn.XLOOKUP(I32,UTILIZADAS[Contacto1],UTILIZADAS[Source.Name],,0) -> Cobros Mayo | B32: =VLOOKUP(J32,Ref!A:C,3,0) -> 0 | C32: =VLOOKUP(J32,Ref!A:D,4,0) -> 0 | D32: =TEXT(H32,"dd/mmm") -> 09/may | E32: =+COUNTIF(I:I,I32) -> 2 | F32: 1 | G32: =IF(I32=I33,0,1) -> 0 | H32: 46151.466 | I32: 60014341 | J32: DROP | K32: VDAD | L32: Outbound Auto Dial | M32: COBRO | O32: 366076280000 | P32: 16018 | Q32: -4 | R32: 1 | S32: 60014341 | U32: Yanishka Yaleima Powell | W32: 3-729-424 | X32: 366076280000 | Y32: MASIVO | Z32: NPN | AF32: U | AG32: 0000-00-00 | AL32: 5 | AN32: NONE | AO32: 0 | AQ32: 2257628 | AR32: Cobros Mayo | AS32: Cobros Mayo NPN | AT32: Agent Not Available
A33: =_xlfn.XLOOKUP(I33,UTILIZADAS[Contacto1],UTILIZADAS[Source.Name],,0) -> Cobros Mayo | B33: =VLOOKUP(J33,Ref!A:C,3,0) -> 0 | C33: =VLOOKUP(J33,Ref!A:D,4,0) -> 0 | D33: =TEXT(H33,"dd/mmm") -> 13/may | E33: =+COUNTIF(I:I,I33) -> 2 | F33: 1 | G33: =IF(I33=I34,0,1) -> 1 | H33: 46155.602 | I33: 60014341 | J33: 6004 | K33: lvelez | L33: Lili Velez | M33: COBRO | O33: 366076280000 | P33: 16018 | Q33: -4 | R33: 1 | S33: 60014341 | U33: Yanishka Yaleima Powell | W33: 3-729-424 | X33: 366076280000 | Y33: MASIVO | Z33: NPN | AF33: U | AG33: 0000-00-00 | AL33: 74 | AM33: Llamaya | AN33: MAIN | AO33: 0 | AQ33: 2257628 | AR33: Cobros Mayo | AS33: Cobros Mayo NPN | AT33: Buzon de voz
A34: =_xlfn.XLOOKUP(I34,UTILIZADAS[Contacto1],UTILIZADAS[Source.Name],,0) -> #N/A | B34: =VLOOKUP(J34,Ref!A:C,3,0) -> 1 | C34: =VLOOKUP(J34,Ref!A:D,4,0) -> 1 | D34: =TEXT(H34,"dd/mmm") -> 13/may | E34: =+COUNTIF(I:I,I34) -> 1 | F34: 1 | G34: =IF(I34=I35,0,1) -> 1 | H34: 46155.51 | I34: 60019453 | J34: 6002 | K34: lvelez | L34: Lili Velez | M34: COBRO | N34: 7958 | O34: 7958 | P34: 6005 | Q34: -4 | R34: 1 | S34: 60019453 | U34: Diana elida rucas pinilla | W34: 7958 | X34: 45381.512 | Y34: dianarucas0330@gmail.com | AA34: PanamÃ¡ | AC34: PanamÃ¡ | AF34: U | AG34: 0000-00-00 | AK34: 341402490000>> DIANA ELIDA RUCAS PINILLA | AL34: 45 | AM34: Llamaya | AN34: MAIN | AO34: 0 | AQ34: 965487 | AR34: PREDIGI | AT34: Cliente al dia
A35: =_xlfn.XLOOKUP(I35,UTILIZADAS[Contacto1],UTILIZADAS[Source.Name],,0) -> #N/A | B35: =VLOOKUP(J35,Ref!A:C,3,0) -> 0 | C35: =VLOOKUP(J35,Ref!A:D,4,0) -> 0 | D35: =TEXT(H35,"dd/mmm") -> 19/may | E35: =+COUNTIF(I:I,I35) -> 1 | F35: 1 | G35: =IF(I35=I36,0,1) -> 1 | H35: 46161.653 | I35: 60043073 | J35: CALLBK | K35: lvelez | L35: Lili Velez | M35: COBRO | O35: 353385040000 | P35: 16016 | Q35: -4 | R35: 1 | S35: 60043073 | U35: Giulio Linares | W35: 10-709-335 | X35: 353385040000 | Y35: MASIVO | Z35: NPN | AF35: U | AG35: 0000-00-00 | AK35: 353385040000>> GIULIO ENRIQUE LINARES FERNANDEZ | AL35: 148 | AM35: Llamaya | AN35: MANUAL | AO35: 0 | AQ35: 2198846 | AR35: Cobros Marzo 2 meses a NPN | AS35: Cobros Marzo 2 meses a NPN | AT35: Call Back
A36: =_xlfn.XLOOKUP(I36,UTILIZADAS[Contacto1],UTILIZADAS[Source.Name],,0) -> Cobros Abril Canal Fijo | B36: =VLOOKUP(J36,Ref!A:C,3,0) -> 0 | C36: =VLOOKUP(J36,Ref!A:D,4,0) -> 0 | D36: =TEXT(H36,"dd/mmm") -> 02/may | E36: =+COUNTIF(I:I,I36) -> 15 | F36: 1 | G36: =IF(I36=I37,0,1) -> 0 | H36: 46144.529 | I36: 60045640 | J36: AB | K36: VDAD | L36: Outbound Auto Dial | M36: COBRO | O36: 361021690000 | P36: 16017 | Q36: -4 | R36: 1 | S36: 60045640 | U36: Jeiker Mendez | W36: 8-1044-1237 | X36: NPN | Y36: MASIVO | Z36: 361021690000 | AG36: 0000-00-00 | AI36: aliciomendez52@gmail.com | AL36: 0 | AN36: NONE | AO36: 0 | AQ36: 2252141 | AR36: Cobros Abril Canal Fijo | AS36: Cobros Abril Canal Fijo 2 meses a NPN | AT36: Auto busy
A37: =_xlfn.XLOOKUP(I37,UTILIZADAS[Contacto1],UTILIZADAS[Source.Name],,0) -> Cobros Abril Canal Fijo | B37: =VLOOKUP(J37,Ref!A:C,3,0) -> 0 | C37: =VLOOKUP(J37,Ref!A:D,4,0) -> 0 | D37: =TEXT(H37,"dd/mmm") -> 05/may | E37: =+COUNTIF(I:I,I37) -> 15 | F37: 1 | G37: =IF(I37=I38,0,1) -> 0 | H37: 46147.743 | I37: 60045640 | J37: AB | K37: VDAD | L37: Outbound Auto Dial | M37: COBRO | O37: 361021690000 | P37: 16017 | Q37: -4 | R37: 1 | S37: 60045640 | U37: Jeiker Mendez | W37: 8-1044-1237 | X37: NPN | Y37: MASIVO | Z37: 361021690000 | AG37: 0000-00-00 | AI37: aliciomendez52@gmail.com | AL37: 0 | AN37: NONE | AO37: 0 | AQ37: 2252141 | AR37: Cobros Abril Canal Fijo | AS37: Cobros Abril Canal Fijo 2 meses a NPN | AT37: Auto busy
A38: =_xlfn.XLOOKUP(I38,UTILIZADAS[Contacto1],UTILIZADAS[Source.Name],,0) -> Cobros Abril Canal Fijo | B38: =VLOOKUP(J38,Ref!A:C,3,0) -> 0 | C38: =VLOOKUP(J38,Ref!A:D,4,0) -> 0 | D38: =TEXT(H38,"dd/mmm") -> 07/may | E38: =+COUNTIF(I:I,I38) -> 15 | F38: 1 | G38: =IF(I38=I39,0,1) -> 0 | H38: 46149.6 | I38: 60045640 | J38: NA | K38: VDAD | L38: Outbound Auto Dial | M38: COBRO | O38: 361021690000 | P38: 16017 | Q38: -4 | R38: 1 | S38: 60045640 | U38: Jeiker Mendez | W38: 8-1044-1237 | X38: NPN | Y38: MASIVO | Z38: 361021690000 | AG38: 0000-00-00 | AI38: aliciomendez52@gmail.com | AL38: 0 | AN38: NONE | AO38: 0 | AQ38: 2252141 | AR38: Cobros Abril Canal Fijo | AS38: Cobros Abril Canal Fijo 2 meses a NPN | AT38: No Answer AutoDial
A39: =_xlfn.XLOOKUP(I39,UTILIZADAS[Contacto1],UTILIZADAS[Source.Name],,0) -> Cobros Abril Canal Fijo | B39: =VLOOKUP(J39,Ref!A:C,3,0) -> 0 | C39: =VLOOKUP(J39,Ref!A:D,4,0) -> 0 | D39: =TEXT(H39,"dd/mmm") -> 08/may | E39: =+COUNTIF(I:I,I39) -> 15 | F39: 1 | G39: =IF(I39=I40,0,1) -> 0 | H39: 46150.412 | I39: 60045640 | J39: AB | K39: VDAD | L39: Outbound Auto Dial | M39: COBRO | O39: 361021690000 | P39: 16017 | Q39: -4 | R39: 1 | S39: 60045640 | U39: Jeiker Mendez | W39: 8-1044-1237 | X39: NPN | Y39: MASIVO | Z39: 361021690000 | AG39: 0000-00-00 | AI39: aliciomendez52@gmail.com | AL39: 0 | AN39: NONE | AO39: 0 | AQ39: 2252141 | AR39: Cobros Abril Canal Fijo | AS39: Cobros Abril Canal Fijo 2 meses a NPN | AT39: Auto busy
A40: =_xlfn.XLOOKUP(I40,UTILIZADAS[Contacto1],UTILIZADAS[Source.Name],,0) -> Cobros Abril Canal Fijo | B40: =VLOOKUP(J40,Ref!A:C,3,0) -> 0 | C40: =VLOOKUP(J40,Ref!A:D,4,0) -> 0 | D40: =TEXT(H40,"dd/mmm") -> 08/may | E40: =+COUNTIF(I:I,I40) -> 15 | F40: 1 | G40: =IF(I40=I41,0,1) -> 0 | H40: 46150.628 | I40: 60045640 | J40: AB | K40: VDAD | L40: Outbound Auto Dial | M40: COBRO | O40: 361021690000 | P40: 16017 | Q40: -4 | R40: 1 | S40: 60045640 | U40: Jeiker Mendez | W40: 8-1044-1237 | X40: NPN | Y40: MASIVO | Z40: 361021690000 | AG40: 0000-00-00 | AI40: aliciomendez52@gmail.com | AL40: 0 | AN40: NONE | AO40: 0 | AQ40: 2252141 | AR40: Cobros Abril Canal Fijo | AS40: Cobros Abril Canal Fijo 2 meses a NPN | AT40: Auto busy
A41: =_xlfn.XLOOKUP(I41,UTILIZADAS[Contacto1],UTILIZADAS[Source.Name],,0) -> Cobros Abril Canal Fijo | B41: =VLOOKUP(J41,Ref!A:C,3,0) -> 0 | C41: =VLOOKUP(J41,Ref!A:D,4,0) -> 0 | D41: =TEXT(H41,"dd/mmm") -> 09/may | E41: =+COUNTIF(I:I,I41) -> 15 | F41: 1 | G41: =IF(I41=I42,0,1) -> 0 | H41: 46151.467 | I41: 60045640 | J41: NA | K41: VDAD | L41: Outbound Auto Dial | M41: COBRO | O41: 361021690000 | P41: 16018 | Q41: -4 | R41: 1 | S41: 60045640 | U41: Jeiker Mendez | W41: 8-1044-1237 | X41: 361021690000 | Y41: MASIVO | Z41: NPN | AG41: 0000-00-00 | AL41: 0 | AN41: NONE | AO41: 0 | AQ41: 2257629 | AR41: Cobros Mayo | AS41: Cobros Mayo NPN | AT41: No Answer AutoDial
A42: =_xlfn.XLOOKUP(I42,UTILIZADAS[Contacto1],UTILIZADAS[Source.Name],,0) -> Cobros Abril Canal Fijo | B42: =VLOOKUP(J42,Ref!A:C,3,0) -> 0 | C42: =VLOOKUP(J42,Ref!A:D,4,0) -> 0 | D42: =TEXT(H42,"dd/mmm") -> 11/may | E42: =+COUNTIF(I:I,I42) -> 15 | F42: 1 | G42: =IF(I42=I43,0,1) -> 0 | H42: 46153.524 | I42: 60045640 | J42: NA | K42: VDAD | L42: Outbound Auto Dial | M42: COBRO | O42: 361021690000 | P42: 16018 | Q42: -4 | R42: 1 | S42: 60045640 | U42: Jeiker Mendez | W42: 8-1044-1237 | X42: 361021690000 | Y42: MASIVO | Z42: NPN | AG42: 0000-00-00 | AL42: 0 | AN42: NONE | AO42: 0 | AQ42: 2257629 | AR42: Cobros Mayo | AS42: Cobros Mayo NPN | AT42: No Answer AutoDial
A43: =_xlfn.XLOOKUP(I43,UTILIZADAS[Contacto1],UTILIZADAS[Source.Name],,0) -> Cobros Abril Canal Fijo | B43: =VLOOKUP(J43,Ref!A:C,3,0) -> 0 | C43: =VLOOKUP(J43,Ref!A:D,4,0) -> 0 | D43: =TEXT(H43,"dd/mmm") -> 11/may | E43: =+COUNTIF(I:I,I43) -> 15 | F43: 1 | G43: =IF(I43=I44,0,1) -> 0 | H43: 46153.618 | I43: 60045640 | J43: AB | K43: VDAD | L43: Outbound Auto Dial | M43: COBRO | O43: 361021690000 | P43: 16018 | Q43: -4 | R43: 1 | S43: 60045640 | U43: Jeiker Mendez | W43: 8-1044-1237 | X43: 361021690000 | Y43: MASIVO | Z43: NPN | AG43: 0000-00-00 | AL43: 0 | AN43: NONE | AO43: 0 | AQ43: 2257629 | AR43: Cobros Mayo | AS43: Cobros Mayo NPN | AT43: Auto busy
A44: =_xlfn.XLOOKUP(I44,UTILIZADAS[Contacto1],UTILIZADAS[Source.Name],,0) -> Cobros Abril Canal Fijo | B44: =VLOOKUP(J44,Ref!A:C,3,0) -> 0 | C44: =VLOOKUP(J44,Ref!A:D,4,0) -> 0 | D44: =TEXT(H44,"dd/mmm") -> 13/may | E44: =+COUNTIF(I:I,I44) -> 15 | F44: 1 | G44: =IF(I44=I45,0,1) -> 0 | H44: 46155.603 | I44: 60045640 | J44: NA | K44: VDAD | L44: Outbound Auto Dial | M44: COBRO | O44: 361021690000 | P44: 16018 | Q44: -4 | R44: 1 | S44: 60045640 | U44: Jeiker Mendez | W44: 8-1044-1237 | X44: 361021690000 | Y44: MASIVO | Z44: NPN | AG44: 0000-00-00 | AL44: 0 | AN44: NONE | AO44: 0 | AQ44: 2257629 | AR44: Cobros Mayo | AS44: Cobros Mayo NPN | AT44: No Answer AutoDial
A45: =_xlfn.XLOOKUP(I45,UTILIZADAS[Contacto1],UTILIZADAS[Source.Name],,0) -> Cobros Abril Canal Fijo | B45: =VLOOKUP(J45,Ref!A:C,3,0) -> 0 | C45: =VLOOKUP(J45,Ref!A:D,4,0) -> 0 | D45: =TEXT(H45,"dd/mmm") -> 13/may | E45: =+COUNTIF(I:I,I45) -> 15 | F45: 1 | G45: =IF(I45=I46,0,1) -> 0 | H45: 46155.712 | I45: 60045640 | J45: NA | K45: VDAD | L45: Outbound Auto Dial | M45: COBRO | O45: 361021690000 | P45: 16018 | Q45: -4 | R45: 1 | S45: 60045640 | U45: Jeiker Mendez | W45: 8-1044-1237 | X45: 361021690000 | Y45: MASIVO | Z45: NPN | AG45: 0000-00-00 | AL45: 0 | AN45: NONE | AO45: 0 | AQ45: 2257629 | AR45: Cobros Mayo | AS45: Cobros Mayo NPN | AT45: No Answer AutoDial
A46: =_xlfn.XLOOKUP(I46,UTILIZADAS[Contacto1],UTILIZADAS[Source.Name],,0) -> Cobros Abril Canal Fijo | B46: =VLOOKUP(J46,Ref!A:C,3,0) -> 0 | C46: =VLOOKUP(J46,Ref!A:D,4,0) -> 0 | D46: =TEXT(H46,"dd/mmm") -> 14/may | E46: =+COUNTIF(I:I,I46) -> 15 | F46: 1 | G46: =IF(I46=I47,0,1) -> 0 | H46: 46156.394 | I46: 60045640 | J46: AB | K46: VDAD | L46: Outbound Auto Dial | M46: COBRO | O46: 361021690000 | P46: 16018 | Q46: -4 | R46: 1 | S46: 60045640 | U46: Jeiker Mendez | W46: 8-1044-1237 | X46: 361021690000 | Y46: MASIVO | Z46: NPN | AG46: 0000-00-00 | AL46: 0 | AN46: NONE | AO46: 0 | AQ46: 2257629 | AR46: Cobros Mayo | AS46: Cobros Mayo NPN | AT46: Auto busy
A47: =_xlfn.XLOOKUP(I47,UTILIZADAS[Contacto1],UTILIZADAS[Source.Name],,0) -> Cobros Abril Canal Fijo | B47: =VLOOKUP(J47,Ref!A:C,3,0) -> 0 | C47: =VLOOKUP(J47,Ref!A:D,4,0) -> 0 | D47: =TEXT(H47,"dd/mmm") -> 16/may | E47: =+COUNTIF(I:I,I47) -> 15 | F47: 1 | G47: =IF(I47=I48,0,1) -> 0 | H47: 46158.425 | I47: 60045640 | J47: AB | K47: VDAD | L47: Outbound Auto Dial | M47: COBRO | O47: 361021690000 | P47: 16018 | Q47: -4 | R47: 1 | S47: 60045640 | U47: Jeiker Mendez | W47: 8-1044-1237 | X47: 361021690000 | Y47: MASIVO | Z47: NPN | AG47: 0000-00-00 | AL47: 0 | AN47: NONE | AO47: 0 | AQ47: 2257629 | AR47: Cobros Mayo | AS47: Cobros Mayo NPN | AT47: Auto busy
A48: =_xlfn.XLOOKUP(I48,UTILIZADAS[Contacto1],UTILIZADAS[Source.Name],,0) -> Cobros Abril Canal Fijo | B48: =VLOOKUP(J48,Ref!A:C,3,0) -> 0 | C48: =VLOOKUP(J48,Ref!A:D,4,0) -> 0 | D48: =TEXT(H48,"dd/mmm") -> 19/may | E48: =+COUNTIF(I:I,I48) -> 15 | F48: 1 | G48: =IF(I48=I49,0,1) -> 0 | H48: 46161.653 | I48: 60045640 | J48: AB | K48: VDAD | L48: Outbound Auto Dial | M48: COBRO | O48: 361021690000 | P48: 16018 | Q48: -4 | R48: 1 | S48: 60045640 | U48: Jeiker Mendez | W48: 8-1044-1237 | X48: 361021690000 | Y48: MASIVO | Z48: NPN | AG48: 0000-00-00 | AL48: 0 | AN48: NONE | AO48: 0 | AQ48: 2257629 | AR48: Cobros Mayo | AS48: Cobros Mayo NPN | AT48: Auto busy
A49: =_xlfn.XLOOKUP(I49,UTILIZADAS[Contacto1],UTILIZADAS[Source.Name],,0) -> Cobros Abril Canal Fijo | B49: =VLOOKUP(J49,Ref!A:C,3,0) -> 0 | C49: =VLOOKUP(J49,Ref!A:D,4,0) -> 0 | D49: =TEXT(H49,"dd/mmm") -> 21/may | E49: =+COUNTIF(I:I,I49) -> 15 | F49: 1 | G49: =IF(I49=I50,0,1) -> 0 | H49: 46163.44 | I49: 60045640 | J49: AB | K49: VDAD | L49: Outbound Auto Dial | M49: COBRO | O49: 361021690000 | P49: 16018 | Q49: -4 | R49: 1 | S49: 60045640 | U49: Jeiker Mendez | W49: 8-1044-1237 | X49: 361021690000 | Y49: MASIVO | Z49: NPN | AG49: 0000-00-00 | AL49: 0 | AN49: NONE | AO49: 0 | AQ49: 2257629 | AR49: Cobros Mayo | AS49: Cobros Mayo NPN | AT49: Auto busy
A50: =_xlfn.XLOOKUP(I50,UTILIZADAS[Contacto1],UTILIZADAS[Source.Name],,0) -> Cobros Abril Canal Fijo | B50: =VLOOKUP(J50,Ref!A:C,3,0) -> 0 | C50: =VLOOKUP(J50,Ref!A:D,4,0) -> 0 | D50: =TEXT(H50,"dd/mmm") -> 21/may | E50: =+COUNTIF(I:I,I50) -> 15 | F50: 1 | G50: =IF(I50=I51,0,1) -> 1 | H50: 46163.703 | I50: 60045640 | J50: AB | K50: VDAD | L50: Outbound Auto Dial | M50: COBRO | O50: 361021690000 | P50: 16018 | Q50: -4 | R50: 1 | S50: 60045640 | U50: Jeiker Mendez | W50: 8-1044-1237 | X50: 361021690000 | Y50: MASIVO | Z50: NPN | AG50: 0000-00-00 | AL50: 0 | AN50: NONE | AO50: 0 | AQ50: 2257629 | AR50: Cobros Mayo | AS50: Cobros Mayo NPN | AT50: Auto busy
A51: =_xlfn.XLOOKUP(I51,UTILIZADAS[Contacto1],UTILIZADAS[Source.Name],,0) -> Cobros Abril Canal Fijo | B51: =VLOOKUP(J51,Ref!A:C,3,0) -> 0 | C51: =VLOOKUP(J51,Ref!A:D,4,0) -> 0 | D51: =TEXT(H51,"dd/mmm") -> 04/may | E51: =+COUNTIF(I:I,I51) -> 13 | F51: 1 | G51: =IF(I51=I52,0,1) -> 0 | H51: 46146.409 | I51: 60082188 | J51: AB | K51: VDAD | L51: Outbound Auto Dial | M51: COBRO | O51: 366038820000 | P51: 16017 | Q51: -4 | R51: 1 | S51: 60082188 | U51: Sakiel Israel alb FernÃ¡ndez | W51: 8-1049-1495 | X51: NPN | Y51: MASIVO | Z51: 366038820000 | AG51: 0000-00-00 | AI51: graciamaikel467@Gmail.com | AL51: 0 | AN51: NONE | AO51: 0 | AQ51: 2252303 | AR51: Cobros Abril Canal Fijo | AS51: Cobros Abril Canal Fijo 2 meses a NPN | AT51: Auto busy
A52: =_xlfn.XLOOKUP(I52,UTILIZADAS[Contacto1],UTILIZADAS[Source.Name],,0) -> Cobros Abril Canal Fijo | B52: =VLOOKUP(J52,Ref!A:C,3,0) -> 0 | C52: =VLOOKUP(J52,Ref!A:D,4,0) -> 0 | D52: =TEXT(H52,"dd/mmm") -> 06/may | E52: =+COUNTIF(I:I,I52) -> 13 | F52: 1 | G52: =IF(I52=I53,0,1) -> 0 | H52: 46148.434 | I52: 60082188 | J52: AB | K52: VDAD | L52: Outbound Auto Dial | M52: COBRO | O52: 366038820000 | P52: 16017 | Q52: -4 | R52: 1 | S52: 60082188 | U52: Sakiel Israel alb FernÃ¡ndez | W52: 8-1049-1495 | X52: NPN | Y52: MASIVO | Z52: 366038820000 | AG52: 0000-00-00 | AI52: graciamaikel467@Gmail.com | AL52: 0 | AN52: NONE | AO52: 0 | AQ52: 2252303 | AR52: Cobros Abril Canal Fijo | AS52: Cobros Abril Canal Fijo 2 meses a NPN | AT52: Auto busy
A53: =_xlfn.XLOOKUP(I53,UTILIZADAS[Contacto1],UTILIZADAS[Source.Name],,0) -> Cobros Abril Canal Fijo | B53: =VLOOKUP(J53,Ref!A:C,3,0) -> 0 | C53: =VLOOKUP(J53,Ref!A:D,4,0) -> 0 | D53: =TEXT(H53,"dd/mmm") -> 07/may | E53: =+COUNTIF(I:I,I53) -> 13 | F53: 1 | G53: =IF(I53=I54,0,1) -> 0 | H53: 46149.636 | I53: 60082188 | J53: AB | K53: VDAD | L53: Outbound Auto Dial | M53: COBRO | O53: 366038820000 | P53: 16017 | Q53: -4 | R53: 1 | S53: 60082188 | U53: Sakiel Israel alb FernÃ¡ndez | W53: 8-1049-1495 | X53: NPN | Y53: MASIVO | Z53: 366038820000 | AG53: 0000-00-00 | AI53: graciamaikel467@Gmail.com | AL53: 0 | AN53: NONE | AO53: 0 | AQ53: 2252303 | AR53: Cobros Abril Canal Fijo | AS53: Cobros Abril Canal Fijo 2 meses a NPN | AT53: Auto busy
A54: =_xlfn.XLOOKUP(I54,UTILIZADAS[Contacto1],UTILIZADAS[Source.Name],,0) -> Cobros Abril Canal Fijo | B54: =VLOOKUP(J54,Ref!A:C,3,0) -> 0 | C54: =VLOOKUP(J54,Ref!A:D,4,0) -> 0 | D54: =TEXT(H54,"dd/mmm") -> 08/may | E54: =+COUNTIF(I:I,I54) -> 13 | F54: 1 | G54: =IF(I54=I55,0,1) -> 0 | H54: 46150.665 | I54: 60082188 | J54: AB | K54: VDAD | L54: Outbound Auto Dial | M54: COBRO | O54: 366038820000 | P54: 16017 | Q54: -4 | R54: 1 | S54: 60082188 | U54: Sakiel Israel alb FernÃ¡ndez | W54: 8-1049-1495 | X54: NPN | Y54: MASIVO | Z54: 366038820000 | AG54: 0000-00-00 | AI54: graciamaikel467@Gmail.com | AL54: 0 | AN54: NONE | AO54: 0 | AQ54: 2252303 | AR54: Cobros Abril Canal Fijo | AS54: Cobros Abril Canal Fijo 2 meses a NPN | AT54: Auto busy
A55: =_xlfn.XLOOKUP(I55,UTILIZADAS[Contacto1],UTILIZADAS[Source.Name],,0) -> Cobros Abril Canal Fijo | B55: =VLOOKUP(J55,Ref!A:C,3,0) -> 0 | C55: =VLOOKUP(J55,Ref!A:D,4,0) -> 0 | D55: =TEXT(H55,"dd/mmm") -> 09/may | E55: =+COUNTIF(I:I,I55) -> 13 | F55: 1 | G55: =IF(I55=I56,0,1) -> 0 | H55: 46151.469 | I55: 60082188 | J55: NA | K55: VDAD | L55: Outbound Auto Dial | M55: COBRO | O55: 366038820000 | P55: 16018 | Q55: -4 | R55: 1 | S55: 60082188 | U55: Sakiel Israel alb FernÃ¡ndez | W55: 8-1049-1495 | X55: 366038820000 | Y55: MASIVO | Z55: NPN | AG55: 0000-00-00 | AL55: 0 | AN55: NONE | AO55: 0 | AQ55: 2257630 | AR55: Cobros Mayo | AS55: Cobros Mayo NPN | AT55: No Answer AutoDial
A56: =_xlfn.XLOOKUP(I56,UTILIZADAS[Contacto1],UTILIZADAS[Source.Name],,0) -> Cobros Abril Canal Fijo | B56: =VLOOKUP(J56,Ref!A:C,3,0) -> 0 | C56: =VLOOKUP(J56,Ref!A:D,4,0) -> 0 | D56: =TEXT(H56,"dd/mmm") -> 11/may | E56: =+COUNTIF(I:I,I56) -> 13 | F56: 1 | G56: =IF(I56=I57,0,1) -> 0 | H56: 46153.524 | I56: 60082188 | J56: AB | K56: VDAD | L56: Outbound Auto Dial | M56: COBRO | O56: 366038820000 | P56: 16018 | Q56: -4 | R56: 1 | S56: 60082188 | U56: Sakiel Israel alb FernÃ¡ndez | W56: 8-1049-1495 | X56: 366038820000 | Y56: MASIVO | Z56: NPN | AG56: 0000-00-00 | AL56: 0 | AN56: NONE | AO56: 0 | AQ56: 2257630 | AR56: Cobros Mayo | AS56: Cobros Mayo NPN | AT56: Auto busy
A57: =_xlfn.XLOOKUP(I57,UTILIZADAS[Contacto1],UTILIZADAS[Source.Name],,0) -> Cobros Abril Canal Fijo | B57: =VLOOKUP(J57,Ref!A:C,3,0) -> 0 | C57: =VLOOKUP(J57,Ref!A:D,4,0) -> 0 | D57: =TEXT(H57,"dd/mmm") -> 13/may | E57: =+COUNTIF(I:I,I57) -> 13 | F57: 1 | G57: =IF(I57=I58,0,1) -> 0 | H57: 46155.604 | I57: 60082188 | J57: NA | K57: VDAD | L57: Outbound Auto Dial | M57: COBRO | O57: 366038820000 | P57: 16018 | Q57: -4 | R57: 1 | S57: 60082188 | U57: Sakiel Israel alb FernÃ¡ndez | W57: 8-1049-1495 | X57: 366038820000 | Y57: MASIVO | Z57: NPN | AG57: 0000-00-00 | AL57: 0 | AN57: NONE | AO57: 0 | AQ57: 2257630 | AR57: Cobros Mayo | AS57: Cobros Mayo NPN | AT57: No Answer AutoDial
A58: =_xlfn.XLOOKUP(I58,UTILIZADAS[Contacto1],UTILIZADAS[Source.Name],,0) -> Cobros Abril Canal Fijo | B58: =VLOOKUP(J58,Ref!A:C,3,0) -> 0 | C58: =VLOOKUP(J58,Ref!A:D,4,0) -> 0 | D58: =TEXT(H58,"dd/mmm") -> 13/may | E58: =+COUNTIF(I:I,I58) -> 13 | F58: 1 | G58: =IF(I58=I59,0,1) -> 0 | H58: 46155.714 | I58: 60082188 | J58: AB | K58: VDAD | L58: Outbound Auto Dial | M58: COBRO | O58: 366038820000 | P58: 16018 | Q58: -4 | R58: 1 | S58: 60082188 | U58: Sakiel Israel alb FernÃ¡ndez | W58: 8-1049-1495 | X58: 366038820000 | Y58: MASIVO | Z58: NPN | AG58: 0000-00-00 | AL58: 0 | AN58: NONE | AO58: 0 | AQ58: 2257630 | AR58: Cobros Mayo | AS58: Cobros Mayo NPN | AT58: Auto busy
A59: =_xlfn.XLOOKUP(I59,UTILIZADAS[Contacto1],UTILIZADAS[Source.Name],,0) -> Cobros Abril Canal Fijo | B59: =VLOOKUP(J59,Ref!A:C,3,0) -> 0 | C59: =VLOOKUP(J59,Ref!A:D,4,0) -> 0 | D59: =TEXT(H59,"dd/mmm") -> 16/may | E59: =+COUNTIF(I:I,I59) -> 13 | F59: 1 | G59: =IF(I59=I60,0,1) -> 0 | H59: 46158.426 | I59: 60082188 | J59: NA | K59: VDAD | L59: Outbound Auto Dial | M59: COBRO | O59: 366038820000 | P59: 16018 | Q59: -4 | R59: 1 | S59: 60082188 | U59: Sakiel Israel alb FernÃ¡ndez | W59: 8-1049-1495 | X59: 366038820000 | Y59: MASIVO | Z59: NPN | AG59: 0000-00-00 | AL59: 0 | AN59: NONE | AO59: 0 | AQ59: 2257630 | AR59: Cobros Mayo | AS59: Cobros Mayo NPN | AT59: No Answer AutoDial
A60: =_xlfn.XLOOKUP(I60,UTILIZADAS[Contacto1],UTILIZADAS[Source.Name],,0) -> Cobros Abril Canal Fijo | B60: =VLOOKUP(J60,Ref!A:C,3,0) -> 0 | C60: =VLOOKUP(J60,Ref!A:D,4,0) -> 0 | D60: =TEXT(H60,"dd/mmm") -> 18/may | E60: =+COUNTIF(I:I,I60) -> 13 | F60: 1 | G60: =IF(I60=I61,0,1) -> 0 | H60: 46160.468 | I60: 60082188 | J60: AB | K60: VDAD | L60: Outbound Auto Dial | M60: COBRO | O60: 366038820000 | P60: 16018 | Q60: -4 | R60: 1 | S60: 60082188 | U60: Sakiel Israel alb FernÃ¡ndez | W60: 8-1049-1495 | X60: 366038820000 | Y60: MASIVO | Z60: NPN | AG60: 0000-00-00 | AL60: 0 | AN60: NONE | AO60: 0 | AQ60: 2257630 | AR60: Cobros Mayo | AS60: Cobros Mayo NPN | AT60: Auto busy
A61: =_xlfn.XLOOKUP(I61,UTILIZADAS[Contacto1],UTILIZADAS[Source.Name],,0) -> Cobros Abril Canal Fijo | B61: =VLOOKUP(J61,Ref!A:C,3,0) -> 0 | C61: =VLOOKUP(J61,Ref!A:D,4,0) -> 0 | D61: =TEXT(H61,"dd/mmm") -> 19/may | E61: =+COUNTIF(I:I,I61) -> 13 | F61: 1 | G61: =IF(I61=I62,0,1) -> 0 | H61: 46161.654 | I61: 60082188 | J61: AB | K61: VDAD | L61: Outbound Auto Dial | M61: COBRO | O61: 366038820000 | P61: 16018 | Q61: -4 | R61: 1 | S61: 60082188 | U61: Sakiel Israel alb FernÃ¡ndez | W61: 8-1049-1495 | X61: 366038820000 | Y61: MASIVO | Z61: NPN | AG61: 0000-00-00 | AL61: 0 | AN61: NONE | AO61: 0 | AQ61: 2257630 | AR61: Cobros Mayo | AS61: Cobros Mayo NPN | AT61: Auto busy
A62: =_xlfn.XLOOKUP(I62,UTILIZADAS[Contacto1],UTILIZADAS[Source.Name],,0) -> Cobros Abril Canal Fijo | B62: =VLOOKUP(J62,Ref!A:C,3,0) -> 0 | C62: =VLOOKUP(J62,Ref!A:D,4,0) -> 0 | D62: =TEXT(H62,"dd/mmm") -> 21/may | E62: =+COUNTIF(I:I,I62) -> 13 | F62: 1 | G62: =IF(I62=I63,0,1) -> 0 | H62: 46163.44 | I62: 60082188 | J62: AB | K62: VDAD | L62: Outbound Auto Dial | M62: COBRO | O62: 366038820000 | P62: 16018 | Q62: -4 | R62: 1 | S62: 60082188 | U62: Sakiel Israel alb FernÃ¡ndez | W62: 8-1049-1495 | X62: 366038820000 | Y62: MASIVO | Z62: NPN | AG62: 0000-00-00 | AL62: 0 | AN62: NONE | AO62: 0 | AQ62: 2257630 | AR62: Cobros Mayo | AS62: Cobros Mayo NPN | AT62: Auto busy
A63: =_xlfn.XLOOKUP(I63,UTILIZADAS[Contacto1],UTILIZADAS[Source.Name],,0) -> Cobros Abril Canal Fijo | B63: =VLOOKUP(J63,Ref!A:C,3,0) -> 0 | C63: =VLOOKUP(J63,Ref!A:D,4,0) -> 0 | D63: =TEXT(H63,"dd/mmm") -> 21/may | E63: =+COUNTIF(I:I,I63) -> 13 | F63: 1 | G63: =IF(I63=I64,0,1) -> 1 | H63: 46163.703 | I63: 60082188 | J63: AB | K63: VDAD | L63: Outbound Auto Dial | M63: COBRO | O63: 366038820000 | P63: 16018 | Q63: -4 | R63: 1 | S63: 60082188 | U63: Sakiel Israel alb FernÃ¡ndez | W63: 8-1049-1495 | X63: 366038820000 | Y63: MASIVO | Z63: NPN | AG63: 0000-00-00 | AL63: 0 | AN63: NONE | AO63: 0 | AQ63: 2257630 | AR63: Cobros Mayo | AS63: Cobros Mayo NPN | AT63: Auto busy
A64: =_xlfn.XLOOKUP(I64,UTILIZADAS[Contacto1],UTILIZADAS[Source.Name],,0) -> Cobros Mayo | B64: =VLOOKUP(J64,Ref!A:C,3,0) -> 0 | C64: =VLOOKUP(J64,Ref!A:D,4,0) -> 0 | D64: =TEXT(H64,"dd/mmm") -> 09/may | E64: =+COUNTIF(I:I,I64) -> 7 | F64: 1 | G64: =IF(I64=I65,0,1) -> 0 | H64: 46151.473 | I64: 60088710 | J64: AB | K64: VDAD | L64: Outbound Auto Dial | M64: COBRO | O64: 363056260000 | P64: 16018 | Q64: -4 | R64: 1 | S64: 60088710 | U64: Vielka valdez | W64: 8-809-1625 | X64: 363056260000 | Y64: MASIVO | Z64: NPN | AG64: 0000-00-00 | AL64: 0 | AN64: NONE | AO64: 0 | AQ64: 2257631 | AR64: Cobros Mayo | AS64: Cobros Mayo NPN | AT64: Auto busy
A65: =_xlfn.XLOOKUP(I65,UTILIZADAS[Contacto1],UTILIZADAS[Source.Name],,0) -> Cobros Mayo | B65: =VLOOKUP(J65,Ref!A:C,3,0) -> 0 | C65: =VLOOKUP(J65,Ref!A:D,4,0) -> 0 | D65: =TEXT(H65,"dd/mmm") -> 13/may | E65: =+COUNTIF(I:I,I65) -> 7 | F65: 1 | G65: =IF(I65=I66,0,1) -> 0 | H65: 46155.603 | I65: 60088710 | J65: AB | K65: VDAD | L65: Outbound Auto Dial | M65: COBRO | O65: 363056260000 | P65: 16018 | Q65: -4 | R65: 1 | S65: 60088710 | U65: Vielka valdez | W65: 8-809-1625 | X65: 363056260000 | Y65: MASIVO | Z65: NPN | AG65: 0000-00-00 | AL65: 0 | AN65: NONE | AO65: 0 | AQ65: 2257631 | AR65: Cobros Mayo | AS65: Cobros Mayo NPN | AT65: Auto busy
A66: =_xlfn.XLOOKUP(I66,UTILIZADAS[Contacto1],UTILIZADAS[Source.Name],,0) -> Cobros Mayo | B66: =VLOOKUP(J66,Ref!A:C,3,0) -> 0 | C66: =VLOOKUP(J66,Ref!A:D,4,0) -> 0 | D66: =TEXT(H66,"dd/mmm") -> 16/may | E66: =+COUNTIF(I:I,I66) -> 7 | F66: 1 | G66: =IF(I66=I67,0,1) -> 0 | H66: 46158.433 | I66: 60088710 | J66: NA | K66: VDAD | L66: Outbound Auto Dial | M66: COBRO | O66: 363056260000 | P66: 16018 | Q66: -4 | R66: 1 | S66: 60088710 | U66: Vielka valdez | W66: 8-809-1625 | X66: 363056260000 | Y66: MASIVO | Z66: NPN | AG66: 0000-00-00 | AL66: 0 | AN66: NONE | AO66: 0 | AQ66: 2257631 | AR66: Cobros Mayo | AS66: Cobros Mayo NPN | AT66: No Answer AutoDial
... A70: =_xlfn.XLOOKUP(I70,UTILIZADAS[Contacto1],UTILIZADAS[Source.Name],,0) -> Cobros Mayo | B70: =VLOOKUP(J70,Ref!A:C,3,0) -> 0 | C70: =VLOOKUP(J70,Ref!A:D,4,0) -> 0 | D70: =TEXT(H70,"dd/mmm") -> 21/may | E70: =+COUNTIF(I:I,I70) -> 7 | F70: 1 | G70: =IF(I70=I71,0,1) -> 1 | H70: 46163.704 | I70: 60088710 | J70: AB | K70: VDAD | L70: Outbound Auto Dial | M70: COBRO | O70: 363056260000 | P70: 16018 | Q70: -4 | R70: 1 | S70: 60088710 | U70: Vielka valdez | W70: 8-809-1625 | X70: 363056260000 | Y70: MASIVO | Z70: NPN | AG70: 0000-00-00 | AL70: 0 | AN70: NONE | AO70: 0 | AQ70: 2257631 | AR70: Cobros Mayo | AS70: Cobros Mayo NPN | AT70: Auto busy
A71: =_xlfn.XLOOKUP(I71,UTILIZADAS[Contacto1],UTILIZADAS[Source.Name],,0) -> Cobros Abril Canal Fijo | B71: =VLOOKUP(J71,Ref!A:C,3,0) -> 0 | C71: =VLOOKUP(J71,Ref!A:D,4,0) -> 0 | D71: =TEXT(H71,"dd/mmm") -> 09/may | E71: =+COUNTIF(I:I,I71) -> 7 | F71: 1 | G71: =IF(I71=I72,0,1) -> 0 | H71: 46151.474 | I71: 60093261 | J71: DROP | K71: VDAD | L71: Outbound Auto Dial | M71: COBRO | O71: 353357320000 | P71: 16018 | Q71: -4 | R71: 1 | S71: 60093261 | U71: Joseph anel Ortega andrade | W71: 8-832-774 | X71: 353357320000 | Y71: MASIVO | Z71: NPN | AF71: U | AG71: 0000-00-00 | AL71: 5 | AN71: NONE | AO71: 0 | AQ71: 2257632 | AR71: Cobros Mayo | AS71: Cobros Mayo NPN | AT71: Agent Not Available
A72: =_xlfn.XLOOKUP(I72,UTILIZADAS[Contacto1],UTILIZADAS[Source.Name],,0) -> Cobros Abril Canal Fijo | B72: =VLOOKUP(J72,Ref!A:C,3,0) -> 0 | C72: =VLOOKUP(J72,Ref!A:D,4,0) -> 0 | D72: =TEXT(H72,"dd/mmm") -> 13/may | E72: =+COUNTIF(I:I,I72) -> 7 | F72: 1 | G72: =IF(I72=I73,0,1) -> 0 | H72: 46155.603 | I72: 60093261 | J72: AB | K72: VDAD | L72: Outbound Auto Dial | M72: COBRO | O72: 353357320000 | P72: 16018 | Q72: -4 | R72: 1 | S72: 60093261 | U72: Joseph anel Ortega andrade | W72: 8-832-774 | X72: 353357320000 | Y72: MASIVO | Z72: NPN | AF72: U | AG72: 0000-00-00 | AL72: 0 | AN72: NONE | AO72: 0 | AQ72: 2257632 | AR72: Cobros Mayo | AS72: Cobros Mayo NPN | AT72: Auto busy
A73: =_xlfn.XLOOKUP(I73,UTILIZADAS[Contacto1],UTILIZADAS[Source.Name],,0) -> Cobros Abril Canal Fijo | B73: =VLOOKUP(J73,Ref!A:C,3,0) -> 0 | C73: =VLOOKUP(J73,Ref!A:D,4,0) -> 0 | D73: =TEXT(H73,"dd/mmm") -> 16/may | E73: =+COUNTIF(I:I,I73) -> 7 | F73: 1 | G73: =IF(I73=I74,0,1) -> 0 | H73: 46158.434 | I73: 60093261 | J73: NA | K73: VDAD | L73: Outbound Auto Dial | M73: COBRO | O73: 353357320000 | P73: 16018 | Q73: -4 | R73: 1 | S73: 60093261 | U73: Joseph anel Ortega andrade | W73: 8-832-774 | X73: 353357320000 | Y73: MASIVO | Z73: NPN | AF73: U | AG73: 0000-00-00 | AL73: 0 | AN73: NONE | AO73: 0 | AQ73: 2257632 | AR73: Cobros Mayo | AS73: Cobros Mayo NPN | AT73: No Answer AutoDial
A74: =_xlfn.XLOOKUP(I74,UTILIZADAS[Contacto1],UTILIZADAS[Source.Name],,0) -> Cobros Abril Canal Fijo | B74: =VLOOKUP(J74,Ref!A:C,3,0) -> 0 | C74: =VLOOKUP(J74,Ref!A:D,4,0) -> 0 | D74: =TEXT(H74,"dd/mmm") -> 18/may | E74: =+COUNTIF(I:I,I74) -> 7 | F74: 1 | G74: =IF(I74=I75,0,1) -> 0 | H74: 46160.469 | I74: 60093261 | J74: AB | K74: VDAD | L74: Outbound Auto Dial | M74: COBRO | O74: 353357320000 | P74: 16018 | Q74: -4 | R74: 1 | S74: 60093261 | U74: Joseph anel Ortega andrade | W74: 8-832-774 | X74: 353357320000 | Y74: MASIVO | Z74: NPN | AF74: U | AG74: 0000-00-00 | AL74: 0 | AN74: NONE | AO74: 0 | AQ74: 2257632 | AR74: Cobros Mayo | AS74: Cobros Mayo NPN | AT74: Auto busy
A75: =_xlfn.XLOOKUP(I75,UTILIZADAS[Contacto1],UTILIZADAS[Source.Name],,0) -> Cobros Abril Canal Fijo | B75: =VLOOKUP(J75,Ref!A:C,3,0) -> 0 | C75: =VLOOKUP(J75,Ref!A:D,4,0) -> 0 | D75: =TEXT(H75,"dd/mmm") -> 19/may | E75: =+COUNTIF(I:I,I75) -> 7 | F75: 1 | G75: =IF(I75=I76,0,1) -> 0 | H75: 46161.658 | I75: 60093261 | J75: AB | K75: VDAD | L75: Outbound Auto Dial | M75: COBRO | O75: 353357320000 | P75: 16018 | Q75: -4 | R75: 1 | S75: 60093261 | U75: Joseph anel Ortega andrade | W75: 8-832-774 | X75: 353357320000 | Y75: MASIVO | Z75: NPN | AF75: U | AG75: 0000-00-00 | AL75: 0 | AN75: NONE | AO75: 0 | AQ75: 2257632 | AR75: Cobros Mayo | AS75: Cobros Mayo NPN | AT75: Auto busy
A76: =_xlfn.XLOOKUP(I76,UTILIZADAS[Contacto1],UTILIZADAS[Source.Name],,0) -> Cobros Abril Canal Fijo | B76: =VLOOKUP(J76,Ref!A:C,3,0) -> 0 | C76: =VLOOKUP(J76,Ref!A:D,4,0) -> 0 | D76: =TEXT(H76,"dd/mmm") -> 21/may | E76: =+COUNTIF(I:I,I76) -> 7 | F76: 1 | G76: =IF(I76=I77,0,1) -> 0 | H76: 46163.44 | I76: 60093261 | J76: AB | K76: VDAD | L76: Outbound Auto Dial | M76: COBRO | O76: 353357320000 | P76: 16018 | Q76: -4 | R76: 1 | S76: 60093261 | U76: Joseph anel Ortega andrade | W76: 8-832-774 | X76: 353357320000 | Y76: MASIVO | Z76: NPN | AF76: U | AG76: 0000-00-00 | AL76: 0 | AN76: NONE | AO76: 0 | AQ76: 2257632 | AR76: Cobros Mayo | AS76: Cobros Mayo NPN | AT76: Auto busy
A77: =_xlfn.XLOOKUP(I77,UTILIZADAS[Contacto1],UTILIZADAS[Source.Name],,0) -> Cobros Abril Canal Fijo | B77: =VLOOKUP(J77,Ref!A:C,3,0) -> 1 | C77: =VLOOKUP(J77,Ref!A:D,4,0) -> 1 | D77: =TEXT(H77,"dd/mmm") -> 21/may | E77: =+COUNTIF(I:I,I77) -> 7 | F77: 1 | G77: =IF(I77=I78,0,1) -> 1 | H77: 46163.704 | I77: 60093261 | J77: 6003 | K77: lvelez | L77: Lili Velez | M77: COBRO | O77: 353357320000 | P77: 16018 | Q77: -4 | R77: 1 | S77: 60093261 | U77: Joseph anel Ortega andrade | W77: 8-832-774 | X77: 353357320000 | Y77: MASIVO | Z77: NPN | AF77: U | AG77: 0000-00-00 | AL77: 88 | AM77: Llamaya | AN77: MAIN | AO77: 0 | AQ77: 2257632 | AR77: Cobros Mayo | AS77: Cobros Mayo NPN | AT77: Cuenta cesada
A78: =_xlfn.XLOOKUP(I78,UTILIZADAS[Contacto1],UTILIZADAS[Source.Name],,0) -> Cobros Abril Canal Fijo | B78: =VLOOKUP(J78,Ref!A:C,3,0) -> 0 | C78: =VLOOKUP(J78,Ref!A:D,4,0) -> 0 | D78: =TEXT(H78,"dd/mmm") -> 09/may | E78: =+COUNTIF(I:I,I78) -> 4 | F78: 1 | G78: =IF(I78=I79,0,1) -> 0 | H78: 46151.474 | I78: 60106162 | J78: AB | K78: VDAD | L78: Outbound Auto Dial | M78: COBRO | O78: 361023060000 | P78: 16018 | Q78: -5 | R78: 1 | S78: 60106162 | U78: Benarda Garcia | W78: 12-700-1888 | X78: 361023060000 | Y78: MASIVO | Z78: NPN | AF78: U | AG78: 0000-00-00 | AL78: 0 | AN78: NONE | AO78: 0 | AQ78: 2257633 | AR78: Cobros Mayo | AS78: Cobros Mayo NPN | AT78: Auto busy
A79: =_xlfn.XLOOKUP(I79,UTILIZADAS[Contacto1],UTILIZADAS[Source.Name],,0) -> Cobros Abril Canal Fijo | B79: =VLOOKUP(J79,Ref!A:C,3,0) -> 0 | C79: =VLOOKUP(J79,Ref!A:D,4,0) -> 0 | D79: =TEXT(H79,"dd/mmm") -> 13/may | E79: =+COUNTIF(I:I,I79) -> 4 | F79: 1 | G79: =IF(I79=I80,0,1) -> 0 | H79: 46155.604 | I79: 60106162 | J79: DROP | K79: VDAD | L79: Outbound Auto Dial | M79: COBRO | O79: 361023060000 | P79: 16018 | Q79: -5 | R79: 1 | S79: 60106162 | U79: Benarda Garcia | W79: 12-700-1888 | X79: 361023060000 | Y79: MASIVO | Z79: NPN | AF79: U | AG79: 0000-00-00 | AL79: 5 | AN79: NONE | AO79: 0 | AQ79: 2257633 | AR79: Cobros Mayo | AS79: Cobros Mayo NPN | AT79: Agent Not Available
A80: =_xlfn.XLOOKUP(I80,UTILIZADAS[Contacto1],UTILIZADAS[Source.Name],,0) -> Cobros Abril Canal Fijo | B80: =VLOOKUP(J80,Ref!A:C,3,0) -> 0 | C80: =VLOOKUP(J80,Ref!A:D,4,0) -> 0 | D80: =TEXT(H80,"dd/mmm") -> 16/may | E80: =+COUNTIF(I:I,I80) -> 4 | F80: 1 | G80: =IF(I80=I81,0,1) -> 0 | H80: 46158.446 | I80: 60106162 | J80: NA | K80: VDAD | L80: Outbound Auto Dial | M80: COBRO | O80: 361023060000 | P80: 16018 | Q80: -5 | R80: 1 | S80: 60106162 | U80: Benarda Garcia | W80: 12-700-1888 | X80: 361023060000 | Y80: MASIVO | Z80: NPN | AF80: U | AG80: 0000-00-00 | AL80: 0 | AN80: NONE | AO80: 0 | AQ80: 2257633 | AR80: Cobros Mayo | AS80: Cobros Mayo NPN | AT80: No Answer AutoDial
A81: =_xlfn.XLOOKUP(I81,UTILIZADAS[Contacto1],UTILIZADAS[Source.Name],,0) -> Cobros Abril Canal Fijo | B81: =VLOOKUP(J81,Ref!A:C,3,0) -> 1 | C81: =VLOOKUP(J81,Ref!A:D,4,0) -> 1 | D81: =TEXT(H81,"dd/mmm") -> 18/may | E81: =+COUNTIF(I:I,I81) -> 4 | F81: 1 | G81: =IF(I81=I82,0,1) -> 1 | H81: 46160.471 | I81: 60106162 | J81: 6003 | K81: lvelez | L81: Lili Velez | M81: COBRO | O81: 361023060000 | P81: 16018 | Q81: -5 | R81: 1 | S81: 60106162 | U81: Benarda Garcia | W81: 12-700-1888 | X81: 361023060000 | Y81: MASIVO | Z81: NPN | AF81: U | AG81: 0000-00-00 | AL81: 26 | AM81: Llamaya | AN81: MAIN | AO81: 0 | AQ81: 2257633 | AR81: Cobros Mayo | AS81: Cobros Mayo NPN | AT81: Cuenta cesada
A82: =_xlfn.XLOOKUP(I82,UTILIZADAS[Contacto1],UTILIZADAS[Source.Name],,0) -> #N/A | B82: =VLOOKUP(J82,Ref!A:C,3,0) -> 0 | C82: =VLOOKUP(J82,Ref!A:D,4,0) -> 0 | D82: =TEXT(H82,"dd/mmm") -> 04/may | E82: =+COUNTIF(I:I,I82) -> 3 | F82: 1 | G82: =IF(I82=I83,0,1) -> 0 | H82: 46146.637 | I82: 60117580 | J82: DROP | K82: VDAD | L82: Outbound Auto Dial | M82: COBRO | O82: 358372310000 | P82: 16017 | Q82: -5 | R82: 1 | S82: 60117580 | U82: MarÃ­a isabel monroy castillo | W82: 4-223-222 | X82: 2 MESES DE MORA | Y82: MASIVO | Z82: 358372310000 | AG82: 0000-00-00 | AI82: yitcibels@gmail.com | AL82: 5 | AN82: NONE | AO82: 0 | AQ82: 2252803 | AR82: Cobros Abril Canal Fijo | AS82: Cobros Abril Canal Fijo 2 meses a NPN | AT82: Agent Not Available
A83: =_xlfn.XLOOKUP(I83,UTILIZADAS[Contacto1],UTILIZADAS[Source.Name],,0) -> #N/A | B83: =VLOOKUP(J83,Ref!A:C,3,0) -> 0 | C83: =VLOOKUP(J83,Ref!A:D,4,0) -> 0 | D83: =TEXT(H83,"dd/mmm") -> 06/may | E83: =+COUNTIF(I:I,I83) -> 3 | F83: 1 | G83: =IF(I83=I84,0,1) -> 0 | H83: 46148.631 | I83: 60117580 | J83: DROP | K83: VDAD | L83: Outbound Auto Dial | M83: COBRO | O83: 358372310000 | P83: 16017 | Q83: -5 | R83: 1 | S83: 60117580 | U83: MarÃ­a isabel monroy castillo | W83: 4-223-222 | X83: 2 MESES DE MORA | Y83: MASIVO | Z83: 358372310000 | AG83: 0000-00-00 | AI83: yitcibels@gmail.com | AL83: 5 | AN83: NONE | AO83: 0 | AQ83: 2252803 | AR83: Cobros Abril Canal Fijo | AS83: Cobros Abril Canal Fijo 2 meses a NPN | AT83: Agent Not Available
