Workbook

Sheet Datos
A1: FUENTE | B1: CUENTA | C1: CUST_NO | D1: NOMBRE | E1: NKEY | F1: MRC | G1: EJECUTIVA | H1: CODIGO | I1: TELEFONO | J1: CANAL | K1: SERVICIOS | L1: CONTACTO_MOVIL
A2: NP | B2: 355382970000 | C2: 35538297 | D2: EDIL GOMEZ ARCE | E2: EDILGOMEZARCE | F2: 15 | G2: Solanye Acuña | H2: Y | I2: 68879413.0 | J2: TIENDA CALL CENTER TIENDA | K2: 0 | L2: 1
A3: NP | B3: 353338240000 | C3: 35333824 | D3: MEYVIS CALVO | E3: MEYVISCALVO | F3: 15 | G3: Michelle Zambrano | H3: V | I3: 67325039.0 | J3: 0 | K3: 0 | L3: 1
A4: NP | B4: 321157030000 | C4: 32115703 | D4: GRUPO CORPORA | E4: GRUPOCORPORA | F4: 226.5 | G4: Ines Lizbeth Trujillo | H4: T | I4: 66711672.0 | J4: TIENDA CALL CENTER TIENDA | K4: 0 | L4: 1
A5: NP | B5: 369050850000 | C5: 36905085 | D5: SILVIA ARAUZ | E5: SILVIAARAUZ | F5: 19.52 | G5: Alejandra Mabel Hawkins | H5: Y | K5: 0 | L5: 1
A6: NP | B6: 355282350000 | C6: 35528235 | D6: SIMON WALTEROVA | E6: SIMONWALTEROVA | F6: 30 | G6: Maria Fernanda | H6: B | I6: 62110427.0 | J6: 0 | K6: 0 | L6: 1
A7: NP | B7: 312235730000 | C7: 31223573 | D7: CORPORACION JEMS, S.A. -- | E7: CORPORACIONJEMSSA | F7: 326.24 | G7: Yarelis Tulloch | H7: C | I7: 62005659.0 | J7: TIENDA CALL CENTER TIENDA | K7: 0 | L7: 1
A8: NP | B8: 322504520000 | C8: 32250452 | D8: Ardines CPA Y Asociados Sa | E8: ARDINESCPAYASOCIADOSSA | F8: 64.25 | G8: Abril Aparicio | H8: T | I8: 69493738.0 | J8: TIENDA CALL CENTER TIENDA | K8: 0 | L8: 1
A9: NP | B9: 323672910000 | C9: 32367291 | D9: Ademar SA | E9: ADEMARSA | F9: 44 | G9: Yariela Galarce | H9: W | I9: 66131951.0 | J9: TIENDA CALL CENTER TIENDA | K9: 0 | L9: 1
A10: NP | B10: 349277210000 | C10: 34927721 | D10: SMART COMMUNICATIONS, SA | E10: SMARTCOMMUNICATIONSSA | F10: 16.25 | G10: Nailyn Martinez | H10: U | I10: 67424735.0 | J10: TIENDA CALL CENTER TIENDA | K10: 0 | L10: 1
A11: NP | B11: 324167750000 | C11: 32416775 | D11: HACIENDA LOMA LINDA | E11: HACIENDALOMALINDA | F11: 291.5 | G11: Yamali Rodriguez | H11: U | I11: 69834668.0 | J11: TIENDA CALL CENTER TIENDA | K11: 0 | L11: 1
A12: NP | B12: 361003450000 | C12: 36100345 | D12: FERNANDO JOSE ARAUZ HERNANDEZ | E12: FERNANDOJOSEARAUZHERNANDEZ | F12: 15 | G12: Osiris Aguilar | H12: A | I12: 69722675.0 | J12: TIENDA CALL CENTER TIENDA | K12: 0 | L12: 1
A13: NP | B13: 352329430000 | C13: 35232943 | D13: YDALIDES VALDES | E13: YDALIDESVALDES | F13: 15 | G13: Karla Mc Intryre | H13: H | I13: 67344173.0 | J13: 0 | K13: 0 | L13: 1
A14: NP | B14: 354175000000 | C14: 35417500 | D14: THIAGO DAVID CABALLERO | E14: THIAGODAVIDCABALLERO | F14: 15 | G14: Michelle Zambrano | H14: U | I14: 62475467.0 | J14: 0 | K14: 0 | L14: 1
A15: NP | B15: 327604400000 | C15: 32760440 | D15: GLOBAL LANGUAGE,S.A. | E15: GLOBALLANGUAGESA | F15: 275 | G15: Ines Lizbeth Trujillo | H15: W | I15: 69973283.0 | J15: TIENDA CALL CENTER TIENDA | K15: 0 | L15: 1
A16: NP | B16: 322366890200 | C16: 32236689 | D16: LIMAYON, S.A | E16: LIMAYONSA | F16: 124.95 | G16: Alejandra Mabel Hawkins | H16: T | I16: 69824192.0 | J16: TIENDA CALL CENTER TIENDA | K16: 0 | L16: 1
A17: NP | B17: 322366890200 | C17: 32236689 | D17: Asociacion de | E17: ASOCIACIONDE | F17: 30.74 | G17: Maria Fernanda | H17: T | I17: 69824192.0 | J17: TIENDA CALL CENTER TIENDA | K17: 0 | L17: 1
... A86: NP | B86: 312209940000 | C86: 31220994 | D86: UROLOGOS ASOCIADOS, S.A. - | E86: UROLOGOSASOCIADOSSA | F86: 31 | G86: Maria Fernanda | H86: S | I86: 62082799.0 | J86: TIENDA CALL CENTER TIENDA | K86: 0 | L86: 1
A87: NP | B87: 364043730000 | C87: 36404373 | D87: BALTAZAR GOMEZ | E87: BALTAZARGOMEZ | F87: 16.94 | G87: Yarelis Tulloch | H87: U | J87: 0 | K87: 0 | L87: 1
A88: NP | B88: 359354310000 | C88: 35935431 | D88: JAFETH LOPEZ | E88: JAFETHLOPEZ | F88: 15 | G88: Abril Aparicio | H88: C | I88: 67793454.0 | J88: 0 | K88: 0 | L88: 1
A89: NP | B89: 325374980000 | C89: 32537498 | D89: HENG CHANG, S.A. | E89: HENGCHANGSA | F89: 215 | G89: Yariela Galarce | H89: V | I89: 67076180.0 | J89: TIENDA CALL CENTER TIENDA | K89: 0 | L89: 1
A90: NP | B90: 353355830000 | C90: 35335583 | D90: MARÍA RIVAS | E90: MARIARIVAS | F90: 15 | G90: Nailyn Martinez | H90: H | I90: 65161910.0 | J90: 0 | K90: 0 | L90: 1
A91: NP | B91: 321439070100 | C91: 32143907 | D91: POWER EXTERMINATOR | E91: POWEREXTERMINATOR | F91: 353.77 | G91: Yamali Rodriguez | H91: U | I91: 69987657.0 | J91: TIENDA CALL CENTER TIENDA | K91: 0 | L91: 1
A92: NP | B92: 346090040000 | C92: 34609004 | D92: MARY HELEN CASTAÑEDA DE CALDERON | E92: MARYHELENCASTANEDADECALDERON | F92: 15 | G92: Osiris Aguilar | H92: T | I92: 66600631.0 | J92: TIENDA CALL CENTER TIENDA | K92: 0 | L92: 1
A93: NP | B93: 345006480000 | C93: 34500648 | D93: THOMAS JEFFERSON SCHOOL, S.A. | E93: THOMASJEFFERSONSCHOOLSA | F93: 245 | G93: Karla Mc Intryre | H93: U | I93: 68784059.0 | J93: TIENDA CALL CENTER TIENDA | K93: 0 | L93: 1
A94: NP | B94: 343249890000 | C94: 34324989 | D94: ISELA MARIA CASTAÑEDAS DE SINGH | E94: ISELAMARIACASTANEDASDESINGH | F94: 12 | G94: Solanye Acuña | H94: S | I94: 66409300.0 | J94: TIENDA CALL CENTER TIENDA | K94: 0 | L94: 1
A95: NP | B95: 353003570000 | C95: 35300357 | D95: FAVIO VANEGAS | E95: FAVIOVANEGAS | F95: 15 | G95: Michelle Zambrano | H95: F | I95: 67035338.0 | J95: TIENDA CALL CENTER TIENDA | K95: 0 | L95: 1
A96: NP | B96: 342412720000 | C96: 34241272 | D96: JAFET BERTIAGA MOSQUERA | E96: JAFETBERTIAGAMOSQUERA | F96: 16.25 | G96: Ines Lizbeth Trujillo | H96: U | I96: 66011050.0 | J96: TIENDA CALL CENTER TIENDA | K96: 0 | L96: 1
A97: NP | B97: 354334670000 | C97: 35433467 | D97: ARISTIDES BARRIOS CARRION | E97: ARISTIDESBARRIOSCARRION | F97: 15 | G97: Alejandra Mabel Hawkins | H97: U | I97: 66951128.0 | J97: 0 | K97: 0 | L97: 1
A98: NP | B98: 312216560000 | C98: 31221656 | D98: JADE TECHNOLOGY S.A - | E98: JADETECHNOLOGYSA | F98: 109.5 | G98: Maria Fernanda | H98: C | I98: 61126980.0 | J98: TIENDA CALL CENTER TIENDA | K98: 0 | L98: 1
A99: NP | B99: 369039290000 | C99: 36903929 | D99: PETRA PABLA MOSQUERA BLANCO | E99: PETRAPABLAMOSQUERABLANCO | F99: 16.94 | G99: Yarelis Tulloch | H99: L | J99: TIENDA CALL CENTER TIENDA | K99: 0 | L99: 1
A100: NP | B100: 323540060100 | C100: 32354006 | D100: Jacqueline Quintero Dominguez | E100: JACQUELINEQUINTERODOMINGUEZ | F100: 52.74 | G100: Abril Aparicio | H100: V | I100: 67812138.0 | J100: TIENDA CALL CENTER TIENDA | K100: 0 | L100: 1
A101: NP | B101: 323540060100 | C101: 32354006 | D101: Jacqueline Quintero Dominguez | E101: JACQUELINEQUINTERODOMINGUEZ | F101: 14.99 | G101: Yariela Galarce | H101: V | I101: 67812138.0 | J101: TIENDA CALL CENTER TIENDA | K101: 0 | L101: 1
A102: NP | B102: 345179830000 | C102: 34517983 | D102: LEGUMBRES Y FRUTAS IVERSON | E102: LEGUMBRESYFRUTASIVERSON | F102: 40 | G102: Nailyn Martinez | H102: W | I102: 69505541.0 | J102: TIENDA CALL CENTER TIENDA | K102: 0 | L102: 1
A103: NP | B103: 349132360000 | C103: 34913236 | D103: AHAVA LATIN AMERCA | E103: AHAVALATINAMERCA | F103: 21 | G103: Yamali Rodriguez | H103: U | I103: 60138979.0 | J103: TIENDA CALL CENTER TIENDA | K103: 0 | L103: 1
A104: NP | B104: 344414740000 | C104: 34441474 | D104: NORBERTO ANTONIO CERNA LOPEZ | E104: NORBERTOANTONIOCERNALOPEZ | F104: 16.25 | G104: Osiris Aguilar | H104: U | I104: 67769361.0 | J104: TIENDA CALL CENTER TIENDA | K104: 0 | L104: 1
A105: NP | B105: 341297900000 | C105: 34129790 | D105: HERCILIA PACHECO SECAIDA | E105: HERCILIAPACHECOSECAIDA | F105: 16.25 | G105: Karla Mc Intryre | H105: C | I105: 65372281.0 | J105: TIENDA CALL CENTER TIENDA | K105: 0 | L105: 1
A106: NP | B106: 312209910000 | C106: 31220991 | D106: DISTRIBUIDORA CARIVA, S.A. - | E106: DISTRIBUIDORACARIVASA | F106: 64 | G106: Michelle Zambrano | H106: S | I106: 62269500.0 | J106: TIENDA CALL CENTER TIENDA | K106: 0 | L106: 1
A107: NP | B107: 325409780200 | C107: 32540978 | D107: NUBIA ARENAS GOMEZ | E107: NUBIAARENASGOMEZ | F107: 28.75 | G107: Ines Lizbeth Trujillo | H107: V | I107: 66131158.0 | J107: TIENDA CALL CENTER TIENDA | K107: 0 | L107: 1
A108: NP | B108: 322462760200 | C108: 32246276 | D108: A.J.FOTOS S.A. | E108: AJFOTOSSA | F108: 42 | G108: Alejandra Mabel Hawkins | H108: V | I108: 67810778.0 | J108: TIENDA CALL CENTER TIENDA | K108: 0 | L108: 1
A109: NP | B109: 341145610000 | C109: 34114561 | D109: LUIS HERNAN VALENCIA | E109: LUISHERNANVALENCIA | F109: 16.25 | G109: Maria Fernanda | H109: V | I109: 60037002.0 | J109: TIENDA CALL CENTER TIENDA | K109: 0 | L109: 1
A110: NP | B110: 346146550000 | C110: 34614655 | D110: LUIS HERNAN VALENCIA | E110: LUISHERNANVALENCIA | F110: 32.5 | G110: Yarelis Tulloch | H110: V | I110: 66283511.0 | J110: TIENDA CALL CENTER TIENDA | K110: 0 | L110: 1
A111: NP | B111: 326656630100 | C111: 32665663 | D111: INVERSIONES KALY, SA | E111: INVERSIONESKALYSA | F111: 40 | G111: Abril Aparicio | H111: W | I111: 66712509.0 | J111: TIENDA CALL CENTER TIENDA | K111: 0 | L111: 1
... A119: NP | B119: 355288540000 | C119: 35528854 | D119: BRENDA ELIZABETH HERAZO ACOSTA | E119: BRENDAELIZABETHHERAZOACOSTA | F119: 18 | G119: Ines Lizbeth Trujillo | H119: C | I119: 69065210.0 | J119: TIENDA CALL CENTER TIENDA | K119: 0 | L119: 1
A120: NP | B120: 365052370000 | C120: 36505237 | D120: ARELIO CABEZON CHOCHO | E120: ARELIOCABEZONCHOCHO | F120: 16.94 | G120: Alejandra Mabel Hawkins | H120: S | K120: 0 | L120: 1
A121: NP | B121: 349093270000 | C121: 34909327 | D121: CARMELO ALVARADO | E121: CARMELOALVARADO | F121: 32.5 | G121: Maria Fernanda | H121: W | I121: 68241659.0 | J121: TIENDA CALL CENTER TIENDA | K121: 0 | L121: 1
A122: NP | B122: 358004430000 | C122: 35800443 | D122: ISMAEL RAMOS MURILLO | E122: ISMAELRAMOSMURILLO | F122: 15 | G122: Yarelis Tulloch | H122: I | I122: 66456509.0 | J122: TIENDA CALL CENTER TIENDA | K122: 0 | L122: 1
A123: NP | B123: 361050650000 | C123: 36105065 | D123: KENY BIPURO | E123: KENYBIPURO | F123: 27.42 | G123: Abril Aparicio | H123: B | K123: 0 | L123: 1
A124: NP | B124: 322390980400 | C124: 32239098 | D124: Servicio de Winche | E124: SERVICIODEWINCHE | F124: 42 | G124: Yariela Galarce | H124: V | I124: 66798629.0 | J124: TIENDA CALL CENTER TIENDA | K124: 0 | L124: 1
A125: NP | B125: 322897600000 | C125: 32289760 | D125: Servidental S.A. | E125: SERVIDENTALSA | F125: 25 | G125: Nailyn Martinez | H125: V | I125: 69532354.0 | J125: 0 | K125: 0 | L125: 1
A126: NP | B126: 312222690000 | C126: 31222269 | D126: SERVIDENTAL, S.A. | E126: SERVIDENTALSA | F126: 50 | G126: Yamali Rodriguez | H126: C | I126: 66707039.0 | J126: TIENDA CALL CENTER TIENDA | K126: 0 | L126: 1
A127: NP | B127: 346344050000 | C127: 34634405 | D127: ADAN RODRIGUEZ | E127: ADANRODRIGUEZ | F127: 16.25 | G127: Osiris Aguilar | H127: U | I127: 69380286.0 | J127: TIENDA CALL CENTER TIENDA | K127: 0 | L127: 1
A128: NP | B128: 312220250000 | C128: 31222025 | D128: SOFTWARE OF HARDWARE PANAMA, S - | E128: SOFTWAREOFHARDWAREPANAMAS | F128: 31 | G128: Karla Mc Intryre | H128: S | I128: 62788377.0 | J128: TIENDA CALL CENTER TIENDA | K128: 0 | L128: 1
A129: NP | B129: 354233640000 | C129: 35423364 | D129: EDGARDO GUEVARA | E129: EDGARDOGUEVARA | F129: 15 | G129: Michelle Zambrano | H129: M | I129: 66740947.0 | J129: 0 | K129: 0 | L129: 1
A130: NP | B130: 355304160000 | C130: 35530416 | D130: ZONA DE PODER | E130: ZONADEPODER | F130: 20 | G130: Ines Lizbeth Trujillo | H130: A | I130: 65000662.0 | J130: 0 | K130: 0 | L130: 1
A131: NP | B131: 357168280000 | C131: 35716828 | D131: EDILSA HITUCAMA NEGRIA | E131: EDILSAHITUCAMANEGRIA | F131: 15 | G131: Alejandra Mabel Hawkins | H131: I | I131: 68894702.0 | J131: 0 | K131: 0 | L131: 1
A132: NP | B132: 321464410000 | C132: 32146441 | D132: PSI Panama S.A | E132: PSIPANAMASA | F132: 386 | G132: Maria Fernanda | H132: W | I132: 67475277.0 | J132: TIENDA CALL CENTER TIENDA | K132: 0 | L132: 1
A133: NP | B133: 312227510000 | C133: 31222751 | D133: CALDERA ENERGY CORP CALDERA ENERGY CORP | E133: CALDERAENERGYCORPCALDERAENERGYCORP | F133: 16.25 | G133: Yarelis Tulloch | H133: S | I133: 62506248.0 | J133: TIENDA CALL CENTER TIENDA | K133: 0 | L133: 1
A134: NP | B134: 334303920000 | C134: 33430392 | D134: SERVICIOS Y ALQUILERES DE EQUIPOS S.A | E134: SERVICIOSYALQUILERESDEEQUIPOSSA | F134: 145 | G134: Abril Aparicio | H134: W | I134: 69496174.0 | J134: TIENDA CALL CENTER TIENDA | K134: 0 | L134: 1
A135: NP | B135: 356219260000 | C135: 35621926 | D135: MANIX CHORCHI | E135: MANIXCHORCHI | F135: 15 | G135: Yariela Galarce | H135: C | I135: 63034976.0 | J135: 0 | K135: 0 | L135: 1
... A279: NP | B279: 312230760000 | C279: 31223076 | D279: SUPLIDORA RAMBAR, S.A. - | E279: SUPLIDORARAMBARSA | F279: 92 | G279: Michelle Zambrano | H279: C | I279: 66128330.0 | J279: TIENDA CALL CENTER TIENDA | K279: 0 | L279: 1
A280: NP | B280: 362040060000 | C280: 36204006 | D280: ROXANA QUINTANA | E280: ROXANAQUINTANA | F280: 18.23 | G280: Ines Lizbeth Trujillo | H280: A | J280: 0 | K280: 0 | L280: 1
A281: NP | B281: 358387480000 | C281: 35838748 | D281: ZORAIDA PALACIO | E281: ZORAIDAPALACIO | F281: 20 | G281: Alejandra Mabel Hawkins | H281: H | I281: 69589128.0 | J281: 0 | K281: 0 | L281: 1
A282: NP | B282: 368051230000 | C282: 36805123 | D282: LEISA BERRUGATE | E282: LEISABERRUGATE | F282: 16.94 | G282: Maria Fernanda | H282: B | K282: 0 | L282: 1
A283: NP | B283: 359348000000 | C283: 35934800 | D283: MARCITA CHANAPI CABRERA | E283: MARCITACHANAPICABRERA | F283: 15 | G283: Yarelis Tulloch | H283: Y | I283: 68339140.0 | J283: 0 | K283: 0 | L283: 1
A284: NP | B284: 345085720000 | C284: 34508572 | D284: TRANSPORTE UMANA SA | E284: TRANSPORTEUMANASA | F284: 65.25 | G284: Abril Aparicio | H284: W | I284: 64886130.0 | J284: TIENDA CALL CENTER TIENDA | K284: 0 | L284: 1
A285: NP | B285: 342109320000 | C285: 34210932 | D285: ESMITT ISMARE GARCIA | E285: ESMITTISMAREGARCIA | F285: 16.25 | G285: Yariela Galarce | H285: T | I285: 62053613.0 | J285: TIENDA CALL CENTER TIENDA | K285: 0 | L285: 1
A286: NP | B286: 357067150000 | C286: 35706715 | D286: ISIDRO CHECA | E286: ISIDROCHECA | F286: 15 | G286: Nailyn Martinez | H286: C | I286: 66981368.0 | J286: 0 | K286: 0 | L286: 1
A287: NP | B287: 358029290000 | C287: 35802929 | D287: FUNERARIA CEMACO | E287: FUNERARIACEMACO | F287: 15 | G287: Yamali Rodriguez | H287: C | I287: 67381314.0 | J287: TIENDA CALL CENTER TIENDA | K287: 0 | L287: 1
A288: NP | B288: 351368860000 | C288: 35136886 | D288: ELIA VELASQUEZ | E288: ELIAVELASQUEZ | F288: 15 | G288: Osiris Aguilar | H288: U | I288: 65854460.0 | J288: 0 | K288: 0 | L288: 1
A289: NP | B289: 358313620000 | C289: 35831362 | D289: ORIEL BONILLA | E289: ORIELBONILLA | F289: 15 | G289: Karla Mc Intryre | H289: B | I289: 61856444.0 | J289: 0 | K289: 0 | L289: 1
A290: NP | B290: 354303340000 | C290: 35430334 | D290: YANETH BENILLDA SERNA CORDOBA | E290: YANETHBENILLDASERNACORDOBA | F290: 15 | G290: Michelle Zambrano | H290: U | I290: 68558258.0 | J290: 0 | K290: 0 | L290: 1
A291: NP | B291: 356096640000 | C291: 35609664 | D291: YOLANDA CEDEÑO | E291: YOLANDACEDENO | F291: 15 | G291: Ines Lizbeth Trujillo | H291: C | I291: 65089323.0 | J291: 0 | K291: 0 | L291: 1
A292: NP | B292: 358201290000 | C292: 35820129 | D292: ERIC YONARD HURTADO GONZALEZ | E292: ERICYONARDHURTADOGONZALEZ | F292: 25 | G292: Alejandra Mabel Hawkins | H292: A | I292: 63615141.0 | J292: TIENDA CALL CENTER TIENDA | K292: 0 | L292: 1
A293: NP | B293: 348369230000 | C293: 34836923 | D293: LISET YARITZA QUINTANA | E293: LISETYARITZAQUINTANA | F293: 30 | G293: Maria Fernanda | H293: G | I293: 67872948.0 | J293: TIENDA CALL CENTER TIENDA | K293: 0 | L293: 1
A294: NP | B294: 349140520000 | C294: 34914052 | D294: SULMA ISMARE PUCHICAMA DE CHAUCARAMA | E294: SULMAISMAREPUCHICAMADECHAUCARAMA | F294: 37.5 | G294: Yarelis Tulloch | H294: U | I294: 63365812.0 | J294: TIENDA CALL CENTER TIENDA | K294: 0 | L294: 1
... A304: NP | B304: 367023820000 | C304: 36702382 | D304: JOSUE CORDOBA | E304: JOSUECORDOBA | F304: 30 | G304: Alejandra Mabel Hawkins | H304: Y | I304: 65295285.0 | J304: 0 | K304: 0 | L304: 1
A305: NP | C305: 35828394 | D305: ELIGIO MOSQUERA BARCO | E305: ELIGIOMOSQUERABARCO | F305: 45 | G305: Maria Fernanda | H305: S | J305: 0 | K305: 0 | L305: 1
A306: NP | B306: 355039520000 | C306: 35503952 | D306: PRISCILA MEDINA | E306: PRISCILAMEDINA | F306: 15 | G306: Yarelis Tulloch | H306: F | I306: 69456169.0 | J306: TIENDA CALL CENTER TIENDA | K306: 0 | L306: 1
A307: NP | B307: 351246120000 | C307: 35124612 | D307: NORBERTO VELANCIA | E307: NORBERTOVELANCIA | F307: 15 | G307: Abril Aparicio | H307: S | I307: 68673589.0 | J307: 0 | K307: 0 | L307: 1
A308: NP | B308: 357364020000 | C308: 35736402 | D308: DAVID REYES | E308: DAVIDREYES | F308: 15 | G308: Yariela Galarce | H308: A | I308: 63643600.0 | J308: 0 | K308: 0 | L308: 1
A309: NP | B309: 356149210000 | C309: 35614921 | D309: NILVA MIGDALIA RIVAS ESPINOZA | E309: NILVAMIGDALIARIVASESPINOZA | F309: 15 | G309: Nailyn Martinez | H309: V | I309: 66685183.0 | J309: 0 | K309: 0 | L309: 1
A310: NP | B310: 356118310000 | C310: 35611831 | D310: DAIHANA DE LA ROSA | E310: DAIHANADELAROSA | F310: 15 | G310: Yamali Rodriguez | H310: B | I310: 63727402.0 | J310: 0 | K310: 0 | L310: 1
A311: NP | B311: 349331440000 | C311: 34933144 | D311: ARNALDO LOPEZ | E311: ARNALDOLOPEZ | F311: 23.25 | G311: Osiris Aguilar | H311: C | I311: 66094339.0 | J311: TIENDA CALL CENTER TIENDA | K311: 0 | L311: 1
A312: NP | B312: 355130350000 | C312: 35513035 | D312: DISMA TOCAMO | E312: DISMATOCAMO | F312: 15 | G312: Karla Mc Intryre | H312: C | I312: 69921447.0 | J312: 0 | K312: 0 | L312: 1
A313: NP | B313: 364037000000 | C313: 36403700 | D313: LIANNE SHERILL PINEDA MOSQUERA | E313: LIANNESHERILLPINEDAMOSQUERA | F313: 16.29 | G313: Michelle Zambrano | H313: I | J313: TIENDA CALL CENTER TIENDA | K313: 0 | L313: 1
A314: NP | B314: 347400570000 | C314: 34740057 | D314: DAYANIS DIMAS | E314: DAYANISDIMAS | F314: 16.25 | G314: Ines Lizbeth Trujillo | H314: D | I314: 68764376.0 | J314: TIENDA CALL CENTER TIENDA | K314: 0 | L314: 1
A315: NP | B315: 341182820000 | C315: 34118282 | D315: ELIDIA PERALTA | E315: ELIDIAPERALTA | F315: 106.5 | G315: Alejandra Mabel Hawkins | H315: W | I315: 60691264.0 | J315: TIENDA CALL CENTER TIENDA | K315: 0 | L315: 1
A316: NP | B316: 337275680000 | C316: 33727568 | D316: THE ENGLISH LANGUAGE CENTER, INC. | E316: THEENGLISHLANGUAGECENTERINC | F316: 200.23 | G316: Maria Fernanda | H316: W | I316: 66775277.0 | J316: TIENDA CALL CENTER TIENDA | K316: 0 | L316: 1
A317: NP | B317: 344330260000 | C317: 34433026 | D317: ISMILDA VICTORIA LOPEZ PALACIOS | E317: ISMILDAVICTORIALOPEZPALACIOS | F317: 20.75 | G317: Yarelis Tulloch | H317: C | I317: 67276141.0 | J317: TIENDA CALL CENTER TIENDA | K317: 0 | L317: 1
A318: NP | B318: 332153930000 | C318: 33215393 | D318: ABDIEL GUASERUCA MESUA | E318: ABDIELGUASERUCAMESUA | F318: 22.5 | G318: Abril Aparicio | H318: T | I318: 63496886.0 | J318: TIENDA CALL CENTER TIENDA | K318: 0 | L318: 1
A319: NP | B319: 362057130000 | C319: 36205713 | D319: BENJAMIN VALDESPINO | E319: BENJAMINVALDESPINO | F319: 16.29 | G319: Yariela Galarce | H319: Y | K319: 0 | L319: 1
A320: NP | B320: 351280280000 | C320: 35128028 | D320: MARTA MACHUCA | E320: MARTAMACHUCA | F320: 15 | G320: Nailyn Martinez | H320: V | I320: 67309564.0 | J320: 0 | K320: 0 | L320: 1
A321: NP | B321: 354353420000 | C321: 35435342 | D321: LLAMILEICA BERRUGATE | E321: LLAMILEICABERRUGATE | F321: 15 | G321: Yamali Rodriguez | H321: C | I321: 65531545.0 | J321: 0 | K321: 0 | L321: 1
A322: NP | B322: 356343590000 | C322: 35634359 | D322: CESAR PUCHIGAMA | E322: CESARPUCHIGAMA | F322: 15 | G322: Osiris Aguilar | H322: B | I322: 65831896.0 | J322: 0 | K322: 0 | L322: 1
A323: NP | B323: 364036650000 | C323: 36403665 | D323: LUIS CHIRIPUA TEUCAMA | E323: LUISCHIRIPUATEUCAMA | F323: 20.16 | G323: Karla Mc Intryre | H323: A | J323: TIENDA CALL CENTER TIENDA | K323: 0 | L323: 1
A324: NP | B324: 352030160000 | C324: 35203016 | D324: MAXIMA MURILLO | E324: MAXIMAMURILLO | F324: 15 | G324: Solanye Acuña | H324: C | I324: 63349166.0 | J324: TIENDA CALL CENTER TIENDA | K324: 0 | L324: 1
A325: NP | B325: 346172980000 | C325: 34617298 | D325: LUIS ENRIQUE ISAZA MARANDOLA | E325: LUISENRIQUEISAZAMARANDOLA | F325: 32.5 | G325: Michelle Zambrano | H325: W | I325: 67654284.0 | J325: TIENDA CALL CENTER TIENDA | K325: 0 | L325: 1
A326: NP | B326: 359324330000 | C326: 35932433 | D326: ROSALINDA MOSQUERA | E326: ROSALINDAMOSQUERA | F326: 15 | G326: Ines Lizbeth Trujillo | H326: C | I326: 65231111.0 | J326: 0 | K326: 0 | L326: 1
A327: NP | B327: 361056030000 | C327: 36105603 | D327: DONAL BARQUEÑO CARDENA | E327: DONALBARQUENOCARDENA | F327: 16.94 | G327: Alejandra Mabel Hawkins | H327: Y | K327: 0 | L327: 1
...

Sheet Winback
A1: CLIENTE | B1: NKEY | C1: EJECUTIVA | D1: MRC | E1: RAZON_SALIDA | F1: RGU | G1: CONTACTO | H1: CORREO | I1: TEL1 | J1: TEL2
A2: COIMSA | B2: COIMSA | C2: Michelle Zambrano | D2: 95 | E2: Solicitado por el Cliente | F2: 3 | G2: Jorge Villarreal ced 8-299-399 | H2: gerencia.coimsa@gmail.com | I2: 66776809.0 | J2: 2602749.0
A3: GRAPHIC SOLUTIONS/ CARMEN R. WILLIAMS 2 | B3: GRAPHICSOLUTIONSCARMENRWILLIAMS2 | C3: Solanye Acuña | D3: 12 | E3: Solicitado por el Cliente | F3: 1 | G3: Angelica Gallego E-8-79314 | I3: 3140588.0
A4: ALEXIS ALEXANDER GOMEZ MENDIETA | B4: ALEXISALEXANDERGOMEZMENDIETA | C4: Maria Fernanda Rivas | D4: 20.75 | E4: Solicitado por el Cliente | F4: 1 | G4: ALEXIS ALEXANDER GOMEZ MENDIETA | I4: 67472064.0
A5: PH COUNTRY CLUB - | B5: PHCOUNTRYCLUB | C5: Nailyn Martinez Johnson | D5: 166 | E5: Solicitado por el Cliente | F5: 8 | G5: MICHAEL HAMOUI | I5: 69144044.0
C6: Michelle Zambrano | D6: 20.75 | E6: Solicitado por el Cliente | F6: 1
C7: Solanye Acuña | D7: 40.5 | E7: Solicitado por el Cliente | F7: 1
C8: Maria Fernanda Rivas | D8: 31 | E8: Solicitado por el Cliente | F8: 1
A9: IDEALO | B9: IDEALO | C9: Nailyn Martinez Johnson | D9: 41.5 | E9: Solicitado por el Cliente | F9: 2 | G9: IDEALO | I9: 68800852.0
A10: INFINITY LOGISTICS INFINITY LOGISTICS AGENCY, CORP | B10: INFINITYLOGISTICSINFINITYLOGISTICSAGENCYCORP | C10: Michelle Zambrano | D10: 60 | E10: Solicitado por el Cliente | F10: 3 | G10: ARCELIS ASPRILLA | I10: 4304648.0
C11: Solanye Acuña | D11: 50 | E11: Solicitado por el Cliente | F11: 2
C12: Maria Fernanda Rivas | D12: 50 | E12: Solicitado por el Cliente | F12: 1
C13: Nailyn Martinez Johnson | D13: 17 | E13: Solicitado por el Cliente | F13: 1
C14: Michelle Zambrano | D14: 170 | E14: Solicitado por el Cliente | F14: 5
C15: Solanye Acuña | D15: 35 | E15: Solicitado por el Cliente | F15: 1
A16: RC SOLUTION, S.A - | B16: RCSOLUTIONSA | C16: Maria Fernanda Rivas | D16: 41.5 | E16: Solicitado por el Cliente | F16: 2 | G16: RC SOLUTION, S.A - | I16: 62608877.0
C17: Nailyn Martinez Johnson | D17: 113.5 | E17: Solicitado por el Cliente | F17: 4
A18: Servicios Logitisticos Imperial S.A | B18: SERVICIOSLOGITISTICOSIMPERIALSA | C18: Michelle Zambrano | D18: 30 | E18: Solicitado por el Cliente | F18: 2 | G18: Servicios Logisticos Imperial S.A. | H18: comercial.panama@petentrega.com | I18: 65146298.0
A19: CLINICA TU SALUD Y BELLEZA - | B19: CLINICATUSALUDYBELLEZA | C19: Solanye Acuña | D19: 16.25 | E19: Solicitado por el Cliente | F19: 1 | G19: Soy Yoli calu N-20-930 | I19: 65081722.0
A20: SERVIEDUCA S,A. - | B20: SERVIEDUCASA | C20: Maria Fernanda Rivas | D20: 20 | E20: Solicitado por el Cliente | F20: 1 | G20: SERVIEDUCA S,A. - GABRIELA ALEJANDRA, | I20: 2366783.0
C21: Nailyn Martinez Johnson | D21: 25 | E21: Solicitado por el Cliente | F21: 1
A22: PANAMA JOURNEYS S,A - | B22: PANAMAJOURNEYSSA | C22: Michelle Zambrano | D22: 31 | E22: Solicitado por el Cliente | F22: 1 | G22: PANAMA JOURNEYS S,A - | I22: 63134216.0
A23: AGRO JP / NILKA ATENCIO | B23: AGROJPNILKAATENCIO | C23: Solanye Acuña | D23: 65 | E23: Solicitado por el Cliente | F23: 2 | G23: AGRO JP / NILKA ATENCIO | H23: ni.lka@hotmail.com | I23: 65767586.0 | J23: 65767586.0
C24: Maria Fernanda Rivas | D24: 31 | E24: Solicitado por el Cliente | F24: 1
C25: Nailyn Martinez Johnson | D25: 40.5 | E25: Solicitado por el Cliente | F25: 1
C26: Michelle Zambrano | D26: 66.5 | E26: Solicitado por el Cliente | F26: 1
A27: UPPER EAST TOWER | B27: UPPEREASTTOWER | C27: Solanye Acuña | D27: 124 | E27: Solicitado por el Cliente | F27: 4 | G27: UPPER EAST TOWER | I27: 2027194.0
A28: FLIX CINEVISION PANAMA, S. DE R.L. - | B28: FLIXCINEVISIONPANAMASDERL | C28: Maria Fernanda Rivas | D28: 81 | E28: Solicitado por el Cliente | F28: 1 | G28: FLIX CINEVISION PANAMA, S. DE R.L. - | I28: 64993246.0
A29: AVAPSA | B29: AVAPSA | C29: Nailyn Martinez Johnson | D29: 40.5 | E29: Solicitado por el Cliente | F29: 1 | G29: AVAPSA | H29: magt.67vetequi@gmail.com | I29: 62605786.0 | J29: 66150700.0
A30: DRAG COLORS | B30: DRAGCOLORS | C30: Michelle Zambrano | D30: 22 | E30: Solicitado por el Cliente | F30: 1 | G30: Salvador Orantes | H30: Chambascar27@gmail.com | I30: 69207844.0 | J30: 69207844.0
C31: Solanye Acuña | D31: 150 | E31: Solicitado por el Cliente | F31: 6
C32: Maria Fernanda Rivas | D32: 21 | E32: Solicitado por el Cliente | F32: 3
A33: Anagan | B33: ANAGAN | C33: Nailyn Martinez Johnson | D33: 42 | E33: Solicitado por el Cliente | F33: 1 | G33: LUIS MARTINEZ 7-83-25 // Amarilis Cristóbal 8-841-1249 | H33: anagan1@cwpanama.net | I33: 3140633.0 | J33: 3140633.0
C34: Michelle Zambrano | D34: 44 | E34: Solicitado por el Cliente | F34: 1
A35: Carmen Valdivia Valdes | B35: CARMENVALDIVIAVALDES | C35: Solanye Acuña | D35: 21 | E35: Solicitado por el Cliente | F35: 1 | I35: 66773196.0
A36: Gixel Guevara Almanza | B36: GIXELGUEVARAALMANZA | C36: Maria Fernanda Rivas | D36: 16 | E36: Solicitado por el Cliente | F36: 1 | I36: 69822979.0
A37: Jaime Arroyo Atencio | B37: JAIMEARROYOATENCIO | C37: Nailyn Martinez Johnson | D37: 21.75 | E37: Solicitado por el Cliente | F37: 1 | I37: 2287216.0
A38: Shirley y Asociados | B38: SHIRLEYYASOCIADOS | C38: Michelle Zambrano | D38: 45.5 | E38: Solicitado por el Cliente | F38: 1 | G38: Luis Antonio Shirley Campbell | H38: administracion@shirleylaw.com | I38: 66752321.0 | J38: 66752321.0
A39: M. Contratista | B39: MCONTRATISTA | C39: Solanye Acuña | D39: 42 | E39: MIGRACION POST-PRE | F39: 1 | G39: Ricardo Raul Mezquita | I39: 2790469.0
A40: Solidus Secur | B40: SOLIDUSSECUR | C40: Maria Fernanda Rivas | D40: 15.99 | E40: Solicitado por el Cliente | F40: 1 | G40: HEINER SPEICH | H40: karoll.arguelles@sardona-capital.com | I40: 69826252.0 | J40: 69826252.0
A41: Bold Impresiones | B41: BOLDIMPRESIONES | C41: Nailyn Martinez Johnson | D41: 75 | E41: Solicitado por el Cliente | F41: 5 | G41: Alexander Romero Martinez | I41: 2702607.0
C42: Michelle Zambrano | D42: 40 | E42: Solicitado por el Cliente | F42: 1
C43: Solanye Acuña | D43: 5.5 | E43: Solicitado por el Cliente | F43: 1
A44: Full Drop Sa | B44: FULLDROPSA | C44: Maria Fernanda Rivas | D44: 21.74 | E44: Solicitado por el Cliente | F44: 1 | G44: EDGAR NORIEL CHANG HERNANDEZ 6-701-17 | I44: 9101722.0
C45: Nailyn Martinez Johnson | D45: 24 | E45: Solicitado por el Cliente | F45: 1
C46: Michelle Zambrano | D46: 44 | E46: Solicitado por el Cliente | F46: 2
A47: Varela Carden | B47: VARELACARDEN | C47: Solanye Acuña | D47: 40 | E47: Solicitado por el Cliente | F47: 1 | G47: Carlos Varela 8-259-337 | I47: 2655785.0
A48: Jestski Panamarin | B48: JESTSKIPANAMARIN | C48: Maria Fernanda Rivas | D48: 42 | E48: Solicitado por el Cliente | F48: 1 | G48: Rene Marin | H48: bbrosi1023@hotmail.com | I48: 65112891.0 | J48: 65112891.0
C49: Nailyn Martinez Johnson | D49: 80.25 | E49: Solicitado por el Cliente | F49: 3
A50: DVA GLASS SERVICES SA | B50: DVAGLASSSERVICESSA | C50: Michelle Zambrano | D50: 72 | E50: Solicitado por el Cliente | F50: 2 | G50: SANDRA ECHEVERRIA | I50: 69835010.0
C51: Solanye Acuña | D51: 26.75 | E51: Solicitado por el Cliente | F51: 1
C52: Maria Fernanda Rivas | D52: 28.75 | E52: Solicitado por el Cliente | F52: 1
A53: Annett Miranda | B53: ANNETTMIRANDA | C53: Nailyn Martinez Johnson | D53: 28.75 | E53: (en blanco) | F53: 1 | G53: Nila Espinoza | I53: 2644225.0
A54: FONSECA, S.A. | B54: FONSECASA | C54: Michelle Zambrano | D54: 20.75 | E54: Solicitado por el Cliente | F54: 1 | G54: YARIBETH HOU JIANG | H54: surtimaxpanama@hotmail.com | I54: 62529492.0 | J54: 62529492.0
C55: Solanye Acuña | D55: 24 | E55: Solicitado por el Cliente | F55: 2
C56: Maria Fernanda Rivas | D56: 117.75 | E56: Solicitado por el Cliente | F56: 3
C57: Nailyn Martinez Johnson | D57: 44.5 | E57: Solicitado por el Cliente | F57: 1
C58: Michelle Zambrano | D58: 43.96 | E58: Solicitado por el Cliente | F58: 4
A59: Agencia De Ad | B59: AGENCIADEAD | C59: Solanye Acuña | D59: 37.5 | E59: Solicitado por el Cliente | F59: 1 | G59: MARCOS VIDES | I59: 67753993.0
A60: Grupo Camberfot, S.A | B60: GRUPOCAMBERFOTSA | C60: Maria Fernanda Rivas | D60: 42 | E60: Solicitado por el Cliente | F60: 1 | G60: Annia Pons Hernandez | H60: recepcion@grupoc.cc | I60: 66765590.0 | J60: 66765590.0
C61: Nailyn Martinez Johnson | D61: 45.5 | E61: Solicitado por el Cliente | F61: 1
C62: Michelle Zambrano | D62: 20.75 | E62: Solicitado por el Cliente | F62: 1
A63: Zarina Saliba | B63: ZARINASALIBA | C63: Solanye Acuña | D63: 37.5 | E63: Solicitado por el Cliente | F63: 1 | I63: 2107400.0
A64: Vanessa Mo | B64: VANESSAMO | C64: Maria Fernanda Rivas | D64: 13.99 | E64: Solicitado por el Cliente | F64: 1 | G64: FRANCISCO LOO CHEN | I64: 61123735.0
A65: Nilka Atencio | B65: NILKAATENCIO | C65: Nailyn Martinez Johnson | D65: 45.5 | E65: MIGRACION POST-PRE | F65: 1 | G65: Maria Carmelina Ramos Salazar | I65: 8464310.0
C66: Michelle Zambrano | D66: 36 | E66: MIGRACION POST-PRE | F66: 1
A67: Inversiones y | B67: INVERSIONESY | C67: Solanye Acuña | D67: 20.75 | E67: Solicitado por el Cliente | F67: 1 | G67: ASLEIGH MAYLIN ESQUIVEL | H67: Asleigh819@gmail.com | I67: 69996889.0 | J67: 69996889.0
A68: Ph Lumiere | B68: PHLUMIERE | C68: Maria Fernanda Rivas | D68: 83 | E68: Solicitado por el Cliente | F68: 2 | G68: ANN MIKUSKI | I68: 64482987.0
A69: Alcides Ivan | B69: ALCIDESIVAN | C69: Nailyn Martinez Johnson | D69: 42.5 | E69: Solicitado por el Cliente | F69: 1 | G69: Alcides Ivan Olaya Gomez | I69: 62927024.0
A70: Mini Centro Abdiel | B70: MINICENTROABDIEL | C70: Michelle Zambrano | D70: 20.75 | E70: Solicitado por el Cliente | F70: 1 | G70: Abdiel Iv¿n D¿az Batista | H70: abdieldiazbatista@gmail.com | I70: 66524832.0 | J70: 66524832.0
A71: Maria De Los Reyes H ernandez De Moran | B71: MARIADELOSREYESHERNANDEZDEMORAN | C71: Solanye Acuña | D71: 20.75 | E71: Solicitado por el Cliente | F71: 1 | G71: Maria De Los Reyes Hernandez De Moran | I71: 69581636.0
A72: Ph Maui | B72: PHMAUI | C72: Maria Fernanda Rivas | D72: 22.74 | E72: Solicitado por el Cliente | F72: 1 | G72: Dania Iveth Barahona Almengor 8-731-2274 | H72: phmaui.adm@gmail.com | I72: 61309833.0 | J72: 61309833.0
C73: Nailyn Martinez Johnson | D73: 36 | E73: Solicitado por el Cliente | F73: 1
A74: Impresiones y Copias I.G | B74: IMPRESIONESYCOPIASIG | C74: Michelle Zambrano | D74: 31.25 | E74: Solicitado por el Cliente | F74: 2 | G74: Jose Angel Casas Barria 6-703-1837 | H74: ventas0101@gmail.com | I74: 65585221.0 | J74: 64830239.0
C75: Solanye Acuña | D75: 28.75 | E75: Solicitado por el Cliente | F75: 1
C76: Maria Fernanda Rivas | D76: 5.5 | E76: Solicitado por el Cliente | F76: 1
A77: Ilmarys Virginia Riv era Lezcano de Serrano | B77: ILMARYSVIRGINIARIVERALEZCANODESERRANO | C77: Nailyn Martinez Johnson | D77: 12 | E77: Solicitado por el Cliente | F77: 1 | G77: Ilmarys Virginia Rivera Lezcano de Serra | H77: maryrivera52427@gmail.com | I77: 66023646.0 | J77: 66023646.0
A78: Gaspar Arsenio Reyes Agudo | B78: GASPARARSENIOREYESAGUDO | C78: Michelle Zambrano | D78: 30 | E78: Solicitado por el Cliente | F78: 3 | G78: Gaspar Arsenio Reyes Agudo | H78: gaspar.reyesagudo@gmail.com | I78: 67242628.0 | J78: 67242628.0
A79: Sergio Garzon | B79: SERGIOGARZON | C79: Solanye Acuña | D79: 38 | E79: Solicitado por el Cliente | F79: 1 | I79: 2297173.0
A80: PH Marquis Tower | B80: PHMARQUISTOWER | C80: Maria Fernanda Rivas | D80: 20.75 | E80: Solicitado por el Cliente | F80: 1 | H80: administracion@phmarquistower.com | I80: 67969384.0 | J80: 67969384.0
A81: INVERSIONES CASCANTE, SA | B81: INVERSIONESCASCANTESA | C81: Nailyn Martinez Johnson | D81: 54.75 | E81: Solicitado por el Cliente | F81: 3 | G81: GRISELDA CASCANTE | H81: gcascanteph@gmail.com | I81: 67475603.0 | J81: 67475603.0
C82: Michelle Zambrano | D82: 36 | E82: Solicitado por el Cliente | F82: 1
C83: Solanye Acuña | D83: 55.5 | E83: Solicitado por el Cliente | F83: 2
A84: SAQUELLA SA | B84: SAQUELLASA | C84: Maria Fernanda Rivas | D84: 20.75 | E84: MIGRACION POST-PRE | F84: 1 | G84: Yilda Selidet Bultron Vergara // Elida Guerra de Shishportish | H84: gruposaquella@gmail.com | I84: 60303765.0
A85: Irving A rceniao Mirones Barsallo | B85: IRVINGARCENIAOMIRONESBARSALLO | C85: Nailyn Martinez Johnson | D85: 27.75 | E85: Solicitado por el Cliente | F85: 1 | G85: Irving Arceniao Mirones Barsallo | I85: 69813438.0
C86: Michelle Zambrano | D86: 38 | E86: Solicitado por el Cliente | F86: 1
A87: Kadir Hinds | B87: KADIRHINDS | C87: Solanye Acuña | D87: 22.75 | E87: Solicitado por el Cliente | F87: 1 | H87: KADIRHIND@GMAIL.COM | I87: 62178735.0 | J87: 62178735.0
A88: Luis Alberto Singh Casta?edas | B88: LUISALBERTOSINGHCASTAEDAS | C88: Maria Fernanda Rivas | D88: 15 | E88: Solicitado por el Cliente | F88: 1 | I88: 62749604.0
A89: Hbo Sa | B89: HBOSA | C89: Nailyn Martinez Johnson | D89: 45.48 | E89: Solicitado por el Cliente | F89: 2 | G89: Ida Osorio Zarraonandia | I89: 62228321.0 | J89: 62405623.0
C90: Michelle Zambrano | D90: 27.75 | E90: Solicitado por el Cliente | F90: 1
C91: Solanye Acuña | D91: 27.75 | E91: Solicitado por el Cliente | F91: 1
C92: Maria Fernanda Rivas | D92: 57.5 | E92: Solicitado por el Cliente | F92: 2
A93: Alba Lassonde Ortiz | B93: ALBALASSONDEORTIZ | C93: Nailyn Martinez Johnson | D93: 12 | E93: Solicitado por el Cliente | F93: 1 | G93: Alba Lassonde Ortiz | I93: 66430667.0
A94: Jorge Alberto Plata Mc Nulty | B94: JORGEALBERTOPLATAMCNULTY | C94: Michelle Zambrano | D94: 30 | E94: Solicitado por el Cliente | F94: 3 | G94: Jorge Alberto Plata Mc Nulty | H94: platalaw@gmail.com | I94: 66135709.0 | J94: 66135709.0
A95: Luismanuelchungyip | B95: LUISMANUELCHUNGYIP | C95: Solanye Acuña | D95: 12 | E95: Solicitado por el Cliente | F95: 1 | G95: Luis Manuel Chung Yip | I95: 68731188.0
A96: Ruth Joyce De La Cruz Diaz | B96: RUTHJOYCEDELACRUZDIAZ | C96: Maria Fernanda Rivas | D96: 25.75 | E96: Solicitado por el Cliente | F96: 1 | G96: Ruth Joyce De La Cruz Diaz | I96: 69491672.0
A97: KALINSON CORP, S.A. | B97: KALINSONCORPSA | C97: Nailyn Martinez Johnson | D97: 90 | E97: Solicitado por el Cliente | F97: 6 | G97: RL ROBERTO ENRIQUE GARCIA DAPENA | H97: compras@kalinsoncorp.com | I97: 60901995.0 | J97: 60901995.0
C98: Michelle Zambrano | D98: 80 | E98: Solicitado por el Cliente | F98: 2
C99: Solanye Acuña | D99: 40 | E99: Solicitado por el Cliente | F99: 1
A100: Alba Lassonde Ortiz | B100: ALBALASSONDEORTIZ | C100: Maria Fernanda Rivas | D100: 12 | E100: Solicitado por el Cliente | F100: 1 | G100: Alba Lassonde Ortiz | I100: 66430667.0
...

Sheet Resumen
A1: CONSOLIDADO SOHO - RESUMEN POR FUENTE
A3: FUENTE | B3: REGISTROS | C3: MRC TOTAL $ | D3: MRC PROM $ | E3: DATO CLAVE
A4: Nextphone | B4: =COUNTIF(Datos!$A$2:$A$6000,"NP") | C4: =SUMIFS(Datos!$F$2:$F$6000,Datos!$A$2:$A$6000,"NP") | D4: =IF($B4=0,0,$C4/$B4) | E4: Base principal de clientes
A5: Móvil sin fijo | B5: =COUNTIF(Datos!$A$2:$A$6000,"MOV") | C5: =SUMIFS(Datos!$F$2:$F$6000,Datos!$A$2:$A$6000,"MOV") | D5: =IF($B5=0,0,$C5/$B5) | E5: Clientes móvil sin fijo
A6: Cross-sell | B6: =COUNTIF(Datos!$A$2:$A$6000,"CS") | C6: =SUMIFS(Datos!$F$2:$F$6000,Datos!$A$2:$A$6000,"CS") | D6: =IF($B6=0,0,$C6/$B6) | E6: Oportunidades de venta
A7: Winback | B7: =COUNTA(Winback!$A$2:$A$300) | C7: =SUM(Winback!$D$2:$D$300) | D7: =IF($B7=0,0,$C7/$B7) | E7: Clientes a recuperar
A8: Llamadas (Vici) | B8: 15796 | C8: N/A | D8: =IF($B8=0,0,$C8/$B8) | E8: Del reporte .xlsb (ver hoja Vici)
A9: TOTAL | B9: =SUM(B4:B8) | C9: =SUMIFS(C4:C8,C4:C8,">0")
A11: VICI (resumen)
A12: Total llamadas | B12: 15796
A13: Números únicos | B13: 7063
A14: Contactados | B14: 6562
A15: No contestan | B15: 8268
A16: Tasa contacto % | B16: =ROUND(6562/15796*100,1)
A17: Duración prom (s) | B17: 70

Sheet Ejecutivas
A1: EJECUTIVA | B1: CLIENTES (NP) | C1: MRC NP $ | D1: CLIENTES WB | E1: MRC WB $
A2: Michelle Zambrano | B2: =COUNTIFS(Datos!$A$2:$A$6000,"NP",Datos!$G$2:$G$6000,$A2) | C2: =SUMIFS(Datos!$F$2:$F$6000,Datos!$A$2:$A$6000,"NP",Datos!$G$2:$G$6000,$A2) | D2: =COUNTIF(Winback!$C$2:$C$300,$A2) | E2: =SUMIFS(Winback!$D$2:$D$300,Winback!$C$2:$C$300,$A2)
A3: Yarelis Tulloch | B3: =COUNTIFS(Datos!$A$2:$A$6000,"NP",Datos!$G$2:$G$6000,$A3) | C3: =SUMIFS(Datos!$F$2:$F$6000,Datos!$A$2:$A$6000,"NP",Datos!$G$2:$G$6000,$A3) | D3: =COUNTIF(Winback!$C$2:$C$300,$A3) | E3: =SUMIFS(Winback!$D$2:$D$300,Winback!$C$2:$C$300,$A3)
A4: Yariela Galarce | B4: =COUNTIFS(Datos!$A$2:$A$6000,"NP",Datos!$G$2:$G$6000,$A4) | C4: =SUMIFS(Datos!$F$2:$F$6000,Datos!$A$2:$A$6000,"NP",Datos!$G$2:$G$6000,$A4) | D4: =COUNTIF(Winback!$C$2:$C$300,$A4) | E4: =SUMIFS(Winback!$D$2:$D$300,Winback!$C$2:$C$300,$A4)
A5: Abril Aparicio | B5: =COUNTIFS(Datos!$A$2:$A$6000,"NP",Datos!$G$2:$G$6000,$A5) | C5: =SUMIFS(Datos!$F$2:$F$6000,Datos!$A$2:$A$6000,"NP",Datos!$G$2:$G$6000,$A5) | D5: =COUNTIF(Winback!$C$2:$C$300,$A5) | E5: =SUMIFS(Winback!$D$2:$D$300,Winback!$C$2:$C$300,$A5)
A6: Karla Mc Intryre | B6: =COUNTIFS(Datos!$A$2:$A$6000,"NP",Datos!$G$2:$G$6000,$A6) | C6: =SUMIFS(Datos!$F$2:$F$6000,Datos!$A$2:$A$6000,"NP",Datos!$G$2:$G$6000,$A6) | D6: =COUNTIF(Winback!$C$2:$C$300,$A6) | E6: =SUMIFS(Winback!$D$2:$D$300,Winback!$C$2:$C$300,$A6)
A7: Alejandra Mabel Hawkins | B7: =COUNTIFS(Datos!$A$2:$A$6000,"NP",Datos!$G$2:$G$6000,$A7) | C7: =SUMIFS(Datos!$F$2:$F$6000,Datos!$A$2:$A$6000,"NP",Datos!$G$2:$G$6000,$A7) | D7: =COUNTIF(Winback!$C$2:$C$300,$A7) | E7: =SUMIFS(Winback!$D$2:$D$300,Winback!$C$2:$C$300,$A7)
A8: Ines Lizbeth Trujillo | B8: =COUNTIFS(Datos!$A$2:$A$6000,"NP",Datos!$G$2:$G$6000,$A8) | C8: =SUMIFS(Datos!$F$2:$F$6000,Datos!$A$2:$A$6000,"NP",Datos!$G$2:$G$6000,$A8) | D8: =COUNTIF(Winback!$C$2:$C$300,$A8) | E8: =SUMIFS(Winback!$D$2:$D$300,Winback!$C$2:$C$300,$A8)
A9: Osiris Aguilar | B9: =COUNTIFS(Datos!$A$2:$A$6000,"NP",Datos!$G$2:$G$6000,$A9) | C9: =SUMIFS(Datos!$F$2:$F$6000,Datos!$A$2:$A$6000,"NP",Datos!$G$2:$G$6000,$A9) | D9: =COUNTIF(Winback!$C$2:$C$300,$A9) | E9: =SUMIFS(Winback!$D$2:$D$300,Winback!$C$2:$C$300,$A9)
A10: Yamali Rodriguez | B10: =COUNTIFS(Datos!$A$2:$A$6000,"NP",Datos!$G$2:$G$6000,$A10) | C10: =SUMIFS(Datos!$F$2:$F$6000,Datos!$A$2:$A$6000,"NP",Datos!$G$2:$G$6000,$A10) | D10: =COUNTIF(Winback!$C$2:$C$300,$A10) | E10: =SUMIFS(Winback!$D$2:$D$300,Winback!$C$2:$C$300,$A10)
A11: Nailyn Martinez | B11: =COUNTIFS(Datos!$A$2:$A$6000,"NP",Datos!$G$2:$G$6000,$A11) | C11: =SUMIFS(Datos!$F$2:$F$6000,Datos!$A$2:$A$6000,"NP",Datos!$G$2:$G$6000,$A11) | D11: =COUNTIF(Winback!$C$2:$C$300,$A11) | E11: =SUMIFS(Winback!$D$2:$D$300,Winback!$C$2:$C$300,$A11)
A12: Maria Fernanda | B12: =COUNTIFS(Datos!$A$2:$A$6000,"NP",Datos!$G$2:$G$6000,$A12) | C12: =SUMIFS(Datos!$F$2:$F$6000,Datos!$A$2:$A$6000,"NP",Datos!$G$2:$G$6000,$A12) | D12: =COUNTIF(Winback!$C$2:$C$300,$A12) | E12: =SUMIFS(Winback!$D$2:$D$300,Winback!$C$2:$C$300,$A12)
A13: Solanye Acuña | B13: =COUNTIFS(Datos!$A$2:$A$6000,"NP",Datos!$G$2:$G$6000,$A13) | C13: =SUMIFS(Datos!$F$2:$F$6000,Datos!$A$2:$A$6000,"NP",Datos!$G$2:$G$6000,$A13) | D13: =COUNTIF(Winback!$C$2:$C$300,$A13) | E13: =SUMIFS(Winback!$D$2:$D$300,Winback!$C$2:$C$300,$A13)
... A16: Keisy Vargas | B16: =COUNTIFS(Datos!$A$2:$A$6000,"NP",Datos!$G$2:$G$6000,$A16) | C16: =SUMIFS(Datos!$F$2:$F$6000,Datos!$A$2:$A$6000,"NP",Datos!$G$2:$G$6000,$A16) | D16: =COUNTIF(Winback!$C$2:$C$300,$A16) | E16: =SUMIFS(Winback!$D$2:$D$300,Winback!$C$2:$C$300,$A16)

Sheet Planes
A1: CODIGO | B1: CLIENTES | C1: MRC TOTAL $
A2: U | B2: =COUNTIFS(Datos!$A$2:$A$6000,"NP",Datos!$H$2:$H$6000,$A2) | C2: =SUMIFS(Datos!$F$2:$F$6000,Datos!$A$2:$A$6000,"NP",Datos!$H$2:$H$6000,$A2)
A3: T | B3: =COUNTIFS(Datos!$A$2:$A$6000,"NP",Datos!$H$2:$H$6000,$A3) | C3: =SUMIFS(Datos!$F$2:$F$6000,Datos!$A$2:$A$6000,"NP",Datos!$H$2:$H$6000,$A3)
A4: W | B4: =COUNTIFS(Datos!$A$2:$A$6000,"NP",Datos!$H$2:$H$6000,$A4) | C4: =SUMIFS(Datos!$F$2:$F$6000,Datos!$A$2:$A$6000,"NP",Datos!$H$2:$H$6000,$A4)
A5: V | B5: =COUNTIFS(Datos!$A$2:$A$6000,"NP",Datos!$H$2:$H$6000,$A5) | C5: =SUMIFS(Datos!$F$2:$F$6000,Datos!$A$2:$A$6000,"NP",Datos!$H$2:$H$6000,$A5)
A6: C | B6: =COUNTIFS(Datos!$A$2:$A$6000,"NP",Datos!$H$2:$H$6000,$A6) | C6: =SUMIFS(Datos!$F$2:$F$6000,Datos!$A$2:$A$6000,"NP",Datos!$H$2:$H$6000,$A6)
A7: S | B7: =COUNTIFS(Datos!$A$2:$A$6000,"NP",Datos!$H$2:$H$6000,$A7) | C7: =SUMIFS(Datos!$F$2:$F$6000,Datos!$A$2:$A$6000,"NP",Datos!$H$2:$H$6000,$A7)
A8: A | B8: =COUNTIFS(Datos!$A$2:$A$6000,"NP",Datos!$H$2:$H$6000,$A8) | C8: =SUMIFS(Datos!$F$2:$F$6000,Datos!$A$2:$A$6000,"NP",Datos!$H$2:$H$6000,$A8)
A9: Y | B9: =COUNTIFS(Datos!$A$2:$A$6000,"NP",Datos!$H$2:$H$6000,$A9) | C9: =SUMIFS(Datos!$F$2:$F$6000,Datos!$A$2:$A$6000,"NP",Datos!$H$2:$H$6000,$A9)
A10: H | B10: =COUNTIFS(Datos!$A$2:$A$6000,"NP",Datos!$H$2:$H$6000,$A10) | C10: =SUMIFS(Datos!$F$2:$F$6000,Datos!$A$2:$A$6000,"NP",Datos!$H$2:$H$6000,$A10)
A11: D | B11: =COUNTIFS(Datos!$A$2:$A$6000,"NP",Datos!$H$2:$H$6000,$A11) | C11: =SUMIFS(Datos!$F$2:$F$6000,Datos!$A$2:$A$6000,"NP",Datos!$H$2:$H$6000,$A11)
A12: B | B12: =COUNTIFS(Datos!$A$2:$A$6000,"NP",Datos!$H$2:$H$6000,$A12) | C12: =SUMIFS(Datos!$F$2:$F$6000,Datos!$A$2:$A$6000,"NP",Datos!$H$2:$H$6000,$A12)
A13: R | B13: =COUNTIFS(Datos!$A$2:$A$6000,"NP",Datos!$H$2:$H$6000,$A13) | C13: =SUMIFS(Datos!$F$2:$F$6000,Datos!$A$2:$A$6000,"NP",Datos!$H$2:$H$6000,$A13)
... A16: F | B16: =COUNTIFS(Datos!$A$2:$A$6000,"NP",Datos!$H$2:$H$6000,$A16) | C16: =SUMIFS(Datos!$F$2:$F$6000,Datos!$A$2:$A$6000,"NP",Datos!$H$2:$H$6000,$A16)

Sheet Vici
A1: VICI - LLAMADAS (del reporte .xlsb)
A2: MÉTRICA | B2: VALOR | C2: NOTA
A3: Total llamadas | B3: 15796 | C3: Hoja Vici del reporte SOHO .xlsb
A4: Números únicos marcados | B4: 7063
A5: Promedio intentos por número | B5: 2.24
A6: Llamadas contactadas | B6: 6562 | C6: Tasa contacto 41.5%
A7: No contestan | B7: 8268 | C7: 52.3% del total
A8: Duración total | B8: 306 h
A9: Duración promedio | B9: 70 s
A10: Máximo intentos a un número | B10: 1 | C10: Ver consolidado.html
A12: Fuente: Reporte_soho_junio_25 (1).xlsb / consolidado.html (datos estáticos de llamadas).
