Workbook

Sheet Registros
A1: FUENTE | B1: CUENTA | C1: CUST_NO | D1: NOMBRE | E1: NKEY | F1: MRC | G1: EJECUTIVA | H1: TELEFONO | I1: SERVICIOS | J1: CONTACTO_MOVIL | K1: TIPO
A2: NP | B2: 355382970000 | C2: 35538297 | D2: EDIL GOMEZ ARCE | E2: EDILGOMEZARCE | F2: 15 | G2: Solanye Acuña | H2: 68879413.0 | I2: 0 | J2: 1
A3: NP | B3: 353338240000 | C3: 35333824 | D3: MEYVIS CALVO | E3: MEYVISCALVO | F3: 15 | G3: Michelle Zambrano | H3: 67325039.0 | I3: 0 | J3: 1
A4: NP | B4: 321157030000 | C4: 32115703 | D4: GRUPO CORPORA | E4: GRUPOCORPORA | F4: 226.5 | G4: Ines Lizbeth Trujillo | H4: 66711672.0 | I4: 0 | J4: 1
A5: NP | B5: 369050850000 | C5: 36905085 | D5: SILVIA ARAUZ | E5: SILVIAARAUZ | F5: 19.52 | G5: Alejandra Mabel Hawkins | I5: 0 | J5: 1
A6: NP | B6: 355282350000 | C6: 35528235 | D6: SIMON WALTEROVA | E6: SIMONWALTEROVA | F6: 30 | G6: Maria Fernanda | H6: 62110427.0 | I6: 0 | J6: 1
A7: NP | B7: 312235730000 | C7: 31223573 | D7: CORPORACION JEMS, S.A. -- | E7: CORPORACIONJEMSSA | F7: 326.24 | G7: Yarelis Tulloch | H7: 62005659.0 | I7: 0 | J7: 1
A8: NP | B8: 322504520000 | C8: 32250452 | D8: Ardines CPA Y Asociados Sa | E8: ARDINESCPAYASOCIADOSSA | F8: 64.25 | G8: Abril Aparicio | H8: 69493738.0 | I8: 0 | J8: 1
A9: NP | B9: 323672910000 | C9: 32367291 | D9: Ademar SA | E9: ADEMARSA | F9: 44 | G9: Yariela Galarce | H9: 66131951.0 | I9: 0 | J9: 1
A10: NP | B10: 349277210000 | C10: 34927721 | D10: SMART COMMUNICATIONS, SA | E10: SMARTCOMMUNICATIONSSA | F10: 16.25 | G10: Nailyn Martinez | H10: 67424735.0 | I10: 0 | J10: 1
A11: NP | B11: 324167750000 | C11: 32416775 | D11: HACIENDA LOMA LINDA | E11: HACIENDALOMALINDA | F11: 291.5 | G11: Yamali Rodriguez | H11: 69834668.0 | I11: 0 | J11: 1
A12: NP | B12: 361003450000 | C12: 36100345 | D12: FERNANDO JOSE ARAUZ HERNANDEZ | E12: FERNANDOJOSEARAUZHERNANDEZ | F12: 15 | G12: Osiris Aguilar | H12: 69722675.0 | I12: 0 | J12: 1
A13: NP | B13: 352329430000 | C13: 35232943 | D13: YDALIDES VALDES | E13: YDALIDESVALDES | F13: 15 | G13: Karla Mc Intryre | H13: 67344173.0 | I13: 0 | J13: 1
A14: NP | B14: 354175000000 | C14: 35417500 | D14: THIAGO DAVID CABALLERO | E14: THIAGODAVIDCABALLERO | F14: 15 | G14: Michelle Zambrano | H14: 62475467.0 | I14: 0 | J14: 1
A15: NP | B15: 327604400000 | C15: 32760440 | D15: GLOBAL LANGUAGE,S.A. | E15: GLOBALLANGUAGESA | F15: 275 | G15: Ines Lizbeth Trujillo | H15: 69973283.0 | I15: 0 | J15: 1
A16: NP | B16: 322366890200 | C16: 32236689 | D16: LIMAYON, S.A | E16: LIMAYONSA | F16: 124.95 | G16: Alejandra Mabel Hawkins | H16: 69824192.0 | I16: 0 | J16: 1
A17: NP | B17: 322366890200 | C17: 32236689 | D17: Asociacion de | E17: ASOCIACIONDE | F17: 30.74 | G17: Maria Fernanda | H17: 69824192.0 | I17: 0 | J17: 1
... A86: NP | B86: 312209940000 | C86: 31220994 | D86: UROLOGOS ASOCIADOS, S.A. - | E86: UROLOGOSASOCIADOSSA | F86: 31 | G86: Maria Fernanda | H86: 62082799.0 | I86: 0 | J86: 1
A87: NP | B87: 364043730000 | C87: 36404373 | D87: BALTAZAR GOMEZ | E87: BALTAZARGOMEZ | F87: 16.94 | G87: Yarelis Tulloch | I87: 0 | J87: 1
A88: NP | B88: 359354310000 | C88: 35935431 | D88: JAFETH LOPEZ | E88: JAFETHLOPEZ | F88: 15 | G88: Abril Aparicio | H88: 67793454.0 | I88: 0 | J88: 1
A89: NP | B89: 325374980000 | C89: 32537498 | D89: HENG CHANG, S.A. | E89: HENGCHANGSA | F89: 215 | G89: Yariela Galarce | H89: 67076180.0 | I89: 0 | J89: 1
A90: NP | B90: 353355830000 | C90: 35335583 | D90: MARÍA RIVAS | E90: MARIARIVAS | F90: 15 | G90: Nailyn Martinez | H90: 65161910.0 | I90: 0 | J90: 1
A91: NP | B91: 321439070100 | C91: 32143907 | D91: POWER EXTERMINATOR | E91: POWEREXTERMINATOR | F91: 353.77 | G91: Yamali Rodriguez | H91: 69987657.0 | I91: 0 | J91: 1
A92: NP | B92: 346090040000 | C92: 34609004 | D92: MARY HELEN CASTAÑEDA DE CALDERON | E92: MARYHELENCASTANEDADECALDERON | F92: 15 | G92: Osiris Aguilar | H92: 66600631.0 | I92: 0 | J92: 1
A93: NP | B93: 345006480000 | C93: 34500648 | D93: THOMAS JEFFERSON SCHOOL, S.A. | E93: THOMASJEFFERSONSCHOOLSA | F93: 245 | G93: Karla Mc Intryre | H93: 68784059.0 | I93: 0 | J93: 1
A94: NP | B94: 343249890000 | C94: 34324989 | D94: ISELA MARIA CASTAÑEDAS DE SINGH | E94: ISELAMARIACASTANEDASDESINGH | F94: 12 | G94: Solanye Acuña | H94: 66409300.0 | I94: 0 | J94: 1
A95: NP | B95: 353003570000 | C95: 35300357 | D95: FAVIO VANEGAS | E95: FAVIOVANEGAS | F95: 15 | G95: Michelle Zambrano | H95: 67035338.0 | I95: 0 | J95: 1
A96: NP | B96: 342412720000 | C96: 34241272 | D96: JAFET BERTIAGA MOSQUERA | E96: JAFETBERTIAGAMOSQUERA | F96: 16.25 | G96: Ines Lizbeth Trujillo | H96: 66011050.0 | I96: 0 | J96: 1
A97: NP | B97: 354334670000 | C97: 35433467 | D97: ARISTIDES BARRIOS CARRION | E97: ARISTIDESBARRIOSCARRION | F97: 15 | G97: Alejandra Mabel Hawkins | H97: 66951128.0 | I97: 0 | J97: 1
A98: NP | B98: 312216560000 | C98: 31221656 | D98: JADE TECHNOLOGY S.A - | E98: JADETECHNOLOGYSA | F98: 109.5 | G98: Maria Fernanda | H98: 61126980.0 | I98: 0 | J98: 1
A99: NP | B99: 369039290000 | C99: 36903929 | D99: PETRA PABLA MOSQUERA BLANCO | E99: PETRAPABLAMOSQUERABLANCO | F99: 16.94 | G99: Yarelis Tulloch | I99: 0 | J99: 1
A100: NP | B100: 323540060100 | C100: 32354006 | D100: Jacqueline Quintero Dominguez | E100: JACQUELINEQUINTERODOMINGUEZ | F100: 52.74 | G100: Abril Aparicio | H100: 67812138.0 | I100: 0 | J100: 1
A101: NP | B101: 323540060100 | C101: 32354006 | D101: Jacqueline Quintero Dominguez | E101: JACQUELINEQUINTERODOMINGUEZ | F101: 14.99 | G101: Yariela Galarce | H101: 67812138.0 | I101: 0 | J101: 1
A102: NP | B102: 345179830000 | C102: 34517983 | D102: LEGUMBRES Y FRUTAS IVERSON | E102: LEGUMBRESYFRUTASIVERSON | F102: 40 | G102: Nailyn Martinez | H102: 69505541.0 | I102: 0 | J102: 1
A103: NP | B103: 349132360000 | C103: 34913236 | D103: AHAVA LATIN AMERCA | E103: AHAVALATINAMERCA | F103: 21 | G103: Yamali Rodriguez | H103: 60138979.0 | I103: 0 | J103: 1
A104: NP | B104: 344414740000 | C104: 34441474 | D104: NORBERTO ANTONIO CERNA LOPEZ | E104: NORBERTOANTONIOCERNALOPEZ | F104: 16.25 | G104: Osiris Aguilar | H104: 67769361.0 | I104: 0 | J104: 1
A105: NP | B105: 341297900000 | C105: 34129790 | D105: HERCILIA PACHECO SECAIDA | E105: HERCILIAPACHECOSECAIDA | F105: 16.25 | G105: Karla Mc Intryre | H105: 65372281.0 | I105: 0 | J105: 1
A106: NP | B106: 312209910000 | C106: 31220991 | D106: DISTRIBUIDORA CARIVA, S.A. - | E106: DISTRIBUIDORACARIVASA | F106: 64 | G106: Michelle Zambrano | H106: 62269500.0 | I106: 0 | J106: 1
A107: NP | B107: 325409780200 | C107: 32540978 | D107: NUBIA ARENAS GOMEZ | E107: NUBIAARENASGOMEZ | F107: 28.75 | G107: Ines Lizbeth Trujillo | H107: 66131158.0 | I107: 0 | J107: 1
A108: NP | B108: 322462760200 | C108: 32246276 | D108: A.J.FOTOS S.A. | E108: AJFOTOSSA | F108: 42 | G108: Alejandra Mabel Hawkins | H108: 67810778.0 | I108: 0 | J108: 1
A109: NP | B109: 341145610000 | C109: 34114561 | D109: LUIS HERNAN VALENCIA | E109: LUISHERNANVALENCIA | F109: 16.25 | G109: Maria Fernanda | H109: 60037002.0 | I109: 0 | J109: 1
A110: NP | B110: 346146550000 | C110: 34614655 | D110: LUIS HERNAN VALENCIA | E110: LUISHERNANVALENCIA | F110: 32.5 | G110: Yarelis Tulloch | H110: 66283511.0 | I110: 0 | J110: 1
A111: NP | B111: 326656630100 | C111: 32665663 | D111: INVERSIONES KALY, SA | E111: INVERSIONESKALYSA | F111: 40 | G111: Abril Aparicio | H111: 66712509.0 | I111: 0 | J111: 1
... A119: NP | B119: 355288540000 | C119: 35528854 | D119: BRENDA ELIZABETH HERAZO ACOSTA | E119: BRENDAELIZABETHHERAZOACOSTA | F119: 18 | G119: Ines Lizbeth Trujillo | H119: 69065210.0 | I119: 0 | J119: 1
A120: NP | B120: 365052370000 | C120: 36505237 | D120: ARELIO CABEZON CHOCHO | E120: ARELIOCABEZONCHOCHO | F120: 16.94 | G120: Alejandra Mabel Hawkins | I120: 0 | J120: 1
A121: NP | B121: 349093270000 | C121: 34909327 | D121: CARMELO ALVARADO | E121: CARMELOALVARADO | F121: 32.5 | G121: Maria Fernanda | H121: 68241659.0 | I121: 0 | J121: 1
A122: NP | B122: 358004430000 | C122: 35800443 | D122: ISMAEL RAMOS MURILLO | E122: ISMAELRAMOSMURILLO | F122: 15 | G122: Yarelis Tulloch | H122: 66456509.0 | I122: 0 | J122: 1
A123: NP | B123: 361050650000 | C123: 36105065 | D123: KENY BIPURO | E123: KENYBIPURO | F123: 27.42 | G123: Abril Aparicio | I123: 0 | J123: 1
A124: NP | B124: 322390980400 | C124: 32239098 | D124: Servicio de Winche | E124: SERVICIODEWINCHE | F124: 42 | G124: Yariela Galarce | H124: 66798629.0 | I124: 0 | J124: 1
A125: NP | B125: 322897600000 | C125: 32289760 | D125: Servidental S.A. | E125: SERVIDENTALSA | F125: 25 | G125: Nailyn Martinez | H125: 69532354.0 | I125: 0 | J125: 1
A126: NP | B126: 312222690000 | C126: 31222269 | D126: SERVIDENTAL, S.A. | E126: SERVIDENTALSA | F126: 50 | G126: Yamali Rodriguez | H126: 66707039.0 | I126: 0 | J126: 1
A127: NP | B127: 346344050000 | C127: 34634405 | D127: ADAN RODRIGUEZ | E127: ADANRODRIGUEZ | F127: 16.25 | G127: Osiris Aguilar | H127: 69380286.0 | I127: 0 | J127: 1
A128: NP | B128: 312220250000 | C128: 31222025 | D128: SOFTWARE OF HARDWARE PANAMA, S - | E128: SOFTWAREOFHARDWAREPANAMAS | F128: 31 | G128: Karla Mc Intryre | H128: 62788377.0 | I128: 0 | J128: 1
A129: NP | B129: 354233640000 | C129: 35423364 | D129: EDGARDO GUEVARA | E129: EDGARDOGUEVARA | F129: 15 | G129: Michelle Zambrano | H129: 66740947.0 | I129: 0 | J129: 1
A130: NP | B130: 355304160000 | C130: 35530416 | D130: ZONA DE PODER | E130: ZONADEPODER | F130: 20 | G130: Ines Lizbeth Trujillo | H130: 65000662.0 | I130: 0 | J130: 1
A131: NP | B131: 357168280000 | C131: 35716828 | D131: EDILSA HITUCAMA NEGRIA | E131: EDILSAHITUCAMANEGRIA | F131: 15 | G131: Alejandra Mabel Hawkins | H131: 68894702.0 | I131: 0 | J131: 1
A132: NP | B132: 321464410000 | C132: 32146441 | D132: PSI Panama S.A | E132: PSIPANAMASA | F132: 386 | G132: Maria Fernanda | H132: 67475277.0 | I132: 0 | J132: 1
A133: NP | B133: 312227510000 | C133: 31222751 | D133: CALDERA ENERGY CORP CALDERA ENERGY CORP | E133: CALDERAENERGYCORPCALDERAENERGYCORP | F133: 16.25 | G133: Yarelis Tulloch | H133: 62506248.0 | I133: 0 | J133: 1
A134: NP | B134: 334303920000 | C134: 33430392 | D134: SERVICIOS Y ALQUILERES DE EQUIPOS S.A | E134: SERVICIOSYALQUILERESDEEQUIPOSSA | F134: 145 | G134: Abril Aparicio | H134: 69496174.0 | I134: 0 | J134: 1
A135: NP | B135: 356219260000 | C135: 35621926 | D135: MANIX CHORCHI | E135: MANIXCHORCHI | F135: 15 | G135: Yariela Galarce | H135: 63034976.0 | I135: 0 | J135: 1
... A279: NP | B279: 312230760000 | C279: 31223076 | D279: SUPLIDORA RAMBAR, S.A. - | E279: SUPLIDORARAMBARSA | F279: 92 | G279: Michelle Zambrano | H279: 66128330.0 | I279: 0 | J279: 1
A280: NP | B280: 362040060000 | C280: 36204006 | D280: ROXANA QUINTANA | E280: ROXANAQUINTANA | F280: 18.23 | G280: Ines Lizbeth Trujillo | I280: 0 | J280: 1
A281: NP | B281: 358387480000 | C281: 35838748 | D281: ZORAIDA PALACIO | E281: ZORAIDAPALACIO | F281: 20 | G281: Alejandra Mabel Hawkins | H281: 69589128.0 | I281: 0 | J281: 1
A282: NP | B282: 368051230000 | C282: 36805123 | D282: LEISA BERRUGATE | E282: LEISABERRUGATE | F282: 16.94 | G282: Maria Fernanda | I282: 0 | J282: 1
A283: NP | B283: 359348000000 | C283: 35934800 | D283: MARCITA CHANAPI CABRERA | E283: MARCITACHANAPICABRERA | F283: 15 | G283: Yarelis Tulloch | H283: 68339140.0 | I283: 0 | J283: 1
A284: NP | B284: 345085720000 | C284: 34508572 | D284: TRANSPORTE UMANA SA | E284: TRANSPORTEUMANASA | F284: 65.25 | G284: Abril Aparicio | H284: 64886130.0 | I284: 0 | J284: 1
A285: NP | B285: 342109320000 | C285: 34210932 | D285: ESMITT ISMARE GARCIA | E285: ESMITTISMAREGARCIA | F285: 16.25 | G285: Yariela Galarce | H285: 62053613.0 | I285: 0 | J285: 1
A286: NP | B286: 357067150000 | C286: 35706715 | D286: ISIDRO CHECA | E286: ISIDROCHECA | F286: 15 | G286: Nailyn Martinez | H286: 66981368.0 | I286: 0 | J286: 1
A287: NP | B287: 358029290000 | C287: 35802929 | D287: FUNERARIA CEMACO | E287: FUNERARIACEMACO | F287: 15 | G287: Yamali Rodriguez | H287: 67381314.0 | I287: 0 | J287: 1
A288: NP | B288: 351368860000 | C288: 35136886 | D288: ELIA VELASQUEZ | E288: ELIAVELASQUEZ | F288: 15 | G288: Osiris Aguilar | H288: 65854460.0 | I288: 0 | J288: 1
A289: NP | B289: 358313620000 | C289: 35831362 | D289: ORIEL BONILLA | E289: ORIELBONILLA | F289: 15 | G289: Karla Mc Intryre | H289: 61856444.0 | I289: 0 | J289: 1
A290: NP | B290: 354303340000 | C290: 35430334 | D290: YANETH BENILLDA SERNA CORDOBA | E290: YANETHBENILLDASERNACORDOBA | F290: 15 | G290: Michelle Zambrano | H290: 68558258.0 | I290: 0 | J290: 1
A291: NP | B291: 356096640000 | C291: 35609664 | D291: YOLANDA CEDEÑO | E291: YOLANDACEDENO | F291: 15 | G291: Ines Lizbeth Trujillo | H291: 65089323.0 | I291: 0 | J291: 1
A292: NP | B292: 358201290000 | C292: 35820129 | D292: ERIC YONARD HURTADO GONZALEZ | E292: ERICYONARDHURTADOGONZALEZ | F292: 25 | G292: Alejandra Mabel Hawkins | H292: 63615141.0 | I292: 0 | J292: 1
A293: NP | B293: 348369230000 | C293: 34836923 | D293: LISET YARITZA QUINTANA | E293: LISETYARITZAQUINTANA | F293: 30 | G293: Maria Fernanda | H293: 67872948.0 | I293: 0 | J293: 1
A294: NP | B294: 349140520000 | C294: 34914052 | D294: SULMA ISMARE PUCHICAMA DE CHAUCARAMA | E294: SULMAISMAREPUCHICAMADECHAUCARAMA | F294: 37.5 | G294: Yarelis Tulloch | H294: 63365812.0 | I294: 0 | J294: 1
... A304: NP | B304: 367023820000 | C304: 36702382 | D304: JOSUE CORDOBA | E304: JOSUECORDOBA | F304: 30 | G304: Alejandra Mabel Hawkins | H304: 65295285.0 | I304: 0 | J304: 1
A305: NP | C305: 35828394 | D305: ELIGIO MOSQUERA BARCO | E305: ELIGIOMOSQUERABARCO | F305: 45 | G305: Maria Fernanda | I305: 0 | J305: 1
A306: NP | B306: 355039520000 | C306: 35503952 | D306: PRISCILA MEDINA | E306: PRISCILAMEDINA | F306: 15 | G306: Yarelis Tulloch | H306: 69456169.0 | I306: 0 | J306: 1
A307: NP | B307: 351246120000 | C307: 35124612 | D307: NORBERTO VELANCIA | E307: NORBERTOVELANCIA | F307: 15 | G307: Abril Aparicio | H307: 68673589.0 | I307: 0 | J307: 1
A308: NP | B308: 357364020000 | C308: 35736402 | D308: DAVID REYES | E308: DAVIDREYES | F308: 15 | G308: Yariela Galarce | H308: 63643600.0 | I308: 0 | J308: 1
A309: NP | B309: 356149210000 | C309: 35614921 | D309: NILVA MIGDALIA RIVAS ESPINOZA | E309: NILVAMIGDALIARIVASESPINOZA | F309: 15 | G309: Nailyn Martinez | H309: 66685183.0 | I309: 0 | J309: 1
A310: NP | B310: 356118310000 | C310: 35611831 | D310: DAIHANA DE LA ROSA | E310: DAIHANADELAROSA | F310: 15 | G310: Yamali Rodriguez | H310: 63727402.0 | I310: 0 | J310: 1
A311: NP | B311: 349331440000 | C311: 34933144 | D311: ARNALDO LOPEZ | E311: ARNALDOLOPEZ | F311: 23.25 | G311: Osiris Aguilar | H311: 66094339.0 | I311: 0 | J311: 1
A312: NP | B312: 355130350000 | C312: 35513035 | D312: DISMA TOCAMO | E312: DISMATOCAMO | F312: 15 | G312: Karla Mc Intryre | H312: 69921447.0 | I312: 0 | J312: 1
A313: NP | B313: 364037000000 | C313: 36403700 | D313: LIANNE SHERILL PINEDA MOSQUERA | E313: LIANNESHERILLPINEDAMOSQUERA | F313: 16.29 | G313: Michelle Zambrano | I313: 0 | J313: 1
A314: NP | B314: 347400570000 | C314: 34740057 | D314: DAYANIS DIMAS | E314: DAYANISDIMAS | F314: 16.25 | G314: Ines Lizbeth Trujillo | H314: 68764376.0 | I314: 0 | J314: 1
A315: NP | B315: 341182820000 | C315: 34118282 | D315: ELIDIA PERALTA | E315: ELIDIAPERALTA | F315: 106.5 | G315: Alejandra Mabel Hawkins | H315: 60691264.0 | I315: 0 | J315: 1
A316: NP | B316: 337275680000 | C316: 33727568 | D316: THE ENGLISH LANGUAGE CENTER, INC. | E316: THEENGLISHLANGUAGECENTERINC | F316: 200.23 | G316: Maria Fernanda | H316: 66775277.0 | I316: 0 | J316: 1
A317: NP | B317: 344330260000 | C317: 34433026 | D317: ISMILDA VICTORIA LOPEZ PALACIOS | E317: ISMILDAVICTORIALOPEZPALACIOS | F317: 20.75 | G317: Yarelis Tulloch | H317: 67276141.0 | I317: 0 | J317: 1
A318: NP | B318: 332153930000 | C318: 33215393 | D318: ABDIEL GUASERUCA MESUA | E318: ABDIELGUASERUCAMESUA | F318: 22.5 | G318: Abril Aparicio | H318: 63496886.0 | I318: 0 | J318: 1
A319: NP | B319: 362057130000 | C319: 36205713 | D319: BENJAMIN VALDESPINO | E319: BENJAMINVALDESPINO | F319: 16.29 | G319: Yariela Galarce | I319: 0 | J319: 1
A320: NP | B320: 351280280000 | C320: 35128028 | D320: MARTA MACHUCA | E320: MARTAMACHUCA | F320: 15 | G320: Nailyn Martinez | H320: 67309564.0 | I320: 0 | J320: 1
A321: NP | B321: 354353420000 | C321: 35435342 | D321: LLAMILEICA BERRUGATE | E321: LLAMILEICABERRUGATE | F321: 15 | G321: Yamali Rodriguez | H321: 65531545.0 | I321: 0 | J321: 1
A322: NP | B322: 356343590000 | C322: 35634359 | D322: CESAR PUCHIGAMA | E322: CESARPUCHIGAMA | F322: 15 | G322: Osiris Aguilar | H322: 65831896.0 | I322: 0 | J322: 1
A323: NP | B323: 364036650000 | C323: 36403665 | D323: LUIS CHIRIPUA TEUCAMA | E323: LUISCHIRIPUATEUCAMA | F323: 20.16 | G323: Karla Mc Intryre | I323: 0 | J323: 1
A324: NP | B324: 352030160000 | C324: 35203016 | D324: MAXIMA MURILLO | E324: MAXIMAMURILLO | F324: 15 | G324: Solanye Acuña | H324: 63349166.0 | I324: 0 | J324: 1
A325: NP | B325: 346172980000 | C325: 34617298 | D325: LUIS ENRIQUE ISAZA MARANDOLA | E325: LUISENRIQUEISAZAMARANDOLA | F325: 32.5 | G325: Michelle Zambrano | H325: 67654284.0 | I325: 0 | J325: 1
A326: NP | B326: 359324330000 | C326: 35932433 | D326: ROSALINDA MOSQUERA | E326: ROSALINDAMOSQUERA | F326: 15 | G326: Ines Lizbeth Trujillo | H326: 65231111.0 | I326: 0 | J326: 1
A327: NP | B327: 361056030000 | C327: 36105603 | D327: DONAL BARQUEÑO CARDENA | E327: DONALBARQUENOCARDENA | F327: 16.94 | G327: Alejandra Mabel Hawkins | I327: 0 | J327: 1
...

Sheet Winback
A1: CLIENTE | B1: NKEY | C1: EJECUTIVA | D1: MRC | E1: RAZON_SALIDA | F1: RGU | G1: CONTACTO | H1: CORREO | I1: TEL1 | J1: TEL2 | K1: NKEY_MATCH | L1: RECUPERADO
A2: COIMSA | B2: COIMSA | C2: Michelle Zambrano | D2: 95 | E2: Solicitado por el Cliente | F2: 3 | G2: Jorge Villarreal ced 8-299-399 | H2: gerencia.coimsa@gmail.com | I2: 66776809.0 | J2: 2602749.0 | K2: COIMSA | L2: =IF(SUMPRODUCT((Cruce!$E$2:$E$6000+Cruce!$G$2:$G$6000+Cruce!$I$2:$I$6000>0)*(Cruce!$D$2:$D$6000=$K2))>0,"SI","NO")
A3: GRAPHIC SOLUTIONS/ CARMEN R. WILLIAMS 2 | B3: GRAPHICSOLUTIONSCARMENRWILLIAMS2 | C3: Solanye Acuña | D3: 12 | E3: Solicitado por el Cliente | F3: 1 | G3: Angelica Gallego E-8-79314 | I3: 3140588.0 | K3: GRAPHICSOLUTIONSCARMENRWILLIAMS2 | L3: =IF(SUMPRODUCT((Cruce!$E$2:$E$6000+Cruce!$G$2:$G$6000+Cruce!$I$2:$I$6000>0)*(Cruce!$D$2:$D$6000=$K3))>0,"SI","NO")
A4: ALEXIS ALEXANDER GOMEZ MENDIETA | B4: ALEXISALEXANDERGOMEZMENDIETA | C4: Maria Fernanda Rivas | D4: 20.75 | E4: Solicitado por el Cliente | F4: 1 | G4: ALEXIS ALEXANDER GOMEZ MENDIETA | I4: 67472064.0 | K4: ALEXISALEXANDERGOMEZMENDIETA | L4: =IF(SUMPRODUCT((Cruce!$E$2:$E$6000+Cruce!$G$2:$G$6000+Cruce!$I$2:$I$6000>0)*(Cruce!$D$2:$D$6000=$K4))>0,"SI","NO")
A5: PH COUNTRY CLUB - | B5: PHCOUNTRYCLUB | C5: Nailyn Martinez Johnson | D5: 166 | E5: Solicitado por el Cliente | F5: 8 | G5: MICHAEL HAMOUI | I5: 69144044.0 | K5: PHCOUNTRYCLUB | L5: =IF(SUMPRODUCT((Cruce!$E$2:$E$6000+Cruce!$G$2:$G$6000+Cruce!$I$2:$I$6000>0)*(Cruce!$D$2:$D$6000=$K5))>0,"SI","NO")
C6: Michelle Zambrano | D6: 20.75 | E6: Solicitado por el Cliente | F6: 1 | L6: =IF(SUMPRODUCT((Cruce!$E$2:$E$6000+Cruce!$G$2:$G$6000+Cruce!$I$2:$I$6000>0)*(Cruce!$D$2:$D$6000=$K6))>0,"SI","NO")
C7: Solanye Acuña | D7: 40.5 | E7: Solicitado por el Cliente | F7: 1 | L7: =IF(SUMPRODUCT((Cruce!$E$2:$E$6000+Cruce!$G$2:$G$6000+Cruce!$I$2:$I$6000>0)*(Cruce!$D$2:$D$6000=$K7))>0,"SI","NO")
C8: Maria Fernanda Rivas | D8: 31 | E8: Solicitado por el Cliente | F8: 1 | L8: =IF(SUMPRODUCT((Cruce!$E$2:$E$6000+Cruce!$G$2:$G$6000+Cruce!$I$2:$I$6000>0)*(Cruce!$D$2:$D$6000=$K8))>0,"SI","NO")
A9: IDEALO | B9: IDEALO | C9: Nailyn Martinez Johnson | D9: 41.5 | E9: Solicitado por el Cliente | F9: 2 | G9: IDEALO | I9: 68800852.0 | K9: IDEALO | L9: =IF(SUMPRODUCT((Cruce!$E$2:$E$6000+Cruce!$G$2:$G$6000+Cruce!$I$2:$I$6000>0)*(Cruce!$D$2:$D$6000=$K9))>0,"SI","NO")
A10: INFINITY LOGISTICS INFINITY LOGISTICS AGENCY, CORP | B10: INFINITYLOGISTICSINFINITYLOGISTICSAGENCYCORP | C10: Michelle Zambrano | D10: 60 | E10: Solicitado por el Cliente | F10: 3 | G10: ARCELIS ASPRILLA | I10: 4304648.0 | K10: INFINITYLOGISTICSINFINITYLOGISTICSAGENCYCORP | L10: =IF(SUMPRODUCT((Cruce!$E$2:$E$6000+Cruce!$G$2:$G$6000+Cruce!$I$2:$I$6000>0)*(Cruce!$D$2:$D$6000=$K10))>0,"SI","NO")
C11: Solanye Acuña | D11: 50 | E11: Solicitado por el Cliente | F11: 2 | L11: =IF(SUMPRODUCT((Cruce!$E$2:$E$6000+Cruce!$G$2:$G$6000+Cruce!$I$2:$I$6000>0)*(Cruce!$D$2:$D$6000=$K11))>0,"SI","NO")
C12: Maria Fernanda Rivas | D12: 50 | E12: Solicitado por el Cliente | F12: 1 | L12: =IF(SUMPRODUCT((Cruce!$E$2:$E$6000+Cruce!$G$2:$G$6000+Cruce!$I$2:$I$6000>0)*(Cruce!$D$2:$D$6000=$K12))>0,"SI","NO")
C13: Nailyn Martinez Johnson | D13: 17 | E13: Solicitado por el Cliente | F13: 1 | L13: =IF(SUMPRODUCT((Cruce!$E$2:$E$6000+Cruce!$G$2:$G$6000+Cruce!$I$2:$I$6000>0)*(Cruce!$D$2:$D$6000=$K13))>0,"SI","NO")
C14: Michelle Zambrano | D14: 170 | E14: Solicitado por el Cliente | F14: 5 | L14: =IF(SUMPRODUCT((Cruce!$E$2:$E$6000+Cruce!$G$2:$G$6000+Cruce!$I$2:$I$6000>0)*(Cruce!$D$2:$D$6000=$K14))>0,"SI","NO")
C15: Solanye Acuña | D15: 35 | E15: Solicitado por el Cliente | F15: 1 | L15: =IF(SUMPRODUCT((Cruce!$E$2:$E$6000+Cruce!$G$2:$G$6000+Cruce!$I$2:$I$6000>0)*(Cruce!$D$2:$D$6000=$K15))>0,"SI","NO")
A16: RC SOLUTION, S.A - | B16: RCSOLUTIONSA | C16: Maria Fernanda Rivas | D16: 41.5 | E16: Solicitado por el Cliente | F16: 2 | G16: RC SOLUTION, S.A - | I16: 62608877.0 | K16: RCSOLUTIONSA | L16: =IF(SUMPRODUCT((Cruce!$E$2:$E$6000+Cruce!$G$2:$G$6000+Cruce!$I$2:$I$6000>0)*(Cruce!$D$2:$D$6000=$K16))>0,"SI","NO")
C17: Nailyn Martinez Johnson | D17: 113.5 | E17: Solicitado por el Cliente | F17: 4 | L17: =IF(SUMPRODUCT((Cruce!$E$2:$E$6000+Cruce!$G$2:$G$6000+Cruce!$I$2:$I$6000>0)*(Cruce!$D$2:$D$6000=$K17))>0,"SI","NO")
A18: Servicios Logitisticos Imperial S.A | B18: SERVICIOSLOGITISTICOSIMPERIALSA | C18: Michelle Zambrano | D18: 30 | E18: Solicitado por el Cliente | F18: 2 | G18: Servicios Logisticos Imperial S.A. | H18: comercial.panama@petentrega.com | I18: 65146298.0 | K18: SERVICIOSLOGITISTICOSIMPERIALSA | L18: =IF(SUMPRODUCT((Cruce!$E$2:$E$6000+Cruce!$G$2:$G$6000+Cruce!$I$2:$I$6000>0)*(Cruce!$D$2:$D$6000=$K18))>0,"SI","NO")
A19: CLINICA TU SALUD Y BELLEZA - | B19: CLINICATUSALUDYBELLEZA | C19: Solanye Acuña | D19: 16.25 | E19: Solicitado por el Cliente | F19: 1 | G19: Soy Yoli calu N-20-930 | I19: 65081722.0 | K19: CLINICATUSALUDYBELLEZA | L19: =IF(SUMPRODUCT((Cruce!$E$2:$E$6000+Cruce!$G$2:$G$6000+Cruce!$I$2:$I$6000>0)*(Cruce!$D$2:$D$6000=$K19))>0,"SI","NO")
A20: SERVIEDUCA S,A. - | B20: SERVIEDUCASA | C20: Maria Fernanda Rivas | D20: 20 | E20: Solicitado por el Cliente | F20: 1 | G20: SERVIEDUCA S,A. - GABRIELA ALEJANDRA, | I20: 2366783.0 | K20: SERVIEDUCASA | L20: =IF(SUMPRODUCT((Cruce!$E$2:$E$6000+Cruce!$G$2:$G$6000+Cruce!$I$2:$I$6000>0)*(Cruce!$D$2:$D$6000=$K20))>0,"SI","NO")
C21: Nailyn Martinez Johnson | D21: 25 | E21: Solicitado por el Cliente | F21: 1 | L21: =IF(SUMPRODUCT((Cruce!$E$2:$E$6000+Cruce!$G$2:$G$6000+Cruce!$I$2:$I$6000>0)*(Cruce!$D$2:$D$6000=$K21))>0,"SI","NO")
A22: PANAMA JOURNEYS S,A - | B22: PANAMAJOURNEYSSA | C22: Michelle Zambrano | D22: 31 | E22: Solicitado por el Cliente | F22: 1 | G22: PANAMA JOURNEYS S,A - | I22: 63134216.0 | K22: PANAMAJOURNEYSSA | L22: =IF(SUMPRODUCT((Cruce!$E$2:$E$6000+Cruce!$G$2:$G$6000+Cruce!$I$2:$I$6000>0)*(Cruce!$D$2:$D$6000=$K22))>0,"SI","NO")
A23: AGRO JP / NILKA ATENCIO | B23: AGROJPNILKAATENCIO | C23: Solanye Acuña | D23: 65 | E23: Solicitado por el Cliente | F23: 2 | G23: AGRO JP / NILKA ATENCIO | H23: ni.lka@hotmail.com | I23: 65767586.0 | J23: 65767586.0 | K23: AGROJPNILKAATENCIO | L23: =IF(SUMPRODUCT((Cruce!$E$2:$E$6000+Cruce!$G$2:$G$6000+Cruce!$I$2:$I$6000>0)*(Cruce!$D$2:$D$6000=$K23))>0,"SI","NO")
C24: Maria Fernanda Rivas | D24: 31 | E24: Solicitado por el Cliente | F24: 1 | L24: =IF(SUMPRODUCT((Cruce!$E$2:$E$6000+Cruce!$G$2:$G$6000+Cruce!$I$2:$I$6000>0)*(Cruce!$D$2:$D$6000=$K24))>0,"SI","NO")
C25: Nailyn Martinez Johnson | D25: 40.5 | E25: Solicitado por el Cliente | F25: 1 | L25: =IF(SUMPRODUCT((Cruce!$E$2:$E$6000+Cruce!$G$2:$G$6000+Cruce!$I$2:$I$6000>0)*(Cruce!$D$2:$D$6000=$K25))>0,"SI","NO")
C26: Michelle Zambrano | D26: 66.5 | E26: Solicitado por el Cliente | F26: 1 | L26: =IF(SUMPRODUCT((Cruce!$E$2:$E$6000+Cruce!$G$2:$G$6000+Cruce!$I$2:$I$6000>0)*(Cruce!$D$2:$D$6000=$K26))>0,"SI","NO")
A27: UPPER EAST TOWER | B27: UPPEREASTTOWER | C27: Solanye Acuña | D27: 124 | E27: Solicitado por el Cliente | F27: 4 | G27: UPPER EAST TOWER | I27: 2027194.0 | K27: UPPEREASTTOWER | L27: =IF(SUMPRODUCT((Cruce!$E$2:$E$6000+Cruce!$G$2:$G$6000+Cruce!$I$2:$I$6000>0)*(Cruce!$D$2:$D$6000=$K27))>0,"SI","NO")
A28: FLIX CINEVISION PANAMA, S. DE R.L. - | B28: FLIXCINEVISIONPANAMASDERL | C28: Maria Fernanda Rivas | D28: 81 | E28: Solicitado por el Cliente | F28: 1 | G28: FLIX CINEVISION PANAMA, S. DE R.L. - | I28: 64993246.0 | K28: FLIXCINEVISIONPANAMASDERL | L28: =IF(SUMPRODUCT((Cruce!$E$2:$E$6000+Cruce!$G$2:$G$6000+Cruce!$I$2:$I$6000>0)*(Cruce!$D$2:$D$6000=$K28))>0,"SI","NO")
A29: AVAPSA | B29: AVAPSA | C29: Nailyn Martinez Johnson | D29: 40.5 | E29: Solicitado por el Cliente | F29: 1 | G29: AVAPSA | H29: magt.67vetequi@gmail.com | I29: 62605786.0 | J29: 66150700.0 | K29: AVAPSA | L29: =IF(SUMPRODUCT((Cruce!$E$2:$E$6000+Cruce!$G$2:$G$6000+Cruce!$I$2:$I$6000>0)*(Cruce!$D$2:$D$6000=$K29))>0,"SI","NO")
A30: DRAG COLORS | B30: DRAGCOLORS | C30: Michelle Zambrano | D30: 22 | E30: Solicitado por el Cliente | F30: 1 | G30: Salvador Orantes | H30: Chambascar27@gmail.com | I30: 69207844.0 | J30: 69207844.0 | K30: DRAGCOLORS | L30: =IF(SUMPRODUCT((Cruce!$E$2:$E$6000+Cruce!$G$2:$G$6000+Cruce!$I$2:$I$6000>0)*(Cruce!$D$2:$D$6000=$K30))>0,"SI","NO")
C31: Solanye Acuña | D31: 150 | E31: Solicitado por el Cliente | F31: 6 | L31: =IF(SUMPRODUCT((Cruce!$E$2:$E$6000+Cruce!$G$2:$G$6000+Cruce!$I$2:$I$6000>0)*(Cruce!$D$2:$D$6000=$K31))>0,"SI","NO")
C32: Maria Fernanda Rivas | D32: 21 | E32: Solicitado por el Cliente | F32: 3 | L32: =IF(SUMPRODUCT((Cruce!$E$2:$E$6000+Cruce!$G$2:$G$6000+Cruce!$I$2:$I$6000>0)*(Cruce!$D$2:$D$6000=$K32))>0,"SI","NO")
A33: Anagan | B33: ANAGAN | C33: Nailyn Martinez Johnson | D33: 42 | E33: Solicitado por el Cliente | F33: 1 | G33: LUIS MARTINEZ 7-83-25 // Amarilis Cristóbal 8-841-1249 | H33: anagan1@cwpanama.net | I33: 3140633.0 | J33: 3140633.0 | K33: ANAGAN | L33: =IF(SUMPRODUCT((Cruce!$E$2:$E$6000+Cruce!$G$2:$G$6000+Cruce!$I$2:$I$6000>0)*(Cruce!$D$2:$D$6000=$K33))>0,"SI","NO")
C34: Michelle Zambrano | D34: 44 | E34: Solicitado por el Cliente | F34: 1 | L34: =IF(SUMPRODUCT((Cruce!$E$2:$E$6000+Cruce!$G$2:$G$6000+Cruce!$I$2:$I$6000>0)*(Cruce!$D$2:$D$6000=$K34))>0,"SI","NO")
A35: Carmen Valdivia Valdes | B35: CARMENVALDIVIAVALDES | C35: Solanye Acuña | D35: 21 | E35: Solicitado por el Cliente | F35: 1 | I35: 66773196.0 | K35: CARMENVALDIVIAVALDES | L35: =IF(SUMPRODUCT((Cruce!$E$2:$E$6000+Cruce!$G$2:$G$6000+Cruce!$I$2:$I$6000>0)*(Cruce!$D$2:$D$6000=$K35))>0,"SI","NO")
A36: Gixel Guevara Almanza | B36: GIXELGUEVARAALMANZA | C36: Maria Fernanda Rivas | D36: 16 | E36: Solicitado por el Cliente | F36: 1 | I36: 69822979.0 | K36: GIXELGUEVARAALMANZA | L36: =IF(SUMPRODUCT((Cruce!$E$2:$E$6000+Cruce!$G$2:$G$6000+Cruce!$I$2:$I$6000>0)*(Cruce!$D$2:$D$6000=$K36))>0,"SI","NO")
A37: Jaime Arroyo Atencio | B37: JAIMEARROYOATENCIO | C37: Nailyn Martinez Johnson | D37: 21.75 | E37: Solicitado por el Cliente | F37: 1 | I37: 2287216.0 | K37: JAIMEARROYOATENCIO | L37: =IF(SUMPRODUCT((Cruce!$E$2:$E$6000+Cruce!$G$2:$G$6000+Cruce!$I$2:$I$6000>0)*(Cruce!$D$2:$D$6000=$K37))>0,"SI","NO")
A38: Shirley y Asociados | B38: SHIRLEYYASOCIADOS | C38: Michelle Zambrano | D38: 45.5 | E38: Solicitado por el Cliente | F38: 1 | G38: Luis Antonio Shirley Campbell | H38: administracion@shirleylaw.com | I38: 66752321.0 | J38: 66752321.0 | K38: SHIRLEYYASOCIADOS | L38: =IF(SUMPRODUCT((Cruce!$E$2:$E$6000+Cruce!$G$2:$G$6000+Cruce!$I$2:$I$6000>0)*(Cruce!$D$2:$D$6000=$K38))>0,"SI","NO")
A39: M. Contratista | B39: MCONTRATISTA | C39: Solanye Acuña | D39: 42 | E39: MIGRACION POST-PRE | F39: 1 | G39: Ricardo Raul Mezquita | I39: 2790469.0 | K39: MCONTRATISTA | L39: =IF(SUMPRODUCT((Cruce!$E$2:$E$6000+Cruce!$G$2:$G$6000+Cruce!$I$2:$I$6000>0)*(Cruce!$D$2:$D$6000=$K39))>0,"SI","NO")
A40: Solidus Secur | B40: SOLIDUSSECUR | C40: Maria Fernanda Rivas | D40: 15.99 | E40: Solicitado por el Cliente | F40: 1 | G40: HEINER SPEICH | H40: karoll.arguelles@sardona-capital.com | I40: 69826252.0 | J40: 69826252.0 | K40: SOLIDUSSECUR | L40: =IF(SUMPRODUCT((Cruce!$E$2:$E$6000+Cruce!$G$2:$G$6000+Cruce!$I$2:$I$6000>0)*(Cruce!$D$2:$D$6000=$K40))>0,"SI","NO")
A41: Bold Impresiones | B41: BOLDIMPRESIONES | C41: Nailyn Martinez Johnson | D41: 75 | E41: Solicitado por el Cliente | F41: 5 | G41: Alexander Romero Martinez | I41: 2702607.0 | K41: BOLDIMPRESIONES | L41: =IF(SUMPRODUCT((Cruce!$E$2:$E$6000+Cruce!$G$2:$G$6000+Cruce!$I$2:$I$6000>0)*(Cruce!$D$2:$D$6000=$K41))>0,"SI","NO")
C42: Michelle Zambrano | D42: 40 | E42: Solicitado por el Cliente | F42: 1 | L42: =IF(SUMPRODUCT((Cruce!$E$2:$E$6000+Cruce!$G$2:$G$6000+Cruce!$I$2:$I$6000>0)*(Cruce!$D$2:$D$6000=$K42))>0,"SI","NO")
C43: Solanye Acuña | D43: 5.5 | E43: Solicitado por el Cliente | F43: 1 | L43: =IF(SUMPRODUCT((Cruce!$E$2:$E$6000+Cruce!$G$2:$G$6000+Cruce!$I$2:$I$6000>0)*(Cruce!$D$2:$D$6000=$K43))>0,"SI","NO")
A44: Full Drop Sa | B44: FULLDROPSA | C44: Maria Fernanda Rivas | D44: 21.74 | E44: Solicitado por el Cliente | F44: 1 | G44: EDGAR NORIEL CHANG HERNANDEZ 6-701-17 | I44: 9101722.0 | K44: FULLDROPSA | L44: =IF(SUMPRODUCT((Cruce!$E$2:$E$6000+Cruce!$G$2:$G$6000+Cruce!$I$2:$I$6000>0)*(Cruce!$D$2:$D$6000=$K44))>0,"SI","NO")
C45: Nailyn Martinez Johnson | D45: 24 | E45: Solicitado por el Cliente | F45: 1 | L45: =IF(SUMPRODUCT((Cruce!$E$2:$E$6000+Cruce!$G$2:$G$6000+Cruce!$I$2:$I$6000>0)*(Cruce!$D$2:$D$6000=$K45))>0,"SI","NO")
C46: Michelle Zambrano | D46: 44 | E46: Solicitado por el Cliente | F46: 2 | L46: =IF(SUMPRODUCT((Cruce!$E$2:$E$6000+Cruce!$G$2:$G$6000+Cruce!$I$2:$I$6000>0)*(Cruce!$D$2:$D$6000=$K46))>0,"SI","NO")
A47: Varela Carden | B47: VARELACARDEN | C47: Solanye Acuña | D47: 40 | E47: Solicitado por el Cliente | F47: 1 | G47: Carlos Varela 8-259-337 | I47: 2655785.0 | K47: VARELACARDEN | L47: =IF(SUMPRODUCT((Cruce!$E$2:$E$6000+Cruce!$G$2:$G$6000+Cruce!$I$2:$I$6000>0)*(Cruce!$D$2:$D$6000=$K47))>0,"SI","NO")
A48: Jestski Panamarin | B48: JESTSKIPANAMARIN | C48: Maria Fernanda Rivas | D48: 42 | E48: Solicitado por el Cliente | F48: 1 | G48: Rene Marin | H48: bbrosi1023@hotmail.com | I48: 65112891.0 | J48: 65112891.0 | K48: JESTSKIPANAMARIN | L48: =IF(SUMPRODUCT((Cruce!$E$2:$E$6000+Cruce!$G$2:$G$6000+Cruce!$I$2:$I$6000>0)*(Cruce!$D$2:$D$6000=$K48))>0,"SI","NO")
C49: Nailyn Martinez Johnson | D49: 80.25 | E49: Solicitado por el Cliente | F49: 3 | L49: =IF(SUMPRODUCT((Cruce!$E$2:$E$6000+Cruce!$G$2:$G$6000+Cruce!$I$2:$I$6000>0)*(Cruce!$D$2:$D$6000=$K49))>0,"SI","NO")
A50: DVA GLASS SERVICES SA | B50: DVAGLASSSERVICESSA | C50: Michelle Zambrano | D50: 72 | E50: Solicitado por el Cliente | F50: 2 | G50: SANDRA ECHEVERRIA | I50: 69835010.0 | K50: DVAGLASSSERVICESSA | L50: =IF(SUMPRODUCT((Cruce!$E$2:$E$6000+Cruce!$G$2:$G$6000+Cruce!$I$2:$I$6000>0)*(Cruce!$D$2:$D$6000=$K50))>0,"SI","NO")
C51: Solanye Acuña | D51: 26.75 | E51: Solicitado por el Cliente | F51: 1 | L51: =IF(SUMPRODUCT((Cruce!$E$2:$E$6000+Cruce!$G$2:$G$6000+Cruce!$I$2:$I$6000>0)*(Cruce!$D$2:$D$6000=$K51))>0,"SI","NO")
C52: Maria Fernanda Rivas | D52: 28.75 | E52: Solicitado por el Cliente | F52: 1 | L52: =IF(SUMPRODUCT((Cruce!$E$2:$E$6000+Cruce!$G$2:$G$6000+Cruce!$I$2:$I$6000>0)*(Cruce!$D$2:$D$6000=$K52))>0,"SI","NO")
A53: Annett Miranda | B53: ANNETTMIRANDA | C53: Nailyn Martinez Johnson | D53: 28.75 | E53: (en blanco) | F53: 1 | G53: Nila Espinoza | I53: 2644225.0 | K53: ANNETTMIRANDA | L53: =IF(SUMPRODUCT((Cruce!$E$2:$E$6000+Cruce!$G$2:$G$6000+Cruce!$I$2:$I$6000>0)*(Cruce!$D$2:$D$6000=$K53))>0,"SI","NO")
A54: FONSECA, S.A. | B54: FONSECASA | C54: Michelle Zambrano | D54: 20.75 | E54: Solicitado por el Cliente | F54: 1 | G54: YARIBETH HOU JIANG | H54: surtimaxpanama@hotmail.com | I54: 62529492.0 | J54: 62529492.0 | K54: FONSECASA | L54: =IF(SUMPRODUCT((Cruce!$E$2:$E$6000+Cruce!$G$2:$G$6000+Cruce!$I$2:$I$6000>0)*(Cruce!$D$2:$D$6000=$K54))>0,"SI","NO")
C55: Solanye Acuña | D55: 24 | E55: Solicitado por el Cliente | F55: 2 | L55: =IF(SUMPRODUCT((Cruce!$E$2:$E$6000+Cruce!$G$2:$G$6000+Cruce!$I$2:$I$6000>0)*(Cruce!$D$2:$D$6000=$K55))>0,"SI","NO")
C56: Maria Fernanda Rivas | D56: 117.75 | E56: Solicitado por el Cliente | F56: 3 | L56: =IF(SUMPRODUCT((Cruce!$E$2:$E$6000+Cruce!$G$2:$G$6000+Cruce!$I$2:$I$6000>0)*(Cruce!$D$2:$D$6000=$K56))>0,"SI","NO")
C57: Nailyn Martinez Johnson | D57: 44.5 | E57: Solicitado por el Cliente | F57: 1 | L57: =IF(SUMPRODUCT((Cruce!$E$2:$E$6000+Cruce!$G$2:$G$6000+Cruce!$I$2:$I$6000>0)*(Cruce!$D$2:$D$6000=$K57))>0,"SI","NO")
C58: Michelle Zambrano | D58: 43.96 | E58: Solicitado por el Cliente | F58: 4 | L58: =IF(SUMPRODUCT((Cruce!$E$2:$E$6000+Cruce!$G$2:$G$6000+Cruce!$I$2:$I$6000>0)*(Cruce!$D$2:$D$6000=$K58))>0,"SI","NO")
A59: Agencia De Ad | B59: AGENCIADEAD | C59: Solanye Acuña | D59: 37.5 | E59: Solicitado por el Cliente | F59: 1 | G59: MARCOS VIDES | I59: 67753993.0 | K59: AGENCIADEAD | L59: =IF(SUMPRODUCT((Cruce!$E$2:$E$6000+Cruce!$G$2:$G$6000+Cruce!$I$2:$I$6000>0)*(Cruce!$D$2:$D$6000=$K59))>0,"SI","NO")
A60: Grupo Camberfot, S.A | B60: GRUPOCAMBERFOTSA | C60: Maria Fernanda Rivas | D60: 42 | E60: Solicitado por el Cliente | F60: 1 | G60: Annia Pons Hernandez | H60: recepcion@grupoc.cc | I60: 66765590.0 | J60: 66765590.0 | K60: GRUPOCAMBERFOTSA | L60: =IF(SUMPRODUCT((Cruce!$E$2:$E$6000+Cruce!$G$2:$G$6000+Cruce!$I$2:$I$6000>0)*(Cruce!$D$2:$D$6000=$K60))>0,"SI","NO")
C61: Nailyn Martinez Johnson | D61: 45.5 | E61: Solicitado por el Cliente | F61: 1 | L61: =IF(SUMPRODUCT((Cruce!$E$2:$E$6000+Cruce!$G$2:$G$6000+Cruce!$I$2:$I$6000>0)*(Cruce!$D$2:$D$6000=$K61))>0,"SI","NO")
C62: Michelle Zambrano | D62: 20.75 | E62: Solicitado por el Cliente | F62: 1 | L62: =IF(SUMPRODUCT((Cruce!$E$2:$E$6000+Cruce!$G$2:$G$6000+Cruce!$I$2:$I$6000>0)*(Cruce!$D$2:$D$6000=$K62))>0,"SI","NO")
A63: Zarina Saliba | B63: ZARINASALIBA | C63: Solanye Acuña | D63: 37.5 | E63: Solicitado por el Cliente | F63: 1 | I63: 2107400.0 | K63: ZARINASALIBA | L63: =IF(SUMPRODUCT((Cruce!$E$2:$E$6000+Cruce!$G$2:$G$6000+Cruce!$I$2:$I$6000>0)*(Cruce!$D$2:$D$6000=$K63))>0,"SI","NO")
A64: Vanessa Mo | B64: VANESSAMO | C64: Maria Fernanda Rivas | D64: 13.99 | E64: Solicitado por el Cliente | F64: 1 | G64: FRANCISCO LOO CHEN | I64: 61123735.0 | K64: VANESSAMO | L64: =IF(SUMPRODUCT((Cruce!$E$2:$E$6000+Cruce!$G$2:$G$6000+Cruce!$I$2:$I$6000>0)*(Cruce!$D$2:$D$6000=$K64))>0,"SI","NO")
A65: Nilka Atencio | B65: NILKAATENCIO | C65: Nailyn Martinez Johnson | D65: 45.5 | E65: MIGRACION POST-PRE | F65: 1 | G65: Maria Carmelina Ramos Salazar | I65: 8464310.0 | K65: AGROJPNILKAATENCIO | L65: =IF(SUMPRODUCT((Cruce!$E$2:$E$6000+Cruce!$G$2:$G$6000+Cruce!$I$2:$I$6000>0)*(Cruce!$D$2:$D$6000=$K65))>0,"SI","NO")
C66: Michelle Zambrano | D66: 36 | E66: MIGRACION POST-PRE | F66: 1 | L66: =IF(SUMPRODUCT((Cruce!$E$2:$E$6000+Cruce!$G$2:$G$6000+Cruce!$I$2:$I$6000>0)*(Cruce!$D$2:$D$6000=$K66))>0,"SI","NO")
A67: Inversiones y | B67: INVERSIONESY | C67: Solanye Acuña | D67: 20.75 | E67: Solicitado por el Cliente | F67: 1 | G67: ASLEIGH MAYLIN ESQUIVEL | H67: Asleigh819@gmail.com | I67: 69996889.0 | J67: 69996889.0 | K67: INVERSIONESYDESARROLLOTURISTICO | L67: =IF(SUMPRODUCT((Cruce!$E$2:$E$6000+Cruce!$G$2:$G$6000+Cruce!$I$2:$I$6000>0)*(Cruce!$D$2:$D$6000=$K67))>0,"SI","NO")
A68: Ph Lumiere | B68: PHLUMIERE | C68: Maria Fernanda Rivas | D68: 83 | E68: Solicitado por el Cliente | F68: 2 | G68: ANN MIKUSKI | I68: 64482987.0 | K68: PHLUMIERE | L68: =IF(SUMPRODUCT((Cruce!$E$2:$E$6000+Cruce!$G$2:$G$6000+Cruce!$I$2:$I$6000>0)*(Cruce!$D$2:$D$6000=$K68))>0,"SI","NO")
A69: Alcides Ivan | B69: ALCIDESIVAN | C69: Nailyn Martinez Johnson | D69: 42.5 | E69: Solicitado por el Cliente | F69: 1 | G69: Alcides Ivan Olaya Gomez | I69: 62927024.0 | K69: ALCIDESIVAN | L69: =IF(SUMPRODUCT((Cruce!$E$2:$E$6000+Cruce!$G$2:$G$6000+Cruce!$I$2:$I$6000>0)*(Cruce!$D$2:$D$6000=$K69))>0,"SI","NO")
A70: Mini Centro Abdiel | B70: MINICENTROABDIEL | C70: Michelle Zambrano | D70: 20.75 | E70: Solicitado por el Cliente | F70: 1 | G70: Abdiel Iv¿n D¿az Batista | H70: abdieldiazbatista@gmail.com | I70: 66524832.0 | J70: 66524832.0 | K70: MINICENTROABDIEL | L70: =IF(SUMPRODUCT((Cruce!$E$2:$E$6000+Cruce!$G$2:$G$6000+Cruce!$I$2:$I$6000>0)*(Cruce!$D$2:$D$6000=$K70))>0,"SI","NO")
A71: Maria De Los Reyes H ernandez De Moran | B71: MARIADELOSREYESHERNANDEZDEMORAN | C71: Solanye Acuña | D71: 20.75 | E71: Solicitado por el Cliente | F71: 1 | G71: Maria De Los Reyes Hernandez De Moran | I71: 69581636.0 | K71: MARIADELOSREYESHERNANDEZDEMORAN | L71: =IF(SUMPRODUCT((Cruce!$E$2:$E$6000+Cruce!$G$2:$G$6000+Cruce!$I$2:$I$6000>0)*(Cruce!$D$2:$D$6000=$K71))>0,"SI","NO")
A72: Ph Maui | B72: PHMAUI | C72: Maria Fernanda Rivas | D72: 22.74 | E72: Solicitado por el Cliente | F72: 1 | G72: Dania Iveth Barahona Almengor 8-731-2274 | H72: phmaui.adm@gmail.com | I72: 61309833.0 | J72: 61309833.0 | K72: PHMAUI | L72: =IF(SUMPRODUCT((Cruce!$E$2:$E$6000+Cruce!$G$2:$G$6000+Cruce!$I$2:$I$6000>0)*(Cruce!$D$2:$D$6000=$K72))>0,"SI","NO")
C73: Nailyn Martinez Johnson | D73: 36 | E73: Solicitado por el Cliente | F73: 1 | L73: =IF(SUMPRODUCT((Cruce!$E$2:$E$6000+Cruce!$G$2:$G$6000+Cruce!$I$2:$I$6000>0)*(Cruce!$D$2:$D$6000=$K73))>0,"SI","NO")
A74: Impresiones y Copias I.G | B74: IMPRESIONESYCOPIASIG | C74: Michelle Zambrano | D74: 31.25 | E74: Solicitado por el Cliente | F74: 2 | G74: Jose Angel Casas Barria 6-703-1837 | H74: ventas0101@gmail.com | I74: 65585221.0 | J74: 64830239.0 | K74: IMPRESIONESYCOPIASIG | L74: =IF(SUMPRODUCT((Cruce!$E$2:$E$6000+Cruce!$G$2:$G$6000+Cruce!$I$2:$I$6000>0)*(Cruce!$D$2:$D$6000=$K74))>0,"SI","NO")
C75: Solanye Acuña | D75: 28.75 | E75: Solicitado por el Cliente | F75: 1 | L75: =IF(SUMPRODUCT((Cruce!$E$2:$E$6000+Cruce!$G$2:$G$6000+Cruce!$I$2:$I$6000>0)*(Cruce!$D$2:$D$6000=$K75))>0,"SI","NO")
C76: Maria Fernanda Rivas | D76: 5.5 | E76: Solicitado por el Cliente | F76: 1 | L76: =IF(SUMPRODUCT((Cruce!$E$2:$E$6000+Cruce!$G$2:$G$6000+Cruce!$I$2:$I$6000>0)*(Cruce!$D$2:$D$6000=$K76))>0,"SI","NO")
A77: Ilmarys Virginia Riv era Lezcano de Serrano | B77: ILMARYSVIRGINIARIVERALEZCANODESERRANO | C77: Nailyn Martinez Johnson | D77: 12 | E77: Solicitado por el Cliente | F77: 1 | G77: Ilmarys Virginia Rivera Lezcano de Serra | H77: maryrivera52427@gmail.com | I77: 66023646.0 | J77: 66023646.0 | K77: ILMARYSVIRGINIARIVERALEZCANODESERRANO | L77: =IF(SUMPRODUCT((Cruce!$E$2:$E$6000+Cruce!$G$2:$G$6000+Cruce!$I$2:$I$6000>0)*(Cruce!$D$2:$D$6000=$K77))>0,"SI","NO")
A78: Gaspar Arsenio Reyes Agudo | B78: GASPARARSENIOREYESAGUDO | C78: Michelle Zambrano | D78: 30 | E78: Solicitado por el Cliente | F78: 3 | G78: Gaspar Arsenio Reyes Agudo | H78: gaspar.reyesagudo@gmail.com | I78: 67242628.0 | J78: 67242628.0 | K78: GASPARARSENIOREYESAGUDO | L78: =IF(SUMPRODUCT((Cruce!$E$2:$E$6000+Cruce!$G$2:$G$6000+Cruce!$I$2:$I$6000>0)*(Cruce!$D$2:$D$6000=$K78))>0,"SI","NO")
A79: Sergio Garzon | B79: SERGIOGARZON | C79: Solanye Acuña | D79: 38 | E79: Solicitado por el Cliente | F79: 1 | I79: 2297173.0 | K79: SERGIOGARZON | L79: =IF(SUMPRODUCT((Cruce!$E$2:$E$6000+Cruce!$G$2:$G$6000+Cruce!$I$2:$I$6000>0)*(Cruce!$D$2:$D$6000=$K79))>0,"SI","NO")
A80: PH Marquis Tower | B80: PHMARQUISTOWER | C80: Maria Fernanda Rivas | D80: 20.75 | E80: Solicitado por el Cliente | F80: 1 | H80: administracion@phmarquistower.com | I80: 67969384.0 | J80: 67969384.0 | K80: PHMARQUISTOWER | L80: =IF(SUMPRODUCT((Cruce!$E$2:$E$6000+Cruce!$G$2:$G$6000+Cruce!$I$2:$I$6000>0)*(Cruce!$D$2:$D$6000=$K80))>0,"SI","NO")
A81: INVERSIONES CASCANTE, SA | B81: INVERSIONESCASCANTESA | C81: Nailyn Martinez Johnson | D81: 54.75 | E81: Solicitado por el Cliente | F81: 3 | G81: GRISELDA CASCANTE | H81: gcascanteph@gmail.com | I81: 67475603.0 | J81: 67475603.0 | K81: INVERSIONESCASCANTESA | L81: =IF(SUMPRODUCT((Cruce!$E$2:$E$6000+Cruce!$G$2:$G$6000+Cruce!$I$2:$I$6000>0)*(Cruce!$D$2:$D$6000=$K81))>0,"SI","NO")
C82: Michelle Zambrano | D82: 36 | E82: Solicitado por el Cliente | F82: 1 | L82: =IF(SUMPRODUCT((Cruce!$E$2:$E$6000+Cruce!$G$2:$G$6000+Cruce!$I$2:$I$6000>0)*(Cruce!$D$2:$D$6000=$K82))>0,"SI","NO")
C83: Solanye Acuña | D83: 55.5 | E83: Solicitado por el Cliente | F83: 2 | L83: =IF(SUMPRODUCT((Cruce!$E$2:$E$6000+Cruce!$G$2:$G$6000+Cruce!$I$2:$I$6000>0)*(Cruce!$D$2:$D$6000=$K83))>0,"SI","NO")
A84: SAQUELLA SA | B84: SAQUELLASA | C84: Maria Fernanda Rivas | D84: 20.75 | E84: MIGRACION POST-PRE | F84: 1 | G84: Yilda Selidet Bultron Vergara // Elida Guerra de Shishportish | H84: gruposaquella@gmail.com | I84: 60303765.0 | K84: SAQUELLASA | L84: =IF(SUMPRODUCT((Cruce!$E$2:$E$6000+Cruce!$G$2:$G$6000+Cruce!$I$2:$I$6000>0)*(Cruce!$D$2:$D$6000=$K84))>0,"SI","NO")
A85: Irving A rceniao Mirones Barsallo | B85: IRVINGARCENIAOMIRONESBARSALLO | C85: Nailyn Martinez Johnson | D85: 27.75 | E85: Solicitado por el Cliente | F85: 1 | G85: Irving Arceniao Mirones Barsallo | I85: 69813438.0 | K85: IRVINGARCENIAOMIRONESBARSALLO | L85: =IF(SUMPRODUCT((Cruce!$E$2:$E$6000+Cruce!$G$2:$G$6000+Cruce!$I$2:$I$6000>0)*(Cruce!$D$2:$D$6000=$K85))>0,"SI","NO")
C86: Michelle Zambrano | D86: 38 | E86: Solicitado por el Cliente | F86: 1 | L86: =IF(SUMPRODUCT((Cruce!$E$2:$E$6000+Cruce!$G$2:$G$6000+Cruce!$I$2:$I$6000>0)*(Cruce!$D$2:$D$6000=$K86))>0,"SI","NO")
A87: Kadir Hinds | B87: KADIRHINDS | C87: Solanye Acuña | D87: 22.75 | E87: Solicitado por el Cliente | F87: 1 | H87: KADIRHIND@GMAIL.COM | I87: 62178735.0 | J87: 62178735.0 | K87: KADIRHINDS | L87: =IF(SUMPRODUCT((Cruce!$E$2:$E$6000+Cruce!$G$2:$G$6000+Cruce!$I$2:$I$6000>0)*(Cruce!$D$2:$D$6000=$K87))>0,"SI","NO")
A88: Luis Alberto Singh Casta?edas | B88: LUISALBERTOSINGHCASTAEDAS | C88: Maria Fernanda Rivas | D88: 15 | E88: Solicitado por el Cliente | F88: 1 | I88: 62749604.0 | K88: LUISALBERTOSINGHCASTAEDAS | L88: =IF(SUMPRODUCT((Cruce!$E$2:$E$6000+Cruce!$G$2:$G$6000+Cruce!$I$2:$I$6000>0)*(Cruce!$D$2:$D$6000=$K88))>0,"SI","NO")
A89: Hbo Sa | B89: HBOSA | C89: Nailyn Martinez Johnson | D89: 45.48 | E89: Solicitado por el Cliente | F89: 2 | G89: Ida Osorio Zarraonandia | I89: 62228321.0 | J89: 62405623.0 | K89: HBOSA | L89: =IF(SUMPRODUCT((Cruce!$E$2:$E$6000+Cruce!$G$2:$G$6000+Cruce!$I$2:$I$6000>0)*(Cruce!$D$2:$D$6000=$K89))>0,"SI","NO")
C90: Michelle Zambrano | D90: 27.75 | E90: Solicitado por el Cliente | F90: 1 | L90: =IF(SUMPRODUCT((Cruce!$E$2:$E$6000+Cruce!$G$2:$G$6000+Cruce!$I$2:$I$6000>0)*(Cruce!$D$2:$D$6000=$K90))>0,"SI","NO")
C91: Solanye Acuña | D91: 27.75 | E91: Solicitado por el Cliente | F91: 1 | L91: =IF(SUMPRODUCT((Cruce!$E$2:$E$6000+Cruce!$G$2:$G$6000+Cruce!$I$2:$I$6000>0)*(Cruce!$D$2:$D$6000=$K91))>0,"SI","NO")
C92: Maria Fernanda Rivas | D92: 57.5 | E92: Solicitado por el Cliente | F92: 2 | L92: =IF(SUMPRODUCT((Cruce!$E$2:$E$6000+Cruce!$G$2:$G$6000+Cruce!$I$2:$I$6000>0)*(Cruce!$D$2:$D$6000=$K92))>0,"SI","NO")
A93: Alba Lassonde Ortiz | B93: ALBALASSONDEORTIZ | C93: Nailyn Martinez Johnson | D93: 12 | E93: Solicitado por el Cliente | F93: 1 | G93: Alba Lassonde Ortiz | I93: 66430667.0 | K93: ALBALASSONDEORTIZ | L93: =IF(SUMPRODUCT((Cruce!$E$2:$E$6000+Cruce!$G$2:$G$6000+Cruce!$I$2:$I$6000>0)*(Cruce!$D$2:$D$6000=$K93))>0,"SI","NO")
A94: Jorge Alberto Plata Mc Nulty | B94: JORGEALBERTOPLATAMCNULTY | C94: Michelle Zambrano | D94: 30 | E94: Solicitado por el Cliente | F94: 3 | G94: Jorge Alberto Plata Mc Nulty | H94: platalaw@gmail.com | I94: 66135709.0 | J94: 66135709.0 | K94: JORGEALBERTOPLATAMCNULTY | L94: =IF(SUMPRODUCT((Cruce!$E$2:$E$6000+Cruce!$G$2:$G$6000+Cruce!$I$2:$I$6000>0)*(Cruce!$D$2:$D$6000=$K94))>0,"SI","NO")
A95: Luismanuelchungyip | B95: LUISMANUELCHUNGYIP | C95: Solanye Acuña | D95: 12 | E95: Solicitado por el Cliente | F95: 1 | G95: Luis Manuel Chung Yip | I95: 68731188.0 | K95: LUISMANUELCHUNGYIP | L95: =IF(SUMPRODUCT((Cruce!$E$2:$E$6000+Cruce!$G$2:$G$6000+Cruce!$I$2:$I$6000>0)*(Cruce!$D$2:$D$6000=$K95))>0,"SI","NO")
A96: Ruth Joyce De La Cruz Diaz | B96: RUTHJOYCEDELACRUZDIAZ | C96: Maria Fernanda Rivas | D96: 25.75 | E96: Solicitado por el Cliente | F96: 1 | G96: Ruth Joyce De La Cruz Diaz | I96: 69491672.0 | K96: RUTHJOYCEDELACRUZDIAZ | L96: =IF(SUMPRODUCT((Cruce!$E$2:$E$6000+Cruce!$G$2:$G$6000+Cruce!$I$2:$I$6000>0)*(Cruce!$D$2:$D$6000=$K96))>0,"SI","NO")
A97: KALINSON CORP, S.A. | B97: KALINSONCORPSA | C97: Nailyn Martinez Johnson | D97: 90 | E97: Solicitado por el Cliente | F97: 6 | G97: RL ROBERTO ENRIQUE GARCIA DAPENA | H97: compras@kalinsoncorp.com | I97: 60901995.0 | J97: 60901995.0 | K97: KALINSONCORPSA | L97: =IF(SUMPRODUCT((Cruce!$E$2:$E$6000+Cruce!$G$2:$G$6000+Cruce!$I$2:$I$6000>0)*(Cruce!$D$2:$D$6000=$K97))>0,"SI","NO")
C98: Michelle Zambrano | D98: 80 | E98: Solicitado por el Cliente | F98: 2 | L98: =IF(SUMPRODUCT((Cruce!$E$2:$E$6000+Cruce!$G$2:$G$6000+Cruce!$I$2:$I$6000>0)*(Cruce!$D$2:$D$6000=$K98))>0,"SI","NO")
C99: Solanye Acuña | D99: 40 | E99: Solicitado por el Cliente | F99: 1 | L99: =IF(SUMPRODUCT((Cruce!$E$2:$E$6000+Cruce!$G$2:$G$6000+Cruce!$I$2:$I$6000>0)*(Cruce!$D$2:$D$6000=$K99))>0,"SI","NO")
A100: Alba Lassonde Ortiz | B100: ALBALASSONDEORTIZ | C100: Maria Fernanda Rivas | D100: 12 | E100: Solicitado por el Cliente | F100: 1 | G100: Alba Lassonde Ortiz | I100: 66430667.0 | K100: ALBALASSONDEORTIZ | L100: =IF(SUMPRODUCT((Cruce!$E$2:$E$6000+Cruce!$G$2:$G$6000+Cruce!$I$2:$I$6000>0)*(Cruce!$D$2:$D$6000=$K100))>0,"SI","NO")
...

Sheet Cruce
A1: CUENTA | B1: CUST_NO | C1: NOMBRE | D1: NKEY | E1: EN_NP | F1: MRC_NP | G1: EN_MOV | H1: MRC_MOV | I1: EN_CS | J1: SERVICIOS_CS | K1: EN_WB | L1: MRC_WB | M1: MOVIL | N1: SERVICIOS | O1: SEGMENTO | P1: OPORTUNIDAD | Q1: MRC_TOTAL | R1: EJECUTIVA | S1: FUENTES | T1: N.BASES
A2: 355382970000 | B2: 35538297 | C2: EDIL GOMEZ ARCE | D2: EDILGOMEZARCE | E2: =IF(COUNTIFS(Registros!$A$2:$A$6000,"NP",Registros!$B$2:$B$6000,$A2)>0,1,0) | F2: =IF($E2=1,SUMIFS(Registros!$F$2:$F$6000,Registros!$A$2:$A$6000,"NP",Registros!$B$2:$B$6000,$A2),0) | G2: =IF(COUNTIFS(Registros!$A$2:$A$6000,"MOV",Registros!$B$2:$B$6000,$A2)>0,1,0) | H2: =IF($G2=1,SUMIFS(Registros!$F$2:$F$6000,Registros!$A$2:$A$6000,"MOV",Registros!$B$2:$B$6000,$A2),0) | I2: =IF(COUNTIFS(Registros!$A$2:$A$6000,"CS",Registros!$B$2:$B$6000,$A2)>0,1,0) | J2: =IF($I2=1,SUMIFS(Registros!$I$2:$I$6000,Registros!$A$2:$A$6000,"CS",Registros!$B$2:$B$6000,$A2),0) | K2: =IF(COUNTIFS(Winback!$K$2:$K$300,$D2)>0,1,0) | L2: =IF(AND($K2=1,LEFT($A2,3)="WB-"),SUMIFS(Winback!$D$2:$D$300,Winback!$K$2:$K$300,$D2),0) | M2: =IF(OR($E2=1,$G2=1,SUMIFS(Registros!$J$2:$J$6000,Registros!$B$2:$B$6000,$A2)>0),1,0) | N2: =IF($J2>0,1,IF(COUNTIFS(Registros!$A$2:$A$6000,"CS",Registros!$B$2:$B$6000,$A2,Registros!$K$2:$K$6000,"<>")>0,1,0)) | O2: =IF(AND($K2=1,$E2=0,$G2=0,$I2=0),"WINBACK",IF(AND($M2=1,$N2>0),"CONVERGENTE",IF($M2=1,"SOLO MÓVIL",IF($N2>0,"SOLO FIJO / INTERNET","SIN SERVICIOS")))) | P2: =IF($O2="WINBACK","Recuperar (winback)",IF($O2="CONVERGENTE","Upgrade / más líneas",IF($O2="SOLO MÓVIL","Ofrecer fijo + internet (FLBBTV)",IF($O2="SOLO FIJO / INTERNET","Ofrecer línea móvil Nextphone","Oferta completa (móvil + fijo + internet)")))) | Q2: =$F2+$H2+$L2 | R2: =IFERROR(VLOOKUP($A2,Registros!$B$2:$G$6000,6,0),IFERROR(VLOOKUP($D2,Winback!$B$2:$C$300,2,0),"")) | S2: =IF($E2=1,"NP","")&IF($G2=1,"+MOV","")&IF($I2=1,"+CS","")&IF($K2=1,"+WB","") | T2: =$E2+$G2+$I2+$K2
A3: 353338240000 | B3: 35333824 | C3: MEYVIS CALVO | D3: MEYVISCALVO | E3: =IF(COUNTIFS(Registros!$A$2:$A$6000,"NP",Registros!$B$2:$B$6000,$A3)>0,1,0) | F3: =IF($E3=1,SUMIFS(Registros!$F$2:$F$6000,Registros!$A$2:$A$6000,"NP",Registros!$B$2:$B$6000,$A3),0) | G3: =IF(COUNTIFS(Registros!$A$2:$A$6000,"MOV",Registros!$B$2:$B$6000,$A3)>0,1,0) | H3: =IF($G3=1,SUMIFS(Registros!$F$2:$F$6000,Registros!$A$2:$A$6000,"MOV",Registros!$B$2:$B$6000,$A3),0) | I3: =IF(COUNTIFS(Registros!$A$2:$A$6000,"CS",Registros!$B$2:$B$6000,$A3)>0,1,0) | J3: =IF($I3=1,SUMIFS(Registros!$I$2:$I$6000,Registros!$A$2:$A$6000,"CS",Registros!$B$2:$B$6000,$A3),0) | K3: =IF(COUNTIFS(Winback!$K$2:$K$300,$D3)>0,1,0) | L3: =IF(AND($K3=1,LEFT($A3,3)="WB-"),SUMIFS(Winback!$D$2:$D$300,Winback!$K$2:$K$300,$D3),0) | M3: =IF(OR($E3=1,$G3=1,SUMIFS(Registros!$J$2:$J$6000,Registros!$B$2:$B$6000,$A3)>0),1,0) | N3: =IF($J3>0,1,IF(COUNTIFS(Registros!$A$2:$A$6000,"CS",Registros!$B$2:$B$6000,$A3,Registros!$K$2:$K$6000,"<>")>0,1,0)) | O3: =IF(AND($K3=1,$E3=0,$G3=0,$I3=0),"WINBACK",IF(AND($M3=1,$N3>0),"CONVERGENTE",IF($M3=1,"SOLO MÓVIL",IF($N3>0,"SOLO FIJO / INTERNET","SIN SERVICIOS")))) | P3: =IF($O3="WINBACK","Recuperar (winback)",IF($O3="CONVERGENTE","Upgrade / más líneas",IF($O3="SOLO MÓVIL","Ofrecer fijo + internet (FLBBTV)",IF($O3="SOLO FIJO / INTERNET","Ofrecer línea móvil Nextphone","Oferta completa (móvil + fijo + internet)")))) | Q3: =$F3+$H3+$L3 | R3: =IFERROR(VLOOKUP($A3,Registros!$B$2:$G$6000,6,0),IFERROR(VLOOKUP($D3,Winback!$B$2:$C$300,2,0),"")) | S3: =IF($E3=1,"NP","")&IF($G3=1,"+MOV","")&IF($I3=1,"+CS","")&IF($K3=1,"+WB","") | T3: =$E3+$G3+$I3+$K3
A4: 321157030000 | B4: 32115703 | C4: GRUPO CORPORA | D4: GRUPOCORPORA | E4: =IF(COUNTIFS(Registros!$A$2:$A$6000,"NP",Registros!$B$2:$B$6000,$A4)>0,1,0) | F4: =IF($E4=1,SUMIFS(Registros!$F$2:$F$6000,Registros!$A$2:$A$6000,"NP",Registros!$B$2:$B$6000,$A4),0) | G4: =IF(COUNTIFS(Registros!$A$2:$A$6000,"MOV",Registros!$B$2:$B$6000,$A4)>0,1,0) | H4: =IF($G4=1,SUMIFS(Registros!$F$2:$F$6000,Registros!$A$2:$A$6000,"MOV",Registros!$B$2:$B$6000,$A4),0) | I4: =IF(COUNTIFS(Registros!$A$2:$A$6000,"CS",Registros!$B$2:$B$6000,$A4)>0,1,0) | J4: =IF($I4=1,SUMIFS(Registros!$I$2:$I$6000,Registros!$A$2:$A$6000,"CS",Registros!$B$2:$B$6000,$A4),0) | K4: =IF(COUNTIFS(Winback!$K$2:$K$300,$D4)>0,1,0) | L4: =IF(AND($K4=1,LEFT($A4,3)="WB-"),SUMIFS(Winback!$D$2:$D$300,Winback!$K$2:$K$300,$D4),0) | M4: =IF(OR($E4=1,$G4=1,SUMIFS(Registros!$J$2:$J$6000,Registros!$B$2:$B$6000,$A4)>0),1,0) | N4: =IF($J4>0,1,IF(COUNTIFS(Registros!$A$2:$A$6000,"CS",Registros!$B$2:$B$6000,$A4,Registros!$K$2:$K$6000,"<>")>0,1,0)) | O4: =IF(AND($K4=1,$E4=0,$G4=0,$I4=0),"WINBACK",IF(AND($M4=1,$N4>0),"CONVERGENTE",IF($M4=1,"SOLO MÓVIL",IF($N4>0,"SOLO FIJO / INTERNET","SIN SERVICIOS")))) | P4: =IF($O4="WINBACK","Recuperar (winback)",IF($O4="CONVERGENTE","Upgrade / más líneas",IF($O4="SOLO MÓVIL","Ofrecer fijo + internet (FLBBTV)",IF($O4="SOLO FIJO / INTERNET","Ofrecer línea móvil Nextphone","Oferta completa (móvil + fijo + internet)")))) | Q4: =$F4+$H4+$L4 | R4: =IFERROR(VLOOKUP($A4,Registros!$B$2:$G$6000,6,0),IFERROR(VLOOKUP($D4,Winback!$B$2:$C$300,2,0),"")) | S4: =IF($E4=1,"NP","")&IF($G4=1,"+MOV","")&IF($I4=1,"+CS","")&IF($K4=1,"+WB","") | T4: =$E4+$G4+$I4+$K4
A5: 369050850000 | B5: 36905085 | C5: SILVIA ARAUZ | D5: SILVIAARAUZ | E5: =IF(COUNTIFS(Registros!$A$2:$A$6000,"NP",Registros!$B$2:$B$6000,$A5)>0,1,0) | F5: =IF($E5=1,SUMIFS(Registros!$F$2:$F$6000,Registros!$A$2:$A$6000,"NP",Registros!$B$2:$B$6000,$A5),0) | G5: =IF(COUNTIFS(Registros!$A$2:$A$6000,"MOV",Registros!$B$2:$B$6000,$A5)>0,1,0) | H5: =IF($G5=1,SUMIFS(Registros!$F$2:$F$6000,Registros!$A$2:$A$6000,"MOV",Registros!$B$2:$B$6000,$A5),0) | I5: =IF(COUNTIFS(Registros!$A$2:$A$6000,"CS",Registros!$B$2:$B$6000,$A5)>0,1,0) | J5: =IF($I5=1,SUMIFS(Registros!$I$2:$I$6000,Registros!$A$2:$A$6000,"CS",Registros!$B$2:$B$6000,$A5),0) | K5: =IF(COUNTIFS(Winback!$K$2:$K$300,$D5)>0,1,0) | L5: =IF(AND($K5=1,LEFT($A5,3)="WB-"),SUMIFS(Winback!$D$2:$D$300,Winback!$K$2:$K$300,$D5),0) | M5: =IF(OR($E5=1,$G5=1,SUMIFS(Registros!$J$2:$J$6000,Registros!$B$2:$B$6000,$A5)>0),1,0) | N5: =IF($J5>0,1,IF(COUNTIFS(Registros!$A$2:$A$6000,"CS",Registros!$B$2:$B$6000,$A5,Registros!$K$2:$K$6000,"<>")>0,1,0)) | O5: =IF(AND($K5=1,$E5=0,$G5=0,$I5=0),"WINBACK",IF(AND($M5=1,$N5>0),"CONVERGENTE",IF($M5=1,"SOLO MÓVIL",IF($N5>0,"SOLO FIJO / INTERNET","SIN SERVICIOS")))) | P5: =IF($O5="WINBACK","Recuperar (winback)",IF($O5="CONVERGENTE","Upgrade / más líneas",IF($O5="SOLO MÓVIL","Ofrecer fijo + internet (FLBBTV)",IF($O5="SOLO FIJO / INTERNET","Ofrecer línea móvil Nextphone","Oferta completa (móvil + fijo + internet)")))) | Q5: =$F5+$H5+$L5 | R5: =IFERROR(VLOOKUP($A5,Registros!$B$2:$G$6000,6,0),IFERROR(VLOOKUP($D5,Winback!$B$2:$C$300,2,0),"")) | S5: =IF($E5=1,"NP","")&IF($G5=1,"+MOV","")&IF($I5=1,"+CS","")&IF($K5=1,"+WB","") | T5: =$E5+$G5+$I5+$K5
A6: 355282350000 | B6: 35528235 | C6: SIMON WALTEROVA | D6: SIMONWALTEROVA | E6: =IF(COUNTIFS(Registros!$A$2:$A$6000,"NP",Registros!$B$2:$B$6000,$A6)>0,1,0) | F6: =IF($E6=1,SUMIFS(Registros!$F$2:$F$6000,Registros!$A$2:$A$6000,"NP",Registros!$B$2:$B$6000,$A6),0) | G6: =IF(COUNTIFS(Registros!$A$2:$A$6000,"MOV",Registros!$B$2:$B$6000,$A6)>0,1,0) | H6: =IF($G6=1,SUMIFS(Registros!$F$2:$F$6000,Registros!$A$2:$A$6000,"MOV",Registros!$B$2:$B$6000,$A6),0) | I6: =IF(COUNTIFS(Registros!$A$2:$A$6000,"CS",Registros!$B$2:$B$6000,$A6)>0,1,0) | J6: =IF($I6=1,SUMIFS(Registros!$I$2:$I$6000,Registros!$A$2:$A$6000,"CS",Registros!$B$2:$B$6000,$A6),0) | K6: =IF(COUNTIFS(Winback!$K$2:$K$300,$D6)>0,1,0) | L6: =IF(AND($K6=1,LEFT($A6,3)="WB-"),SUMIFS(Winback!$D$2:$D$300,Winback!$K$2:$K$300,$D6),0) | M6: =IF(OR($E6=1,$G6=1,SUMIFS(Registros!$J$2:$J$6000,Registros!$B$2:$B$6000,$A6)>0),1,0) | N6: =IF($J6>0,1,IF(COUNTIFS(Registros!$A$2:$A$6000,"CS",Registros!$B$2:$B$6000,$A6,Registros!$K$2:$K$6000,"<>")>0,1,0)) | O6: =IF(AND($K6=1,$E6=0,$G6=0,$I6=0),"WINBACK",IF(AND($M6=1,$N6>0),"CONVERGENTE",IF($M6=1,"SOLO MÓVIL",IF($N6>0,"SOLO FIJO / INTERNET","SIN SERVICIOS")))) | P6: =IF($O6="WINBACK","Recuperar (winback)",IF($O6="CONVERGENTE","Upgrade / más líneas",IF($O6="SOLO MÓVIL","Ofrecer fijo + internet (FLBBTV)",IF($O6="SOLO FIJO / INTERNET","Ofrecer línea móvil Nextphone","Oferta completa (móvil + fijo + internet)")))) | Q6: =$F6+$H6+$L6 | R6: =IFERROR(VLOOKUP($A6,Registros!$B$2:$G$6000,6,0),IFERROR(VLOOKUP($D6,Winback!$B$2:$C$300,2,0),"")) | S6: =IF($E6=1,"NP","")&IF($G6=1,"+MOV","")&IF($I6=1,"+CS","")&IF($K6=1,"+WB","") | T6: =$E6+$G6+$I6+$K6
A7: 312235730000 | B7: 31223573 | C7: CORPORACION JEMS, S.A. -- | D7: CORPORACIONJEMSSA | E7: =IF(COUNTIFS(Registros!$A$2:$A$6000,"NP",Registros!$B$2:$B$6000,$A7)>0,1,0) | F7: =IF($E7=1,SUMIFS(Registros!$F$2:$F$6000,Registros!$A$2:$A$6000,"NP",Registros!$B$2:$B$6000,$A7),0) | G7: =IF(COUNTIFS(Registros!$A$2:$A$6000,"MOV",Registros!$B$2:$B$6000,$A7)>0,1,0) | H7: =IF($G7=1,SUMIFS(Registros!$F$2:$F$6000,Registros!$A$2:$A$6000,"MOV",Registros!$B$2:$B$6000,$A7),0) | I7: =IF(COUNTIFS(Registros!$A$2:$A$6000,"CS",Registros!$B$2:$B$6000,$A7)>0,1,0) | J7: =IF($I7=1,SUMIFS(Registros!$I$2:$I$6000,Registros!$A$2:$A$6000,"CS",Registros!$B$2:$B$6000,$A7),0) | K7: =IF(COUNTIFS(Winback!$K$2:$K$300,$D7)>0,1,0) | L7: =IF(AND($K7=1,LEFT($A7,3)="WB-"),SUMIFS(Winback!$D$2:$D$300,Winback!$K$2:$K$300,$D7),0) | M7: =IF(OR($E7=1,$G7=1,SUMIFS(Registros!$J$2:$J$6000,Registros!$B$2:$B$6000,$A7)>0),1,0) | N7: =IF($J7>0,1,IF(COUNTIFS(Registros!$A$2:$A$6000,"CS",Registros!$B$2:$B$6000,$A7,Registros!$K$2:$K$6000,"<>")>0,1,0)) | O7: =IF(AND($K7=1,$E7=0,$G7=0,$I7=0),"WINBACK",IF(AND($M7=1,$N7>0),"CONVERGENTE",IF($M7=1,"SOLO MÓVIL",IF($N7>0,"SOLO FIJO / INTERNET","SIN SERVICIOS")))) | P7: =IF($O7="WINBACK","Recuperar (winback)",IF($O7="CONVERGENTE","Upgrade / más líneas",IF($O7="SOLO MÓVIL","Ofrecer fijo + internet (FLBBTV)",IF($O7="SOLO FIJO / INTERNET","Ofrecer línea móvil Nextphone","Oferta completa (móvil + fijo + internet)")))) | Q7: =$F7+$H7+$L7 | R7: =IFERROR(VLOOKUP($A7,Registros!$B$2:$G$6000,6,0),IFERROR(VLOOKUP($D7,Winback!$B$2:$C$300,2,0),"")) | S7: =IF($E7=1,"NP","")&IF($G7=1,"+MOV","")&IF($I7=1,"+CS","")&IF($K7=1,"+WB","") | T7: =$E7+$G7+$I7+$K7
A8: 322504520000 | B8: 32250452 | C8: Ardines CPA Y Asociados Sa | D8: ARDINESCPAYASOCIADOSSA | E8: =IF(COUNTIFS(Registros!$A$2:$A$6000,"NP",Registros!$B$2:$B$6000,$A8)>0,1,0) | F8: =IF($E8=1,SUMIFS(Registros!$F$2:$F$6000,Registros!$A$2:$A$6000,"NP",Registros!$B$2:$B$6000,$A8),0) | G8: =IF(COUNTIFS(Registros!$A$2:$A$6000,"MOV",Registros!$B$2:$B$6000,$A8)>0,1,0) | H8: =IF($G8=1,SUMIFS(Registros!$F$2:$F$6000,Registros!$A$2:$A$6000,"MOV",Registros!$B$2:$B$6000,$A8),0) | I8: =IF(COUNTIFS(Registros!$A$2:$A$6000,"CS",Registros!$B$2:$B$6000,$A8)>0,1,0) | J8: =IF($I8=1,SUMIFS(Registros!$I$2:$I$6000,Registros!$A$2:$A$6000,"CS",Registros!$B$2:$B$6000,$A8),0) | K8: =IF(COUNTIFS(Winback!$K$2:$K$300,$D8)>0,1,0) | L8: =IF(AND($K8=1,LEFT($A8,3)="WB-"),SUMIFS(Winback!$D$2:$D$300,Winback!$K$2:$K$300,$D8),0) | M8: =IF(OR($E8=1,$G8=1,SUMIFS(Registros!$J$2:$J$6000,Registros!$B$2:$B$6000,$A8)>0),1,0) | N8: =IF($J8>0,1,IF(COUNTIFS(Registros!$A$2:$A$6000,"CS",Registros!$B$2:$B$6000,$A8,Registros!$K$2:$K$6000,"<>")>0,1,0)) | O8: =IF(AND($K8=1,$E8=0,$G8=0,$I8=0),"WINBACK",IF(AND($M8=1,$N8>0),"CONVERGENTE",IF($M8=1,"SOLO MÓVIL",IF($N8>0,"SOLO FIJO / INTERNET","SIN SERVICIOS")))) | P8: =IF($O8="WINBACK","Recuperar (winback)",IF($O8="CONVERGENTE","Upgrade / más líneas",IF($O8="SOLO MÓVIL","Ofrecer fijo + internet (FLBBTV)",IF($O8="SOLO FIJO / INTERNET","Ofrecer línea móvil Nextphone","Oferta completa (móvil + fijo + internet)")))) | Q8: =$F8+$H8+$L8 | R8: =IFERROR(VLOOKUP($A8,Registros!$B$2:$G$6000,6,0),IFERROR(VLOOKUP($D8,Winback!$B$2:$C$300,2,0),"")) | S8: =IF($E8=1,"NP","")&IF($G8=1,"+MOV","")&IF($I8=1,"+CS","")&IF($K8=1,"+WB","") | T8: =$E8+$G8+$I8+$K8
A9: 323672910000 | B9: 32367291 | C9: Ademar SA | D9: ADEMARSA | E9: =IF(COUNTIFS(Registros!$A$2:$A$6000,"NP",Registros!$B$2:$B$6000,$A9)>0,1,0) | F9: =IF($E9=1,SUMIFS(Registros!$F$2:$F$6000,Registros!$A$2:$A$6000,"NP",Registros!$B$2:$B$6000,$A9),0) | G9: =IF(COUNTIFS(Registros!$A$2:$A$6000,"MOV",Registros!$B$2:$B$6000,$A9)>0,1,0) | H9: =IF($G9=1,SUMIFS(Registros!$F$2:$F$6000,Registros!$A$2:$A$6000,"MOV",Registros!$B$2:$B$6000,$A9),0) | I9: =IF(COUNTIFS(Registros!$A$2:$A$6000,"CS",Registros!$B$2:$B$6000,$A9)>0,1,0) | J9: =IF($I9=1,SUMIFS(Registros!$I$2:$I$6000,Registros!$A$2:$A$6000,"CS",Registros!$B$2:$B$6000,$A9),0) | K9: =IF(COUNTIFS(Winback!$K$2:$K$300,$D9)>0,1,0) | L9: =IF(AND($K9=1,LEFT($A9,3)="WB-"),SUMIFS(Winback!$D$2:$D$300,Winback!$K$2:$K$300,$D9),0) | M9: =IF(OR($E9=1,$G9=1,SUMIFS(Registros!$J$2:$J$6000,Registros!$B$2:$B$6000,$A9)>0),1,0) | N9: =IF($J9>0,1,IF(COUNTIFS(Registros!$A$2:$A$6000,"CS",Registros!$B$2:$B$6000,$A9,Registros!$K$2:$K$6000,"<>")>0,1,0)) | O9: =IF(AND($K9=1,$E9=0,$G9=0,$I9=0),"WINBACK",IF(AND($M9=1,$N9>0),"CONVERGENTE",IF($M9=1,"SOLO MÓVIL",IF($N9>0,"SOLO FIJO / INTERNET","SIN SERVICIOS")))) | P9: =IF($O9="WINBACK","Recuperar (winback)",IF($O9="CONVERGENTE","Upgrade / más líneas",IF($O9="SOLO MÓVIL","Ofrecer fijo + internet (FLBBTV)",IF($O9="SOLO FIJO / INTERNET","Ofrecer línea móvil Nextphone","Oferta completa (móvil + fijo + internet)")))) | Q9: =$F9+$H9+$L9 | R9: =IFERROR(VLOOKUP($A9,Registros!$B$2:$G$6000,6,0),IFERROR(VLOOKUP($D9,Winback!$B$2:$C$300,2,0),"")) | S9: =IF($E9=1,"NP","")&IF($G9=1,"+MOV","")&IF($I9=1,"+CS","")&IF($K9=1,"+WB","") | T9: =$E9+$G9+$I9+$K9
A10: 349277210000 | B10: 34927721 | C10: SMART COMMUNICATIONS, SA | D10: SMARTCOMMUNICATIONSSA | E10: =IF(COUNTIFS(Registros!$A$2:$A$6000,"NP",Registros!$B$2:$B$6000,$A10)>0,1,0) | F10: =IF($E10=1,SUMIFS(Registros!$F$2:$F$6000,Registros!$A$2:$A$6000,"NP",Registros!$B$2:$B$6000,$A10),0) | G10: =IF(COUNTIFS(Registros!$A$2:$A$6000,"MOV",Registros!$B$2:$B$6000,$A10)>0,1,0) | H10: =IF($G10=1,SUMIFS(Registros!$F$2:$F$6000,Registros!$A$2:$A$6000,"MOV",Registros!$B$2:$B$6000,$A10),0) | I10: =IF(COUNTIFS(Registros!$A$2:$A$6000,"CS",Registros!$B$2:$B$6000,$A10)>0,1,0) | J10: =IF($I10=1,SUMIFS(Registros!$I$2:$I$6000,Registros!$A$2:$A$6000,"CS",Registros!$B$2:$B$6000,$A10),0) | K10: =IF(COUNTIFS(Winback!$K$2:$K$300,$D10)>0,1,0) | L10: =IF(AND($K10=1,LEFT($A10,3)="WB-"),SUMIFS(Winback!$D$2:$D$300,Winback!$K$2:$K$300,$D10),0) | M10: =IF(OR($E10=1,$G10=1,SUMIFS(Registros!$J$2:$J$6000,Registros!$B$2:$B$6000,$A10)>0),1,0) | N10: =IF($J10>0,1,IF(COUNTIFS(Registros!$A$2:$A$6000,"CS",Registros!$B$2:$B$6000,$A10,Registros!$K$2:$K$6000,"<>")>0,1,0)) | O10: =IF(AND($K10=1,$E10=0,$G10=0,$I10=0),"WINBACK",IF(AND($M10=1,$N10>0),"CONVERGENTE",IF($M10=1,"SOLO MÓVIL",IF($N10>0,"SOLO FIJO / INTERNET","SIN SERVICIOS")))) | P10: =IF($O10="WINBACK","Recuperar (winback)",IF($O10="CONVERGENTE","Upgrade / más líneas",IF($O10="SOLO MÓVIL","Ofrecer fijo + internet (FLBBTV)",IF($O10="SOLO FIJO / INTERNET","Ofrecer línea móvil Nextphone","Oferta completa (móvil + fijo + internet)")))) | Q10: =$F10+$H10+$L10 | R10: =IFERROR(VLOOKUP($A10,Registros!$B$2:$G$6000,6,0),IFERROR(VLOOKUP($D10,Winback!$B$2:$C$300,2,0),"")) | S10: =IF($E10=1,"NP","")&IF($G10=1,"+MOV","")&IF($I10=1,"+CS","")&IF($K10=1,"+WB","") | T10: =$E10+$G10+$I10+$K10
A11: 324167750000 | B11: 32416775 | C11: HACIENDA LOMA LINDA | D11: HACIENDALOMALINDA | E11: =IF(COUNTIFS(Registros!$A$2:$A$6000,"NP",Registros!$B$2:$B$6000,$A11)>0,1,0) | F11: =IF($E11=1,SUMIFS(Registros!$F$2:$F$6000,Registros!$A$2:$A$6000,"NP",Registros!$B$2:$B$6000,$A11),0) | G11: =IF(COUNTIFS(Registros!$A$2:$A$6000,"MOV",Registros!$B$2:$B$6000,$A11)>0,1,0) | H11: =IF($G11=1,SUMIFS(Registros!$F$2:$F$6000,Registros!$A$2:$A$6000,"MOV",Registros!$B$2:$B$6000,$A11),0) | I11: =IF(COUNTIFS(Registros!$A$2:$A$6000,"CS",Registros!$B$2:$B$6000,$A11)>0,1,0) | J11: =IF($I11=1,SUMIFS(Registros!$I$2:$I$6000,Registros!$A$2:$A$6000,"CS",Registros!$B$2:$B$6000,$A11),0) | K11: =IF(COUNTIFS(Winback!$K$2:$K$300,$D11)>0,1,0) | L11: =IF(AND($K11=1,LEFT($A11,3)="WB-"),SUMIFS(Winback!$D$2:$D$300,Winback!$K$2:$K$300,$D11),0) | M11: =IF(OR($E11=1,$G11=1,SUMIFS(Registros!$J$2:$J$6000,Registros!$B$2:$B$6000,$A11)>0),1,0) | N11: =IF($J11>0,1,IF(COUNTIFS(Registros!$A$2:$A$6000,"CS",Registros!$B$2:$B$6000,$A11,Registros!$K$2:$K$6000,"<>")>0,1,0)) | O11: =IF(AND($K11=1,$E11=0,$G11=0,$I11=0),"WINBACK",IF(AND($M11=1,$N11>0),"CONVERGENTE",IF($M11=1,"SOLO MÓVIL",IF($N11>0,"SOLO FIJO / INTERNET","SIN SERVICIOS")))) | P11: =IF($O11="WINBACK","Recuperar (winback)",IF($O11="CONVERGENTE","Upgrade / más líneas",IF($O11="SOLO MÓVIL","Ofrecer fijo + internet (FLBBTV)",IF($O11="SOLO FIJO / INTERNET","Ofrecer línea móvil Nextphone","Oferta completa (móvil + fijo + internet)")))) | Q11: =$F11+$H11+$L11 | R11: =IFERROR(VLOOKUP($A11,Registros!$B$2:$G$6000,6,0),IFERROR(VLOOKUP($D11,Winback!$B$2:$C$300,2,0),"")) | S11: =IF($E11=1,"NP","")&IF($G11=1,"+MOV","")&IF($I11=1,"+CS","")&IF($K11=1,"+WB","") | T11: =$E11+$G11+$I11+$K11
A12: 361003450000 | B12: 36100345 | C12: FERNANDO JOSE ARAUZ HERNANDEZ | D12: FERNANDOJOSEARAUZHERNANDEZ | E12: =IF(COUNTIFS(Registros!$A$2:$A$6000,"NP",Registros!$B$2:$B$6000,$A12)>0,1,0) | F12: =IF($E12=1,SUMIFS(Registros!$F$2:$F$6000,Registros!$A$2:$A$6000,"NP",Registros!$B$2:$B$6000,$A12),0) | G12: =IF(COUNTIFS(Registros!$A$2:$A$6000,"MOV",Registros!$B$2:$B$6000,$A12)>0,1,0) | H12: =IF($G12=1,SUMIFS(Registros!$F$2:$F$6000,Registros!$A$2:$A$6000,"MOV",Registros!$B$2:$B$6000,$A12),0) | I12: =IF(COUNTIFS(Registros!$A$2:$A$6000,"CS",Registros!$B$2:$B$6000,$A12)>0,1,0) | J12: =IF($I12=1,SUMIFS(Registros!$I$2:$I$6000,Registros!$A$2:$A$6000,"CS",Registros!$B$2:$B$6000,$A12),0) | K12: =IF(COUNTIFS(Winback!$K$2:$K$300,$D12)>0,1,0) | L12: =IF(AND($K12=1,LEFT($A12,3)="WB-"),SUMIFS(Winback!$D$2:$D$300,Winback!$K$2:$K$300,$D12),0) | M12: =IF(OR($E12=1,$G12=1,SUMIFS(Registros!$J$2:$J$6000,Registros!$B$2:$B$6000,$A12)>0),1,0) | N12: =IF($J12>0,1,IF(COUNTIFS(Registros!$A$2:$A$6000,"CS",Registros!$B$2:$B$6000,$A12,Registros!$K$2:$K$6000,"<>")>0,1,0)) | O12: =IF(AND($K12=1,$E12=0,$G12=0,$I12=0),"WINBACK",IF(AND($M12=1,$N12>0),"CONVERGENTE",IF($M12=1,"SOLO MÓVIL",IF($N12>0,"SOLO FIJO / INTERNET","SIN SERVICIOS")))) | P12: =IF($O12="WINBACK","Recuperar (winback)",IF($O12="CONVERGENTE","Upgrade / más líneas",IF($O12="SOLO MÓVIL","Ofrecer fijo + internet (FLBBTV)",IF($O12="SOLO FIJO / INTERNET","Ofrecer línea móvil Nextphone","Oferta completa (móvil + fijo + internet)")))) | Q12: =$F12+$H12+$L12 | R12: =IFERROR(VLOOKUP($A12,Registros!$B$2:$G$6000,6,0),IFERROR(VLOOKUP($D12,Winback!$B$2:$C$300,2,0),"")) | S12: =IF($E12=1,"NP","")&IF($G12=1,"+MOV","")&IF($I12=1,"+CS","")&IF($K12=1,"+WB","") | T12: =$E12+$G12+$I12+$K12
A13: 352329430000 | B13: 35232943 | C13: YDALIDES VALDES | D13: YDALIDESVALDES | E13: =IF(COUNTIFS(Registros!$A$2:$A$6000,"NP",Registros!$B$2:$B$6000,$A13)>0,1,0) | F13: =IF($E13=1,SUMIFS(Registros!$F$2:$F$6000,Registros!$A$2:$A$6000,"NP",Registros!$B$2:$B$6000,$A13),0) | G13: =IF(COUNTIFS(Registros!$A$2:$A$6000,"MOV",Registros!$B$2:$B$6000,$A13)>0,1,0) | H13: =IF($G13=1,SUMIFS(Registros!$F$2:$F$6000,Registros!$A$2:$A$6000,"MOV",Registros!$B$2:$B$6000,$A13),0) | I13: =IF(COUNTIFS(Registros!$A$2:$A$6000,"CS",Registros!$B$2:$B$6000,$A13)>0,1,0) | J13: =IF($I13=1,SUMIFS(Registros!$I$2:$I$6000,Registros!$A$2:$A$6000,"CS",Registros!$B$2:$B$6000,$A13),0) | K13: =IF(COUNTIFS(Winback!$K$2:$K$300,$D13)>0,1,0) | L13: =IF(AND($K13=1,LEFT($A13,3)="WB-"),SUMIFS(Winback!$D$2:$D$300,Winback!$K$2:$K$300,$D13),0) | M13: =IF(OR($E13=1,$G13=1,SUMIFS(Registros!$J$2:$J$6000,Registros!$B$2:$B$6000,$A13)>0),1,0) | N13: =IF($J13>0,1,IF(COUNTIFS(Registros!$A$2:$A$6000,"CS",Registros!$B$2:$B$6000,$A13,Registros!$K$2:$K$6000,"<>")>0,1,0)) | O13: =IF(AND($K13=1,$E13=0,$G13=0,$I13=0),"WINBACK",IF(AND($M13=1,$N13>0),"CONVERGENTE",IF($M13=1,"SOLO MÓVIL",IF($N13>0,"SOLO FIJO / INTERNET","SIN SERVICIOS")))) | P13: =IF($O13="WINBACK","Recuperar (winback)",IF($O13="CONVERGENTE","Upgrade / más líneas",IF($O13="SOLO MÓVIL","Ofrecer fijo + internet (FLBBTV)",IF($O13="SOLO FIJO / INTERNET","Ofrecer línea móvil Nextphone","Oferta completa (móvil + fijo + internet)")))) | Q13: =$F13+$H13+$L13 | R13: =IFERROR(VLOOKUP($A13,Registros!$B$2:$G$6000,6,0),IFERROR(VLOOKUP($D13,Winback!$B$2:$C$300,2,0),"")) | S13: =IF($E13=1,"NP","")&IF($G13=1,"+MOV","")&IF($I13=1,"+CS","")&IF($K13=1,"+WB","") | T13: =$E13+$G13+$I13+$K13
... A284: 367023820000 | B284: 36702382 | C284: JOSUE CORDOBA | D284: JOSUECORDOBA | E284: =IF(COUNTIFS(Registros!$A$2:$A$6000,"NP",Registros!$B$2:$B$6000,$A284)>0,1,0) | F284: =IF($E284=1,SUMIFS(Registros!$F$2:$F$6000,Registros!$A$2:$A$6000,"NP",Registros!$B$2:$B$6000,$A284),0) | G284: =IF(COUNTIFS(Registros!$A$2:$A$6000,"MOV",Registros!$B$2:$B$6000,$A284)>0,1,0) | H284: =IF($G284=1,SUMIFS(Registros!$F$2:$F$6000,Registros!$A$2:$A$6000,"MOV",Registros!$B$2:$B$6000,$A284),0) | I284: =IF(COUNTIFS(Registros!$A$2:$A$6000,"CS",Registros!$B$2:$B$6000,$A284)>0,1,0) | J284: =IF($I284=1,SUMIFS(Registros!$I$2:$I$6000,Registros!$A$2:$A$6000,"CS",Registros!$B$2:$B$6000,$A284),0) | K284: =IF(COUNTIFS(Winback!$K$2:$K$300,$D284)>0,1,0) | L284: =IF(AND($K284=1,LEFT($A284,3)="WB-"),SUMIFS(Winback!$D$2:$D$300,Winback!$K$2:$K$300,$D284),0) | M284: =IF(OR($E284=1,$G284=1,SUMIFS(Registros!$J$2:$J$6000,Registros!$B$2:$B$6000,$A284)>0),1,0) | N284: =IF($J284>0,1,IF(COUNTIFS(Registros!$A$2:$A$6000,"CS",Registros!$B$2:$B$6000,$A284,Registros!$K$2:$K$6000,"<>")>0,1,0)) | O284: =IF(AND($K284=1,$E284=0,$G284=0,$I284=0),"WINBACK",IF(AND($M284=1,$N284>0),"CONVERGENTE",IF($M284=1,"SOLO MÓVIL",IF($N284>0,"SOLO FIJO / INTERNET","SIN SERVICIOS")))) | P284: =IF($O284="WINBACK","Recuperar (winback)",IF($O284="CONVERGENTE","Upgrade / más líneas",IF($O284="SOLO MÓVIL","Ofrecer fijo + internet (FLBBTV)",IF($O284="SOLO FIJO / INTERNET","Ofrecer línea móvil Nextphone","Oferta completa (móvil + fijo + internet)")))) | Q284: =$F284+$H284+$L284 | R284: =IFERROR(VLOOKUP($A284,Registros!$B$2:$G$6000,6,0),IFERROR(VLOOKUP($D284,Winback!$B$2:$C$300,2,0),"")) | S284: =IF($E284=1,"NP","")&IF($G284=1,"+MOV","")&IF($I284=1,"+CS","")&IF($K284=1,"+WB","") | T284: =$E284+$G284+$I284+$K284
B285: 35828394 | C285: ELIGIO MOSQUERA BARCO | D285: ELIGIOMOSQUERABARCO | E285: =IF(COUNTIFS(Registros!$A$2:$A$6000,"NP",Registros!$B$2:$B$6000,$A285)>0,1,0) | F285: =IF($E285=1,SUMIFS(Registros!$F$2:$F$6000,Registros!$A$2:$A$6000,"NP",Registros!$B$2:$B$6000,$A285),0) | G285: =IF(COUNTIFS(Registros!$A$2:$A$6000,"MOV",Registros!$B$2:$B$6000,$A285)>0,1,0) | H285: =IF($G285=1,SUMIFS(Registros!$F$2:$F$6000,Registros!$A$2:$A$6000,"MOV",Registros!$B$2:$B$6000,$A285),0) | I285: =IF(COUNTIFS(Registros!$A$2:$A$6000,"CS",Registros!$B$2:$B$6000,$A285)>0,1,0) | J285: =IF($I285=1,SUMIFS(Registros!$I$2:$I$6000,Registros!$A$2:$A$6000,"CS",Registros!$B$2:$B$6000,$A285),0) | K285: =IF(COUNTIFS(Winback!$K$2:$K$300,$D285)>0,1,0) | L285: =IF(AND($K285=1,LEFT($A285,3)="WB-"),SUMIFS(Winback!$D$2:$D$300,Winback!$K$2:$K$300,$D285),0) | M285: =IF(OR($E285=1,$G285=1,SUMIFS(Registros!$J$2:$J$6000,Registros!$B$2:$B$6000,$A285)>0),1,0) | N285: =IF($J285>0,1,IF(COUNTIFS(Registros!$A$2:$A$6000,"CS",Registros!$B$2:$B$6000,$A285,Registros!$K$2:$K$6000,"<>")>0,1,0)) | O285: =IF(AND($K285=1,$E285=0,$G285=0,$I285=0),"WINBACK",IF(AND($M285=1,$N285>0),"CONVERGENTE",IF($M285=1,"SOLO MÓVIL",IF($N285>0,"SOLO FIJO / INTERNET","SIN SERVICIOS")))) | P285: =IF($O285="WINBACK","Recuperar (winback)",IF($O285="CONVERGENTE","Upgrade / más líneas",IF($O285="SOLO MÓVIL","Ofrecer fijo + internet (FLBBTV)",IF($O285="SOLO FIJO / INTERNET","Ofrecer línea móvil Nextphone","Oferta completa (móvil + fijo + internet)")))) | Q285: =$F285+$H285+$L285 | R285: =IFERROR(VLOOKUP($A285,Registros!$B$2:$G$6000,6,0),IFERROR(VLOOKUP($D285,Winback!$B$2:$C$300,2,0),"")) | S285: =IF($E285=1,"NP","")&IF($G285=1,"+MOV","")&IF($I285=1,"+CS","")&IF($K285=1,"+WB","") | T285: =$E285+$G285+$I285+$K285
A286: 355039520000 | B286: 35503952 | C286: PRISCILA MEDINA | D286: PRISCILAMEDINA | E286: =IF(COUNTIFS(Registros!$A$2:$A$6000,"NP",Registros!$B$2:$B$6000,$A286)>0,1,0) | F286: =IF($E286=1,SUMIFS(Registros!$F$2:$F$6000,Registros!$A$2:$A$6000,"NP",Registros!$B$2:$B$6000,$A286),0) | G286: =IF(COUNTIFS(Registros!$A$2:$A$6000,"MOV",Registros!$B$2:$B$6000,$A286)>0,1,0) | H286: =IF($G286=1,SUMIFS(Registros!$F$2:$F$6000,Registros!$A$2:$A$6000,"MOV",Registros!$B$2:$B$6000,$A286),0) | I286: =IF(COUNTIFS(Registros!$A$2:$A$6000,"CS",Registros!$B$2:$B$6000,$A286)>0,1,0) | J286: =IF($I286=1,SUMIFS(Registros!$I$2:$I$6000,Registros!$A$2:$A$6000,"CS",Registros!$B$2:$B$6000,$A286),0) | K286: =IF(COUNTIFS(Winback!$K$2:$K$300,$D286)>0,1,0) | L286: =IF(AND($K286=1,LEFT($A286,3)="WB-"),SUMIFS(Winback!$D$2:$D$300,Winback!$K$2:$K$300,$D286),0) | M286: =IF(OR($E286=1,$G286=1,SUMIFS(Registros!$J$2:$J$6000,Registros!$B$2:$B$6000,$A286)>0),1,0) | N286: =IF($J286>0,1,IF(COUNTIFS(Registros!$A$2:$A$6000,"CS",Registros!$B$2:$B$6000,$A286,Registros!$K$2:$K$6000,"<>")>0,1,0)) | O286: =IF(AND($K286=1,$E286=0,$G286=0,$I286=0),"WINBACK",IF(AND($M286=1,$N286>0),"CONVERGENTE",IF($M286=1,"SOLO MÓVIL",IF($N286>0,"SOLO FIJO / INTERNET","SIN SERVICIOS")))) | P286: =IF($O286="WINBACK","Recuperar (winback)",IF($O286="CONVERGENTE","Upgrade / más líneas",IF($O286="SOLO MÓVIL","Ofrecer fijo + internet (FLBBTV)",IF($O286="SOLO FIJO / INTERNET","Ofrecer línea móvil Nextphone","Oferta completa (móvil + fijo + internet)")))) | Q286: =$F286+$H286+$L286 | R286: =IFERROR(VLOOKUP($A286,Registros!$B$2:$G$6000,6,0),IFERROR(VLOOKUP($D286,Winback!$B$2:$C$300,2,0),"")) | S286: =IF($E286=1,"NP","")&IF($G286=1,"+MOV","")&IF($I286=1,"+CS","")&IF($K286=1,"+WB","") | T286: =$E286+$G286+$I286+$K286
A287: 351246120000 | B287: 35124612 | C287: NORBERTO VELANCIA | D287: NORBERTOVELANCIA | E287: =IF(COUNTIFS(Registros!$A$2:$A$6000,"NP",Registros!$B$2:$B$6000,$A287)>0,1,0) | F287: =IF($E287=1,SUMIFS(Registros!$F$2:$F$6000,Registros!$A$2:$A$6000,"NP",Registros!$B$2:$B$6000,$A287),0) | G287: =IF(COUNTIFS(Registros!$A$2:$A$6000,"MOV",Registros!$B$2:$B$6000,$A287)>0,1,0) | H287: =IF($G287=1,SUMIFS(Registros!$F$2:$F$6000,Registros!$A$2:$A$6000,"MOV",Registros!$B$2:$B$6000,$A287),0) | I287: =IF(COUNTIFS(Registros!$A$2:$A$6000,"CS",Registros!$B$2:$B$6000,$A287)>0,1,0) | J287: =IF($I287=1,SUMIFS(Registros!$I$2:$I$6000,Registros!$A$2:$A$6000,"CS",Registros!$B$2:$B$6000,$A287),0) | K287: =IF(COUNTIFS(Winback!$K$2:$K$300,$D287)>0,1,0) | L287: =IF(AND($K287=1,LEFT($A287,3)="WB-"),SUMIFS(Winback!$D$2:$D$300,Winback!$K$2:$K$300,$D287),0) | M287: =IF(OR($E287=1,$G287=1,SUMIFS(Registros!$J$2:$J$6000,Registros!$B$2:$B$6000,$A287)>0),1,0) | N287: =IF($J287>0,1,IF(COUNTIFS(Registros!$A$2:$A$6000,"CS",Registros!$B$2:$B$6000,$A287,Registros!$K$2:$K$6000,"<>")>0,1,0)) | O287: =IF(AND($K287=1,$E287=0,$G287=0,$I287=0),"WINBACK",IF(AND($M287=1,$N287>0),"CONVERGENTE",IF($M287=1,"SOLO MÓVIL",IF($N287>0,"SOLO FIJO / INTERNET","SIN SERVICIOS")))) | P287: =IF($O287="WINBACK","Recuperar (winback)",IF($O287="CONVERGENTE","Upgrade / más líneas",IF($O287="SOLO MÓVIL","Ofrecer fijo + internet (FLBBTV)",IF($O287="SOLO FIJO / INTERNET","Ofrecer línea móvil Nextphone","Oferta completa (móvil + fijo + internet)")))) | Q287: =$F287+$H287+$L287 | R287: =IFERROR(VLOOKUP($A287,Registros!$B$2:$G$6000,6,0),IFERROR(VLOOKUP($D287,Winback!$B$2:$C$300,2,0),"")) | S287: =IF($E287=1,"NP","")&IF($G287=1,"+MOV","")&IF($I287=1,"+CS","")&IF($K287=1,"+WB","") | T287: =$E287+$G287+$I287+$K287
A288: 357364020000 | B288: 35736402 | C288: DAVID REYES | D288: DAVIDREYES | E288: =IF(COUNTIFS(Registros!$A$2:$A$6000,"NP",Registros!$B$2:$B$6000,$A288)>0,1,0) | F288: =IF($E288=1,SUMIFS(Registros!$F$2:$F$6000,Registros!$A$2:$A$6000,"NP",Registros!$B$2:$B$6000,$A288),0) | G288: =IF(COUNTIFS(Registros!$A$2:$A$6000,"MOV",Registros!$B$2:$B$6000,$A288)>0,1,0) | H288: =IF($G288=1,SUMIFS(Registros!$F$2:$F$6000,Registros!$A$2:$A$6000,"MOV",Registros!$B$2:$B$6000,$A288),0) | I288: =IF(COUNTIFS(Registros!$A$2:$A$6000,"CS",Registros!$B$2:$B$6000,$A288)>0,1,0) | J288: =IF($I288=1,SUMIFS(Registros!$I$2:$I$6000,Registros!$A$2:$A$6000,"CS",Registros!$B$2:$B$6000,$A288),0) | K288: =IF(COUNTIFS(Winback!$K$2:$K$300,$D288)>0,1,0) | L288: =IF(AND($K288=1,LEFT($A288,3)="WB-"),SUMIFS(Winback!$D$2:$D$300,Winback!$K$2:$K$300,$D288),0) | M288: =IF(OR($E288=1,$G288=1,SUMIFS(Registros!$J$2:$J$6000,Registros!$B$2:$B$6000,$A288)>0),1,0) | N288: =IF($J288>0,1,IF(COUNTIFS(Registros!$A$2:$A$6000,"CS",Registros!$B$2:$B$6000,$A288,Registros!$K$2:$K$6000,"<>")>0,1,0)) | O288: =IF(AND($K288=1,$E288=0,$G288=0,$I288=0),"WINBACK",IF(AND($M288=1,$N288>0),"CONVERGENTE",IF($M288=1,"SOLO MÓVIL",IF($N288>0,"SOLO FIJO / INTERNET","SIN SERVICIOS")))) | P288: =IF($O288="WINBACK","Recuperar (winback)",IF($O288="CONVERGENTE","Upgrade / más líneas",IF($O288="SOLO MÓVIL","Ofrecer fijo + internet (FLBBTV)",IF($O288="SOLO FIJO / INTERNET","Ofrecer línea móvil Nextphone","Oferta completa (móvil + fijo + internet)")))) | Q288: =$F288+$H288+$L288 | R288: =IFERROR(VLOOKUP($A288,Registros!$B$2:$G$6000,6,0),IFERROR(VLOOKUP($D288,Winback!$B$2:$C$300,2,0),"")) | S288: =IF($E288=1,"NP","")&IF($G288=1,"+MOV","")&IF($I288=1,"+CS","")&IF($K288=1,"+WB","") | T288: =$E288+$G288+$I288+$K288
A289: 356149210000 | B289: 35614921 | C289: NILVA MIGDALIA RIVAS ESPINOZA | D289: NILVAMIGDALIARIVASESPINOZA | E289: =IF(COUNTIFS(Registros!$A$2:$A$6000,"NP",Registros!$B$2:$B$6000,$A289)>0,1,0) | F289: =IF($E289=1,SUMIFS(Registros!$F$2:$F$6000,Registros!$A$2:$A$6000,"NP",Registros!$B$2:$B$6000,$A289),0) | G289: =IF(COUNTIFS(Registros!$A$2:$A$6000,"MOV",Registros!$B$2:$B$6000,$A289)>0,1,0) | H289: =IF($G289=1,SUMIFS(Registros!$F$2:$F$6000,Registros!$A$2:$A$6000,"MOV",Registros!$B$2:$B$6000,$A289),0) | I289: =IF(COUNTIFS(Registros!$A$2:$A$6000,"CS",Registros!$B$2:$B$6000,$A289)>0,1,0) | J289: =IF($I289=1,SUMIFS(Registros!$I$2:$I$6000,Registros!$A$2:$A$6000,"CS",Registros!$B$2:$B$6000,$A289),0) | K289: =IF(COUNTIFS(Winback!$K$2:$K$300,$D289)>0,1,0) | L289: =IF(AND($K289=1,LEFT($A289,3)="WB-"),SUMIFS(Winback!$D$2:$D$300,Winback!$K$2:$K$300,$D289),0) | M289: =IF(OR($E289=1,$G289=1,SUMIFS(Registros!$J$2:$J$6000,Registros!$B$2:$B$6000,$A289)>0),1,0) | N289: =IF($J289>0,1,IF(COUNTIFS(Registros!$A$2:$A$6000,"CS",Registros!$B$2:$B$6000,$A289,Registros!$K$2:$K$6000,"<>")>0,1,0)) | O289: =IF(AND($K289=1,$E289=0,$G289=0,$I289=0),"WINBACK",IF(AND($M289=1,$N289>0),"CONVERGENTE",IF($M289=1,"SOLO MÓVIL",IF($N289>0,"SOLO FIJO / INTERNET","SIN SERVICIOS")))) | P289: =IF($O289="WINBACK","Recuperar (winback)",IF($O289="CONVERGENTE","Upgrade / más líneas",IF($O289="SOLO MÓVIL","Ofrecer fijo + internet (FLBBTV)",IF($O289="SOLO FIJO / INTERNET","Ofrecer línea móvil Nextphone","Oferta completa (móvil + fijo + internet)")))) | Q289: =$F289+$H289+$L289 | R289: =IFERROR(VLOOKUP($A289,Registros!$B$2:$G$6000,6,0),IFERROR(VLOOKUP($D289,Winback!$B$2:$C$300,2,0),"")) | S289: =IF($E289=1,"NP","")&IF($G289=1,"+MOV","")&IF($I289=1,"+CS","")&IF($K289=1,"+WB","") | T289: =$E289+$G289+$I289+$K289
A290: 356118310000 | B290: 35611831 | C290: DAIHANA DE LA ROSA | D290: DAIHANADELAROSA | E290: =IF(COUNTIFS(Registros!$A$2:$A$6000,"NP",Registros!$B$2:$B$6000,$A290)>0,1,0) | F290: =IF($E290=1,SUMIFS(Registros!$F$2:$F$6000,Registros!$A$2:$A$6000,"NP",Registros!$B$2:$B$6000,$A290),0) | G290: =IF(COUNTIFS(Registros!$A$2:$A$6000,"MOV",Registros!$B$2:$B$6000,$A290)>0,1,0) | H290: =IF($G290=1,SUMIFS(Registros!$F$2:$F$6000,Registros!$A$2:$A$6000,"MOV",Registros!$B$2:$B$6000,$A290),0) | I290: =IF(COUNTIFS(Registros!$A$2:$A$6000,"CS",Registros!$B$2:$B$6000,$A290)>0,1,0) | J290: =IF($I290=1,SUMIFS(Registros!$I$2:$I$6000,Registros!$A$2:$A$6000,"CS",Registros!$B$2:$B$6000,$A290),0) | K290: =IF(COUNTIFS(Winback!$K$2:$K$300,$D290)>0,1,0) | L290: =IF(AND($K290=1,LEFT($A290,3)="WB-"),SUMIFS(Winback!$D$2:$D$300,Winback!$K$2:$K$300,$D290),0) | M290: =IF(OR($E290=1,$G290=1,SUMIFS(Registros!$J$2:$J$6000,Registros!$B$2:$B$6000,$A290)>0),1,0) | N290: =IF($J290>0,1,IF(COUNTIFS(Registros!$A$2:$A$6000,"CS",Registros!$B$2:$B$6000,$A290,Registros!$K$2:$K$6000,"<>")>0,1,0)) | O290: =IF(AND($K290=1,$E290=0,$G290=0,$I290=0),"WINBACK",IF(AND($M290=1,$N290>0),"CONVERGENTE",IF($M290=1,"SOLO MÓVIL",IF($N290>0,"SOLO FIJO / INTERNET","SIN SERVICIOS")))) | P290: =IF($O290="WINBACK","Recuperar (winback)",IF($O290="CONVERGENTE","Upgrade / más líneas",IF($O290="SOLO MÓVIL","Ofrecer fijo + internet (FLBBTV)",IF($O290="SOLO FIJO / INTERNET","Ofrecer línea móvil Nextphone","Oferta completa (móvil + fijo + internet)")))) | Q290: =$F290+$H290+$L290 | R290: =IFERROR(VLOOKUP($A290,Registros!$B$2:$G$6000,6,0),IFERROR(VLOOKUP($D290,Winback!$B$2:$C$300,2,0),"")) | S290: =IF($E290=1,"NP","")&IF($G290=1,"+MOV","")&IF($I290=1,"+CS","")&IF($K290=1,"+WB","") | T290: =$E290+$G290+$I290+$K290
A291: 349331440000 | B291: 34933144 | C291: ARNALDO LOPEZ | D291: ARNALDOLOPEZ | E291: =IF(COUNTIFS(Registros!$A$2:$A$6000,"NP",Registros!$B$2:$B$6000,$A291)>0,1,0) | F291: =IF($E291=1,SUMIFS(Registros!$F$2:$F$6000,Registros!$A$2:$A$6000,"NP",Registros!$B$2:$B$6000,$A291),0) | G291: =IF(COUNTIFS(Registros!$A$2:$A$6000,"MOV",Registros!$B$2:$B$6000,$A291)>0,1,0) | H291: =IF($G291=1,SUMIFS(Registros!$F$2:$F$6000,Registros!$A$2:$A$6000,"MOV",Registros!$B$2:$B$6000,$A291),0) | I291: =IF(COUNTIFS(Registros!$A$2:$A$6000,"CS",Registros!$B$2:$B$6000,$A291)>0,1,0) | J291: =IF($I291=1,SUMIFS(Registros!$I$2:$I$6000,Registros!$A$2:$A$6000,"CS",Registros!$B$2:$B$6000,$A291),0) | K291: =IF(COUNTIFS(Winback!$K$2:$K$300,$D291)>0,1,0) | L291: =IF(AND($K291=1,LEFT($A291,3)="WB-"),SUMIFS(Winback!$D$2:$D$300,Winback!$K$2:$K$300,$D291),0) | M291: =IF(OR($E291=1,$G291=1,SUMIFS(Registros!$J$2:$J$6000,Registros!$B$2:$B$6000,$A291)>0),1,0) | N291: =IF($J291>0,1,IF(COUNTIFS(Registros!$A$2:$A$6000,"CS",Registros!$B$2:$B$6000,$A291,Registros!$K$2:$K$6000,"<>")>0,1,0)) | O291: =IF(AND($K291=1,$E291=0,$G291=0,$I291=0),"WINBACK",IF(AND($M291=1,$N291>0),"CONVERGENTE",IF($M291=1,"SOLO MÓVIL",IF($N291>0,"SOLO FIJO / INTERNET","SIN SERVICIOS")))) | P291: =IF($O291="WINBACK","Recuperar (winback)",IF($O291="CONVERGENTE","Upgrade / más líneas",IF($O291="SOLO MÓVIL","Ofrecer fijo + internet (FLBBTV)",IF($O291="SOLO FIJO / INTERNET","Ofrecer línea móvil Nextphone","Oferta completa (móvil + fijo + internet)")))) | Q291: =$F291+$H291+$L291 | R291: =IFERROR(VLOOKUP($A291,Registros!$B$2:$G$6000,6,0),IFERROR(VLOOKUP($D291,Winback!$B$2:$C$300,2,0),"")) | S291: =IF($E291=1,"NP","")&IF($G291=1,"+MOV","")&IF($I291=1,"+CS","")&IF($K291=1,"+WB","") | T291: =$E291+$G291+$I291+$K291
A292: 355130350000 | B292: 35513035 | C292: DISMA TOCAMO | D292: DISMATOCAMO | E292: =IF(COUNTIFS(Registros!$A$2:$A$6000,"NP",Registros!$B$2:$B$6000,$A292)>0,1,0) | F292: =IF($E292=1,SUMIFS(Registros!$F$2:$F$6000,Registros!$A$2:$A$6000,"NP",Registros!$B$2:$B$6000,$A292),0) | G292: =IF(COUNTIFS(Registros!$A$2:$A$6000,"MOV",Registros!$B$2:$B$6000,$A292)>0,1,0) | H292: =IF($G292=1,SUMIFS(Registros!$F$2:$F$6000,Registros!$A$2:$A$6000,"MOV",Registros!$B$2:$B$6000,$A292),0) | I292: =IF(COUNTIFS(Registros!$A$2:$A$6000,"CS",Registros!$B$2:$B$6000,$A292)>0,1,0) | J292: =IF($I292=1,SUMIFS(Registros!$I$2:$I$6000,Registros!$A$2:$A$6000,"CS",Registros!$B$2:$B$6000,$A292),0) | K292: =IF(COUNTIFS(Winback!$K$2:$K$300,$D292)>0,1,0) | L292: =IF(AND($K292=1,LEFT($A292,3)="WB-"),SUMIFS(Winback!$D$2:$D$300,Winback!$K$2:$K$300,$D292),0) | M292: =IF(OR($E292=1,$G292=1,SUMIFS(Registros!$J$2:$J$6000,Registros!$B$2:$B$6000,$A292)>0),1,0) | N292: =IF($J292>0,1,IF(COUNTIFS(Registros!$A$2:$A$6000,"CS",Registros!$B$2:$B$6000,$A292,Registros!$K$2:$K$6000,"<>")>0,1,0)) | O292: =IF(AND($K292=1,$E292=0,$G292=0,$I292=0),"WINBACK",IF(AND($M292=1,$N292>0),"CONVERGENTE",IF($M292=1,"SOLO MÓVIL",IF($N292>0,"SOLO FIJO / INTERNET","SIN SERVICIOS")))) | P292: =IF($O292="WINBACK","Recuperar (winback)",IF($O292="CONVERGENTE","Upgrade / más líneas",IF($O292="SOLO MÓVIL","Ofrecer fijo + internet (FLBBTV)",IF($O292="SOLO FIJO / INTERNET","Ofrecer línea móvil Nextphone","Oferta completa (móvil + fijo + internet)")))) | Q292: =$F292+$H292+$L292 | R292: =IFERROR(VLOOKUP($A292,Registros!$B$2:$G$6000,6,0),IFERROR(VLOOKUP($D292,Winback!$B$2:$C$300,2,0),"")) | S292: =IF($E292=1,"NP","")&IF($G292=1,"+MOV","")&IF($I292=1,"+CS","")&IF($K292=1,"+WB","") | T292: =$E292+$G292+$I292+$K292
A293: 364037000000 | B293: 36403700 | C293: LIANNE SHERILL PINEDA MOSQUERA | D293: LIANNESHERILLPINEDAMOSQUERA | E293: =IF(COUNTIFS(Registros!$A$2:$A$6000,"NP",Registros!$B$2:$B$6000,$A293)>0,1,0) | F293: =IF($E293=1,SUMIFS(Registros!$F$2:$F$6000,Registros!$A$2:$A$6000,"NP",Registros!$B$2:$B$6000,$A293),0) | G293: =IF(COUNTIFS(Registros!$A$2:$A$6000,"MOV",Registros!$B$2:$B$6000,$A293)>0,1,0) | H293: =IF($G293=1,SUMIFS(Registros!$F$2:$F$6000,Registros!$A$2:$A$6000,"MOV",Registros!$B$2:$B$6000,$A293),0) | I293: =IF(COUNTIFS(Registros!$A$2:$A$6000,"CS",Registros!$B$2:$B$6000,$A293)>0,1,0) | J293: =IF($I293=1,SUMIFS(Registros!$I$2:$I$6000,Registros!$A$2:$A$6000,"CS",Registros!$B$2:$B$6000,$A293),0) | K293: =IF(COUNTIFS(Winback!$K$2:$K$300,$D293)>0,1,0) | L293: =IF(AND($K293=1,LEFT($A293,3)="WB-"),SUMIFS(Winback!$D$2:$D$300,Winback!$K$2:$K$300,$D293),0) | M293: =IF(OR($E293=1,$G293=1,SUMIFS(Registros!$J$2:$J$6000,Registros!$B$2:$B$6000,$A293)>0),1,0) | N293: =IF($J293>0,1,IF(COUNTIFS(Registros!$A$2:$A$6000,"CS",Registros!$B$2:$B$6000,$A293,Registros!$K$2:$K$6000,"<>")>0,1,0)) | O293: =IF(AND($K293=1,$E293=0,$G293=0,$I293=0),"WINBACK",IF(AND($M293=1,$N293>0),"CONVERGENTE",IF($M293=1,"SOLO MÓVIL",IF($N293>0,"SOLO FIJO / INTERNET","SIN SERVICIOS")))) | P293: =IF($O293="WINBACK","Recuperar (winback)",IF($O293="CONVERGENTE","Upgrade / más líneas",IF($O293="SOLO MÓVIL","Ofrecer fijo + internet (FLBBTV)",IF($O293="SOLO FIJO / INTERNET","Ofrecer línea móvil Nextphone","Oferta completa (móvil + fijo + internet)")))) | Q293: =$F293+$H293+$L293 | R293: =IFERROR(VLOOKUP($A293,Registros!$B$2:$G$6000,6,0),IFERROR(VLOOKUP($D293,Winback!$B$2:$C$300,2,0),"")) | S293: =IF($E293=1,"NP","")&IF($G293=1,"+MOV","")&IF($I293=1,"+CS","")&IF($K293=1,"+WB","") | T293: =$E293+$G293+$I293+$K293
A294: 347400570000 | B294: 34740057 | C294: DAYANIS DIMAS | D294: DAYANISDIMAS | E294: =IF(COUNTIFS(Registros!$A$2:$A$6000,"NP",Registros!$B$2:$B$6000,$A294)>0,1,0) | F294: =IF($E294=1,SUMIFS(Registros!$F$2:$F$6000,Registros!$A$2:$A$6000,"NP",Registros!$B$2:$B$6000,$A294),0) | G294: =IF(COUNTIFS(Registros!$A$2:$A$6000,"MOV",Registros!$B$2:$B$6000,$A294)>0,1,0) | H294: =IF($G294=1,SUMIFS(Registros!$F$2:$F$6000,Registros!$A$2:$A$6000,"MOV",Registros!$B$2:$B$6000,$A294),0) | I294: =IF(COUNTIFS(Registros!$A$2:$A$6000,"CS",Registros!$B$2:$B$6000,$A294)>0,1,0) | J294: =IF($I294=1,SUMIFS(Registros!$I$2:$I$6000,Registros!$A$2:$A$6000,"CS",Registros!$B$2:$B$6000,$A294),0) | K294: =IF(COUNTIFS(Winback!$K$2:$K$300,$D294)>0,1,0) | L294: =IF(AND($K294=1,LEFT($A294,3)="WB-"),SUMIFS(Winback!$D$2:$D$300,Winback!$K$2:$K$300,$D294),0) | M294: =IF(OR($E294=1,$G294=1,SUMIFS(Registros!$J$2:$J$6000,Registros!$B$2:$B$6000,$A294)>0),1,0) | N294: =IF($J294>0,1,IF(COUNTIFS(Registros!$A$2:$A$6000,"CS",Registros!$B$2:$B$6000,$A294,Registros!$K$2:$K$6000,"<>")>0,1,0)) | O294: =IF(AND($K294=1,$E294=0,$G294=0,$I294=0),"WINBACK",IF(AND($M294=1,$N294>0),"CONVERGENTE",IF($M294=1,"SOLO MÓVIL",IF($N294>0,"SOLO FIJO / INTERNET","SIN SERVICIOS")))) | P294: =IF($O294="WINBACK","Recuperar (winback)",IF($O294="CONVERGENTE","Upgrade / más líneas",IF($O294="SOLO MÓVIL","Ofrecer fijo + internet (FLBBTV)",IF($O294="SOLO FIJO / INTERNET","Ofrecer línea móvil Nextphone","Oferta completa (móvil + fijo + internet)")))) | Q294: =$F294+$H294+$L294 | R294: =IFERROR(VLOOKUP($A294,Registros!$B$2:$G$6000,6,0),IFERROR(VLOOKUP($D294,Winback!$B$2:$C$300,2,0),"")) | S294: =IF($E294=1,"NP","")&IF($G294=1,"+MOV","")&IF($I294=1,"+CS","")&IF($K294=1,"+WB","") | T294: =$E294+$G294+$I294+$K294
A295: 341182820000 | B295: 34118282 | C295: ELIDIA PERALTA | D295: ELIDIAPERALTA | E295: =IF(COUNTIFS(Registros!$A$2:$A$6000,"NP",Registros!$B$2:$B$6000,$A295)>0,1,0) | F295: =IF($E295=1,SUMIFS(Registros!$F$2:$F$6000,Registros!$A$2:$A$6000,"NP",Registros!$B$2:$B$6000,$A295),0) | G295: =IF(COUNTIFS(Registros!$A$2:$A$6000,"MOV",Registros!$B$2:$B$6000,$A295)>0,1,0) | H295: =IF($G295=1,SUMIFS(Registros!$F$2:$F$6000,Registros!$A$2:$A$6000,"MOV",Registros!$B$2:$B$6000,$A295),0) | I295: =IF(COUNTIFS(Registros!$A$2:$A$6000,"CS",Registros!$B$2:$B$6000,$A295)>0,1,0) | J295: =IF($I295=1,SUMIFS(Registros!$I$2:$I$6000,Registros!$A$2:$A$6000,"CS",Registros!$B$2:$B$6000,$A295),0) | K295: =IF(COUNTIFS(Winback!$K$2:$K$300,$D295)>0,1,0) | L295: =IF(AND($K295=1,LEFT($A295,3)="WB-"),SUMIFS(Winback!$D$2:$D$300,Winback!$K$2:$K$300,$D295),0) | M295: =IF(OR($E295=1,$G295=1,SUMIFS(Registros!$J$2:$J$6000,Registros!$B$2:$B$6000,$A295)>0),1,0) | N295: =IF($J295>0,1,IF(COUNTIFS(Registros!$A$2:$A$6000,"CS",Registros!$B$2:$B$6000,$A295,Registros!$K$2:$K$6000,"<>")>0,1,0)) | O295: =IF(AND($K295=1,$E295=0,$G295=0,$I295=0),"WINBACK",IF(AND($M295=1,$N295>0),"CONVERGENTE",IF($M295=1,"SOLO MÓVIL",IF($N295>0,"SOLO FIJO / INTERNET","SIN SERVICIOS")))) | P295: =IF($O295="WINBACK","Recuperar (winback)",IF($O295="CONVERGENTE","Upgrade / más líneas",IF($O295="SOLO MÓVIL","Ofrecer fijo + internet (FLBBTV)",IF($O295="SOLO FIJO / INTERNET","Ofrecer línea móvil Nextphone","Oferta completa (móvil + fijo + internet)")))) | Q295: =$F295+$H295+$L295 | R295: =IFERROR(VLOOKUP($A295,Registros!$B$2:$G$6000,6,0),IFERROR(VLOOKUP($D295,Winback!$B$2:$C$300,2,0),"")) | S295: =IF($E295=1,"NP","")&IF($G295=1,"+MOV","")&IF($I295=1,"+CS","")&IF($K295=1,"+WB","") | T295: =$E295+$G295+$I295+$K295
A296: 337275680000 | B296: 33727568 | C296: THE ENGLISH LANGUAGE CENTER, INC. | D296: THEENGLISHLANGUAGECENTERINC | E296: =IF(COUNTIFS(Registros!$A$2:$A$6000,"NP",Registros!$B$2:$B$6000,$A296)>0,1,0) | F296: =IF($E296=1,SUMIFS(Registros!$F$2:$F$6000,Registros!$A$2:$A$6000,"NP",Registros!$B$2:$B$6000,$A296),0) | G296: =IF(COUNTIFS(Registros!$A$2:$A$6000,"MOV",Registros!$B$2:$B$6000,$A296)>0,1,0) | H296: =IF($G296=1,SUMIFS(Registros!$F$2:$F$6000,Registros!$A$2:$A$6000,"MOV",Registros!$B$2:$B$6000,$A296),0) | I296: =IF(COUNTIFS(Registros!$A$2:$A$6000,"CS",Registros!$B$2:$B$6000,$A296)>0,1,0) | J296: =IF($I296=1,SUMIFS(Registros!$I$2:$I$6000,Registros!$A$2:$A$6000,"CS",Registros!$B$2:$B$6000,$A296),0) | K296: =IF(COUNTIFS(Winback!$K$2:$K$300,$D296)>0,1,0) | L296: =IF(AND($K296=1,LEFT($A296,3)="WB-"),SUMIFS(Winback!$D$2:$D$300,Winback!$K$2:$K$300,$D296),0) | M296: =IF(OR($E296=1,$G296=1,SUMIFS(Registros!$J$2:$J$6000,Registros!$B$2:$B$6000,$A296)>0),1,0) | N296: =IF($J296>0,1,IF(COUNTIFS(Registros!$A$2:$A$6000,"CS",Registros!$B$2:$B$6000,$A296,Registros!$K$2:$K$6000,"<>")>0,1,0)) | O296: =IF(AND($K296=1,$E296=0,$G296=0,$I296=0),"WINBACK",IF(AND($M296=1,$N296>0),"CONVERGENTE",IF($M296=1,"SOLO MÓVIL",IF($N296>0,"SOLO FIJO / INTERNET","SIN SERVICIOS")))) | P296: =IF($O296="WINBACK","Recuperar (winback)",IF($O296="CONVERGENTE","Upgrade / más líneas",IF($O296="SOLO MÓVIL","Ofrecer fijo + internet (FLBBTV)",IF($O296="SOLO FIJO / INTERNET","Ofrecer línea móvil Nextphone","Oferta completa (móvil + fijo + internet)")))) | Q296: =$F296+$H296+$L296 | R296: =IFERROR(VLOOKUP($A296,Registros!$B$2:$G$6000,6,0),IFERROR(VLOOKUP($D296,Winback!$B$2:$C$300,2,0),"")) | S296: =IF($E296=1,"NP","")&IF($G296=1,"+MOV","")&IF($I296=1,"+CS","")&IF($K296=1,"+WB","") | T296: =$E296+$G296+$I296+$K296
A297: 344330260000 | B297: 34433026 | C297: ISMILDA VICTORIA LOPEZ PALACIOS | D297: ISMILDAVICTORIALOPEZPALACIOS | E297: =IF(COUNTIFS(Registros!$A$2:$A$6000,"NP",Registros!$B$2:$B$6000,$A297)>0,1,0) | F297: =IF($E297=1,SUMIFS(Registros!$F$2:$F$6000,Registros!$A$2:$A$6000,"NP",Registros!$B$2:$B$6000,$A297),0) | G297: =IF(COUNTIFS(Registros!$A$2:$A$6000,"MOV",Registros!$B$2:$B$6000,$A297)>0,1,0) | H297: =IF($G297=1,SUMIFS(Registros!$F$2:$F$6000,Registros!$A$2:$A$6000,"MOV",Registros!$B$2:$B$6000,$A297),0) | I297: =IF(COUNTIFS(Registros!$A$2:$A$6000,"CS",Registros!$B$2:$B$6000,$A297)>0,1,0) | J297: =IF($I297=1,SUMIFS(Registros!$I$2:$I$6000,Registros!$A$2:$A$6000,"CS",Registros!$B$2:$B$6000,$A297),0) | K297: =IF(COUNTIFS(Winback!$K$2:$K$300,$D297)>0,1,0) | L297: =IF(AND($K297=1,LEFT($A297,3)="WB-"),SUMIFS(Winback!$D$2:$D$300,Winback!$K$2:$K$300,$D297),0) | M297: =IF(OR($E297=1,$G297=1,SUMIFS(Registros!$J$2:$J$6000,Registros!$B$2:$B$6000,$A297)>0),1,0) | N297: =IF($J297>0,1,IF(COUNTIFS(Registros!$A$2:$A$6000,"CS",Registros!$B$2:$B$6000,$A297,Registros!$K$2:$K$6000,"<>")>0,1,0)) | O297: =IF(AND($K297=1,$E297=0,$G297=0,$I297=0),"WINBACK",IF(AND($M297=1,$N297>0),"CONVERGENTE",IF($M297=1,"SOLO MÓVIL",IF($N297>0,"SOLO FIJO / INTERNET","SIN SERVICIOS")))) | P297: =IF($O297="WINBACK","Recuperar (winback)",IF($O297="CONVERGENTE","Upgrade / más líneas",IF($O297="SOLO MÓVIL","Ofrecer fijo + internet (FLBBTV)",IF($O297="SOLO FIJO / INTERNET","Ofrecer línea móvil Nextphone","Oferta completa (móvil + fijo + internet)")))) | Q297: =$F297+$H297+$L297 | R297: =IFERROR(VLOOKUP($A297,Registros!$B$2:$G$6000,6,0),IFERROR(VLOOKUP($D297,Winback!$B$2:$C$300,2,0),"")) | S297: =IF($E297=1,"NP","")&IF($G297=1,"+MOV","")&IF($I297=1,"+CS","")&IF($K297=1,"+WB","") | T297: =$E297+$G297+$I297+$K297
... A4940: 173068280000>> Yuqin Yuan | B4940: 17306828.0 | C4940: YUQIN YUAN | D4940: YUQINYUAN | E4940: =IF(COUNTIFS(Registros!$A$2:$A$6000,"NP",Registros!$B$2:$B$6000,$A4940)>0,1,0) | F4940: =IF($E4940=1,SUMIFS(Registros!$F$2:$F$6000,Registros!$A$2:$A$6000,"NP",Registros!$B$2:$B$6000,$A4940),0) | G4940: =IF(COUNTIFS(Registros!$A$2:$A$6000,"MOV",Registros!$B$2:$B$6000,$A4940)>0,1,0) | H4940: =IF($G4940=1,SUMIFS(Registros!$F$2:$F$6000,Registros!$A$2:$A$6000,"MOV",Registros!$B$2:$B$6000,$A4940),0) | I4940: =IF(COUNTIFS(Registros!$A$2:$A$6000,"CS",Registros!$B$2:$B$6000,$A4940)>0,1,0) | J4940: =IF($I4940=1,SUMIFS(Registros!$I$2:$I$6000,Registros!$A$2:$A$6000,"CS",Registros!$B$2:$B$6000,$A4940),0) | K4940: =IF(COUNTIFS(Winback!$K$2:$K$300,$D4940)>0,1,0) | L4940: =IF(AND($K4940=1,LEFT($A4940,3)="WB-"),SUMIFS(Winback!$D$2:$D$300,Winback!$K$2:$K$300,$D4940),0) | M4940: =IF(OR($E4940=1,$G4940=1,SUMIFS(Registros!$J$2:$J$6000,Registros!$B$2:$B$6000,$A4940)>0),1,0) | N4940: =IF($J4940>0,1,IF(COUNTIFS(Registros!$A$2:$A$6000,"CS",Registros!$B$2:$B$6000,$A4940,Registros!$K$2:$K$6000,"<>")>0,1,0)) | O4940: =IF(AND($K4940=1,$E4940=0,$G4940=0,$I4940=0),"WINBACK",IF(AND($M4940=1,$N4940>0),"CONVERGENTE",IF($M4940=1,"SOLO MÓVIL",IF($N4940>0,"SOLO FIJO / INTERNET","SIN SERVICIOS")))) | P4940: =IF($O4940="WINBACK","Recuperar (winback)",IF($O4940="CONVERGENTE","Upgrade / más líneas",IF($O4940="SOLO MÓVIL","Ofrecer fijo + internet (FLBBTV)",IF($O4940="SOLO FIJO / INTERNET","Ofrecer línea móvil Nextphone","Oferta completa (móvil + fijo + internet)")))) | Q4940: =$F4940+$H4940+$L4940 | R4940: =IFERROR(VLOOKUP($A4940,Registros!$B$2:$G$6000,6,0),IFERROR(VLOOKUP($D4940,Winback!$B$2:$C$300,2,0),"")) | S4940: =IF($E4940=1,"NP","")&IF($G4940=1,"+MOV","")&IF($I4940=1,"+CS","")&IF($K4940=1,"+WB","") | T4940: =$E4940+$G4940+$I4940+$K4940
A4941: WB-COIMSA | C4941: COIMSA | D4941: COIMSA | E4941: =IF(COUNTIFS(Registros!$A$2:$A$6000,"NP",Registros!$B$2:$B$6000,$A4941)>0,1,0) | F4941: =IF($E4941=1,SUMIFS(Registros!$F$2:$F$6000,Registros!$A$2:$A$6000,"NP",Registros!$B$2:$B$6000,$A4941),0) | G4941: =IF(COUNTIFS(Registros!$A$2:$A$6000,"MOV",Registros!$B$2:$B$6000,$A4941)>0,1,0) | H4941: =IF($G4941=1,SUMIFS(Registros!$F$2:$F$6000,Registros!$A$2:$A$6000,"MOV",Registros!$B$2:$B$6000,$A4941),0) | I4941: =IF(COUNTIFS(Registros!$A$2:$A$6000,"CS",Registros!$B$2:$B$6000,$A4941)>0,1,0) | J4941: =IF($I4941=1,SUMIFS(Registros!$I$2:$I$6000,Registros!$A$2:$A$6000,"CS",Registros!$B$2:$B$6000,$A4941),0) | K4941: =IF(COUNTIFS(Winback!$K$2:$K$300,$D4941)>0,1,0) | L4941: =IF(AND($K4941=1,LEFT($A4941,3)="WB-"),SUMIFS(Winback!$D$2:$D$300,Winback!$K$2:$K$300,$D4941),0) | M4941: =IF(OR($E4941=1,$G4941=1,SUMIFS(Registros!$J$2:$J$6000,Registros!$B$2:$B$6000,$A4941)>0),1,0) | N4941: =IF($J4941>0,1,IF(COUNTIFS(Registros!$A$2:$A$6000,"CS",Registros!$B$2:$B$6000,$A4941,Registros!$K$2:$K$6000,"<>")>0,1,0)) | O4941: =IF(AND($K4941=1,$E4941=0,$G4941=0,$I4941=0),"WINBACK",IF(AND($M4941=1,$N4941>0),"CONVERGENTE",IF($M4941=1,"SOLO MÓVIL",IF($N4941>0,"SOLO FIJO / INTERNET","SIN SERVICIOS")))) | P4941: =IF($O4941="WINBACK","Recuperar (winback)",IF($O4941="CONVERGENTE","Upgrade / más líneas",IF($O4941="SOLO MÓVIL","Ofrecer fijo + internet (FLBBTV)",IF($O4941="SOLO FIJO / INTERNET","Ofrecer línea móvil Nextphone","Oferta completa (móvil + fijo + internet)")))) | Q4941: =$F4941+$H4941+$L4941 | R4941: =IFERROR(VLOOKUP($A4941,Registros!$B$2:$G$6000,6,0),IFERROR(VLOOKUP($D4941,Winback!$B$2:$C$300,2,0),"")) | S4941: =IF($E4941=1,"NP","")&IF($G4941=1,"+MOV","")&IF($I4941=1,"+CS","")&IF($K4941=1,"+WB","") | T4941: =$E4941+$G4941+$I4941+$K4941
A4942: WB-GRAPHICSOLUT | C4942: GRAPHIC SOLUTIONS/ CARMEN R. WILLIAMS 2 | D4942: GRAPHICSOLUTIONSCARMENRWILLIAMS2 | E4942: =IF(COUNTIFS(Registros!$A$2:$A$6000,"NP",Registros!$B$2:$B$6000,$A4942)>0,1,0) | F4942: =IF($E4942=1,SUMIFS(Registros!$F$2:$F$6000,Registros!$A$2:$A$6000,"NP",Registros!$B$2:$B$6000,$A4942),0) | G4942: =IF(COUNTIFS(Registros!$A$2:$A$6000,"MOV",Registros!$B$2:$B$6000,$A4942)>0,1,0) | H4942: =IF($G4942=1,SUMIFS(Registros!$F$2:$F$6000,Registros!$A$2:$A$6000,"MOV",Registros!$B$2:$B$6000,$A4942),0) | I4942: =IF(COUNTIFS(Registros!$A$2:$A$6000,"CS",Registros!$B$2:$B$6000,$A4942)>0,1,0) | J4942: =IF($I4942=1,SUMIFS(Registros!$I$2:$I$6000,Registros!$A$2:$A$6000,"CS",Registros!$B$2:$B$6000,$A4942),0) | K4942: =IF(COUNTIFS(Winback!$K$2:$K$300,$D4942)>0,1,0) | L4942: =IF(AND($K4942=1,LEFT($A4942,3)="WB-"),SUMIFS(Winback!$D$2:$D$300,Winback!$K$2:$K$300,$D4942),0) | M4942: =IF(OR($E4942=1,$G4942=1,SUMIFS(Registros!$J$2:$J$6000,Registros!$B$2:$B$6000,$A4942)>0),1,0) | N4942: =IF($J4942>0,1,IF(COUNTIFS(Registros!$A$2:$A$6000,"CS",Registros!$B$2:$B$6000,$A4942,Registros!$K$2:$K$6000,"<>")>0,1,0)) | O4942: =IF(AND($K4942=1,$E4942=0,$G4942=0,$I4942=0),"WINBACK",IF(AND($M4942=1,$N4942>0),"CONVERGENTE",IF($M4942=1,"SOLO MÓVIL",IF($N4942>0,"SOLO FIJO / INTERNET","SIN SERVICIOS")))) | P4942: =IF($O4942="WINBACK","Recuperar (winback)",IF($O4942="CONVERGENTE","Upgrade / más líneas",IF($O4942="SOLO MÓVIL","Ofrecer fijo + internet (FLBBTV)",IF($O4942="SOLO FIJO / INTERNET","Ofrecer línea móvil Nextphone","Oferta completa (móvil + fijo + internet)")))) | Q4942: =$F4942+$H4942+$L4942 | R4942: =IFERROR(VLOOKUP($A4942,Registros!$B$2:$G$6000,6,0),IFERROR(VLOOKUP($D4942,Winback!$B$2:$C$300,2,0),"")) | S4942: =IF($E4942=1,"NP","")&IF($G4942=1,"+MOV","")&IF($I4942=1,"+CS","")&IF($K4942=1,"+WB","") | T4942: =$E4942+$G4942+$I4942+$K4942
A4943: WB-ALEXISALEXAN | C4943: ALEXIS ALEXANDER GOMEZ MENDIETA | D4943: ALEXISALEXANDERGOMEZMENDIETA | E4943: =IF(COUNTIFS(Registros!$A$2:$A$6000,"NP",Registros!$B$2:$B$6000,$A4943)>0,1,0) | F4943: =IF($E4943=1,SUMIFS(Registros!$F$2:$F$6000,Registros!$A$2:$A$6000,"NP",Registros!$B$2:$B$6000,$A4943),0) | G4943: =IF(COUNTIFS(Registros!$A$2:$A$6000,"MOV",Registros!$B$2:$B$6000,$A4943)>0,1,0) | H4943: =IF($G4943=1,SUMIFS(Registros!$F$2:$F$6000,Registros!$A$2:$A$6000,"MOV",Registros!$B$2:$B$6000,$A4943),0) | I4943: =IF(COUNTIFS(Registros!$A$2:$A$6000,"CS",Registros!$B$2:$B$6000,$A4943)>0,1,0) | J4943: =IF($I4943=1,SUMIFS(Registros!$I$2:$I$6000,Registros!$A$2:$A$6000,"CS",Registros!$B$2:$B$6000,$A4943),0) | K4943: =IF(COUNTIFS(Winback!$K$2:$K$300,$D4943)>0,1,0) | L4943: =IF(AND($K4943=1,LEFT($A4943,3)="WB-"),SUMIFS(Winback!$D$2:$D$300,Winback!$K$2:$K$300,$D4943),0) | M4943: =IF(OR($E4943=1,$G4943=1,SUMIFS(Registros!$J$2:$J$6000,Registros!$B$2:$B$6000,$A4943)>0),1,0) | N4943: =IF($J4943>0,1,IF(COUNTIFS(Registros!$A$2:$A$6000,"CS",Registros!$B$2:$B$6000,$A4943,Registros!$K$2:$K$6000,"<>")>0,1,0)) | O4943: =IF(AND($K4943=1,$E4943=0,$G4943=0,$I4943=0),"WINBACK",IF(AND($M4943=1,$N4943>0),"CONVERGENTE",IF($M4943=1,"SOLO MÓVIL",IF($N4943>0,"SOLO FIJO / INTERNET","SIN SERVICIOS")))) | P4943: =IF($O4943="WINBACK","Recuperar (winback)",IF($O4943="CONVERGENTE","Upgrade / más líneas",IF($O4943="SOLO MÓVIL","Ofrecer fijo + internet (FLBBTV)",IF($O4943="SOLO FIJO / INTERNET","Ofrecer línea móvil Nextphone","Oferta completa (móvil + fijo + internet)")))) | Q4943: =$F4943+$H4943+$L4943 | R4943: =IFERROR(VLOOKUP($A4943,Registros!$B$2:$G$6000,6,0),IFERROR(VLOOKUP($D4943,Winback!$B$2:$C$300,2,0),"")) | S4943: =IF($E4943=1,"NP","")&IF($G4943=1,"+MOV","")&IF($I4943=1,"+CS","")&IF($K4943=1,"+WB","") | T4943: =$E4943+$G4943+$I4943+$K4943
A4944: WB-PHCOUNTRYCLU | C4944: PH COUNTRY CLUB - | D4944: PHCOUNTRYCLUB | E4944: =IF(COUNTIFS(Registros!$A$2:$A$6000,"NP",Registros!$B$2:$B$6000,$A4944)>0,1,0) | F4944: =IF($E4944=1,SUMIFS(Registros!$F$2:$F$6000,Registros!$A$2:$A$6000,"NP",Registros!$B$2:$B$6000,$A4944),0) | G4944: =IF(COUNTIFS(Registros!$A$2:$A$6000,"MOV",Registros!$B$2:$B$6000,$A4944)>0,1,0) | H4944: =IF($G4944=1,SUMIFS(Registros!$F$2:$F$6000,Registros!$A$2:$A$6000,"MOV",Registros!$B$2:$B$6000,$A4944),0) | I4944: =IF(COUNTIFS(Registros!$A$2:$A$6000,"CS",Registros!$B$2:$B$6000,$A4944)>0,1,0) | J4944: =IF($I4944=1,SUMIFS(Registros!$I$2:$I$6000,Registros!$A$2:$A$6000,"CS",Registros!$B$2:$B$6000,$A4944),0) | K4944: =IF(COUNTIFS(Winback!$K$2:$K$300,$D4944)>0,1,0) | L4944: =IF(AND($K4944=1,LEFT($A4944,3)="WB-"),SUMIFS(Winback!$D$2:$D$300,Winback!$K$2:$K$300,$D4944),0) | M4944: =IF(OR($E4944=1,$G4944=1,SUMIFS(Registros!$J$2:$J$6000,Registros!$B$2:$B$6000,$A4944)>0),1,0) | N4944: =IF($J4944>0,1,IF(COUNTIFS(Registros!$A$2:$A$6000,"CS",Registros!$B$2:$B$6000,$A4944,Registros!$K$2:$K$6000,"<>")>0,1,0)) | O4944: =IF(AND($K4944=1,$E4944=0,$G4944=0,$I4944=0),"WINBACK",IF(AND($M4944=1,$N4944>0),"CONVERGENTE",IF($M4944=1,"SOLO MÓVIL",IF($N4944>0,"SOLO FIJO / INTERNET","SIN SERVICIOS")))) | P4944: =IF($O4944="WINBACK","Recuperar (winback)",IF($O4944="CONVERGENTE","Upgrade / más líneas",IF($O4944="SOLO MÓVIL","Ofrecer fijo + internet (FLBBTV)",IF($O4944="SOLO FIJO / INTERNET","Ofrecer línea móvil Nextphone","Oferta completa (móvil + fijo + internet)")))) | Q4944: =$F4944+$H4944+$L4944 | R4944: =IFERROR(VLOOKUP($A4944,Registros!$B$2:$G$6000,6,0),IFERROR(VLOOKUP($D4944,Winback!$B$2:$C$300,2,0),"")) | S4944: =IF($E4944=1,"NP","")&IF($G4944=1,"+MOV","")&IF($I4944=1,"+CS","")&IF($K4944=1,"+WB","") | T4944: =$E4944+$G4944+$I4944+$K4944
A4945: WB- | E4945: =IF(COUNTIFS(Registros!$A$2:$A$6000,"NP",Registros!$B$2:$B$6000,$A4945)>0,1,0) | F4945: =IF($E4945=1,SUMIFS(Registros!$F$2:$F$6000,Registros!$A$2:$A$6000,"NP",Registros!$B$2:$B$6000,$A4945),0) | G4945: =IF(COUNTIFS(Registros!$A$2:$A$6000,"MOV",Registros!$B$2:$B$6000,$A4945)>0,1,0) | H4945: =IF($G4945=1,SUMIFS(Registros!$F$2:$F$6000,Registros!$A$2:$A$6000,"MOV",Registros!$B$2:$B$6000,$A4945),0) | I4945: =IF(COUNTIFS(Registros!$A$2:$A$6000,"CS",Registros!$B$2:$B$6000,$A4945)>0,1,0) | J4945: =IF($I4945=1,SUMIFS(Registros!$I$2:$I$6000,Registros!$A$2:$A$6000,"CS",Registros!$B$2:$B$6000,$A4945),0) | K4945: =IF(COUNTIFS(Winback!$K$2:$K$300,$D4945)>0,1,0) | L4945: =IF(AND($K4945=1,LEFT($A4945,3)="WB-"),SUMIFS(Winback!$D$2:$D$300,Winback!$K$2:$K$300,$D4945),0) | M4945: =IF(OR($E4945=1,$G4945=1,SUMIFS(Registros!$J$2:$J$6000,Registros!$B$2:$B$6000,$A4945)>0),1,0) | N4945: =IF($J4945>0,1,IF(COUNTIFS(Registros!$A$2:$A$6000,"CS",Registros!$B$2:$B$6000,$A4945,Registros!$K$2:$K$6000,"<>")>0,1,0)) | O4945: =IF(AND($K4945=1,$E4945=0,$G4945=0,$I4945=0),"WINBACK",IF(AND($M4945=1,$N4945>0),"CONVERGENTE",IF($M4945=1,"SOLO MÓVIL",IF($N4945>0,"SOLO FIJO / INTERNET","SIN SERVICIOS")))) | P4945: =IF($O4945="WINBACK","Recuperar (winback)",IF($O4945="CONVERGENTE","Upgrade / más líneas",IF($O4945="SOLO MÓVIL","Ofrecer fijo + internet (FLBBTV)",IF($O4945="SOLO FIJO / INTERNET","Ofrecer línea móvil Nextphone","Oferta completa (móvil + fijo + internet)")))) | Q4945: =$F4945+$H4945+$L4945 | R4945: =IFERROR(VLOOKUP($A4945,Registros!$B$2:$G$6000,6,0),IFERROR(VLOOKUP($D4945,Winback!$B$2:$C$300,2,0),"")) | S4945: =IF($E4945=1,"NP","")&IF($G4945=1,"+MOV","")&IF($I4945=1,"+CS","")&IF($K4945=1,"+WB","") | T4945: =$E4945+$G4945+$I4945+$K4945
A4946: WB-IDEALO | C4946: IDEALO | D4946: IDEALO | E4946: =IF(COUNTIFS(Registros!$A$2:$A$6000,"NP",Registros!$B$2:$B$6000,$A4946)>0,1,0) | F4946: =IF($E4946=1,SUMIFS(Registros!$F$2:$F$6000,Registros!$A$2:$A$6000,"NP",Registros!$B$2:$B$6000,$A4946),0) | G4946: =IF(COUNTIFS(Registros!$A$2:$A$6000,"MOV",Registros!$B$2:$B$6000,$A4946)>0,1,0) | H4946: =IF($G4946=1,SUMIFS(Registros!$F$2:$F$6000,Registros!$A$2:$A$6000,"MOV",Registros!$B$2:$B$6000,$A4946),0) | I4946: =IF(COUNTIFS(Registros!$A$2:$A$6000,"CS",Registros!$B$2:$B$6000,$A4946)>0,1,0) | J4946: =IF($I4946=1,SUMIFS(Registros!$I$2:$I$6000,Registros!$A$2:$A$6000,"CS",Registros!$B$2:$B$6000,$A4946),0) | K4946: =IF(COUNTIFS(Winback!$K$2:$K$300,$D4946)>0,1,0) | L4946: =IF(AND($K4946=1,LEFT($A4946,3)="WB-"),SUMIFS(Winback!$D$2:$D$300,Winback!$K$2:$K$300,$D4946),0) | M4946: =IF(OR($E4946=1,$G4946=1,SUMIFS(Registros!$J$2:$J$6000,Registros!$B$2:$B$6000,$A4946)>0),1,0) | N4946: =IF($J4946>0,1,IF(COUNTIFS(Registros!$A$2:$A$6000,"CS",Registros!$B$2:$B$6000,$A4946,Registros!$K$2:$K$6000,"<>")>0,1,0)) | O4946: =IF(AND($K4946=1,$E4946=0,$G4946=0,$I4946=0),"WINBACK",IF(AND($M4946=1,$N4946>0),"CONVERGENTE",IF($M4946=1,"SOLO MÓVIL",IF($N4946>0,"SOLO FIJO / INTERNET","SIN SERVICIOS")))) | P4946: =IF($O4946="WINBACK","Recuperar (winback)",IF($O4946="CONVERGENTE","Upgrade / más líneas",IF($O4946="SOLO MÓVIL","Ofrecer fijo + internet (FLBBTV)",IF($O4946="SOLO FIJO / INTERNET","Ofrecer línea móvil Nextphone","Oferta completa (móvil + fijo + internet)")))) | Q4946: =$F4946+$H4946+$L4946 | R4946: =IFERROR(VLOOKUP($A4946,Registros!$B$2:$G$6000,6,0),IFERROR(VLOOKUP($D4946,Winback!$B$2:$C$300,2,0),"")) | S4946: =IF($E4946=1,"NP","")&IF($G4946=1,"+MOV","")&IF($I4946=1,"+CS","")&IF($K4946=1,"+WB","") | T4946: =$E4946+$G4946+$I4946+$K4946
A4947: WB-INFINITYLOGI | C4947: INFINITY LOGISTICS INFINITY LOGISTICS AGENCY, CORP | D4947: INFINITYLOGISTICSINFINITYLOGISTICSAGENCYCORP | E4947: =IF(COUNTIFS(Registros!$A$2:$A$6000,"NP",Registros!$B$2:$B$6000,$A4947)>0,1,0) | F4947: =IF($E4947=1,SUMIFS(Registros!$F$2:$F$6000,Registros!$A$2:$A$6000,"NP",Registros!$B$2:$B$6000,$A4947),0) | G4947: =IF(COUNTIFS(Registros!$A$2:$A$6000,"MOV",Registros!$B$2:$B$6000,$A4947)>0,1,0) | H4947: =IF($G4947=1,SUMIFS(Registros!$F$2:$F$6000,Registros!$A$2:$A$6000,"MOV",Registros!$B$2:$B$6000,$A4947),0) | I4947: =IF(COUNTIFS(Registros!$A$2:$A$6000,"CS",Registros!$B$2:$B$6000,$A4947)>0,1,0) | J4947: =IF($I4947=1,SUMIFS(Registros!$I$2:$I$6000,Registros!$A$2:$A$6000,"CS",Registros!$B$2:$B$6000,$A4947),0) | K4947: =IF(COUNTIFS(Winback!$K$2:$K$300,$D4947)>0,1,0) | L4947: =IF(AND($K4947=1,LEFT($A4947,3)="WB-"),SUMIFS(Winback!$D$2:$D$300,Winback!$K$2:$K$300,$D4947),0) | M4947: =IF(OR($E4947=1,$G4947=1,SUMIFS(Registros!$J$2:$J$6000,Registros!$B$2:$B$6000,$A4947)>0),1,0) | N4947: =IF($J4947>0,1,IF(COUNTIFS(Registros!$A$2:$A$6000,"CS",Registros!$B$2:$B$6000,$A4947,Registros!$K$2:$K$6000,"<>")>0,1,0)) | O4947: =IF(AND($K4947=1,$E4947=0,$G4947=0,$I4947=0),"WINBACK",IF(AND($M4947=1,$N4947>0),"CONVERGENTE",IF($M4947=1,"SOLO MÓVIL",IF($N4947>0,"SOLO FIJO / INTERNET","SIN SERVICIOS")))) | P4947: =IF($O4947="WINBACK","Recuperar (winback)",IF($O4947="CONVERGENTE","Upgrade / más líneas",IF($O4947="SOLO MÓVIL","Ofrecer fijo + internet (FLBBTV)",IF($O4947="SOLO FIJO / INTERNET","Ofrecer línea móvil Nextphone","Oferta completa (móvil + fijo + internet)")))) | Q4947: =$F4947+$H4947+$L4947 | R4947: =IFERROR(VLOOKUP($A4947,Registros!$B$2:$G$6000,6,0),IFERROR(VLOOKUP($D4947,Winback!$B$2:$C$300,2,0),"")) | S4947: =IF($E4947=1,"NP","")&IF($G4947=1,"+MOV","")&IF($I4947=1,"+CS","")&IF($K4947=1,"+WB","") | T4947: =$E4947+$G4947+$I4947+$K4947
A4948: WB-RCSOLUTIONSA | C4948: RC SOLUTION, S.A - | D4948: RCSOLUTIONSA | E4948: =IF(COUNTIFS(Registros!$A$2:$A$6000,"NP",Registros!$B$2:$B$6000,$A4948)>0,1,0) | F4948: =IF($E4948=1,SUMIFS(Registros!$F$2:$F$6000,Registros!$A$2:$A$6000,"NP",Registros!$B$2:$B$6000,$A4948),0) | G4948: =IF(COUNTIFS(Registros!$A$2:$A$6000,"MOV",Registros!$B$2:$B$6000,$A4948)>0,1,0) | H4948: =IF($G4948=1,SUMIFS(Registros!$F$2:$F$6000,Registros!$A$2:$A$6000,"MOV",Registros!$B$2:$B$6000,$A4948),0) | I4948: =IF(COUNTIFS(Registros!$A$2:$A$6000,"CS",Registros!$B$2:$B$6000,$A4948)>0,1,0) | J4948: =IF($I4948=1,SUMIFS(Registros!$I$2:$I$6000,Registros!$A$2:$A$6000,"CS",Registros!$B$2:$B$6000,$A4948),0) | K4948: =IF(COUNTIFS(Winback!$K$2:$K$300,$D4948)>0,1,0) | L4948: =IF(AND($K4948=1,LEFT($A4948,3)="WB-"),SUMIFS(Winback!$D$2:$D$300,Winback!$K$2:$K$300,$D4948),0) | M4948: =IF(OR($E4948=1,$G4948=1,SUMIFS(Registros!$J$2:$J$6000,Registros!$B$2:$B$6000,$A4948)>0),1,0) | N4948: =IF($J4948>0,1,IF(COUNTIFS(Registros!$A$2:$A$6000,"CS",Registros!$B$2:$B$6000,$A4948,Registros!$K$2:$K$6000,"<>")>0,1,0)) | O4948: =IF(AND($K4948=1,$E4948=0,$G4948=0,$I4948=0),"WINBACK",IF(AND($M4948=1,$N4948>0),"CONVERGENTE",IF($M4948=1,"SOLO MÓVIL",IF($N4948>0,"SOLO FIJO / INTERNET","SIN SERVICIOS")))) | P4948: =IF($O4948="WINBACK","Recuperar (winback)",IF($O4948="CONVERGENTE","Upgrade / más líneas",IF($O4948="SOLO MÓVIL","Ofrecer fijo + internet (FLBBTV)",IF($O4948="SOLO FIJO / INTERNET","Ofrecer línea móvil Nextphone","Oferta completa (móvil + fijo + internet)")))) | Q4948: =$F4948+$H4948+$L4948 | R4948: =IFERROR(VLOOKUP($A4948,Registros!$B$2:$G$6000,6,0),IFERROR(VLOOKUP($D4948,Winback!$B$2:$C$300,2,0),"")) | S4948: =IF($E4948=1,"NP","")&IF($G4948=1,"+MOV","")&IF($I4948=1,"+CS","")&IF($K4948=1,"+WB","") | T4948: =$E4948+$G4948+$I4948+$K4948
A4949: WB-SERVICIOSLOG | C4949: Servicios Logitisticos Imperial S.A | D4949: SERVICIOSLOGITISTICOSIMPERIALSA | E4949: =IF(COUNTIFS(Registros!$A$2:$A$6000,"NP",Registros!$B$2:$B$6000,$A4949)>0,1,0) | F4949: =IF($E4949=1,SUMIFS(Registros!$F$2:$F$6000,Registros!$A$2:$A$6000,"NP",Registros!$B$2:$B$6000,$A4949),0) | G4949: =IF(COUNTIFS(Registros!$A$2:$A$6000,"MOV",Registros!$B$2:$B$6000,$A4949)>0,1,0) | H4949: =IF($G4949=1,SUMIFS(Registros!$F$2:$F$6000,Registros!$A$2:$A$6000,"MOV",Registros!$B$2:$B$6000,$A4949),0) | I4949: =IF(COUNTIFS(Registros!$A$2:$A$6000,"CS",Registros!$B$2:$B$6000,$A4949)>0,1,0) | J4949: =IF($I4949=1,SUMIFS(Registros!$I$2:$I$6000,Registros!$A$2:$A$6000,"CS",Registros!$B$2:$B$6000,$A4949),0) | K4949: =IF(COUNTIFS(Winback!$K$2:$K$300,$D4949)>0,1,0) | L4949: =IF(AND($K4949=1,LEFT($A4949,3)="WB-"),SUMIFS(Winback!$D$2:$D$300,Winback!$K$2:$K$300,$D4949),0) | M4949: =IF(OR($E4949=1,$G4949=1,SUMIFS(Registros!$J$2:$J$6000,Registros!$B$2:$B$6000,$A4949)>0),1,0) | N4949: =IF($J4949>0,1,IF(COUNTIFS(Registros!$A$2:$A$6000,"CS",Registros!$B$2:$B$6000,$A4949,Registros!$K$2:$K$6000,"<>")>0,1,0)) | O4949: =IF(AND($K4949=1,$E4949=0,$G4949=0,$I4949=0),"WINBACK",IF(AND($M4949=1,$N4949>0),"CONVERGENTE",IF($M4949=1,"SOLO MÓVIL",IF($N4949>0,"SOLO FIJO / INTERNET","SIN SERVICIOS")))) | P4949: =IF($O4949="WINBACK","Recuperar (winback)",IF($O4949="CONVERGENTE","Upgrade / más líneas",IF($O4949="SOLO MÓVIL","Ofrecer fijo + internet (FLBBTV)",IF($O4949="SOLO FIJO / INTERNET","Ofrecer línea móvil Nextphone","Oferta completa (móvil + fijo + internet)")))) | Q4949: =$F4949+$H4949+$L4949 | R4949: =IFERROR(VLOOKUP($A4949,Registros!$B$2:$G$6000,6,0),IFERROR(VLOOKUP($D4949,Winback!$B$2:$C$300,2,0),"")) | S4949: =IF($E4949=1,"NP","")&IF($G4949=1,"+MOV","")&IF($I4949=1,"+CS","")&IF($K4949=1,"+WB","") | T4949: =$E4949+$G4949+$I4949+$K4949
A4950: WB-CLINICATUSAL | C4950: CLINICA TU SALUD Y BELLEZA - | D4950: CLINICATUSALUDYBELLEZA | E4950: =IF(COUNTIFS(Registros!$A$2:$A$6000,"NP",Registros!$B$2:$B$6000,$A4950)>0,1,0) | F4950: =IF($E4950=1,SUMIFS(Registros!$F$2:$F$6000,Registros!$A$2:$A$6000,"NP",Registros!$B$2:$B$6000,$A4950),0) | G4950: =IF(COUNTIFS(Registros!$A$2:$A$6000,"MOV",Registros!$B$2:$B$6000,$A4950)>0,1,0) | H4950: =IF($G4950=1,SUMIFS(Registros!$F$2:$F$6000,Registros!$A$2:$A$6000,"MOV",Registros!$B$2:$B$6000,$A4950),0) | I4950: =IF(COUNTIFS(Registros!$A$2:$A$6000,"CS",Registros!$B$2:$B$6000,$A4950)>0,1,0) | J4950: =IF($I4950=1,SUMIFS(Registros!$I$2:$I$6000,Registros!$A$2:$A$6000,"CS",Registros!$B$2:$B$6000,$A4950),0) | K4950: =IF(COUNTIFS(Winback!$K$2:$K$300,$D4950)>0,1,0) | L4950: =IF(AND($K4950=1,LEFT($A4950,3)="WB-"),SUMIFS(Winback!$D$2:$D$300,Winback!$K$2:$K$300,$D4950),0) | M4950: =IF(OR($E4950=1,$G4950=1,SUMIFS(Registros!$J$2:$J$6000,Registros!$B$2:$B$6000,$A4950)>0),1,0) | N4950: =IF($J4950>0,1,IF(COUNTIFS(Registros!$A$2:$A$6000,"CS",Registros!$B$2:$B$6000,$A4950,Registros!$K$2:$K$6000,"<>")>0,1,0)) | O4950: =IF(AND($K4950=1,$E4950=0,$G4950=0,$I4950=0),"WINBACK",IF(AND($M4950=1,$N4950>0),"CONVERGENTE",IF($M4950=1,"SOLO MÓVIL",IF($N4950>0,"SOLO FIJO / INTERNET","SIN SERVICIOS")))) | P4950: =IF($O4950="WINBACK","Recuperar (winback)",IF($O4950="CONVERGENTE","Upgrade / más líneas",IF($O4950="SOLO MÓVIL","Ofrecer fijo + internet (FLBBTV)",IF($O4950="SOLO FIJO / INTERNET","Ofrecer línea móvil Nextphone","Oferta completa (móvil + fijo + internet)")))) | Q4950: =$F4950+$H4950+$L4950 | R4950: =IFERROR(VLOOKUP($A4950,Registros!$B$2:$G$6000,6,0),IFERROR(VLOOKUP($D4950,Winback!$B$2:$C$300,2,0),"")) | S4950: =IF($E4950=1,"NP","")&IF($G4950=1,"+MOV","")&IF($I4950=1,"+CS","")&IF($K4950=1,"+WB","") | T4950: =$E4950+$G4950+$I4950+$K4950
A4951: WB-SERVIEDUCASA | C4951: SERVIEDUCA S,A. - | D4951: SERVIEDUCASA | E4951: =IF(COUNTIFS(Registros!$A$2:$A$6000,"NP",Registros!$B$2:$B$6000,$A4951)>0,1,0) | F4951: =IF($E4951=1,SUMIFS(Registros!$F$2:$F$6000,Registros!$A$2:$A$6000,"NP",Registros!$B$2:$B$6000,$A4951),0) | G4951: =IF(COUNTIFS(Registros!$A$2:$A$6000,"MOV",Registros!$B$2:$B$6000,$A4951)>0,1,0) | H4951: =IF($G4951=1,SUMIFS(Registros!$F$2:$F$6000,Registros!$A$2:$A$6000,"MOV",Registros!$B$2:$B$6000,$A4951),0) | I4951: =IF(COUNTIFS(Registros!$A$2:$A$6000,"CS",Registros!$B$2:$B$6000,$A4951)>0,1,0) | J4951: =IF($I4951=1,SUMIFS(Registros!$I$2:$I$6000,Registros!$A$2:$A$6000,"CS",Registros!$B$2:$B$6000,$A4951),0) | K4951: =IF(COUNTIFS(Winback!$K$2:$K$300,$D4951)>0,1,0) | L4951: =IF(AND($K4951=1,LEFT($A4951,3)="WB-"),SUMIFS(Winback!$D$2:$D$300,Winback!$K$2:$K$300,$D4951),0) | M4951: =IF(OR($E4951=1,$G4951=1,SUMIFS(Registros!$J$2:$J$6000,Registros!$B$2:$B$6000,$A4951)>0),1,0) | N4951: =IF($J4951>0,1,IF(COUNTIFS(Registros!$A$2:$A$6000,"CS",Registros!$B$2:$B$6000,$A4951,Registros!$K$2:$K$6000,"<>")>0,1,0)) | O4951: =IF(AND($K4951=1,$E4951=0,$G4951=0,$I4951=0),"WINBACK",IF(AND($M4951=1,$N4951>0),"CONVERGENTE",IF($M4951=1,"SOLO MÓVIL",IF($N4951>0,"SOLO FIJO / INTERNET","SIN SERVICIOS")))) | P4951: =IF($O4951="WINBACK","Recuperar (winback)",IF($O4951="CONVERGENTE","Upgrade / más líneas",IF($O4951="SOLO MÓVIL","Ofrecer fijo + internet (FLBBTV)",IF($O4951="SOLO FIJO / INTERNET","Ofrecer línea móvil Nextphone","Oferta completa (móvil + fijo + internet)")))) | Q4951: =$F4951+$H4951+$L4951 | R4951: =IFERROR(VLOOKUP($A4951,Registros!$B$2:$G$6000,6,0),IFERROR(VLOOKUP($D4951,Winback!$B$2:$C$300,2,0),"")) | S4951: =IF($E4951=1,"NP","")&IF($G4951=1,"+MOV","")&IF($I4951=1,"+CS","")&IF($K4951=1,"+WB","") | T4951: =$E4951+$G4951+$I4951+$K4951
A4952: WB-PANAMAJOURNE | C4952: PANAMA JOURNEYS S,A - | D4952: PANAMAJOURNEYSSA | E4952: =IF(COUNTIFS(Registros!$A$2:$A$6000,"NP",Registros!$B$2:$B$6000,$A4952)>0,1,0) | F4952: =IF($E4952=1,SUMIFS(Registros!$F$2:$F$6000,Registros!$A$2:$A$6000,"NP",Registros!$B$2:$B$6000,$A4952),0) | G4952: =IF(COUNTIFS(Registros!$A$2:$A$6000,"MOV",Registros!$B$2:$B$6000,$A4952)>0,1,0) | H4952: =IF($G4952=1,SUMIFS(Registros!$F$2:$F$6000,Registros!$A$2:$A$6000,"MOV",Registros!$B$2:$B$6000,$A4952),0) | I4952: =IF(COUNTIFS(Registros!$A$2:$A$6000,"CS",Registros!$B$2:$B$6000,$A4952)>0,1,0) | J4952: =IF($I4952=1,SUMIFS(Registros!$I$2:$I$6000,Registros!$A$2:$A$6000,"CS",Registros!$B$2:$B$6000,$A4952),0) | K4952: =IF(COUNTIFS(Winback!$K$2:$K$300,$D4952)>0,1,0) | L4952: =IF(AND($K4952=1,LEFT($A4952,3)="WB-"),SUMIFS(Winback!$D$2:$D$300,Winback!$K$2:$K$300,$D4952),0) | M4952: =IF(OR($E4952=1,$G4952=1,SUMIFS(Registros!$J$2:$J$6000,Registros!$B$2:$B$6000,$A4952)>0),1,0) | N4952: =IF($J4952>0,1,IF(COUNTIFS(Registros!$A$2:$A$6000,"CS",Registros!$B$2:$B$6000,$A4952,Registros!$K$2:$K$6000,"<>")>0,1,0)) | O4952: =IF(AND($K4952=1,$E4952=0,$G4952=0,$I4952=0),"WINBACK",IF(AND($M4952=1,$N4952>0),"CONVERGENTE",IF($M4952=1,"SOLO MÓVIL",IF($N4952>0,"SOLO FIJO / INTERNET","SIN SERVICIOS")))) | P4952: =IF($O4952="WINBACK","Recuperar (winback)",IF($O4952="CONVERGENTE","Upgrade / más líneas",IF($O4952="SOLO MÓVIL","Ofrecer fijo + internet (FLBBTV)",IF($O4952="SOLO FIJO / INTERNET","Ofrecer línea móvil Nextphone","Oferta completa (móvil + fijo + internet)")))) | Q4952: =$F4952+$H4952+$L4952 | R4952: =IFERROR(VLOOKUP($A4952,Registros!$B$2:$G$6000,6,0),IFERROR(VLOOKUP($D4952,Winback!$B$2:$C$300,2,0),"")) | S4952: =IF($E4952=1,"NP","")&IF($G4952=1,"+MOV","")&IF($I4952=1,"+CS","")&IF($K4952=1,"+WB","") | T4952: =$E4952+$G4952+$I4952+$K4952
A4953: WB-AGROJPNILKAA | C4953: AGRO JP / NILKA ATENCIO | D4953: AGROJPNILKAATENCIO | E4953: =IF(COUNTIFS(Registros!$A$2:$A$6000,"NP",Registros!$B$2:$B$6000,$A4953)>0,1,0) | F4953: =IF($E4953=1,SUMIFS(Registros!$F$2:$F$6000,Registros!$A$2:$A$6000,"NP",Registros!$B$2:$B$6000,$A4953),0) | G4953: =IF(COUNTIFS(Registros!$A$2:$A$6000,"MOV",Registros!$B$2:$B$6000,$A4953)>0,1,0) | H4953: =IF($G4953=1,SUMIFS(Registros!$F$2:$F$6000,Registros!$A$2:$A$6000,"MOV",Registros!$B$2:$B$6000,$A4953),0) | I4953: =IF(COUNTIFS(Registros!$A$2:$A$6000,"CS",Registros!$B$2:$B$6000,$A4953)>0,1,0) | J4953: =IF($I4953=1,SUMIFS(Registros!$I$2:$I$6000,Registros!$A$2:$A$6000,"CS",Registros!$B$2:$B$6000,$A4953),0) | K4953: =IF(COUNTIFS(Winback!$K$2:$K$300,$D4953)>0,1,0) | L4953: =IF(AND($K4953=1,LEFT($A4953,3)="WB-"),SUMIFS(Winback!$D$2:$D$300,Winback!$K$2:$K$300,$D4953),0) | M4953: =IF(OR($E4953=1,$G4953=1,SUMIFS(Registros!$J$2:$J$6000,Registros!$B$2:$B$6000,$A4953)>0),1,0) | N4953: =IF($J4953>0,1,IF(COUNTIFS(Registros!$A$2:$A$6000,"CS",Registros!$B$2:$B$6000,$A4953,Registros!$K$2:$K$6000,"<>")>0,1,0)) | O4953: =IF(AND($K4953=1,$E4953=0,$G4953=0,$I4953=0),"WINBACK",IF(AND($M4953=1,$N4953>0),"CONVERGENTE",IF($M4953=1,"SOLO MÓVIL",IF($N4953>0,"SOLO FIJO / INTERNET","SIN SERVICIOS")))) | P4953: =IF($O4953="WINBACK","Recuperar (winback)",IF($O4953="CONVERGENTE","Upgrade / más líneas",IF($O4953="SOLO MÓVIL","Ofrecer fijo + internet (FLBBTV)",IF($O4953="SOLO FIJO / INTERNET","Ofrecer línea móvil Nextphone","Oferta completa (móvil + fijo + internet)")))) | Q4953: =$F4953+$H4953+$L4953 | R4953: =IFERROR(VLOOKUP($A4953,Registros!$B$2:$G$6000,6,0),IFERROR(VLOOKUP($D4953,Winback!$B$2:$C$300,2,0),"")) | S4953: =IF($E4953=1,"NP","")&IF($G4953=1,"+MOV","")&IF($I4953=1,"+CS","")&IF($K4953=1,"+WB","") | T4953: =$E4953+$G4953+$I4953+$K4953
A4954: WB-UPPEREASTTOW | C4954: UPPER EAST TOWER | D4954: UPPEREASTTOWER | E4954: =IF(COUNTIFS(Registros!$A$2:$A$6000,"NP",Registros!$B$2:$B$6000,$A4954)>0,1,0) | F4954: =IF($E4954=1,SUMIFS(Registros!$F$2:$F$6000,Registros!$A$2:$A$6000,"NP",Registros!$B$2:$B$6000,$A4954),0) | G4954: =IF(COUNTIFS(Registros!$A$2:$A$6000,"MOV",Registros!$B$2:$B$6000,$A4954)>0,1,0) | H4954: =IF($G4954=1,SUMIFS(Registros!$F$2:$F$6000,Registros!$A$2:$A$6000,"MOV",Registros!$B$2:$B$6000,$A4954),0) | I4954: =IF(COUNTIFS(Registros!$A$2:$A$6000,"CS",Registros!$B$2:$B$6000,$A4954)>0,1,0) | J4954: =IF($I4954=1,SUMIFS(Registros!$I$2:$I$6000,Registros!$A$2:$A$6000,"CS",Registros!$B$2:$B$6000,$A4954),0) | K4954: =IF(COUNTIFS(Winback!$K$2:$K$300,$D4954)>0,1,0) | L4954: =IF(AND($K4954=1,LEFT($A4954,3)="WB-"),SUMIFS(Winback!$D$2:$D$300,Winback!$K$2:$K$300,$D4954),0) | M4954: =IF(OR($E4954=1,$G4954=1,SUMIFS(Registros!$J$2:$J$6000,Registros!$B$2:$B$6000,$A4954)>0),1,0) | N4954: =IF($J4954>0,1,IF(COUNTIFS(Registros!$A$2:$A$6000,"CS",Registros!$B$2:$B$6000,$A4954,Registros!$K$2:$K$6000,"<>")>0,1,0)) | O4954: =IF(AND($K4954=1,$E4954=0,$G4954=0,$I4954=0),"WINBACK",IF(AND($M4954=1,$N4954>0),"CONVERGENTE",IF($M4954=1,"SOLO MÓVIL",IF($N4954>0,"SOLO FIJO / INTERNET","SIN SERVICIOS")))) | P4954: =IF($O4954="WINBACK","Recuperar (winback)",IF($O4954="CONVERGENTE","Upgrade / más líneas",IF($O4954="SOLO MÓVIL","Ofrecer fijo + internet (FLBBTV)",IF($O4954="SOLO FIJO / INTERNET","Ofrecer línea móvil Nextphone","Oferta completa (móvil + fijo + internet)")))) | Q4954: =$F4954+$H4954+$L4954 | R4954: =IFERROR(VLOOKUP($A4954,Registros!$B$2:$G$6000,6,0),IFERROR(VLOOKUP($D4954,Winback!$B$2:$C$300,2,0),"")) | S4954: =IF($E4954=1,"NP","")&IF($G4954=1,"+MOV","")&IF($I4954=1,"+CS","")&IF($K4954=1,"+WB","") | T4954: =$E4954+$G4954+$I4954+$K4954
A4955: WB-FLIXCINEVISI | C4955: FLIX CINEVISION PANAMA, S. DE R.L. - | D4955: FLIXCINEVISIONPANAMASDERL | E4955: =IF(COUNTIFS(Registros!$A$2:$A$6000,"NP",Registros!$B$2:$B$6000,$A4955)>0,1,0) | F4955: =IF($E4955=1,SUMIFS(Registros!$F$2:$F$6000,Registros!$A$2:$A$6000,"NP",Registros!$B$2:$B$6000,$A4955),0) | G4955: =IF(COUNTIFS(Registros!$A$2:$A$6000,"MOV",Registros!$B$2:$B$6000,$A4955)>0,1,0) | H4955: =IF($G4955=1,SUMIFS(Registros!$F$2:$F$6000,Registros!$A$2:$A$6000,"MOV",Registros!$B$2:$B$6000,$A4955),0) | I4955: =IF(COUNTIFS(Registros!$A$2:$A$6000,"CS",Registros!$B$2:$B$6000,$A4955)>0,1,0) | J4955: =IF($I4955=1,SUMIFS(Registros!$I$2:$I$6000,Registros!$A$2:$A$6000,"CS",Registros!$B$2:$B$6000,$A4955),0) | K4955: =IF(COUNTIFS(Winback!$K$2:$K$300,$D4955)>0,1,0) | L4955: =IF(AND($K4955=1,LEFT($A4955,3)="WB-"),SUMIFS(Winback!$D$2:$D$300,Winback!$K$2:$K$300,$D4955),0) | M4955: =IF(OR($E4955=1,$G4955=1,SUMIFS(Registros!$J$2:$J$6000,Registros!$B$2:$B$6000,$A4955)>0),1,0) | N4955: =IF($J4955>0,1,IF(COUNTIFS(Registros!$A$2:$A$6000,"CS",Registros!$B$2:$B$6000,$A4955,Registros!$K$2:$K$6000,"<>")>0,1,0)) | O4955: =IF(AND($K4955=1,$E4955=0,$G4955=0,$I4955=0),"WINBACK",IF(AND($M4955=1,$N4955>0),"CONVERGENTE",IF($M4955=1,"SOLO MÓVIL",IF($N4955>0,"SOLO FIJO / INTERNET","SIN SERVICIOS")))) | P4955: =IF($O4955="WINBACK","Recuperar (winback)",IF($O4955="CONVERGENTE","Upgrade / más líneas",IF($O4955="SOLO MÓVIL","Ofrecer fijo + internet (FLBBTV)",IF($O4955="SOLO FIJO / INTERNET","Ofrecer línea móvil Nextphone","Oferta completa (móvil + fijo + internet)")))) | Q4955: =$F4955+$H4955+$L4955 | R4955: =IFERROR(VLOOKUP($A4955,Registros!$B$2:$G$6000,6,0),IFERROR(VLOOKUP($D4955,Winback!$B$2:$C$300,2,0),"")) | S4955: =IF($E4955=1,"NP","")&IF($G4955=1,"+MOV","")&IF($I4955=1,"+CS","")&IF($K4955=1,"+WB","") | T4955: =$E4955+$G4955+$I4955+$K4955
A4956: WB-AVAPSA | C4956: AVAPSA | D4956: AVAPSA | E4956: =IF(COUNTIFS(Registros!$A$2:$A$6000,"NP",Registros!$B$2:$B$6000,$A4956)>0,1,0) | F4956: =IF($E4956=1,SUMIFS(Registros!$F$2:$F$6000,Registros!$A$2:$A$6000,"NP",Registros!$B$2:$B$6000,$A4956),0) | G4956: =IF(COUNTIFS(Registros!$A$2:$A$6000,"MOV",Registros!$B$2:$B$6000,$A4956)>0,1,0) | H4956: =IF($G4956=1,SUMIFS(Registros!$F$2:$F$6000,Registros!$A$2:$A$6000,"MOV",Registros!$B$2:$B$6000,$A4956),0) | I4956: =IF(COUNTIFS(Registros!$A$2:$A$6000,"CS",Registros!$B$2:$B$6000,$A4956)>0,1,0) | J4956: =IF($I4956=1,SUMIFS(Registros!$I$2:$I$6000,Registros!$A$2:$A$6000,"CS",Registros!$B$2:$B$6000,$A4956),0) | K4956: =IF(COUNTIFS(Winback!$K$2:$K$300,$D4956)>0,1,0) | L4956: =IF(AND($K4956=1,LEFT($A4956,3)="WB-"),SUMIFS(Winback!$D$2:$D$300,Winback!$K$2:$K$300,$D4956),0) | M4956: =IF(OR($E4956=1,$G4956=1,SUMIFS(Registros!$J$2:$J$6000,Registros!$B$2:$B$6000,$A4956)>0),1,0) | N4956: =IF($J4956>0,1,IF(COUNTIFS(Registros!$A$2:$A$6000,"CS",Registros!$B$2:$B$6000,$A4956,Registros!$K$2:$K$6000,"<>")>0,1,0)) | O4956: =IF(AND($K4956=1,$E4956=0,$G4956=0,$I4956=0),"WINBACK",IF(AND($M4956=1,$N4956>0),"CONVERGENTE",IF($M4956=1,"SOLO MÓVIL",IF($N4956>0,"SOLO FIJO / INTERNET","SIN SERVICIOS")))) | P4956: =IF($O4956="WINBACK","Recuperar (winback)",IF($O4956="CONVERGENTE","Upgrade / más líneas",IF($O4956="SOLO MÓVIL","Ofrecer fijo + internet (FLBBTV)",IF($O4956="SOLO FIJO / INTERNET","Ofrecer línea móvil Nextphone","Oferta completa (móvil + fijo + internet)")))) | Q4956: =$F4956+$H4956+$L4956 | R4956: =IFERROR(VLOOKUP($A4956,Registros!$B$2:$G$6000,6,0),IFERROR(VLOOKUP($D4956,Winback!$B$2:$C$300,2,0),"")) | S4956: =IF($E4956=1,"NP","")&IF($G4956=1,"+MOV","")&IF($I4956=1,"+CS","")&IF($K4956=1,"+WB","") | T4956: =$E4956+$G4956+$I4956+$K4956
A4957: WB-DRAGCOLORS | C4957: DRAG COLORS | D4957: DRAGCOLORS | E4957: =IF(COUNTIFS(Registros!$A$2:$A$6000,"NP",Registros!$B$2:$B$6000,$A4957)>0,1,0) | F4957: =IF($E4957=1,SUMIFS(Registros!$F$2:$F$6000,Registros!$A$2:$A$6000,"NP",Registros!$B$2:$B$6000,$A4957),0) | G4957: =IF(COUNTIFS(Registros!$A$2:$A$6000,"MOV",Registros!$B$2:$B$6000,$A4957)>0,1,0) | H4957: =IF($G4957=1,SUMIFS(Registros!$F$2:$F$6000,Registros!$A$2:$A$6000,"MOV",Registros!$B$2:$B$6000,$A4957),0) | I4957: =IF(COUNTIFS(Registros!$A$2:$A$6000,"CS",Registros!$B$2:$B$6000,$A4957)>0,1,0) | J4957: =IF($I4957=1,SUMIFS(Registros!$I$2:$I$6000,Registros!$A$2:$A$6000,"CS",Registros!$B$2:$B$6000,$A4957),0) | K4957: =IF(COUNTIFS(Winback!$K$2:$K$300,$D4957)>0,1,0) | L4957: =IF(AND($K4957=1,LEFT($A4957,3)="WB-"),SUMIFS(Winback!$D$2:$D$300,Winback!$K$2:$K$300,$D4957),0) | M4957: =IF(OR($E4957=1,$G4957=1,SUMIFS(Registros!$J$2:$J$6000,Registros!$B$2:$B$6000,$A4957)>0),1,0) | N4957: =IF($J4957>0,1,IF(COUNTIFS(Registros!$A$2:$A$6000,"CS",Registros!$B$2:$B$6000,$A4957,Registros!$K$2:$K$6000,"<>")>0,1,0)) | O4957: =IF(AND($K4957=1,$E4957=0,$G4957=0,$I4957=0),"WINBACK",IF(AND($M4957=1,$N4957>0),"CONVERGENTE",IF($M4957=1,"SOLO MÓVIL",IF($N4957>0,"SOLO FIJO / INTERNET","SIN SERVICIOS")))) | P4957: =IF($O4957="WINBACK","Recuperar (winback)",IF($O4957="CONVERGENTE","Upgrade / más líneas",IF($O4957="SOLO MÓVIL","Ofrecer fijo + internet (FLBBTV)",IF($O4957="SOLO FIJO / INTERNET","Ofrecer línea móvil Nextphone","Oferta completa (móvil + fijo + internet)")))) | Q4957: =$F4957+$H4957+$L4957 | R4957: =IFERROR(VLOOKUP($A4957,Registros!$B$2:$G$6000,6,0),IFERROR(VLOOKUP($D4957,Winback!$B$2:$C$300,2,0),"")) | S4957: =IF($E4957=1,"NP","")&IF($G4957=1,"+MOV","")&IF($I4957=1,"+CS","")&IF($K4957=1,"+WB","") | T4957: =$E4957+$G4957+$I4957+$K4957
... A5080: WB-LUISANGELFER | C5080: LUIS ANGEL FERNANDEZ LEDEZMA | D5080: LUISANGELFERNANDEZLEDEZMA | E5080: =IF(COUNTIFS(Registros!$A$2:$A$6000,"NP",Registros!$B$2:$B$6000,$A5080)>0,1,0) | F5080: =IF($E5080=1,SUMIFS(Registros!$F$2:$F$6000,Registros!$A$2:$A$6000,"NP",Registros!$B$2:$B$6000,$A5080),0) | G5080: =IF(COUNTIFS(Registros!$A$2:$A$6000,"MOV",Registros!$B$2:$B$6000,$A5080)>0,1,0) | H5080: =IF($G5080=1,SUMIFS(Registros!$F$2:$F$6000,Registros!$A$2:$A$6000,"MOV",Registros!$B$2:$B$6000,$A5080),0) | I5080: =IF(COUNTIFS(Registros!$A$2:$A$6000,"CS",Registros!$B$2:$B$6000,$A5080)>0,1,0) | J5080: =IF($I5080=1,SUMIFS(Registros!$I$2:$I$6000,Registros!$A$2:$A$6000,"CS",Registros!$B$2:$B$6000,$A5080),0) | K5080: =IF(COUNTIFS(Winback!$K$2:$K$300,$D5080)>0,1,0) | L5080: =IF(AND($K5080=1,LEFT($A5080,3)="WB-"),SUMIFS(Winback!$D$2:$D$300,Winback!$K$2:$K$300,$D5080),0) | M5080: =IF(OR($E5080=1,$G5080=1,SUMIFS(Registros!$J$2:$J$6000,Registros!$B$2:$B$6000,$A5080)>0),1,0) | N5080: =IF($J5080>0,1,IF(COUNTIFS(Registros!$A$2:$A$6000,"CS",Registros!$B$2:$B$6000,$A5080,Registros!$K$2:$K$6000,"<>")>0,1,0)) | O5080: =IF(AND($K5080=1,$E5080=0,$G5080=0,$I5080=0),"WINBACK",IF(AND($M5080=1,$N5080>0),"CONVERGENTE",IF($M5080=1,"SOLO MÓVIL",IF($N5080>0,"SOLO FIJO / INTERNET","SIN SERVICIOS")))) | P5080: =IF($O5080="WINBACK","Recuperar (winback)",IF($O5080="CONVERGENTE","Upgrade / más líneas",IF($O5080="SOLO MÓVIL","Ofrecer fijo + internet (FLBBTV)",IF($O5080="SOLO FIJO / INTERNET","Ofrecer línea móvil Nextphone","Oferta completa (móvil + fijo + internet)")))) | Q5080: =$F5080+$H5080+$L5080 | R5080: =IFERROR(VLOOKUP($A5080,Registros!$B$2:$G$6000,6,0),IFERROR(VLOOKUP($D5080,Winback!$B$2:$C$300,2,0),"")) | S5080: =IF($E5080=1,"NP","")&IF($G5080=1,"+MOV","")&IF($I5080=1,"+CS","")&IF($K5080=1,"+WB","") | T5080: =$E5080+$G5080+$I5080+$K5080

Sheet Resumen
A1: CRUCE DE BASES - RESUMEN (fórmulas vinculadas)
A3: 1. TAMAÑO
A4: Clientes únicos (post cruce) | B4: =COUNTA(Cruce!$A$2:$A$6000) | C4: =COUNTA(Cruce!$A$2:$A$6000)
A5: Registros (suma de bases) | B5: =COUNTA(Registros!$A$2:$A$6000)
A6: Duplicados eliminados por el cruce | B6: =COUNTA(Registros!$A$2:$A$6000)-COUNTA(Cruce!$A$2:$A$6000)
A7: Registros Nextphone | B7: =COUNTIF(Registros!$A$2:$A$6000,"NP")
A8: Registros Móvil sin fijo | B8: =COUNTIF(Registros!$A$2:$A$6000,"MOV")
A9: Cuentas Cross-sell | B9: =COUNTIF(Registros!$A$2:$A$6000,"CS")
A10: Clientes en lista Winback | B10: =COUNTA(Winback!$A$2:$A$300)
A12: 2. SOLAPAMIENTO (clientes por nº de bases)
A13: Clientes en 1 base | B13: =SUMPRODUCT(--(Cruce!$T$2:$T$6000=1))
A14: Clientes en 2 bases | B14: =SUMPRODUCT(--(Cruce!$T$2:$T$6000=2))
A15: Clientes en 3 bases | B15: =SUMPRODUCT(--(Cruce!$T$2:$T$6000=3))
A16: Clientes en 4 bases | B16: =SUMPRODUCT(--(Cruce!$T$2:$T$6000=4))
A18: Solo Nextphone | B18: =COUNTIFS(Cruce!$E$2:$E$6000,1,Cruce!$G$2:$G$6000,0,Cruce!$I$2:$I$6000,0,Cruce!$K$2:$K$6000,0)
A19: Solo Móvil | B19: =COUNTIFS(Cruce!$E$2:$E$6000,0,Cruce!$G$2:$G$6000,1,Cruce!$I$2:$I$6000,0,Cruce!$K$2:$K$6000,0)
A20: Solo Cross-sell | B20: =COUNTIFS(Cruce!$E$2:$E$6000,0,Cruce!$G$2:$G$6000,0,Cruce!$I$2:$I$6000,1,Cruce!$K$2:$K$6000,0)
A21: Solo Winback | B21: =COUNTIFS(Cruce!$E$2:$E$6000,0,Cruce!$G$2:$G$6000,0,Cruce!$I$2:$I$6000,0,Cruce!$K$2:$K$6000,1)
A22: Nextphone + Cross-sell | B22: =COUNTIFS(Cruce!$E$2:$E$6000,1,Cruce!$G$2:$G$6000,0,Cruce!$I$2:$I$6000,1,Cruce!$K$2:$K$6000,0)
A23: Nextphone + Winback (recuperados) | B23: =COUNTIFS(Cruce!$E$2:$E$6000,1,Cruce!$G$2:$G$6000,0,Cruce!$I$2:$I$6000,0,Cruce!$K$2:$K$6000,1)
A24: Móvil + Winback (recuperados) | B24: =COUNTIFS(Cruce!$E$2:$E$6000,0,Cruce!$G$2:$G$6000,1,Cruce!$I$2:$I$6000,0,Cruce!$K$2:$K$6000,1)
A25: Nextphone + Móvil | B25: =COUNTIFS(Cruce!$E$2:$E$6000,1,Cruce!$G$2:$G$6000,1,Cruce!$I$2:$I$6000,0,Cruce!$K$2:$K$6000,0)
A26: Cross-sell + Winback | B26: =COUNTIFS(Cruce!$E$2:$E$6000,0,Cruce!$G$2:$G$6000,0,Cruce!$I$2:$I$6000,1,Cruce!$K$2:$K$6000,1)
A28: 3. SEGMENTACIÓN
A29: CONVERGENTE | B29: =COUNTIF(Cruce!$O$2:$O$6000,"CONVERGENTE")
A30: SOLO MÓVIL | B30: =COUNTIF(Cruce!$O$2:$O$6000,"SOLO MÓVIL")
A31: SOLO FIJO / INTERNET | B31: =COUNTIF(Cruce!$O$2:$O$6000,"SOLO FIJO / INTERNET")
A32: SIN SERVICIOS | B32: =COUNTIF(Cruce!$O$2:$O$6000,"SIN SERVICIOS")
A33: WINBACK | B33: =COUNTIF(Cruce!$O$2:$O$6000,"WINBACK")
A35: 4. OPORTUNIDADES
A36: Ofrecer fijo + internet (FLBBTV) | B36: =COUNTIF(Cruce!$P$2:$P$6000,"Ofrecer fijo + internet (FLBBTV)")
A37: Upgrade / más líneas | B37: =COUNTIF(Cruce!$P$2:$P$6000,"Upgrade / más líneas")
A38: Recuperar (winback) | B38: =COUNTIF(Cruce!$P$2:$P$6000,"Recuperar (winback)")
A39: Oferta completa (móvil + fijo + internet) | B39: =COUNTIF(Cruce!$P$2:$P$6000,"Oferta completa (móvil + fijo + internet)")
A40: Ofrecer línea móvil Nextphone | B40: =COUNTIF(Cruce!$P$2:$P$6000,"Ofrecer línea móvil Nextphone")
A42: 5. MRC
A43: MRC total consolidado | B43: =SUM(Cruce!$Q$2:$Q$6000)
A44: MRC Nextphone | B44: =SUM(Cruce!$F$2:$F$6000)
A45: MRC Móvil | B45: =SUM(Cruce!$H$2:$H$6000)
A46: MRC Winback (histórico) | B46: =SUM(Winback!$D$2:$D$300)
A47: MRC Winback en riesgo (solo no activos) | B47: =SUMIFS(Cruce!$Q$2:$Q$6000,Cruce!$O$2:$O$6000,"WINBACK")
A49: 6. WINBACK
A50: Recuperados (activos en otra base) | B50: =COUNTIF(Winback!$L$2:$L$300,"SI")
A51: Solo winback (a recuperar) | B51: =COUNTIF(Cruce!$O$2:$O$6000,"WINBACK")
